Workbook
Name CouponRate_bonds_0: #REF!
Name detailTableName_bonds: #REF!
Name Eurobonds_NewBonds_price_hdcp: 'EBs & NBs Prices'!$BW$14:$CA$313
Name Eurobonds_NewBonds_yield_hdcp: 'EBs & NBs Prices'!$BO$14:$BS$313
Name Eurobonds_OldBonds_price_hdcp: 'EBs & NBs Prices'!$AO$14:$AY$538
Name Eurobonds_OldBonds_yield_hdcp: 'EBs & NBs Prices'!$BB$14:$BL$538
Name NYBonds_NewBonds_prices: 'EBs & NBs Prices'!$AI$15:$AM$313
Name NYBonds_NewBonds_yields: 'EBs & NBs Prices'!$AA$14:$AE$313
Name orders_beforeAPPs_newbonds: #REF!
Name orders_beforeAPPs_vals: #REF!
Name orders_oldbonds: #REF!
Name results_names: #REF!
Name results_vals: #REF!

Sheet README
A1: Companion Spreadsheet for
A2: "Majority Voting in Sovereign Restructurings: The Aggregation Dilemma"
A3: by Carlo Galli and Stephane Guibaud
A5: Abbreviations
A6: EB | B6: Eligible Bonds
A7: NB | B7: New Bonds
A8: NPV | B8: Net Present Value
A9: PA | B9: Principal Amount
A10: FV | B10: Face Value
A11: SD | B11: Settlement Date
A13: List of Sheets | B13: Description
A14: EBs List | B14: Details on EBs
A15: EBs NPVs | B15: NPV and duration calculations for the EBs
A16: Exchange Offer & Results | B16: Details on the exchange conversion rates and recovery rates
A17: NBs List | B17: Details on the New Bonds
A18: NBs NPVs | B18: NPV and duration calculations for the NBs
A19: EBs & NBs Prices | B19: Historical prices and yields of the Ebs and NBs. Source: LSEG Workspace

Sheet EBs List
A1: Bond Name | B1: Bond Description (Exchange Offer terminology) | C1: Issue date | D1: ISIN (NY listed) | E1: ISIN (Euro listed) | F1: Coupon Rate | G1: Amortization terms | H1: Maturity date | I1: Total PA Oustanding | J1: PA Controlled by Ecuador
A2: ="USD "&YEAR(H2) -> USD 2022 | B2: 10.750% Notes due March 28, 2022 | C2: 42579 | D2: XS1458516967 | E2: XS1458514673 | F2: 0.1075 | G2: bullet | H2: 44648 | I2: 2000000000 | J2: 0
A3: ="USD "&YEAR(H3) -> USD 2023 | B3: 8.750% Notes due June 2, 2023 | C3: 42888 | D3: XS1626768656 | E3: XS1626768730 | F3: 0.0875 | G3: bullet | H3: 45079 | I3: 1000000000 | J3: 0
A4: ="USD "&YEAR(H4) -> USD 2024 | B4: 7.950% Notes due June 20, 2024 | C4: 41810 | D4: XS1080331181 | E4: XS1080330704 | F4: 0.0795 | G4: bullet | H4: 45463 | I4: 2000000000 | J4: 105027000
A5: ="USD "&YEAR(H5) -> USD 2025 | B5: 7.875% Notes due March 27, 2025 | C5: 43735 | D5: XS2058848826 | E5: XS2058845210 | F5: 0.07875 | G5: bullet | H5: 45743 | I5: 600000000 | J5: 0
A6: ="USD "&YEAR(H6) -> USD 2026 | B6: 9.650% Notes due December 13, 2026 | C6: 42717 | D6: XS1535072109 | E6: XS1535071986 | F6: 0.0965 | G6: bullet | H6: 46369 | I6: 1750000000 | J6: 11750000
A7: USD 9.625% 2027 | B7: 9.625% Notes due June 2, 2027 | C7: 42888 | D7: XS1626529157 | E7: XS1626530320 | F7: 0.09625 | G7: bullet | H7: 46540 | I7: 1000000000 | J7: 0
A8: USD 8.875% 2027 | B8: 8.875% Notes due October 23, 2027 | C8: 43031 | D8: XS1707041429 | E8: XS1707041262 | F8: 0.08875 | G8: bullet | H8: 46683 | I8: 2500000000 | J8: 0
A9: ="USD "&YEAR(H9) -> USD 2028 | B9: 7.875% Notes due January 23, 2028 | C9: 43123 | D9: XS1755432363 | E9: XS1755429732 | F9: 0.07875 | G9: bullet | H9: 46775 | I9: 3000000000 | J9: 26000000
A10: ="USD "&YEAR(H10) -> USD 2029 | B10: 10.750% Notes due January 31, 2029 | C10: 43496 | D10: XS1929377015 | E10: XS1929376710 | F10: 0.1075 | G10: bullet | H10: 47149 | I10: 2125000000 | J10: 19000000
A11: ="USD "&YEAR(H11) -> USD 2030 | B11: 9.500% Notes due March 27, 2030 | C11: 43735 | D11: XS2058866307 | E11: XS2058864948 | F11: 0.095 | G11: bullet | H11: 47569 | I11: 1400000000 | J11: 0
D119: NPV of Old Bond at New Bond Basket Exit Yield | E119: NPV of Old Bond at Average Exit Yield
B120: 10.75 | 2022 | D120: 0.62568323 | E120: 0.62022251
B121: 8.75 | 2023 | D121: 0.64815109 | E121: 0.63875131
B122: 7.88 | 2025 | D122: 0.65930932 | E122: 0.6449094
B123: 9.65 | 2026 | D123: 0.62614712 | E123: 0.6088923
B124: 9.63 | 2027 | D124: 0.62508634 | E124: 0.60698901
B125: 8.88 | 2027 | D125: 0.64412816 | E125: 0.62463012
B126: 7.88 | 2028 | D126: 0.69774114 | E126: 0.67516417
B127: 10.75 | 2029 | D127: 0.59656454 | E127: 0.57661478
B128: 9.5 | 2030 | D128: 0.6194912 | E128: 0.59720306

Sheet EBs NPVs
A1: Valuation date | B1: ='NBs List'!$E$1 -> 44081
A2: Exit yield | B2: ='NBs List'!F9/100 -> 0.097537113
A4: ISINs | B4: Bond Name | D4: Payment dates
A5: XS1458516967 | B5: =INDEX('EBs List'!$B$1:$M$11,MATCH(A5,'EBs List'!$D$1:$D$11,0),1) -> 10.750% Notes due March 28, 2022 | C5: 43918 | D5: 44102 | E5: 44283 | F5: 44467 | G5: 44648
A6: XS1626768656 | B6: =INDEX('EBs List'!$B$1:$M$11,MATCH(A6,'EBs List'!$D$1:$D$11,0),1) -> 8.750% Notes due June 2, 2023 | C6: 43984 | D6: 44167 | E6: 44349 | F6: 44532 | G6: 44714 | H6: 44897 | I6: 45079
A7: XS1080331181 | B7: =INDEX('EBs List'!$B$1:$M$11,MATCH(A7,'EBs List'!$D$1:$D$11,0),1) -> 7.950% Notes due June 20, 2024 | C7: 44002 | D7: 44185 | E7: 44367 | F7: 44550 | G7: 44732 | H7: 44915 | I7: 45097 | J7: 45280 | K7: 45463
A8: XS2058848826 | B8: =INDEX('EBs List'!$B$1:$M$11,MATCH(A8,'EBs List'!$D$1:$D$11,0),1) -> 7.875% Notes due March 27, 2025 | C8: 43917 | D8: 44101 | E8: 44282 | F8: 44466 | G8: 44647 | H8: 44831 | I8: 45012 | J8: 45196 | K8: 45378 | L8: 45562 | M8: 45743
A9: XS1535072109 | B9: =INDEX('EBs List'!$B$1:$M$11,MATCH(A9,'EBs List'!$D$1:$D$11,0),1) -> 9.650% Notes due December 13, 2026 | C9: 43995 | D9: 44178 | E9: 44360 | F9: 44543 | G9: 44725 | H9: 44908 | I9: 45090 | J9: 45273 | K9: 45456 | L9: 45639 | M9: 45821 | N9: 46004 | O9: 46186 | P9: 46369
A10: XS1626529157 | B10: =INDEX('EBs List'!$B$1:$M$11,MATCH(A10,'EBs List'!$D$1:$D$11,0),1) -> 9.625% Notes due June 2, 2027 | C10: 43984 | D10: 44167 | E10: 44349 | F10: 44532 | G10: 44714 | H10: 44897 | I10: 45079 | J10: 45262 | K10: 45445 | L10: 45628 | M10: 45810 | N10: 45993 | O10: 46175 | P10: 46358 | Q10: 46540
A11: XS1707041429 | B11: =INDEX('EBs List'!$B$1:$M$11,MATCH(A11,'EBs List'!$D$1:$D$11,0),1) -> 8.875% Notes due October 23, 2027 | C11: 43944 | D11: 44127 | E11: 44309 | F11: 44492 | G11: 44674 | H11: 44857 | I11: 45039 | J11: 45222 | K11: 45405 | L11: 45588 | M11: 45770 | N11: 45953 | O11: 46135 | P11: 46318 | Q11: 46500 | R11: 46683
A12: XS1755432363 | B12: =INDEX('EBs List'!$B$1:$M$11,MATCH(A12,'EBs List'!$D$1:$D$11,0),1) -> 7.875% Notes due January 23, 2028 | C12: 44035 | D12: 44219 | E12: 44400 | F12: 44584 | G12: 44765 | H12: 44949 | I12: 45130 | J12: 45314 | K12: 45496 | L12: 45680 | M12: 45861 | N12: 46045 | O12: 46226 | P12: 46410 | Q12: 46591 | R12: 46775
A13: XS1929377015 | B13: =INDEX('EBs List'!$B$1:$M$11,MATCH(A13,'EBs List'!$D$1:$D$11,0),1) -> 10.750% Notes due January 31, 2029 | C13: 44043 | D13: 44227 | E13: 44408 | F13: 44592 | G13: 44773 | H13: 44957 | I13: 45138 | J13: 45322 | K13: 45504 | L13: 45688 | M13: 45869 | N13: 46053 | O13: 46234 | P13: 46418 | Q13: 46599 | R13: 46783 | S13: 46965 | T13: 47149
A14: XS2058866307 | B14: =INDEX('EBs List'!$B$1:$M$11,MATCH(A14,'EBs List'!$D$1:$D$11,0),1) -> 9.500% Notes due March 27, 2030 | C14: 43917 | D14: 44101 | E14: 44282 | F14: 44466 | G14: 44647 | H14: 44831 | I14: 45012 | J14: 45196 | K14: 45378 | L14: 45562 | M14: 45743 | N14: 45927 | O14: 46108 | P14: 46292 | Q14: 46473 | R14: 46657 | S14: 46839 | T14: 47023 | U14: 47204 | V14: 47388 | W14: 47569
D16: Cash Flow | E16: Note on below: First column is in the past so assuming no CF there. Second column is in less than 1 payment period, so we compute the accrued coupon.
A17: XS1458516967 | B17: =INDEX('EBs List'!$B$1:$M$11,MATCH(A17,'EBs List'!$D$1:$D$11,0),1) -> 10.750% Notes due March 28, 2022 | D17: =E17*(D5-$B$1)/(D5-C5) -> 0.61345109 | E17: =IF(E5="","",IF(E5='EBs List'!$H2,100+'EBs List'!$F2*100/2,'EBs List'!$F2*100/2)) -> 5.375 | F17: =IF(F5="","",IF(F5='EBs List'!$H2,100+'EBs List'!$F2*100/2,'EBs List'!$F2*100/2)) -> 5.375 | G17: =IF(G5="","",IF(G5='EBs List'!$H2,100+'EBs List'!$F2*100/2,'EBs List'!$F2*100/2)) -> 105.375 | H17: =IF(H5="","",IF(H5='EBs List'!$H2,100+'EBs List'!$F2*100/2,'EBs List'!$F2*100/2)) | I17: =IF(I5="","",IF(I5='EBs List'!$H2,100+'EBs List'!$F2*100/2,'EBs List'!$F2*100/2)) | J17: =IF(J5="","",IF(J5='EBs List'!$H2,100+'EBs List'!$F2*100/2,'EBs List'!$F2*100/2)) | K17: =IF(K5="","",IF(K5='EBs List'!$H2,100+'EBs List'!$F2*100/2,'EBs List'!$F2*100/2)) | L17: =IF(L5="","",IF(L5='EBs List'!$H2,100+'EBs List'!$F2*100/2,'EBs List'!$F2*100/2)) | ... W17: =IF(W5="","",IF(W5='EBs List'!$H2,100+'EBs List'!$F2*100/2,'EBs List'!$F2*100/2))
A18: XS1626768656 | B18: =INDEX('EBs List'!$B$1:$M$11,MATCH(A18,'EBs List'!$D$1:$D$11,0),1) -> 8.750% Notes due June 2, 2023 | D18: =E18*(D6-$B$1)/(D6-C6) -> 2.0560109 | E18: =IF(E6="","",IF(E6='EBs List'!$H3,100+'EBs List'!$F3*100/2,'EBs List'!$F3*100/2)) -> 4.375 | F18: =IF(F6="","",IF(F6='EBs List'!$H3,100+'EBs List'!$F3*100/2,'EBs List'!$F3*100/2)) -> 4.375 | G18: =IF(G6="","",IF(G6='EBs List'!$H3,100+'EBs List'!$F3*100/2,'EBs List'!$F3*100/2)) -> 4.375 | H18: =IF(H6="","",IF(H6='EBs List'!$H3,100+'EBs List'!$F3*100/2,'EBs List'!$F3*100/2)) -> 4.375 | I18: =IF(I6="","",IF(I6='EBs List'!$H3,100+'EBs List'!$F3*100/2,'EBs List'!$F3*100/2)) -> 104.375 | J18: =IF(J6="","",IF(J6='EBs List'!$H3,100+'EBs List'!$F3*100/2,'EBs List'!$F3*100/2)) | K18: =IF(K6="","",IF(K6='EBs List'!$H3,100+'EBs List'!$F3*100/2,'EBs List'!$F3*100/2)) | L18: =IF(L6="","",IF(L6='EBs List'!$H3,100+'EBs List'!$F3*100/2,'EBs List'!$F3*100/2)) | ... W18: =IF(W6="","",IF(W6='EBs List'!$H3,100+'EBs List'!$F3*100/2,'EBs List'!$F3*100/2))
A19: XS1080331181 | B19: =INDEX('EBs List'!$B$1:$M$11,MATCH(A19,'EBs List'!$D$1:$D$11,0),1) -> 7.950% Notes due June 20, 2024 | D19: =E19*(D7-$B$1)/(D7-C7) -> 2.2590164 | E19: =IF(E7="","",IF(E7='EBs List'!$H4,100+'EBs List'!$F4*100/2,'EBs List'!$F4*100/2)) -> 3.975 | F19: =IF(F7="","",IF(F7='EBs List'!$H4,100+'EBs List'!$F4*100/2,'EBs List'!$F4*100/2)) -> 3.975 | G19: =IF(G7="","",IF(G7='EBs List'!$H4,100+'EBs List'!$F4*100/2,'EBs List'!$F4*100/2)) -> 3.975 | H19: =IF(H7="","",IF(H7='EBs List'!$H4,100+'EBs List'!$F4*100/2,'EBs List'!$F4*100/2)) -> 3.975 | I19: =IF(I7="","",IF(I7='EBs List'!$H4,100+'EBs List'!$F4*100/2,'EBs List'!$F4*100/2)) -> 3.975 | J19: =IF(J7="","",IF(J7='EBs List'!$H4,100+'EBs List'!$F4*100/2,'EBs List'!$F4*100/2)) -> 3.975 | K19: =IF(K7="","",IF(K7='EBs List'!$H4,100+'EBs List'!$F4*100/2,'EBs List'!$F4*100/2)) -> 103.975 | L19: =IF(L7="","",IF(L7='EBs List'!$H4,100+'EBs List'!$F4*100/2,'EBs List'!$F4*100/2)) | ... W19: =IF(W7="","",IF(W7='EBs List'!$H4,100+'EBs List'!$F4*100/2,'EBs List'!$F4*100/2))
A20: XS2058848826 | B20: =INDEX('EBs List'!$B$1:$M$11,MATCH(A20,'EBs List'!$D$1:$D$11,0),1) -> 7.875% Notes due March 27, 2025 | D20: =E20*(D8-$B$1)/(D8-C8) -> 0.42798913 | E20: =IF(E8="","",IF(E8='EBs List'!$H5,100+'EBs List'!$F5*100/2,'EBs List'!$F5*100/2)) -> 3.9375 | F20: =IF(F8="","",IF(F8='EBs List'!$H5,100+'EBs List'!$F5*100/2,'EBs List'!$F5*100/2)) -> 3.9375 | G20: =IF(G8="","",IF(G8='EBs List'!$H5,100+'EBs List'!$F5*100/2,'EBs List'!$F5*100/2)) -> 3.9375 | H20: =IF(H8="","",IF(H8='EBs List'!$H5,100+'EBs List'!$F5*100/2,'EBs List'!$F5*100/2)) -> 3.9375 | I20: =IF(I8="","",IF(I8='EBs List'!$H5,100+'EBs List'!$F5*100/2,'EBs List'!$F5*100/2)) -> 3.9375 | J20: =IF(J8="","",IF(J8='EBs List'!$H5,100+'EBs List'!$F5*100/2,'EBs List'!$F5*100/2)) -> 3.9375 | K20: =IF(K8="","",IF(K8='EBs List'!$H5,100+'EBs List'!$F5*100/2,'EBs List'!$F5*100/2)) -> 3.9375 | L20: =IF(L8="","",IF(L8='EBs List'!$H5,100+'EBs List'!$F5*100/2,'EBs List'!$F5*100/2)) -> 3.9375 | ... W20: =IF(W8="","",IF(W8='EBs List'!$H5,100+'EBs List'!$F5*100/2,'EBs List'!$F5*100/2))
A21: XS1535072109 | B21: =INDEX('EBs List'!$B$1:$M$11,MATCH(A21,'EBs List'!$D$1:$D$11,0),1) -> 9.650% Notes due December 13, 2026 | D21: =E21*(D9-$B$1)/(D9-C9) -> 2.5575137 | E21: =IF(E9="","",IF(E9='EBs List'!$H6,100+'EBs List'!$F6*100/2,'EBs List'!$F6*100/2)) -> 4.825 | F21: =IF(F9="","",IF(F9='EBs List'!$H6,100+'EBs List'!$F6*100/2,'EBs List'!$F6*100/2)) -> 4.825 | G21: =IF(G9="","",IF(G9='EBs List'!$H6,100+'EBs List'!$F6*100/2,'EBs List'!$F6*100/2)) -> 4.825 | H21: =IF(H9="","",IF(H9='EBs List'!$H6,100+'EBs List'!$F6*100/2,'EBs List'!$F6*100/2)) -> 4.825 | I21: =IF(I9="","",IF(I9='EBs List'!$H6,100+'EBs List'!$F6*100/2,'EBs List'!$F6*100/2)) -> 4.825 | J21: =IF(J9="","",IF(J9='EBs List'!$H6,100+'EBs List'!$F6*100/2,'EBs List'!$F6*100/2)) -> 4.825 | K21: =IF(K9="","",IF(K9='EBs List'!$H6,100+'EBs List'!$F6*100/2,'EBs List'!$F6*100/2)) -> 4.825 | L21: =IF(L9="","",IF(L9='EBs List'!$H6,100+'EBs List'!$F6*100/2,'EBs List'!$F6*100/2)) -> 4.825 | ... W21: =IF(W9="","",IF(W9='EBs List'!$H6,100+'EBs List'!$F6*100/2,'EBs List'!$F6*100/2))
A22: XS1626529157 | B22: =INDEX('EBs List'!$B$1:$M$11,MATCH(A22,'EBs List'!$D$1:$D$11,0),1) -> 9.625% Notes due June 2, 2027 | D22: =E22*(D10-$B$1)/(D10-C10) -> 2.261612 | E22: =IF(E10="","",IF(E10='EBs List'!$H7,100+'EBs List'!$F7*100/2,'EBs List'!$F7*100/2)) -> 4.8125 | F22: =IF(F10="","",IF(F10='EBs List'!$H7,100+'EBs List'!$F7*100/2,'EBs List'!$F7*100/2)) -> 4.8125 | G22: =IF(G10="","",IF(G10='EBs List'!$H7,100+'EBs List'!$F7*100/2,'EBs List'!$F7*100/2)) -> 4.8125 | H22: =IF(H10="","",IF(H10='EBs List'!$H7,100+'EBs List'!$F7*100/2,'EBs List'!$F7*100/2)) -> 4.8125 | I22: =IF(I10="","",IF(I10='EBs List'!$H7,100+'EBs List'!$F7*100/2,'EBs List'!$F7*100/2)) -> 4.8125 | J22: =IF(J10="","",IF(J10='EBs List'!$H7,100+'EBs List'!$F7*100/2,'EBs List'!$F7*100/2)) -> 4.8125 | K22: =IF(K10="","",IF(K10='EBs List'!$H7,100+'EBs List'!$F7*100/2,'EBs List'!$F7*100/2)) -> 4.8125 | L22: =IF(L10="","",IF(L10='EBs List'!$H7,100+'EBs List'!$F7*100/2,'EBs List'!$F7*100/2)) -> 4.8125 | ... W22: =IF(W10="","",IF(W10='EBs List'!$H7,100+'EBs List'!$F7*100/2,'EBs List'!$F7*100/2))
A23: XS1707041429 | B23: =INDEX('EBs List'!$B$1:$M$11,MATCH(A23,'EBs List'!$D$1:$D$11,0),1) -> 8.875% Notes due October 23, 2027 | D23: =E23*(D11-$B$1)/(D11-C11) -> 1.1154372 | E23: =IF(E11="","",IF(E11='EBs List'!$H8,100+'EBs List'!$F8*100/2,'EBs List'!$F8*100/2)) -> 4.4375 | F23: =IF(F11="","",IF(F11='EBs List'!$H8,100+'EBs List'!$F8*100/2,'EBs List'!$F8*100/2)) -> 4.4375 | G23: =IF(G11="","",IF(G11='EBs List'!$H8,100+'EBs List'!$F8*100/2,'EBs List'!$F8*100/2)) -> 4.4375 | H23: =IF(H11="","",IF(H11='EBs List'!$H8,100+'EBs List'!$F8*100/2,'EBs List'!$F8*100/2)) -> 4.4375 | I23: =IF(I11="","",IF(I11='EBs List'!$H8,100+'EBs List'!$F8*100/2,'EBs List'!$F8*100/2)) -> 4.4375 | J23: =IF(J11="","",IF(J11='EBs List'!$H8,100+'EBs List'!$F8*100/2,'EBs List'!$F8*100/2)) -> 4.4375 | K23: =IF(K11="","",IF(K11='EBs List'!$H8,100+'EBs List'!$F8*100/2,'EBs List'!$F8*100/2)) -> 4.4375 | L23: =IF(L11="","",IF(L11='EBs List'!$H8,100+'EBs List'!$F8*100/2,'EBs List'!$F8*100/2)) -> 4.4375 | ... W23: =IF(W11="","",IF(W11='EBs List'!$H8,100+'EBs List'!$F8*100/2,'EBs List'!$F8*100/2))
A24: XS1755432363 | B24: =INDEX('EBs List'!$B$1:$M$11,MATCH(A24,'EBs List'!$D$1:$D$11,0),1) -> 7.875% Notes due January 23, 2028 | D24: =E24*(D12-$B$1)/(D12-C12) -> 2.953125 | E24: =IF(E12="","",IF(E12='EBs List'!$H9,100+'EBs List'!$F9*100/2,'EBs List'!$F9*100/2)) -> 3.9375 | F24: =IF(F12="","",IF(F12='EBs List'!$H9,100+'EBs List'!$F9*100/2,'EBs List'!$F9*100/2)) -> 3.9375 | G24: =IF(G12="","",IF(G12='EBs List'!$H9,100+'EBs List'!$F9*100/2,'EBs List'!$F9*100/2)) -> 3.9375 | H24: =IF(H12="","",IF(H12='EBs List'!$H9,100+'EBs List'!$F9*100/2,'EBs List'!$F9*100/2)) -> 3.9375 | I24: =IF(I12="","",IF(I12='EBs List'!$H9,100+'EBs List'!$F9*100/2,'EBs List'!$F9*100/2)) -> 3.9375 | J24: =IF(J12="","",IF(J12='EBs List'!$H9,100+'EBs List'!$F9*100/2,'EBs List'!$F9*100/2)) -> 3.9375 | K24: =IF(K12="","",IF(K12='EBs List'!$H9,100+'EBs List'!$F9*100/2,'EBs List'!$F9*100/2)) -> 3.9375 | L24: =IF(L12="","",IF(L12='EBs List'!$H9,100+'EBs List'!$F9*100/2,'EBs List'!$F9*100/2)) -> 3.9375 | ... W24: =IF(W12="","",IF(W12='EBs List'!$H9,100+'EBs List'!$F9*100/2,'EBs List'!$F9*100/2))
A25: XS1929377015 | B25: =INDEX('EBs List'!$B$1:$M$11,MATCH(A25,'EBs List'!$D$1:$D$11,0),1) -> 10.750% Notes due January 31, 2029 | D25: =E25*(D13-$B$1)/(D13-C13) -> 4.2649457 | E25: =IF(E13="","",IF(E13='EBs List'!$H10,100+'EBs List'!$F10*100/2,'EBs List'!$F10*100/2)) -> 5.375 | F25: =IF(F13="","",IF(F13='EBs List'!$H10,100+'EBs List'!$F10*100/2,'EBs List'!$F10*100/2)) -> 5.375 | G25: =IF(G13="","",IF(G13='EBs List'!$H10,100+'EBs List'!$F10*100/2,'EBs List'!$F10*100/2)) -> 5.375 | H25: =IF(H13="","",IF(H13='EBs List'!$H10,100+'EBs List'!$F10*100/2,'EBs List'!$F10*100/2)) -> 5.375 | I25: =IF(I13="","",IF(I13='EBs List'!$H10,100+'EBs List'!$F10*100/2,'EBs List'!$F10*100/2)) -> 5.375 | J25: =IF(J13="","",IF(J13='EBs List'!$H10,100+'EBs List'!$F10*100/2,'EBs List'!$F10*100/2)) -> 5.375 | K25: =IF(K13="","",IF(K13='EBs List'!$H10,100+'EBs List'!$F10*100/2,'EBs List'!$F10*100/2)) -> 5.375 | L25: =IF(L13="","",IF(L13='EBs List'!$H10,100+'EBs List'!$F10*100/2,'EBs List'!$F10*100/2)) -> 5.375 | ... W25: =IF(W13="","",IF(W13='EBs List'!$H10,100+'EBs List'!$F10*100/2,'EBs List'!$F10*100/2))
A26: XS2058866307 | B26: =INDEX('EBs List'!$B$1:$M$11,MATCH(A26,'EBs List'!$D$1:$D$11,0),1) -> 9.500% Notes due March 27, 2030 | D26: =E26*(D14-$B$1)/(D14-C14) -> 0.51630435 | E26: =IF(E14="","",IF(E14='EBs List'!$H11,100+'EBs List'!$F11*100/2,'EBs List'!$F11*100/2)) -> 4.75 | F26: =IF(F14="","",IF(F14='EBs List'!$H11,100+'EBs List'!$F11*100/2,'EBs List'!$F11*100/2)) -> 4.75 | G26: =IF(G14="","",IF(G14='EBs List'!$H11,100+'EBs List'!$F11*100/2,'EBs List'!$F11*100/2)) -> 4.75 | H26: =IF(H14="","",IF(H14='EBs List'!$H11,100+'EBs List'!$F11*100/2,'EBs List'!$F11*100/2)) -> 4.75 | I26: =IF(I14="","",IF(I14='EBs List'!$H11,100+'EBs List'!$F11*100/2,'EBs List'!$F11*100/2)) -> 4.75 | J26: =IF(J14="","",IF(J14='EBs List'!$H11,100+'EBs List'!$F11*100/2,'EBs List'!$F11*100/2)) -> 4.75 | K26: =IF(K14="","",IF(K14='EBs List'!$H11,100+'EBs List'!$F11*100/2,'EBs List'!$F11*100/2)) -> 4.75 | L26: =IF(L14="","",IF(L14='EBs List'!$H11,100+'EBs List'!$F11*100/2,'EBs List'!$F11*100/2)) -> 4.75 | ... W26: =IF(W14="","",IF(W14='EBs List'!$H11,100+'EBs List'!$F11*100/2,'EBs List'!$F11*100/2)) -> 104.75
D28: Time (years)
A29: XS1458516967 | B29: =INDEX('EBs List'!$B$1:$M$11,MATCH(A29,'EBs List'!$D$1:$D$11,0),1) -> 10.750% Notes due March 28, 2022 | D29: =IF(D5="","",(MAX(D5-$B$1,0)/365)) -> 0.057534247 | E29: =IF(E5="","",(MAX(E5-$B$1,0)/365)) -> 0.55342466 | F29: =IF(F5="","",(MAX(F5-$B$1,0)/365)) -> 1.0575342 | G29: =IF(G5="","",(MAX(G5-$B$1,0)/365)) -> 1.5534247 | H29: =IF(H5="","",(MAX(H5-$B$1,0)/365)) | I29: =IF(I5="","",(MAX(I5-$B$1,0)/365)) | J29: =IF(J5="","",(MAX(J5-$B$1,0)/365)) | K29: =IF(K5="","",(MAX(K5-$B$1,0)/365)) | ... W29: =IF(W5="","",(MAX(W5-$B$1,0)/365))
A30: XS1626768656 | B30: =INDEX('EBs List'!$B$1:$M$11,MATCH(A30,'EBs List'!$D$1:$D$11,0),1) -> 8.750% Notes due June 2, 2023 | D30: =IF(D6="","",(MAX(D6-$B$1,0)/365)) -> 0.23561644 | E30: =IF(E6="","",(MAX(E6-$B$1,0)/365)) -> 0.73424658 | F30: =IF(F6="","",(MAX(F6-$B$1,0)/365)) -> 1.2356164 | G30: =IF(G6="","",(MAX(G6-$B$1,0)/365)) -> 1.7342466 | H30: =IF(H6="","",(MAX(H6-$B$1,0)/365)) -> 2.2356164 | I30: =IF(I6="","",(MAX(I6-$B$1,0)/365)) -> 2.7342466 | J30: =IF(J6="","",(MAX(J6-$B$1,0)/365)) | K30: =IF(K6="","",(MAX(K6-$B$1,0)/365)) | ... W30: =IF(W6="","",(MAX(W6-$B$1,0)/365))
A31: XS1080331181 | B31: =INDEX('EBs List'!$B$1:$M$11,MATCH(A31,'EBs List'!$D$1:$D$11,0),1) -> 7.950% Notes due June 20, 2024 | D31: =IF(D7="","",(MAX(D7-$B$1,0)/365)) -> 0.28493151 | E31: =IF(E7="","",(MAX(E7-$B$1,0)/365)) -> 0.78356164 | F31: =IF(F7="","",(MAX(F7-$B$1,0)/365)) -> 1.2849315 | G31: =IF(G7="","",(MAX(G7-$B$1,0)/365)) -> 1.7835616 | H31: =IF(H7="","",(MAX(H7-$B$1,0)/365)) -> 2.2849315 | I31: =IF(I7="","",(MAX(I7-$B$1,0)/365)) -> 2.7835616 | J31: =IF(J7="","",(MAX(J7-$B$1,0)/365)) -> 3.2849315 | K31: =IF(K7="","",(MAX(K7-$B$1,0)/365)) -> 3.7863014 | ... W31: =IF(W7="","",(MAX(W7-$B$1,0)/365))
A32: XS2058848826 | B32: =INDEX('EBs List'!$B$1:$M$11,MATCH(A32,'EBs List'!$D$1:$D$11,0),1) -> 7.875% Notes due March 27, 2025 | D32: =IF(D8="","",(MAX(D8-$B$1,0)/365)) -> 0.054794521 | E32: =IF(E8="","",(MAX(E8-$B$1,0)/365)) -> 0.55068493 | F32: =IF(F8="","",(MAX(F8-$B$1,0)/365)) -> 1.0547945 | G32: =IF(G8="","",(MAX(G8-$B$1,0)/365)) -> 1.5506849 | H32: =IF(H8="","",(MAX(H8-$B$1,0)/365)) -> 2.0547945 | I32: =IF(I8="","",(MAX(I8-$B$1,0)/365)) -> 2.5506849 | J32: =IF(J8="","",(MAX(J8-$B$1,0)/365)) -> 3.0547945 | K32: =IF(K8="","",(MAX(K8-$B$1,0)/365)) -> 3.5534247 | ... W32: =IF(W8="","",(MAX(W8-$B$1,0)/365))
A33: XS1535072109 | B33: =INDEX('EBs List'!$B$1:$M$11,MATCH(A33,'EBs List'!$D$1:$D$11,0),1) -> 9.650% Notes due December 13, 2026 | D33: =IF(D9="","",(MAX(D9-$B$1,0)/365)) -> 0.26575342 | E33: =IF(E9="","",(MAX(E9-$B$1,0)/365)) -> 0.76438356 | F33: =IF(F9="","",(MAX(F9-$B$1,0)/365)) -> 1.2657534 | G33: =IF(G9="","",(MAX(G9-$B$1,0)/365)) -> 1.7643836 | H33: =IF(H9="","",(MAX(H9-$B$1,0)/365)) -> 2.2657534 | I33: =IF(I9="","",(MAX(I9-$B$1,0)/365)) -> 2.7643836 | J33: =IF(J9="","",(MAX(J9-$B$1,0)/365)) -> 3.2657534 | K33: =IF(K9="","",(MAX(K9-$B$1,0)/365)) -> 3.7671233 | ... W33: =IF(W9="","",(MAX(W9-$B$1,0)/365))
A34: XS1626529157 | B34: =INDEX('EBs List'!$B$1:$M$11,MATCH(A34,'EBs List'!$D$1:$D$11,0),1) -> 9.625% Notes due June 2, 2027 | D34: =IF(D10="","",(MAX(D10-$B$1,0)/365)) -> 0.23561644 | E34: =IF(E10="","",(MAX(E10-$B$1,0)/365)) -> 0.73424658 | F34: =IF(F10="","",(MAX(F10-$B$1,0)/365)) -> 1.2356164 | G34: =IF(G10="","",(MAX(G10-$B$1,0)/365)) -> 1.7342466 | H34: =IF(H10="","",(MAX(H10-$B$1,0)/365)) -> 2.2356164 | I34: =IF(I10="","",(MAX(I10-$B$1,0)/365)) -> 2.7342466 | J34: =IF(J10="","",(MAX(J10-$B$1,0)/365)) -> 3.2356164 | K34: =IF(K10="","",(MAX(K10-$B$1,0)/365)) -> 3.7369863 | ... W34: =IF(W10="","",(MAX(W10-$B$1,0)/365))
A35: XS1707041429 | B35: =INDEX('EBs List'!$B$1:$M$11,MATCH(A35,'EBs List'!$D$1:$D$11,0),1) -> 8.875% Notes due October 23, 2027 | D35: =IF(D11="","",(MAX(D11-$B$1,0)/365)) -> 0.1260274 | E35: =IF(E11="","",(MAX(E11-$B$1,0)/365)) -> 0.62465753 | F35: =IF(F11="","",(MAX(F11-$B$1,0)/365)) -> 1.1260274 | G35: =IF(G11="","",(MAX(G11-$B$1,0)/365)) -> 1.6246575 | H35: =IF(H11="","",(MAX(H11-$B$1,0)/365)) -> 2.1260274 | I35: =IF(I11="","",(MAX(I11-$B$1,0)/365)) -> 2.6246575 | J35: =IF(J11="","",(MAX(J11-$B$1,0)/365)) -> 3.1260274 | K35: =IF(K11="","",(MAX(K11-$B$1,0)/365)) -> 3.6273973 | ... W35: =IF(W11="","",(MAX(W11-$B$1,0)/365))
A36: XS1755432363 | B36: =INDEX('EBs List'!$B$1:$M$11,MATCH(A36,'EBs List'!$D$1:$D$11,0),1) -> 7.875% Notes due January 23, 2028 | D36: =IF(D12="","",(MAX(D12-$B$1,0)/365)) -> 0.37808219 | E36: =IF(E12="","",(MAX(E12-$B$1,0)/365)) -> 0.8739726 | F36: =IF(F12="","",(MAX(F12-$B$1,0)/365)) -> 1.3780822 | G36: =IF(G12="","",(MAX(G12-$B$1,0)/365)) -> 1.8739726 | H36: =IF(H12="","",(MAX(H12-$B$1,0)/365)) -> 2.3780822 | I36: =IF(I12="","",(MAX(I12-$B$1,0)/365)) -> 2.8739726 | J36: =IF(J12="","",(MAX(J12-$B$1,0)/365)) -> 3.3780822 | K36: =IF(K12="","",(MAX(K12-$B$1,0)/365)) -> 3.8767123 | ... W36: =IF(W12="","",(MAX(W12-$B$1,0)/365))
A37: XS1929377015 | B37: =INDEX('EBs List'!$B$1:$M$11,MATCH(A37,'EBs List'!$D$1:$D$11,0),1) -> 10.750% Notes due January 31, 2029 | D37: =IF(D13="","",(MAX(D13-$B$1,0)/365)) -> 0.4 | E37: =IF(E13="","",(MAX(E13-$B$1,0)/365)) -> 0.89589041 | F37: =IF(F13="","",(MAX(F13-$B$1,0)/365)) -> 1.4 | G37: =IF(G13="","",(MAX(G13-$B$1,0)/365)) -> 1.8958904 | H37: =IF(H13="","",(MAX(H13-$B$1,0)/365)) -> 2.4 | I37: =IF(I13="","",(MAX(I13-$B$1,0)/365)) -> 2.8958904 | J37: =IF(J13="","",(MAX(J13-$B$1,0)/365)) -> 3.4 | K37: =IF(K13="","",(MAX(K13-$B$1,0)/365)) -> 3.8986301 | ... W37: =IF(W13="","",(MAX(W13-$B$1,0)/365))
A38: XS2058866307 | B38: =INDEX('EBs List'!$B$1:$M$11,MATCH(A38,'EBs List'!$D$1:$D$11,0),1) -> 9.500% Notes due March 27, 2030 | D38: =IF(D14="","",(MAX(D14-$B$1,0)/365)) -> 0.054794521 | E38: =IF(E14="","",(MAX(E14-$B$1,0)/365)) -> 0.55068493 | F38: =IF(F14="","",(MAX(F14-$B$1,0)/365)) -> 1.0547945 | G38: =IF(G14="","",(MAX(G14-$B$1,0)/365)) -> 1.5506849 | H38: =IF(H14="","",(MAX(H14-$B$1,0)/365)) -> 2.0547945 | I38: =IF(I14="","",(MAX(I14-$B$1,0)/365)) -> 2.5506849 | J38: =IF(J14="","",(MAX(J14-$B$1,0)/365)) -> 3.0547945 | K38: =IF(K14="","",(MAX(K14-$B$1,0)/365)) -> 3.5534247 | ... W38: =IF(W14="","",(MAX(W14-$B$1,0)/365)) -> 9.5561644
D40: Discounted Cash Flow
A41: XS1458516967 | B41: =INDEX('EBs List'!$B$1:$M$11,MATCH(A41,'EBs List'!$D$1:$D$11,0),1) -> 10.750% Notes due March 28, 2022 | D41: =IF(D29="","",D17/(1+$B$2)^D29) -> 0.61017506 | E41: =IF(E29="","",E17/(1+$B$2)^E29) -> 5.1051614 | F41: =IF(F29="","",F17/(1+$B$2)^F29) -> 4.8711754 | G41: =IF(G29="","",G17/(1+$B$2)^G29) -> 91.190455 | H41: =IF(H29="","",H17/(1+$B$2)^H29) | I41: =IF(I29="","",I17/(1+$B$2)^I29) | J41: =IF(J29="","",J17/(1+$B$2)^J29) | K41: =IF(K29="","",K17/(1+$B$2)^K29) | ... W41: =IF(W29="","",W17/(1+$B$2)^W29)
A42: XS1626768656 | B42: =INDEX('EBs List'!$B$1:$M$11,MATCH(A42,'EBs List'!$D$1:$D$11,0),1) -> 8.750% Notes due June 2, 2023 | D42: =IF(D30="","",D18/(1+$B$2)^D30) -> 2.0114164 | E42: =IF(E30="","",E18/(1+$B$2)^E30) -> 4.0860191 | F42: =IF(F30="","",F18/(1+$B$2)^F30) -> 3.8997378 | G42: =IF(G30="","",G18/(1+$B$2)^G30) -> 3.7228983 | H42: =IF(H30="","",H18/(1+$B$2)^H30) -> 3.5531717 | I42: =IF(I30="","",I18/(1+$B$2)^I30) -> 80.924568 | J42: =IF(J30="","",J18/(1+$B$2)^J30) | K42: =IF(K30="","",K18/(1+$B$2)^K30) | ... W42: =IF(W30="","",W18/(1+$B$2)^W30)
A43: XS1080331181 | B43: =INDEX('EBs List'!$B$1:$M$11,MATCH(A43,'EBs List'!$D$1:$D$11,0),1) -> 7.950% Notes due June 20, 2024 | D43: =IF(D31="","",D19/(1+$B$2)^D31) -> 2.1998987 | E43: =IF(E31="","",E19/(1+$B$2)^E31) -> 3.6954403 | F43: =IF(F31="","",F19/(1+$B$2)^F31) -> 3.5269655 | G43: =IF(G31="","",G19/(1+$B$2)^G31) -> 3.3670299 | H43: =IF(H31="","",H19/(1+$B$2)^H31) -> 3.2135273 | I43: =IF(I31="","",I19/(1+$B$2)^I31) -> 3.067805 | J43: =IF(J31="","",J19/(1+$B$2)^J31) -> 2.9279441 | K43: =IF(K31="","",K19/(1+$B$2)^K31) -> 73.095325 | ... W43: =IF(W31="","",W19/(1+$B$2)^W31)
A44: XS2058848826 | B44: =INDEX('EBs List'!$B$1:$M$11,MATCH(A44,'EBs List'!$D$1:$D$11,0),1) -> 7.875% Notes due March 27, 2025 | D44: =IF(D32="","",D20/(1+$B$2)^D32) -> 0.42581209 | E44: =IF(E32="","",E20/(1+$B$2)^E32) -> 3.7407813 | F44: =IF(F32="","",F20/(1+$B$2)^F32) -> 3.5693292 | G44: =IF(G32="","",G20/(1+$B$2)^G32) -> 3.4083415 | H44: =IF(H32="","",H20/(1+$B$2)^H32) -> 3.2521262 | I44: =IF(I32="","",I20/(1+$B$2)^I32) -> 3.1054453 | J44: =IF(J32="","",J20/(1+$B$2)^J32) -> 2.9631127 | K44: =IF(K32="","",K20/(1+$B$2)^K32) -> 2.8287459 | ... W44: =IF(W32="","",W20/(1+$B$2)^W32)
A45: XS1535072109 | B45: =INDEX('EBs List'!$B$1:$M$11,MATCH(A45,'EBs List'!$D$1:$D$11,0),1) -> 9.650% Notes due December 13, 2026 | D45: =IF(D33="","",D21/(1+$B$2)^D33) -> 2.4950337 | E45: =IF(E33="","",E21/(1+$B$2)^E33) -> 4.4936737 | F45: =IF(F33="","",F21/(1+$B$2)^F33) -> 4.2888075 | G45: =IF(G33="","",G21/(1+$B$2)^G33) -> 4.0943251 | H45: =IF(H33="","",H21/(1+$B$2)^H33) -> 3.9076652 | I45: =IF(I33="","",I21/(1+$B$2)^I33) -> 3.7304662 | J45: =IF(J33="","",J21/(1+$B$2)^J33) -> 3.5603946 | K45: =IF(K33="","",K21/(1+$B$2)^K33) -> 3.3980765 | ... W45: =IF(W33="","",W21/(1+$B$2)^W33)
A46: XS1626529157 | B46: =INDEX('EBs List'!$B$1:$M$11,MATCH(A46,'EBs List'!$D$1:$D$11,0),1) -> 9.625% Notes due June 2, 2027 | D46: =IF(D34="","",D22/(1+$B$2)^D34) -> 2.212558 | E46: =IF(E34="","",E22/(1+$B$2)^E34) -> 4.494621 | F46: =IF(F34="","",F22/(1+$B$2)^F34) -> 4.2897116 | G46: =IF(G34="","",G22/(1+$B$2)^G34) -> 4.0951881 | H46: =IF(H34="","",H22/(1+$B$2)^H34) -> 3.9084889 | I46: =IF(I34="","",I22/(1+$B$2)^I34) -> 3.7312525 | J46: =IF(J34="","",J22/(1+$B$2)^J34) -> 3.5611451 | K46: =IF(K34="","",K22/(1+$B$2)^K34) -> 3.3987928 | ... W46: =IF(W34="","",W22/(1+$B$2)^W34)
A47: XS1707041429 | B47: =INDEX('EBs List'!$B$1:$M$11,MATCH(A47,'EBs List'!$D$1:$D$11,0),1) -> 8.875% Notes due October 23, 2027 | D47: =IF(D35="","",D23/(1+$B$2)^D35) -> 1.1024304 | E47: =IF(E35="","",E23/(1+$B$2)^E35) -> 4.186877 | F47: =IF(F35="","",F23/(1+$B$2)^F35) -> 3.9959976 | G47: =IF(G35="","",G23/(1+$B$2)^G35) -> 3.8147931 | H47: =IF(H35="","",H23/(1+$B$2)^H35) -> 3.640877 | I47: =IF(I35="","",I23/(1+$B$2)^I35) -> 3.4757759 | J47: =IF(J35="","",J23/(1+$B$2)^J35) -> 3.3173156 | K47: =IF(K35="","",K23/(1+$B$2)^K35) -> 3.1660795 | ... W47: =IF(W35="","",W23/(1+$B$2)^W35)
A48: XS1755432363 | B48: =INDEX('EBs List'!$B$1:$M$11,MATCH(A48,'EBs List'!$D$1:$D$11,0),1) -> 7.875% Notes due January 23, 2028 | D48: =IF(D36="","",D24/(1+$B$2)^D36) -> 2.8510186 | E48: =IF(E36="","",E24/(1+$B$2)^E36) -> 3.6299052 | F48: =IF(F36="","",F24/(1+$B$2)^F36) -> 3.4635349 | G48: =IF(G36="","",G24/(1+$B$2)^G36) -> 3.3073188 | H48: =IF(H36="","",H24/(1+$B$2)^H36) -> 3.1557337 | I48: =IF(I36="","",I24/(1+$B$2)^I36) -> 3.0134005 | J48: =IF(J36="","",J24/(1+$B$2)^J36) -> 2.8752866 | K48: =IF(K36="","",K24/(1+$B$2)^K36) -> 2.7449024 | ... W48: =IF(W36="","",W24/(1+$B$2)^W36)
A49: XS1929377015 | B49: =INDEX('EBs List'!$B$1:$M$11,MATCH(A49,'EBs List'!$D$1:$D$11,0),1) -> 10.750% Notes due January 31, 2029 | D49: =IF(D37="","",D25/(1+$B$2)^D37) -> 4.1090915 | E49: =IF(E37="","",E25/(1+$B$2)^E37) -> 4.9450112 | F49: =IF(F37="","",F25/(1+$B$2)^F37) -> 4.7183654 | G49: =IF(G37="","",G25/(1+$B$2)^G37) -> 4.5055526 | H49: =IF(H37="","",H25/(1+$B$2)^H37) -> 4.2990486 | I49: =IF(I37="","",I25/(1+$B$2)^I37) -> 4.1051483 | J49: =IF(J37="","",J25/(1+$B$2)^J37) -> 3.9169961 | K49: =IF(K37="","",K25/(1+$B$2)^K37) -> 3.739374 | ... W49: =IF(W37="","",W25/(1+$B$2)^W37)
A50: XS2058866307 | B50: =INDEX('EBs List'!$B$1:$M$11,MATCH(A50,'EBs List'!$D$1:$D$11,0),1) -> 9.500% Notes due March 27, 2030 | D50: =IF(D38="","",D26/(1+$B$2)^D38) -> 0.51367808 | E50: =IF(E38="","",E26/(1+$B$2)^E38) -> 4.5126885 | F50: =IF(F38="","",F26/(1+$B$2)^F38) -> 4.3058574 | G50: =IF(G38="","",G26/(1+$B$2)^G38) -> 4.11165 | H50: =IF(H38="","",H26/(1+$B$2)^H38) -> 3.9231998 | I50: =IF(I38="","",I26/(1+$B$2)^I38) -> 3.7462515 | J50: =IF(J38="","",J26/(1+$B$2)^J38) -> 3.5745487 | K50: =IF(K38="","",K26/(1+$B$2)^K38) -> 3.4124553 | ... W50: =IF(W38="","",W26/(1+$B$2)^W38) -> 43.042885
D54: NPV @ Exit yield | E54: Macaulay duration
A55: XS1458516967 | B55: =INDEX('EBs List'!$B$1:$M$11,MATCH(A55,'EBs List'!$D$1:$D$11,0),1) -> 10.750% Notes due March 28, 2022 | C55: USD 2022 | D55: =SUM(D41:W41) -> 101.77697 | E55: =SUMPRODUCT(D41:W41,D29:W29)/D55 -> 1.4705622
A56: XS1626768656 | B56: =INDEX('EBs List'!$B$1:$M$11,MATCH(A56,'EBs List'!$D$1:$D$11,0),1) -> 8.750% Notes due June 2, 2023 | C56: USD 2023 | D56: =SUM(D42:W42) -> 98.197811 | E56: =SUMPRODUCT(D42:W42,D30:W30)/D56 -> 2.4843764
A57: XS1080331181 | B57: =INDEX('EBs List'!$B$1:$M$11,MATCH(A57,'EBs List'!$D$1:$D$11,0),1) -> 7.950% Notes due June 20, 2024 | C57: USD 2024 | D57: =SUM(D43:W43) -> 95.093936 | E57: =SUMPRODUCT(D43:W43,D31:W31)/D57 -> 3.3264033
A58: XS2058848826 | B58: =INDEX('EBs List'!$B$1:$M$11,MATCH(A58,'EBs List'!$D$1:$D$11,0),1) -> 7.875% Notes due March 27, 2025 | C58: USD 2025 | D58: =SUM(D44:W44) -> 94.026854 | E58: =SUMPRODUCT(D44:W44,D32:W32)/D58 -> 3.8880388
A59: XS1535072109 | B59: =INDEX('EBs List'!$B$1:$M$11,MATCH(A59,'EBs List'!$D$1:$D$11,0),1) -> 9.650% Notes due December 13, 2026 | C59: USD 2026 | D59: =SUM(D45:W45) -> 100.57569 | E59: =SUMPRODUCT(D45:W45,D33:W33)/D59 -> 4.8465206
A60: XS1626529157 | B60: =INDEX('EBs List'!$B$1:$M$11,MATCH(A60,'EBs List'!$D$1:$D$11,0),1) -> 9.625% Notes due June 2, 2027 | C60: USD 9.625% 2027 | D60: =SUM(D46:W46) -> 100.49222 | E60: =SUMPRODUCT(D46:W46,D34:W34)/D60 -> 5.1096219
A61: XS1707041429 | B61: =INDEX('EBs List'!$B$1:$M$11,MATCH(A61,'EBs List'!$D$1:$D$11,0),1) -> 8.875% Notes due October 23, 2027 | C61: USD 8.875% 2027 | D61: =SUM(D47:W47) -> 96.683396 | E61: =SUMPRODUCT(D47:W47,D35:W35)/D61 -> 5.395148
A62: XS1755432363 | B62: =INDEX('EBs List'!$B$1:$M$11,MATCH(A62,'EBs List'!$D$1:$D$11,0),1) -> 7.875% Notes due January 23, 2028 | C62: USD 2028 | D62: =SUM(D48:W48) -> 91.369875 | E62: =SUMPRODUCT(D48:W48,D36:W36)/D62 -> 5.6447521
A63: XS1929377015 | B63: =INDEX('EBs List'!$B$1:$M$11,MATCH(A63,'EBs List'!$D$1:$D$11,0),1) -> 10.750% Notes due January 31, 2029 | C63: USD 2029 | D63: =SUM(D49:W49) -> 106.92856 | E63: =SUMPRODUCT(D49:W49,D37:W37)/D63 -> 5.8310402
A64: XS2058866307 | B64: =INDEX('EBs List'!$B$1:$M$11,MATCH(A64,'EBs List'!$D$1:$D$11,0),1) -> 9.500% Notes due March 27, 2030 | C64: USD 2030 | D64: =SUM(D50:W50) -> 99.835772 | E64: =SUMPRODUCT(D50:W50,D38:W38)/D64 -> 6.479543

Sheet Exchange Offer & Results
A1: Exchange Offer | H1: Exchange Results
C2: PA of NB per USD 1,000 PA of EB | F2: PA of NB per USD 1,000 of accrued & unpaid interest of EB (up to, but excluding, the SD) | L2: Without Arrear Bond | N2: With Arrear Bond
A3: Bond Name | B3: Eligible Bonds | C3: New 2030 | D3: New 2035 | E3: New 2040 | F3: New PDI 2030 | H3: Consents Delivered and Accepted | I3: PA Controlled by Ecuador | J3: Total PA Oustanding | K3: Consent Share | L3: Value of exchange basket (with FV reduction) | M3: SZ recovery | N3: Value of exchange basket (with FV reduction) | O3: SZ Recovery
A4: USD 2022 | B4: 10.750% Notes due March 28, 2022 | C4: 300 | D4: 495.3 | E4: 116 | F4: 78.92 | H4: 1972287000 | I4: 0 | J4: 2000000000 | K4: 0.9861 | L4: =SUMPRODUCT(C4:E4,$C$16:$E$16)/SUM(C4:E4) -> 65.762729 | M4: =L4/VLOOKUP($A4,'EBs NPVs'!$C$55:$D$64,2,FALSE)*100 -> 64.61455 | N4: =SUMPRODUCT(C4:F4,$C$16:$F$16)/SUM(C4:F4) -> 64.466598 | O4: =N4/VLOOKUP($A4,'EBs NPVs'!$C$55:$D$64,2,FALSE)*100 -> 63.341049
A5: USD 2023 | B5: 8.750% Notes due June 2, 2023 | C5: 229 | D5: 495.3 | E5: 187 | F5: 50.78 | H5: 977614000 | I5: 0 | J5: 1000000000 | K5: 0.9776 | L5: =SUMPRODUCT(C5:E5,$C$16:$E$16)/SUM(C5:E5) -> 64.428509 | M5: =L5/VLOOKUP($A5,'EBs NPVs'!$C$55:$D$64,2,FALSE)*100 -> 65.610942 | N5: =SUMPRODUCT(C5:F5,$C$16:$F$16)/SUM(C5:F5) -> 63.64056 | O5: =N5/VLOOKUP($A5,'EBs NPVs'!$C$55:$D$64,2,FALSE)*100 -> 64.808532
A6: USD 2024 | B6: 7.950% Notes due June 20, 2024 | C6: 300 | D6: 495.3 | E6: 116 | F6: 42.68 | H6: 1808157000 | I6: 105027000 | J6: 2000000000 | K6: 0.9542 | L6: =SUMPRODUCT(C6:E6,$C$16:$E$16)/SUM(C6:E6) -> 65.762729 | M6: =L6/VLOOKUP($A6,'EBs NPVs'!$C$55:$D$64,2,FALSE)*100 -> 69.155544 | N6: =SUMPRODUCT(C6:F6,$C$16:$F$16)/SUM(C6:F6) -> 65.035153 | O6: =N6/VLOOKUP($A6,'EBs NPVs'!$C$55:$D$64,2,FALSE)*100 -> 68.390431
A7: USD 2025 | B7: 7.875% Notes due March 27, 2025 | C7: 189 | D7: 495.3 | E7: 227 | F7: 57.89 | H7: 587055000 | I7: 0 | J7: 600000000 | K7: 0.9784 | L7: =SUMPRODUCT(C7:E7,$C$16:$E$16)/SUM(C7:E7) -> 63.676835 | M7: =L7/VLOOKUP($A7,'EBs NPVs'!$C$55:$D$64,2,FALSE)*100 -> 67.721967 | N7: =SUMPRODUCT(C7:F7,$C$16:$F$16)/SUM(C7:F7) -> 62.830049 | O7: =N7/VLOOKUP($A7,'EBs NPVs'!$C$55:$D$64,2,FALSE)*100 -> 66.821388
A8: USD 2026 | B8: 9.650% Notes due December 13, 2026 | C8: 189 | D8: 495.3 | E8: 227 | F8: 53.51 | H8: 1703336000 | I8: 11750000 | J8: 1750000000 | K8: 0.9799 | L8: =SUMPRODUCT(C8:E8,$C$16:$E$16)/SUM(C8:E8) -> 63.676835 | M8: =L8/VLOOKUP($A8,'EBs NPVs'!$C$55:$D$64,2,FALSE)*100 -> 63.312351 | N8: =SUMPRODUCT(C8:F8,$C$16:$F$16)/SUM(C8:F8) -> 62.890564 | O8: =N8/VLOOKUP($A8,'EBs NPVs'!$C$55:$D$64,2,FALSE)*100 -> 62.53058
A9: USD 9.625% 2027 | B9: 9.625% Notes due June 2, 2027 | C9: 189 | D9: 495.3 | E9: 227 | F9: 55.9 | H9: 982142000 | I9: 0 | J9: 1000000000 | K9: 0.9821 | L9: =SUMPRODUCT(C9:E9,$C$16:$E$16)/SUM(C9:E9) -> 63.676835 | M9: =L9/VLOOKUP($A9,'EBs NPVs'!$C$55:$D$64,2,FALSE)*100 -> 63.364942 | N9: =SUMPRODUCT(C9:F9,$C$16:$F$16)/SUM(C9:F9) -> 62.857475 | O9: =N9/VLOOKUP($A9,'EBs NPVs'!$C$55:$D$64,2,FALSE)*100 -> 62.549595
A10: USD 8.875% 2027 | B10: 8.875% Notes due October 23, 2027 | C10: 189 | D10: 495.3 | E10: 227 | F10: 59.78 | H10: 2454719000 | I10: 0 | J10: 2500000000 | K10: 0.9819 | L10: =SUMPRODUCT(C10:E10,$C$16:$E$16)/SUM(C10:E10) -> 63.676835 | M10: =L10/VLOOKUP($A10,'EBs NPVs'!$C$55:$D$64,2,FALSE)*100 -> 65.86119 | N10: =SUMPRODUCT(C10:F10,$C$16:$F$16)/SUM(C10:F10) -> 62.804105 | O10: =N10/VLOOKUP($A10,'EBs NPVs'!$C$55:$D$64,2,FALSE)*100 -> 64.958522
A11: USD 2028 | B11: 7.875% Notes due January 23, 2028 | C11: 189 | D11: 495.3 | E11: 227 | F11: 36.07 | H11: 2906442000 | I11: 26000000 | J11: 3000000000 | K11: 0.9773 | L11: =SUMPRODUCT(C11:E11,$C$16:$E$16)/SUM(C11:E11) -> 63.676835 | M11: =L11/VLOOKUP($A11,'EBs NPVs'!$C$55:$D$64,2,FALSE)*100 -> 69.69128 | N11: =SUMPRODUCT(C11:F11,$C$16:$F$16)/SUM(C11:F11) -> 63.137069 | O11: =N11/VLOOKUP($A11,'EBs NPVs'!$C$55:$D$64,2,FALSE)*100 -> 69.100531
A12: USD 2029 | B12: 10.750% Notes due January 31, 2029 | C12: 189 | D12: 495.3 | E12: 227 | F12: 47.59 | H12: 2069176000 | I12: 19000000 | J12: 2125000000 | K12: 0.9825 | L12: =SUMPRODUCT(C12:E12,$C$16:$E$16)/SUM(C12:E12) -> 63.676835 | M12: =L12/VLOOKUP($A12,'EBs NPVs'!$C$55:$D$64,2,FALSE)*100 -> 59.550819 | N12: =SUMPRODUCT(C12:F12,$C$16:$F$16)/SUM(C12:F12) -> 62.973235 | O12: =N12/VLOOKUP($A12,'EBs NPVs'!$C$55:$D$64,2,FALSE)*100 -> 58.892809
A13: USD 2030 | B13: 9.500% Notes due March 27, 2030 | C13: 189 | D13: 495.3 | E13: 227 | F13: 69.92 | H13: 1382144000 | I13: 0 | J13: 1400000000 | K13: 0.9872 | L13: =SUMPRODUCT(C13:E13,$C$16:$E$16)/SUM(C13:E13) -> 63.676835 | M13: =L13/VLOOKUP($A13,'EBs NPVs'!$C$55:$D$64,2,FALSE)*100 -> 63.781583 | N13: =SUMPRODUCT(C13:F13,$C$16:$F$16)/SUM(C13:F13) -> 62.666619 | O13: =N13/VLOOKUP($A13,'EBs NPVs'!$C$55:$D$64,2,FALSE)*100 -> 62.769705
B14: Any EB not consenting | C14: 0 | D14: 0 | E14: 911.3 | F14: 0
B16: ="NBs Exit Price on "&TEXT('NBs List'!$E$1,"dd-mmm-aa") -> NBs Exit Price on 07-Sep-20 | C16: =INDEX('NBs List'!$E$3:$E$6,MATCH(C3,'NBs List'!$A$3:$A$6,0)) -> 74.125 | D16: =INDEX('NBs List'!$E$3:$E$6,MATCH(D3,'NBs List'!$A$3:$A$6,0)) -> 62.75 | E16: =INDEX('NBs List'!$E$3:$E$6,MATCH(E3,'NBs List'!$A$3:$A$6,0)) -> 57 | F16: =INDEX('NBs List'!$E$3:$E$6,MATCH(F3,'NBs List'!$A$3:$A$6,0)) -> 49.5
B122: 10.75 | 2022
B123: 8.75 | 2023
B124: 7.88 | 2025
B125: 9.65 | 2026
B126: 9.63 | 2027
B127: 8.88 | 2027
B128: 7.88 | 2028
B129: 10.75 | 2029
B130: 9.5 | 2030

Sheet NBs List
E1: 44081
A2: Name | B2: Principal Amortization | C2: Principal repayment start date | D2: Issued Amount (USD mm) | E2: ="Exit Price on "&TEXT(E1,"dd-mmm-aa") -> Exit Price on 07-Sep-20 | F2: ="Exit Yield on "& TEXT(E1,"dd-mmm-aa") -> Exit Yield on 07-Sep-20 | G2: Maturity Date | H2: Macaulay Duration | I2: ISIN (NY listed) | J2: ISIN (Euro listed)
A3: New 2030 | B3: 10 | C3: 46053 | D3: 3701 | E3: =VLOOKUP($E$1,NYBonds_NewBonds_prices,MATCH($I3,'EBs & NBs Prices'!$AA$14:$AE$14,0),FALSE) -> 74.125 | F3: =VLOOKUP($E$1,NYBonds_NewBonds_yields,MATCH($I3,'EBs & NBs Prices'!$AA$14:$AE$14,0),FALSE) -> 10.231664 | G3: 47695 | H3: =SUMPRODUCT('NBs NPVs'!E33:AQ33,'NBs NPVs'!E27:AQ27)/SUM('NBs NPVs'!E33:AQ33) -> 6.6412199 | I3: XS2214238102 | J3: XS2214238102
A4: New 2035 | B4: 10 | C4: 47879 | D4: 8459 | E4: =VLOOKUP($E$1,NYBonds_NewBonds_prices,MATCH($I4,'EBs & NBs Prices'!$AA$14:$AE$14,0),FALSE) -> 62.75 | F4: =VLOOKUP($E$1,NYBonds_NewBonds_yields,MATCH($I4,'EBs & NBs Prices'!$AA$14:$AE$14,0),FALSE) -> 9.705758 | G4: 49521 | H4: =SUMPRODUCT('NBs NPVs'!E34:AQ34,'NBs NPVs'!E28:AQ28)/SUM('NBs NPVs'!E34:AQ34) -> 10.138578 | I4: XS2214238524 | J4: XS2214238524
A5: New 2040 | B5: 10 | C5: 49705 | D5: 3403 | E5: =VLOOKUP($E$1,NYBonds_NewBonds_prices,MATCH($I5,'EBs & NBs Prices'!$AA$14:$AE$14,0),FALSE) -> 57 | F5: =VLOOKUP($E$1,NYBonds_NewBonds_yields,MATCH($I5,'EBs & NBs Prices'!$AA$14:$AE$14,0),FALSE) -> 9.353104 | G5: 51348 | H5: =SUMPRODUCT('NBs NPVs'!E35:AQ35,'NBs NPVs'!E29:AQ29)/SUM('NBs NPVs'!E35:AQ35) -> 12.617302 | I5: XS2214239258 | J5: XS2214239258
A6: New PDI 2030 | B6: 10 | C6: 46053 | D6: 1005 | E6: =VLOOKUP($E$1,NYBonds_NewBonds_prices,MATCH($I6,'EBs & NBs Prices'!$AA$14:$AE$14,0),FALSE) -> 49.5 | F6: =VLOOKUP($E$1,NYBonds_NewBonds_yields,MATCH($I6,'EBs & NBs Prices'!$AA$14:$AE$14,0),FALSE) -> 9.536024 | G6: 47695 | H6: =SUMPRODUCT('NBs NPVs'!E36:AQ36,'NBs NPVs'!E30:AQ30)/SUM('NBs NPVs'!E36:AQ36) -> 7.5617713 | I6: XS2214239688 | J6: XS2214239688
E8: Avg Exit Price | F8: Avg Exit Yield
D9: Weighted average without PDI bond | E9: =SUMPRODUCT(E3:E5,D3:D5)/SUM(D3:D5) -> 64.197769 | F9: =SUMPRODUCT(F3:F5,D3:D5)/SUM(D3:D5) -> 9.7537113
D10: Weighted average with PDI bond | E10: =SUMPRODUCT($D$3:$D$6,E3:E6)/SUM($D$3:$D$6) -> 63.306215 | F10: =SUMPRODUCT($D$3:$D$6,F3:F6)/SUM($D$3:$D$6) -> 9.7405065

Sheet NBs NPVs
A1: Exit Yield | B1: ='NBs List'!F10/100 -> 0.097405065
A2: Valuation date | B2: ='NBs List'!E1 -> 44081
A5: Coupon dates & rates
A6: New 2030 | B6: 44408 | C6: 44773 | D6: 45138 | E6: 45504 | F6: 47695
A7: New 2030 | B7: 0.5 | C7: 5 | D7: 5.5 | E7: 6 | F7: 6.9
A8: New 2035 | B8: 44408 | C8: 44773 | D8: 45138 | E8: 45504 | F8: 45869 | G8: 49521
A9: New 2035 | B9: 0.5 | C9: 1 | D9: 2.5 | E9: 3.5 | F9: 5.5 | G9: 6.9
A10: New 2040 | B10: 44408 | C10: 44773 | D10: 45138 | E10: 45504 | F10: 46234 | G10: 46599 | H10: 46965 | I10: 47330 | J10: 51348
A11: New 2040 | B11: 0.5 | C11: 0.5 | D11: 1.5 | E11: 2.5 | F11: 5 | G11: 5.5 | H11: 6 | I11: 6.5 | J11: 6.9
A12: New PDI 2030 | B12: 0
A14: Annual Coupon | D14: 44227 | E14: =EDATE(D14,6) -> 44408 | F14: =EDATE(E14,6) -> 44592 | G14: =EDATE(F14,6) -> 44773 | H14: =EDATE(G14,6) -> 44957 | I14: =EDATE(H14,6) -> 45138 | J14: =EDATE(I14,6) -> 45322 | K14: =EDATE(J14,6) -> 45504 | L14: =EDATE(K14,6) -> 45688 | ... AQ14: =EDATE(AP14,6) -> 51348
A15: New 2030 | E15: =IF(E$14<=$B$6,$B$7,IF(E$14<=$C$6,$C$7,IF(E$14<=$D$6,$D$7,IF(E$14<=$E$6,$E$7,IF(E$14<=$F$6,$F$7,0))))) -> 0.5 | F15: =IF(F$14<=$B$6,$B$7,IF(F$14<=$C$6,$C$7,IF(F$14<=$D$6,$D$7,IF(F$14<=$E$6,$E$7,IF(F$14<=$F$6,$F$7,0))))) -> 5 | G15: =IF(G$14<=$B$6,$B$7,IF(G$14<=$C$6,$C$7,IF(G$14<=$D$6,$D$7,IF(G$14<=$E$6,$E$7,IF(G$14<=$F$6,$F$7,0))))) -> 5 | H15: =IF(H$14<=$B$6,$B$7,IF(H$14<=$C$6,$C$7,IF(H$14<=$D$6,$D$7,IF(H$14<=$E$6,$E$7,IF(H$14<=$F$6,$F$7,0))))) -> 5.5 | I15: =IF(I$14<=$B$6,$B$7,IF(I$14<=$C$6,$C$7,IF(I$14<=$D$6,$D$7,IF(I$14<=$E$6,$E$7,IF(I$14<=$F$6,$F$7,0))))) -> 5.5 | J15: =IF(J$14<=$B$6,$B$7,IF(J$14<=$C$6,$C$7,IF(J$14<=$D$6,$D$7,IF(J$14<=$E$6,$E$7,IF(J$14<=$F$6,$F$7,0))))) -> 6 | K15: =IF(K$14<=$B$6,$B$7,IF(K$14<=$C$6,$C$7,IF(K$14<=$D$6,$D$7,IF(K$14<=$E$6,$E$7,IF(K$14<=$F$6,$F$7,0))))) -> 6 | L15: =IF(L$14<=$B$6,$B$7,IF(L$14<=$C$6,$C$7,IF(L$14<=$D$6,$D$7,IF(L$14<=$E$6,$E$7,IF(L$14<=$F$6,$F$7,0))))) -> 6.9 | ... AQ15: =IF(AQ$14<=$B$6,$B$7,IF(AQ$14<=$C$6,$C$7,IF(AQ$14<=$D$6,$D$7,IF(AQ$14<=$E$6,$E$7,IF(AQ$14<=$F$6,$F$7,0))))) -> 0
A16: New 2035 | E16: =IF(E$14<=$B8,$B9,IF(E$14<=$C8,$C9,IF(E$14<=$D8,$D9,IF(E$14<=$E8,$E9,IF(E$14<=$F8,$F9,IF(E$14<=$G8,$G9,0)))))) -> 0.5 | F16: =IF(F$14<=$B8,$B9,IF(F$14<=$C8,$C9,IF(F$14<=$D8,$D9,IF(F$14<=$E8,$E9,IF(F$14<=$F8,$F9,IF(F$14<=$G8,$G9,0)))))) -> 1 | G16: =IF(G$14<=$B8,$B9,IF(G$14<=$C8,$C9,IF(G$14<=$D8,$D9,IF(G$14<=$E8,$E9,IF(G$14<=$F8,$F9,IF(G$14<=$G8,$G9,0)))))) -> 1 | H16: =IF(H$14<=$B8,$B9,IF(H$14<=$C8,$C9,IF(H$14<=$D8,$D9,IF(H$14<=$E8,$E9,IF(H$14<=$F8,$F9,IF(H$14<=$G8,$G9,0)))))) -> 2.5 | I16: =IF(I$14<=$B8,$B9,IF(I$14<=$C8,$C9,IF(I$14<=$D8,$D9,IF(I$14<=$E8,$E9,IF(I$14<=$F8,$F9,IF(I$14<=$G8,$G9,0)))))) -> 2.5 | J16: =IF(J$14<=$B8,$B9,IF(J$14<=$C8,$C9,IF(J$14<=$D8,$D9,IF(J$14<=$E8,$E9,IF(J$14<=$F8,$F9,IF(J$14<=$G8,$G9,0)))))) -> 3.5 | K16: =IF(K$14<=$B8,$B9,IF(K$14<=$C8,$C9,IF(K$14<=$D8,$D9,IF(K$14<=$E8,$E9,IF(K$14<=$F8,$F9,IF(K$14<=$G8,$G9,0)))))) -> 3.5 | L16: =IF(L$14<=$B8,$B9,IF(L$14<=$C8,$C9,IF(L$14<=$D8,$D9,IF(L$14<=$E8,$E9,IF(L$14<=$F8,$F9,IF(L$14<=$G8,$G9,0)))))) -> 5.5 | ... AQ16: =IF(AQ$14<=$B8,$B9,IF(AQ$14<=$C8,$C9,IF(AQ$14<=$D8,$D9,IF(AQ$14<=$E8,$E9,IF(AQ$14<=$F8,$F9,IF(AQ$14<=$G8,$G9,0)))))) -> 0
A17: New 2040 | E17: =IF(E$14<=$B10,$B11,IF(E$14<=$C10,$C11,IF(E$14<=$D10,$D11,IF(E$14<=$E10,$E11,IF(E$14<=$F10,$F11,IF(E$14<=$G10,$G11,IF(E$14<=$H10,$H11,IF(E$14<=$I10,$I11,IF(E$14<=$J10,$J11,0))))))))) -> 0.5 | F17: =IF(F$14<=$B10,$B11,IF(F$14<=$C10,$C11,IF(F$14<=$D10,$D11,IF(F$14<=$E10,$E11,IF(F$14<=$F10,$F11,IF(F$14<=$G10,$G11,IF(F$14<=$H10,$H11,IF(F$14<=$I10,$I11,IF(F$14<=$J10,$J11,0))))))))) -> 0.5 | G17: =IF(G$14<=$B10,$B11,IF(G$14<=$C10,$C11,IF(G$14<=$D10,$D11,IF(G$14<=$E10,$E11,IF(G$14<=$F10,$F11,IF(G$14<=$G10,$G11,IF(G$14<=$H10,$H11,IF(G$14<=$I10,$I11,IF(G$14<=$J10,$J11,0))))))))) -> 0.5 | H17: =IF(H$14<=$B10,$B11,IF(H$14<=$C10,$C11,IF(H$14<=$D10,$D11,IF(H$14<=$E10,$E11,IF(H$14<=$F10,$F11,IF(H$14<=$G10,$G11,IF(H$14<=$H10,$H11,IF(H$14<=$I10,$I11,IF(H$14<=$J10,$J11,0))))))))) -> 1.5 | I17: =IF(I$14<=$B10,$B11,IF(I$14<=$C10,$C11,IF(I$14<=$D10,$D11,IF(I$14<=$E10,$E11,IF(I$14<=$F10,$F11,IF(I$14<=$G10,$G11,IF(I$14<=$H10,$H11,IF(I$14<=$I10,$I11,IF(I$14<=$J10,$J11,0))))))))) -> 1.5 | J17: =IF(J$14<=$B10,$B11,IF(J$14<=$C10,$C11,IF(J$14<=$D10,$D11,IF(J$14<=$E10,$E11,IF(J$14<=$F10,$F11,IF(J$14<=$G10,$G11,IF(J$14<=$H10,$H11,IF(J$14<=$I10,$I11,IF(J$14<=$J10,$J11,0))))))))) -> 2.5 | K17: =IF(K$14<=$B10,$B11,IF(K$14<=$C10,$C11,IF(K$14<=$D10,$D11,IF(K$14<=$E10,$E11,IF(K$14<=$F10,$F11,IF(K$14<=$G10,$G11,IF(K$14<=$H10,$H11,IF(K$14<=$I10,$I11,IF(K$14<=$J10,$J11,0))))))))) -> 2.5 | L17: =IF(L$14<=$B10,$B11,IF(L$14<=$C10,$C11,IF(L$14<=$D10,$D11,IF(L$14<=$E10,$E11,IF(L$14<=$F10,$F11,IF(L$14<=$G10,$G11,IF(L$14<=$H10,$H11,IF(L$14<=$I10,$I11,IF(L$14<=$J10,$J11,0))))))))) -> 5 | ... AQ17: =IF(AQ$14<=$B10,$B11,IF(AQ$14<=$C10,$C11,IF(AQ$14<=$D10,$D11,IF(AQ$14<=$E10,$E11,IF(AQ$14<=$F10,$F11,IF(AQ$14<=$G10,$G11,IF(AQ$14<=$H10,$H11,IF(AQ$14<=$I10,$I11,IF(AQ$14<=$J10,$J11,0))))))))) -> 6.9
A18: New PDI 2030 | E18: 0 | F18: 0 | G18: 0 | H18: 0 | I18: 0 | J18: 0 | K18: 0 | L18: 0 | M18: 0 | N18: 0 | O18: 0 | P18: 0 | Q18: 0 | R18: 0 | S18: 0 | T18: 0 | U18: 0 | V18: 0 | W18: 0 | X18: 0 | Y18: 0 | Z18: 0 | AA18: 0 | AB18: 0 | AC18: 0 | AD18: 0 | AE18: 0 | AF18: 0 | AG18: 0 | AH18: 0 | AI18: 0 | AJ18: 0 | AK18: 0 | AL18: 0 | AM18: 0 | AN18: 0 | AO18: 0 | AP18: 0 | AQ18: 0
A20: Principal Amortization | D20: 44227 | E20: =EDATE(D20,6) -> 44408 | F20: =EDATE(E20,6) -> 44592 | G20: =EDATE(F20,6) -> 44773 | H20: =EDATE(G20,6) -> 44957 | I20: =EDATE(H20,6) -> 45138 | J20: =EDATE(I20,6) -> 45322 | K20: =EDATE(J20,6) -> 45504 | L20: =EDATE(K20,6) -> 45688 | ... AQ20: =EDATE(AP20,6) -> 51348
A21: New 2030 | E21: =IF(AND(E$20>='NBs List'!$C3,E$20<='NBs List'!$G3),'NBs List'!$B3,0) -> 0 | F21: =IF(AND(F$20>='NBs List'!$C3,F$20<='NBs List'!$G3),'NBs List'!$B3,0) -> 0 | G21: =IF(AND(G$20>='NBs List'!$C3,G$20<='NBs List'!$G3),'NBs List'!$B3,0) -> 0 | H21: =IF(AND(H$20>='NBs List'!$C3,H$20<='NBs List'!$G3),'NBs List'!$B3,0) -> 0 | I21: =IF(AND(I$20>='NBs List'!$C3,I$20<='NBs List'!$G3),'NBs List'!$B3,0) -> 0 | J21: =IF(AND(J$20>='NBs List'!$C3,J$20<='NBs List'!$G3),'NBs List'!$B3,0) -> 0 | K21: =IF(AND(K$20>='NBs List'!$C3,K$20<='NBs List'!$G3),'NBs List'!$B3,0) -> 0 | L21: =IF(AND(L$20>='NBs List'!$C3,L$20<='NBs List'!$G3),'NBs List'!$B3,0) -> 0 | ... AQ21: =IF(AND(AQ$20>='NBs List'!$C3,AQ$20<='NBs List'!$G3),'NBs List'!$B3,0) -> 0
A22: New 2035 | E22: =IF(AND(E$20>='NBs List'!$C4,E$20<='NBs List'!$G4),'NBs List'!$B4,0) -> 0 | F22: =IF(AND(F$20>='NBs List'!$C4,F$20<='NBs List'!$G4),'NBs List'!$B4,0) -> 0 | G22: =IF(AND(G$20>='NBs List'!$C4,G$20<='NBs List'!$G4),'NBs List'!$B4,0) -> 0 | H22: =IF(AND(H$20>='NBs List'!$C4,H$20<='NBs List'!$G4),'NBs List'!$B4,0) -> 0 | I22: =IF(AND(I$20>='NBs List'!$C4,I$20<='NBs List'!$G4),'NBs List'!$B4,0) -> 0 | J22: =IF(AND(J$20>='NBs List'!$C4,J$20<='NBs List'!$G4),'NBs List'!$B4,0) -> 0 | K22: =IF(AND(K$20>='NBs List'!$C4,K$20<='NBs List'!$G4),'NBs List'!$B4,0) -> 0 | L22: =IF(AND(L$20>='NBs List'!$C4,L$20<='NBs List'!$G4),'NBs List'!$B4,0) -> 0 | ... AQ22: =IF(AND(AQ$20>='NBs List'!$C4,AQ$20<='NBs List'!$G4),'NBs List'!$B4,0) -> 0
A23: New 2040 | E23: =IF(AND(E$20>='NBs List'!$C5,E$20<='NBs List'!$G5),'NBs List'!$B5,0) -> 0 | F23: =IF(AND(F$20>='NBs List'!$C5,F$20<='NBs List'!$G5),'NBs List'!$B5,0) -> 0 | G23: =IF(AND(G$20>='NBs List'!$C5,G$20<='NBs List'!$G5),'NBs List'!$B5,0) -> 0 | H23: =IF(AND(H$20>='NBs List'!$C5,H$20<='NBs List'!$G5),'NBs List'!$B5,0) -> 0 | I23: =IF(AND(I$20>='NBs List'!$C5,I$20<='NBs List'!$G5),'NBs List'!$B5,0) -> 0 | J23: =IF(AND(J$20>='NBs List'!$C5,J$20<='NBs List'!$G5),'NBs List'!$B5,0) -> 0 | K23: =IF(AND(K$20>='NBs List'!$C5,K$20<='NBs List'!$G5),'NBs List'!$B5,0) -> 0 | L23: =IF(AND(L$20>='NBs List'!$C5,L$20<='NBs List'!$G5),'NBs List'!$B5,0) -> 0 | ... AQ23: =IF(AND(AQ$20>='NBs List'!$C5,AQ$20<='NBs List'!$G5),'NBs List'!$B5,0) -> 10
A24: New PDI 2030 | E24: =IF(AND(E$20>='NBs List'!$C6,E$20<='NBs List'!$G6),'NBs List'!$B6,0) -> 0 | F24: =IF(AND(F$20>='NBs List'!$C6,F$20<='NBs List'!$G6),'NBs List'!$B6,0) -> 0 | G24: =IF(AND(G$20>='NBs List'!$C6,G$20<='NBs List'!$G6),'NBs List'!$B6,0) -> 0 | H24: =IF(AND(H$20>='NBs List'!$C6,H$20<='NBs List'!$G6),'NBs List'!$B6,0) -> 0 | I24: =IF(AND(I$20>='NBs List'!$C6,I$20<='NBs List'!$G6),'NBs List'!$B6,0) -> 0 | J24: =IF(AND(J$20>='NBs List'!$C6,J$20<='NBs List'!$G6),'NBs List'!$B6,0) -> 0 | K24: =IF(AND(K$20>='NBs List'!$C6,K$20<='NBs List'!$G6),'NBs List'!$B6,0) -> 0 | L24: =IF(AND(L$20>='NBs List'!$C6,L$20<='NBs List'!$G6),'NBs List'!$B6,0) -> 0 | ... AQ24: =IF(AND(AQ$20>='NBs List'!$C6,AQ$20<='NBs List'!$G6),'NBs List'!$B6,0) -> 0
A26: Time | D26: 44227 | E26: =EDATE(D26,6) -> 44408 | F26: =EDATE(E26,6) -> 44592 | G26: =EDATE(F26,6) -> 44773 | H26: =EDATE(G26,6) -> 44957 | I26: =EDATE(H26,6) -> 45138 | J26: =EDATE(I26,6) -> 45322 | K26: =EDATE(J26,6) -> 45504 | L26: =EDATE(K26,6) -> 45688 | ... AQ26: =EDATE(AP26,6) -> 51348
A27: New 2030 | E27: =(E$26-$B$2)/360 -> 0.90833333 | F27: =(F$26-$B$2)/360 -> 1.4194444 | G27: =(G$26-$B$2)/360 -> 1.9222222 | H27: =(H$26-$B$2)/360 -> 2.4333333 | I27: =(I$26-$B$2)/360 -> 2.9361111 | J27: =(J$26-$B$2)/360 -> 3.4472222 | K27: =(K$26-$B$2)/360 -> 3.9527778 | L27: =(L$26-$B$2)/360 -> 4.4638889 | ... AQ27: =(AQ$26-$B$2)/360 -> 20.186111
A28: New 2035 | E28: =(E$26-$B$2)/360 -> 0.90833333 | F28: =(F$26-$B$2)/360 -> 1.4194444 | G28: =(G$26-$B$2)/360 -> 1.9222222 | H28: =(H$26-$B$2)/360 -> 2.4333333 | I28: =(I$26-$B$2)/360 -> 2.9361111 | J28: =(J$26-$B$2)/360 -> 3.4472222 | K28: =(K$26-$B$2)/360 -> 3.9527778 | L28: =(L$26-$B$2)/360 -> 4.4638889 | ... AQ28: =(AQ$26-$B$2)/360 -> 20.186111
A29: New 2040 | E29: =(E$26-$B$2)/360 -> 0.90833333 | F29: =(F$26-$B$2)/360 -> 1.4194444 | G29: =(G$26-$B$2)/360 -> 1.9222222 | H29: =(H$26-$B$2)/360 -> 2.4333333 | I29: =(I$26-$B$2)/360 -> 2.9361111 | J29: =(J$26-$B$2)/360 -> 3.4472222 | K29: =(K$26-$B$2)/360 -> 3.9527778 | L29: =(L$26-$B$2)/360 -> 4.4638889 | ... AQ29: =(AQ$26-$B$2)/360 -> 20.186111
A30: New PDI 2030 | E30: =(E$26-$B$2)/360 -> 0.90833333 | F30: =(F$26-$B$2)/360 -> 1.4194444 | G30: =(G$26-$B$2)/360 -> 1.9222222 | H30: =(H$26-$B$2)/360 -> 2.4333333 | I30: =(I$26-$B$2)/360 -> 2.9361111 | J30: =(J$26-$B$2)/360 -> 3.4472222 | K30: =(K$26-$B$2)/360 -> 3.9527778 | L30: =(L$26-$B$2)/360 -> 4.4638889 | ... AQ30: =(AQ$26-$B$2)/360 -> 20.186111
A32: Discounted Cashflows | D32: 44227 | E32: =EDATE(D32,6) -> 44408 | F32: =EDATE(E32,6) -> 44592 | G32: =EDATE(F32,6) -> 44773 | H32: =EDATE(G32,6) -> 44957 | I32: =EDATE(H32,6) -> 45138 | J32: =EDATE(I32,6) -> 45322 | K32: =EDATE(J32,6) -> 45504 | L32: =EDATE(K32,6) -> 45688 | ... AQ32: =EDATE(AP32,6) -> 51348
A33: New 2030 | E33: =(E15/2+E21)/(1+$B$1)^E27 -> 0.22975943 | F33: =(F15/2+F21)/(1+$B$1)^F27 -> 2.1909948 | G33: =(G15/2+G21)/(1+$B$1)^G27 -> 2.0909601 | H33: =(H15/2+H21)/(1+$B$1)^H27 -> 2.1933423 | I33: =(I15/2+I21)/(1+$B$1)^I27 -> 2.0932004 | J33: =(J15/2+J21)/(1+$B$1)^J27 -> 2.1775462 | K33: =(K15/2+K21)/(1+$B$1)^K27 -> 2.077589 | L33: =(L15/2+L21)/(1+$B$1)^L27 -> 2.2783764 | ... AQ33: =(AQ15/2+AQ21)/(1+$B$1)^AQ27 -> 0
A34: New 2035 | E34: =(E16/2+E22)/(1+$B$1)^E28 -> 0.22975943 | F34: =(F16/2+F22)/(1+$B$1)^F28 -> 0.43819896 | G34: =(G16/2+G22)/(1+$B$1)^G28 -> 0.41819201 | H34: =(H16/2+H22)/(1+$B$1)^H28 -> 0.99697379 | I34: =(I16/2+I22)/(1+$B$1)^I28 -> 0.95145474 | J34: =(J16/2+J22)/(1+$B$1)^J28 -> 1.2702353 | K34: =(K16/2+K22)/(1+$B$1)^K28 -> 1.2119269 | L34: =(L16/2+L22)/(1+$B$1)^L28 -> 1.8160971 | ... AQ34: =(AQ16/2+AQ22)/(1+$B$1)^AQ28 -> 0
A35: New 2040 | E35: =(E17/2+E23)/(1+$B$1)^E29 -> 0.22975943 | F35: =(F17/2+F23)/(1+$B$1)^F29 -> 0.21909948 | G35: =(G17/2+G23)/(1+$B$1)^G29 -> 0.20909601 | H35: =(H17/2+H23)/(1+$B$1)^H29 -> 0.59818428 | I35: =(I17/2+I23)/(1+$B$1)^I29 -> 0.57087284 | J35: =(J17/2+J23)/(1+$B$1)^J29 -> 0.9073109 | K35: =(K17/2+K23)/(1+$B$1)^K29 -> 0.86566207 | L35: =(L17/2+L23)/(1+$B$1)^L29 -> 1.6509974 | ... AQ35: =(AQ17/2+AQ23)/(1+$B$1)^AQ29 -> 2.0600148
A36: New PDI 2030 | E36: =(E18/2+E24)/(1+$B$1)^E30 -> 0 | F36: =(F18/2+F24)/(1+$B$1)^F30 -> 0 | G36: =(G18/2+G24)/(1+$B$1)^G30 -> 0 | H36: =(H18/2+H24)/(1+$B$1)^H30 -> 0 | I36: =(I18/2+I24)/(1+$B$1)^I30 -> 0 | J36: =(J18/2+J24)/(1+$B$1)^J30 -> 0 | K36: =(K18/2+K24)/(1+$B$1)^K30 -> 0 | L36: =(L18/2+L24)/(1+$B$1)^L30 -> 0 | ... AQ36: =(AQ18/2+AQ24)/(1+$B$1)^AQ30 -> 0

Sheet EBs & NBs Prices
A1: NY Bonds | AO1: Euro (Luxembourg) Bonds
A2: Sdate | B2: 43753 | N2: Sdate | O2: 43753 | AA2: Sdate | AB2: 44068 | AI2: Sdate | AJ2: 44068 | AO2: Sdate | AP2: 43753 | BB2: Sdate | BC2: 43753 | BO2: Sdate | BP2: 44068 | BW2: Sdate | BX2: 44068
A3: Edate | B3: 44484 | N3: Edate | O3: 44484 | AA3: Edate | AB3: 44484 | AI3: Edate | AJ3: 44484 | AO3: Edate | AP3: 44484 | BB3: Edate | BC3: 44484 | BO3: Edate | BP3: 44484 | BW3: Edate | BX3: 44484
A4: Frequency | B4: D | N4: Frequency | O4: D | AA4: Frequency | AB4: D | AI4: Frequency | AJ4: D | AO4: Frequency | AP4: D | BB4: Frequency | BC4: D | BO4: Frequency | BP4: D | BW4: Frequency | BX4: D
A5: Currency | B5: USD | N5: Currency | O5: USD | AA5: Currency | AB5: USD | AI5: Currency | AJ5: USD | AO5: Currency | AP5: USD | AR5: 43983 | BB5: Currency | BC5: USD | BO5: Currency | BP5: USD | BW5: Currency | BX5: USD
A6: Null Handling | B6: 'NA' | N6: Null Handling | O6: 'NA' | AA6: Null Handling | AB6: 'NA' | AI6: Null Handling | AJ6: 'NA' | AO6: Null Handling | AP6: 'NA' | AR6: 44089 | BB6: Null Handling | BC6: 'NA' | BO6: Null Handling | BP6: 'NA' | BW6: Null Handling | BX6: 'NA'
A7: Row Header | B7: CalcDate | N7: Row Header | O7: CalcDate | AA7: Row Header | AB7: CalcDate | AI7: Row Header | AJ7: CalcDate | AO7: Row Header | AP7: CalcDate | BB7: Row Header | BC7: CalcDate | BO7: Row Header | BP7: CalcDate | BW7: Row Header | BX7: CalcDate
A8: Column Header | B8: In | N8: Column Header | O8: In | AA8: Column Header | AB8: In | AI8: Column Header | AJ8: In | AO8: Column Header | AP8: In | BB8: Column Header | BC8: In | BO8: Column Header | BP8: In | BW8: Column Header | BX8: In
A9: Data Item | B9: TR.MidPrice | N9: Data Item | O9: TR.MidYield | AA9: Data Item | AB9: TR.MidYield | AI9: Data Item | AJ9: TR.MidPrice | AO9: Data Item | AP9: TR.MidPrice | BB9: Data Item | BC9: TR.MidYield | BO9: Data Item | BP9: TR.MidYield | BW9: Data Item | BX9: TR.MidPrice
AE11: ZC bond | AM11: ZC bond | BS11: ZC bond | CA11: ZC bond
A12: Eligible Bonds | B12: 10.750% Notes due March 28, 2022 | C12: 8.750% Notes due June 2, 2023 | D12: 7.950% Notes due June 20, 2024 | E12: 7.875% Notes due March 27, 2025 | F12: 9.650% Notes due December 13, 2026 | G12: 9.625% Notes due June 2, 2027 | H12: 8.875% Notes due October 23, 2027 | I12: 7.875% Notes due January 23, 2028 | J12: 10.750% Notes due January 31, 2029 | K12: 9.500% Notes due March 27, 2030 | N12: Eligible Bonds | O12: 10.750% Notes due March 28, 2022 | P12: 8.750% Notes due June 2, 2023 | Q12: 7.950% Notes due June 20, 2024 | R12: 7.875% Notes due March 27, 2025 | S12: 9.650% Notes due December 13, 2026 | T12: 9.625% Notes due June 2, 2027 | U12: 8.875% Notes due October 23, 2027 | V12: 7.875% Notes due January 23, 2028 | W12: 10.750% Notes due January 31, 2029 | X12: 9.500% Notes due March 27, 2030 | AA12: New Bonds | AB12: ECUAD / ECGV 5.500 31-Jul-2030 | AC12: ECUAD / ECGV 2.500 31-Jul-2035 | AD12: ECUAD / ECGV 1.500 31-Jul-2040 | AE12: ECUAD / ECGV 31-Jul-2030 | AI12: New Bonds | AJ12: ECUAD / ECGV 5.500 31-Jul-2030 | AK12: ECUAD / ECGV 2.500 31-Jul-2035 | AL12: ECUAD / ECGV 1.500 31-Jul-2040 | AM12: ECUAD / ECGV 31-Jul-2030 | AO12: Eligible Bonds | AP12: 10.750% Notes due March 28, 2022 | AQ12: 8.750% Notes due June 2, 2023 | AR12: 7.950% Notes due June 20, 2024 | AS12: 7.875% Notes due March 27, 2025 | AT12: 9.650% Notes due December 13, 2026 | AU12: 9.625% Notes due June 2, 2027 | AV12: 8.875% Notes due October 23, 2027 | AW12: 7.875% Notes due January 23, 2028 | AX12: 10.750% Notes due January 31, 2029 | AY12: 9.500% Notes due March 27, 2030 | BB12: Eligible Bonds | BC12: 10.750% Notes due March 28, 2022 | BD12: 8.750% Notes due June 2, 2023 | BE12: 7.950% Notes due June 20, 2024 | BF12: 7.875% Notes due March 27, 2025 | BG12: 9.650% Notes due December 13, 2026 | BH12: 9.625% Notes due June 2, 2027 | BI12: 8.875% Notes due October 23, 2027 | BJ12: 7.875% Notes due January 23, 2028 | BK12: 10.750% Notes due January 31, 2029 | BL12: 9.500% Notes due March 27, 2030 | BO12: New Bonds | BP12: ECUAD / ECGV 5.500 31-Jul-2030 | BQ12: ECUAD / ECGV 2.500 31-Jul-2035 | BR12: ECUAD / ECGV 1.500 31-Jul-2040 | BS12: ECUAD / ECGV 31-Jul-2030 | BW12: New Bonds | BX12: ECUAD / ECGV 5.500 31-Jul-2030 | BY12: ECUAD / ECGV 2.500 31-Jul-2035 | BZ12: ECUAD / ECGV 1.500 31-Jul-2040 | CA12: ECUAD / ECGV 31-Jul-2030
B13: XS1458516967 | C13: XS1626768656 | D13: XS1080331181 | E13: XS2058848826 | F13: XS1535072109 | G13: XS1626529157 | H13: XS1707041429 | I13: XS1755432363 | J13: XS1929377015 | K13: XS2058866307 | O13: XS1458516967 | P13: XS1626768656 | Q13: XS1080331181 | R13: XS2058848826 | S13: XS1535072109 | T13: XS1626529157 | U13: XS1707041429 | V13: XS1755432363 | W13: XS1929377015 | X13: XS2058866307 | AB13: XS2214238102 | AC13: XS2214238524 | AD13: XS2214239258 | AE13: XS2214239688 | AJ13: XS2214238102 | AK13: XS2214238524 | AL13: XS2214239258 | AM13: XS2214239688 | AP13: XS1458514673 | AQ13: XS1626768730 | AR13: XS1080330704 | AS13: XS2058845210 | AT13: XS1535071986 | AU13: XS1626530320 | AV13: XS1707041262 | AW13: XS1755429732 | AX13: XS1929376710 | AY13: XS2058864948 | BC13: XS1458514673 | BD13: XS1626768730 | BE13: XS1080330704 | BF13: XS2058845210 | BG13: XS1535071986 | BH13: XS1626530320 | BI13: XS1707041262 | BJ13: XS1755429732 | BK13: XS1929376710 | BL13: XS2058864948 | BP13: XS2214237807 | BQ13: XS2214238441 | BR13: XS2214239175 | BS13: XS2214239506 | BX13: XS2214237807 | BY13: XS2214238441 | BZ13: XS2214239175 | CA13: XS2214239506
A14: Updated at 19:14:14 | B14: XS1458516967 | C14: XS1626768656 | D14: XS1080331181 | E14: XS2058848826 | F14: XS1535072109 | G14: XS1626529157 | H14: XS1707041429 | I14: XS1755432363 | J14: XS1929377015 | K14: XS2058866307 | N14: Updated at 19:14:14 | O14: XS1458516967 | P14: XS1626768656 | Q14: XS1080331181 | R14: XS2058848826 | S14: XS1535072109 | T14: XS1626529157 | U14: XS1707041429 | V14: XS1755432363 | W14: XS1929377015 | X14: XS2058866307 | AA14: Updated at 19:14:14 | AB14: XS2214238102 | AC14: XS2214238524 | AD14: XS2214239258 | AE14: XS2214239688 | AI14: Updated at 19:14:14 | AJ14: XS2214238102 | AK14: XS2214238524 | AL14: XS2214239258 | AM14: XS2214239688 | AO14: Updated at 19:14:14 | AP14: XS1458514673 | AQ14: XS1626768730 | AR14: XS1080330704 | AS14: XS2058845210 | AT14: XS1535071986 | AU14: XS1626530320 | AV14: XS1707041262 | AW14: XS1755429732 | AX14: XS1929376710 | AY14: XS2058864948 | BB14: Updated at 19:14:14 | BC14: XS1458514673 | BD14: XS1626768730 | BE14: XS1080330704 | BF14: XS2058845210 | BG14: XS1535071986 | BH14: XS1626530320 | BI14: XS1707041262 | BJ14: XS1755429732 | BK14: XS1929376710 | BL14: XS2058864948 | BO14: Updated at 19:14:14 | BP14: XS2214237807 | BQ14: XS2214238441 | BR14: XS2214239175 | BS14: XS2214239506 | BW14: Updated at 19:14:14 | BX14: XS2214237807 | BY14: XS2214238441 | BZ14: XS2214239175 | CA14: XS2214239506
A15: 43753 | B15: 104.875 | C15: 101.5 | D15: 92.6 | E15: 90.4425 | F15: 101 | G15: 101 | H15: 97.125 | I15: 93.25 | J15: 99.15 | K15: 97.9885 | N15: 43753 | O15: 8.49765 | P15: 8.25785 | Q15: 9.96 | R15: 10.20405 | S15: 9.45 | T15: 9.4345 | U15: 9.39315 | V15: 9.0487 | W15: 10.89 | X15: 9.8105 | AA15: 44068 | AB15: NA | AC15: NA | AD15: NA | AE15: NA | AI15: 44068 | AJ15: NA | AK15: NA | AL15: NA | AM15: NA | AO15: 43753 | AP15: 100 | AQ15: 101.19 | AR15: 92.6 | AS15: 90.442 | AT15: 96.945 | AU15: 96.27 | AV15: 92.97 | AW15: 88 | AX15: 99.15 | AY15: 99.43 | BB15: 43753 | BC15: 10.74 | BD15: 8.36 | BE15: 9.96 | BF15: 10.2 | BG15: 10.26 | BH15: 10.34 | BI15: 10.18 | BJ15: 10.04 | BK15: 10.89 | BL15: 9.59 | BO15: 44068 | BP15: NA | BQ15: NA | BR15: NA | BS15: NA | BW15: 44068 | BX15: NA | BY15: NA | BZ15: NA | CA15: NA
A16: 43754 | B16: 102.375 | C16: 98.375 | D16: 94.5 | E16: 92.046 | F16: 97.375 | G16: 96.875 | H16: 93.25 | I16: 89.875 | J16: 100.875 | K16: 94.7265 | N16: 43754 | O16: 9.63135 | P16: 9.28295 | Q16: 9.43 | R16: 9.79305 | S16: 10.17 | T16: 10.22115 | U16: 10.1245 | V16: 9.67895 | W16: 10.59 | X16: 10.33555 | AA16: 44069 | AB16: NA | AC16: NA | AD16: NA | AE16: NA | AI16: 44069 | AJ16: NA | AK16: NA | AL16: NA | AM16: NA | AO16: 43754 | AP16: 102.375 | AQ16: 101.19 | AR16: 94.5 | AS16: 92.046 | AT16: 97.375 | AU16: 96.5 | AV16: 93.25 | AW16: 88 | AX16: 100.875 | AY16: 99.43 | BB16: 43754 | BC16: 9.63 | BD16: 8.36 | BE16: 9.43 | BF16: 9.79 | BG16: 10.17 | BH16: 10.29 | BI16: 10.12 | BJ16: 10.04 | BK16: 10.59 | BL16: 9.59 | BO16: 44069 | BP16: NA | BQ16: NA | BR16: NA | BS16: NA | BW16: 44069 | BX16: NA | BY16: NA | BZ16: NA | CA16: NA
A17: 43755 | B17: 104.25 | C17: 99.25 | D17: 96 | E17: 92.948 | F17: 98.25 | G17: 97.75 | H17: 94 | I17: 90.25 | J17: 101.125 | K17: 94.977 | N17: 43755 | O17: 8.7694 | P17: 8.99255 | Q17: 9.01 | R17: 9.567 | S17: 9.99 | T17: 10.0512 | U17: 9.98105 | V17: 9.6087 | W17: 10.55 | X17: 10.29445 | AA17: 44070 | AB17: NA | AC17: NA | AD17: NA | AE17: NA | AI17: 44070 | AJ17: NA | AK17: NA | AL17: NA | AM17: NA | AO17: 43755 | AP17: 104.25 | AQ17: 98.395 | AR17: 96 | AS17: 92.948 | AT17: 97.25 | AU17: 95.915 | AV17: 93 | AW17: 88 | AX17: 101.125 | AY17: 94.977 | BB17: 43755 | BC17: 8.77 | BD17: 9.28 | BE17: 9.01 | BF17: 9.57 | BG17: 10.2 | BH17: 10.41 | BI17: 10.17 | BJ17: 10.04 | BK17: 10.55 | BL17: 10.29 | BO17: 44070 | BP17: NA | BQ17: NA | BR17: NA | BS17: NA | BW17: 44070 | BX17: NA | BY17: NA | BZ17: NA | CA17: NA
A18: 43756 | B18: 104.25 | C18: 99.125 | D18: 95.125 | E18: 93.2015 | F18: 97.75 | G18: 97.375 | H18: 93.875 | I18: 90 | J18: 101.125 | K18: 94.9775 | N18: 43756 | O18: 8.76715 | P18: 9.03435 | Q18: 9.26 | R18: 9.504 | S18: 10.09 | T18: 10.1243 | U18: 10.00545 | V18: 9.65675 | W18: 10.55 | X18: 10.29445 | AA18: 44071 | AB18: NA | AC18: NA | AD18: NA | AE18: NA | AI18: 44071 | AJ18: NA | AK18: NA | AL18: NA | AM18: NA | AO18: 43756 | AP18: 104.25 | AQ18: 98.815 | AR18: 95.125 | AS18: 93.201 | AT18: 97.75 | AU18: 95.995 | AV18: 92.985 | AW18: 88 | AX18: 101.125 | AY18: 95.53 | BB18: 43756 | BC18: 8.77 | BD18: 9.14 | BE18: 9.26 | BF18: 9.5 | BG18: 10.09 | BH18: 10.4 | BI18: 10.18 | BJ18: 10.04 | BK18: 10.55 | BL18: 10.2 | BO18: 44071 | BP18: NA | BQ18: NA | BR18: NA | BS18: NA | BW18: 44071 | BX18: NA | BY18: NA | BZ18: NA | CA18: NA
A19: 43759 | B19: 103.75 | C19: 98.875 | D19: 95 | E19: 93.2035 | F19: 97.75 | G19: 97 | H19: 93.25 | I19: 88.875 | J19: 100.5 | K19: 94.9775 | N19: 43759 | O19: 8.99225 | P19: 9.11785 | Q19: 9.29 | R19: 9.50405 | S19: 10.1 | T19: 10.19775 | U19: 10.1266 | V19: 9.87385 | W19: 10.66 | X19: 10.2945 | AA19: 44074 | AB19: NA | AC19: NA | AD19: NA | AE19: NA | AI19: 44074 | AJ19: NA | AK19: NA | AL19: NA | AM19: NA | AO19: 43759 | AP19: 103.75 | AQ19: 98.875 | AR19: 95 | AS19: 93.203 | AT19: 97.75 | AU19: 97 | AV19: 93.25 | AW19: 88 | AX19: 100.5 | AY19: 95.545 | BB19: 43759 | BC19: 8.99 | BD19: 9.12 | BE19: 9.29 | BF19: 9.5 | BG19: 10.1 | BH19: 10.2 | BI19: 10.13 | BJ19: 10.04 | BK19: 10.66 | BL19: 10.2 | BO19: 44074 | BP19: 3.44 | BQ19: 3.71 | BR19: 3.69 | BS19: NA | BW19: 44074 | BX19: 75.5 | BY19: 63.5 | BZ19: 55.25 | CA19: NA
A20: 43760 | B20: 104.375 | C20: 99.125 | D20: 95.625 | E20: 93.702 | F20: 98.375 | G20: 97.625 | H20: 94.25 | I20: 89.75 | J20: 101.25 | K20: 95.854 | N20: 43760 | O20: 8.70615 | P20: 9.03495 | Q20: 9.12 | R20: 9.38 | S20: 9.97 | T20: 10.07605 | U20: 9.93405 | V20: 9.70545 | W20: 10.53 | X20: 10.15145 | AA20: 44075 | AB20: NA | AC20: NA | AD20: NA | AE20: NA | AI20: 44075 | AJ20: NA | AK20: NA | AL20: NA | AM20: NA | AO20: 43760 | AP20: 104.375 | AQ20: 99.185 | AR20: 95.625 | AS20: 93.702 | AT20: 98.375 | AU20: 97.625 | AV20: 94.25 | AW20: 88 | AX20: 101.25 | AY20: 95.854 | BB20: 43760 | BC20: 8.71 | BD20: 9.01 | BE20: 9.12 | BF20: 9.38 | BG20: 9.97 | BH20: 10.08 | BI20: 9.93 | BJ20: 10.04 | BK20: 10.53 | BL20: 10.15 | BO20: 44075 | BP20: 3.44 | BQ20: 3.71 | BR20: 3.69 | BS20: NA | BW20: 44075 | BX20: 75.5 | BY20: 63.5 | BZ20: 55.25 | CA20: NA
A21: 43761 | B21: 103.875 | C21: 98.75 | D21: 94.75 | E21: 93.2005 | F21: 97.25 | G21: 96.375 | H21: 92.75 | I21: 88.875 | J21: 99.875 | K21: 95.854 | N21: 43761 | O21: 8.93125 | P21: 9.16035 | Q21: 9.36 | R21: 9.50595 | S21: 10.2 | T21: 10.3212 | U21: 10.2243 | V21: 9.8748 | W21: 10.77 | X21: 10.15145 | AA21: 44076 | AB21: NA | AC21: NA | AD21: NA | AE21: NA | AI21: 44076 | AJ21: NA | AK21: NA | AL21: NA | AM21: NA | AO21: 43761 | AP21: 103.875 | AQ21: 98.75 | AR21: 94.75 | AS21: 93.201 | AT21: 97.25 | AU21: 97.327 | AV21: 92.75 | AW21: 88 | AX21: 99.875 | AY21: 94.96 | BB21: 43761 | BC21: 8.93 | BD21: 9.16 | BE21: 9.36 | BF21: 9.51 | BG21: 10.2 | BH21: 10.13 | BI21: 10.22 | BJ21: 10.04 | BK21: 10.77 | BL21: 10.3 | BO21: 44076 | BP21: 3.44 | BQ21: 3.71 | BR21: 3.69 | BS21: NA | BW21: 44076 | BX21: 75.5 | BY21: 63.5 | BZ21: 55.25 | CA21: NA
A22: 43762 | B22: 105.125 | C22: 100 | D22: 95.875 | E22: 93.207 | F22: 98.75 | G22: 97.875 | H22: 94 | I22: 90 | J22: 101.5 | K22: 95.854 | N22: 43762 | O22: 8.3577 | P22: 8.74575 | Q22: 9.05 | R22: 9.5061 | S22: 9.89 | T22: 10.02825 | U22: 9.9826 | V22: 9.6593 | W22: 10.49 | X22: 10.1516 | AA22: 44077 | AB22: 3.63647 | AC22: 3.797054 | AD22: 3.525146 | AE22: NA | AI22: 44077 | AJ22: 74.125 | AK22: 62.75 | AL22: 57 | AM22: NA | AO22: 43762 | AP22: 105.125 | AQ22: 99.23 | AR22: 95.875 | AS22: 93.207 | AT22: 97.625 | AU22: 96.588 | AV22: 93.25 | AW22: 88 | AX22: 101.5 | AY22: 95.3 | BB22: 43762 | BC22: 8.36 | BD22: 9 | BE22: 9.05 | BF22: 9.51 | BG22: 10.12 | BH22: 10.28 | BI22: 10.13 | BJ22: 10.04 | BK22: 10.49 | BL22: 10.24 | BO22: 44077 | BP22: 3.44 | BQ22: 3.71 | BR22: 3.69 | BS22: NA | BW22: 44077 | BX22: 75.5 | BY22: 63.5 | BZ22: 55.25 | CA22: NA
A23: 43763 | B23: 105.5 | C23: 100.375 | D23: 96.25 | E23: 94.2035 | F23: 99.125 | G23: 98.375 | H23: 94.5 | I23: 90.125 | J23: 102 | K23: 95.855 | N23: 43763 | O23: 8.1864 | P23: 8.62235 | Q23: 8.95 | R23: 9.25795 | S23: 9.82 | T23: 9.9318 | U23: 9.88695 | V23: 9.63585 | W23: 10.4 | X23: 10.1514 | AA23: 44078 | AB23: 9.626998 | AC23: 9.428146 | AD23: 9.206656 | AE23: 7.234776 | AI23: 44078 | AJ23: 74.125 | AK23: 62.75 | AL23: 57 | AM23: 49.5 | AO23: 43763 | AP23: 105.5 | AQ23: 100.375 | AR23: 96.25 | AS23: 94.203 | AT23: 99.125 | AU23: 96.802 | AV23: 94.5 | AW23: 89.375 | AX23: 102 | AY23: 96.315 | BB23: 43763 | BC23: 8.19 | BD23: 8.62 | BE23: 8.95 | BF23: 9.26 | BG23: 9.82 | BH23: 10.24 | BI23: 9.89 | BJ23: 9.78 | BK23: 10.4 | BL23: 10.08 | BO23: 44078 | BP23: 3.44 | BQ23: 3.71 | BR23: 3.69 | BS23: NA | BW23: 44078 | BX23: 75.5 | BY23: 63.5 | BZ23: 55.25 | CA23: NA
A24: 43766 | B24: 106 | C24: 100.25 | D24: 96.25 | E24: 94.2055 | F24: 99.125 | G24: 98 | H24: 94.125 | I24: 90.125 | J24: 102.125 | K24: 95.855 | N24: 43766 | O24: 7.9597 | P24: 8.6635 | Q24: 8.95 | R24: 9.2579 | S24: 9.82 | T24: 10.0044 | U24: 9.9589 | V24: 9.6363 | W24: 10.38 | X24: 10.1515 | AA24: 44081 | AB24: 10.231664 | AC24: 9.705758 | AD24: 9.353104 | AE24: 9.536024 | AI24: 44081 | AJ24: 74.125 | AK24: 62.75 | AL24: 57 | AM24: 49.5 | AO24: 43766 | AP24: 106 | AQ24: 100.25 | AR24: 96.25 | AS24: 94.205 | AT24: 99.125 | AU24: 98 | AV24: 94.125 | AW24: 89.375 | AX24: 102.125 | AY24: 96.315 | BB24: 43766 | BC24: 7.96 | BD24: 8.66 | BE24: 8.95 | BF24: 9.26 | BG24: 9.82 | BH24: 10 | BI24: 9.96 | BJ24: 9.78 | BK24: 10.38 | BL24: 10.08 | BO24: 44081 | BP24: 10.23 | BQ24: 9.71 | BR24: 9.35 | BS24: NA | BW24: 44081 | BX24: 74.125 | BY24: 62.75 | BZ24: 57 | CA24: NA
A25: 43767 | B25: 105.875 | C25: 100.5 | D25: 96.5 | E25: 94.1835 | F25: 99.25 | G25: 98.125 | H25: 94.125 | I25: 90.25 | J25: 102 | K25: 95.8285 | N25: 43767 | O25: 8.01555 | P25: 8.57325 | Q25: 8.88 | R25: 9.25795 | S25: 9.79 | T25: 9.9802 | U25: 9.95415 | V25: 9.61245 | W25: 10.4 | X25: 10.1515 | AA25: 44082 | AB25: 10.240271 | AC25: 9.708362 | AD25: 9.355079 | AE25: 9.539663 | AI25: 44082 | AJ25: 74.125 | AK25: 62.75 | AL25: 57 | AM25: 49.5 | AO25: 43767 | AP25: 105.875 | AQ25: 100.5 | AR25: 96.5 | AS25: 94.184 | AT25: 99.25 | AU25: 98.125 | AV25: 94.125 | AW25: 89.765 | AX25: 102 | AY25: 96.465 | BB25: 43767 | BC25: 8.01 | BD25: 8.57 | BE25: 8.88 | BF25: 9.26 | BG25: 9.79 | BH25: 9.98 | BI25: 9.96 | BJ25: 9.7 | BK25: 10.4 | BL25: 10.05 | BO25: 44082 | BP25: 10.24 | BQ25: 9.71 | BR25: 9.36 | BS25: 9.76805 | BW25: 44082 | BX25: 74.125 | BY25: 62.75 | BZ25: 57 | CA25: 49.5
A26: 43768 | B26: 105.5 | C26: 99.75 | D26: 95.75 | E26: 94.2075 | F26: 98.125 | G26: 97.25 | H26: 93 | I26: 89.125 | J26: 100.875 | K26: 95.855 | N26: 43768 | O26: 8.1809 | P26: 8.82885 | Q26: 9.09 | R26: 9.2579 | S26: 10.02 | T26: 10.15055 | U26: 10.17675 | V26: 9.8291 | W26: 10.59 | X26: 10.1515 | AA26: 44083 | AB26: 10.244575 | AC26: 9.710966 | AD26: 9.357054 | AE26: 9.543304 | AI26: 44083 | AJ26: 74.125 | AK26: 62.75 | AL26: 57 | AM26: 49.5 | AO26: 43768 | AP26: 105.5 | AQ26: 99.75 | AR26: 95.75 | AS26: 94.207 | AT26: 98.125 | AU26: 97.728 | AV26: 93 | AW26: 89.765 | AX26: 100.875 | AY26: 95.435 | BB26: 43768 | BC26: 8.18 | BD26: 8.83 | BE26: 9.09 | BF26: 9.26 | BG26: 10.02 | BH26: 10.06 | BI26: 10.18 | BJ26: 9.7 | BK26: 10.59 | BL26: 10.22 | BO26: 44083 | BP26: 10.24 | BQ26: 9.71 | BR26: 9.36 | BS26: 9.77 | BW26: 44083 | BX26: 74.125 | BY26: 62.75 | BZ26: 57 | CA26: 49.5
A27: 43769 | B27: 106.25 | C27: 101 | D27: 96.5 | E27: 94.213 | F27: 98.625 | G27: 97.625 | H27: 93.5 | I27: 89.75 | J27: 101.5 | K27: 95.856 | N27: 43769 | O27: 7.8358 | P27: 8.41705 | Q27: 8.88 | R27: 9.25805 | S27: 9.92 | T27: 10.078 | U27: 10.0801 | V27: 9.7099 | W27: 10.49 | X27: 10.15145 | AA27: 44084 | AB27: 10.25751 | AC27: 9.71879 | AD27: 9.362986 | AE27: 9.554246 | AI27: 44084 | AJ27: 74.125 | AK27: 62.75 | AL27: 57 | AM27: 49.5 | AO27: 43769 | AP27: 106.25 | AQ27: 101 | AR27: 96.5 | AS27: 94.213 | AT27: 98.625 | AU27: 97.753 | AV27: 93.125 | AW27: 89.515 | AX27: 101.5 | AY27: 96.195 | BB27: 43769 | BC27: 7.84 | BD27: 8.42 | BE27: 8.88 | BF27: 9.26 | BG27: 9.92 | BH27: 10.05 | BI27: 10.15 | BJ27: 9.75 | BK27: 10.49 | BL27: 10.1 | BO27: 44084 | BP27: 10.26 | BQ27: 9.72 | BR27: 9.36 | BS27: 9.78 | BW27: 44084 | BX27: 74.125 | BY27: 62.75 | BZ27: 57 | CA27: 49.5
A28: 43770 | B28: 107.5 | C28: 102.375 | D28: 98 | E28: 94.215 | F28: 100 | G28: 98.875 | H28: 94.875 | I28: 91.125 | J28: 102.625 | K28: 95.856 | N28: 43770 | O28: 7.2776 | P28: 7.97035 | Q28: 8.48 | R28: 9.25805 | S28: 9.65 | T28: 9.8366 | U28: 9.8163 | V28: 9.44855 | W28: 10.3 | X28: 10.1515 | AA28: 44085 | AB28: 10.26183 | AC28: 9.721402 | AD28: 9.364965 | AE28: 9.5579 | AI28: 44085 | AJ28: 74.125 | AK28: 62.75 | AL28: 57 | AM28: 49.5 | AO28: 43770 | AP28: 107.5 | AQ28: 102.375 | AR28: 98 | AS28: 94.215 | AT28: 100 | AU28: 98.495 | AV28: 94.875 | AW28: 91.125 | AX28: 102.625 | AY28: 97.645 | BB28: 43770 | BC28: 7.28 | BD28: 7.97 | BE28: 8.48 | BF28: 9.26 | BG28: 9.65 | BH28: 9.91 | BI28: 9.82 | BJ28: 9.45 | BK28: 10.3 | BL28: 9.86 | BO28: 44085 | BP28: 10.26 | BQ28: 9.72 | BR28: 9.36 | BS28: 9.79 | BW28: 44085 | BX28: 74.125 | BY28: 62.75 | BZ28: 57 | CA28: 49.5
A29: 43773 | B29: 108 | C29: 103.125 | D29: 98.625 | E29: 94.217 | F29: 100.875 | G29: 100 | H29: 96 | I29: 92.125 | J29: 103.75 | K29: 95.8565 | N29: 43773 | O29: 7.0539 | P29: 7.7293 | Q29: 8.31 | R29: 9.25805 | S29: 9.47 | T29: 9.62265 | U29: 9.60405 | V29: 9.2617 | W29: 10.11 | X29: 10.15145 | AA29: 44088 | AB29: 10.266142 | AC29: 9.723775 | AD29: 9.366736 | AE29: 9.561555 | AI29: 44088 | AJ29: 74.125 | AK29: 62.75 | AL29: 57 | AM29: 49.5 | AO29: 43773 | AP29: 108 | AQ29: 102.375 | AR29: 98.625 | AS29: 94.217 | AT29: 100.857 | AU29: 100 | AV29: 95.247 | AW29: 92.125 | AX29: 103.75 | AY29: 97.89 | BB29: 43773 | BC29: 7.05 | BD29: 7.97 | BE29: 8.31 | BF29: 9.26 | BG29: 9.48 | BH29: 9.62 | BI29: 9.75 | BJ29: 9.26 | BK29: 10.11 | BL29: 9.83 | BO29: 44088 | BP29: 10.27 | BQ29: 9.72 | BR29: 9.37 | BS29: 9.79 | BW29: 44088 | BX29: 74.125 | BY29: 62.75 | BZ29: 57 | CA29: 49.5
A30: 43774 | B30: 107.375 | C30: 103 | D30: 97.75 | E30: 94.219 | F30: 100.5 | G30: 99.375 | H30: 95.5 | I30: 91.5 | J30: 103.5 | K30: 95.8565 | N30: 43774 | O30: 7.32545 | P30: 7.76875 | Q30: 8.55 | R30: 9.2581 | S30: 9.55 | T30: 9.74135 | U30: 9.69815 | V30: 9.3788 | W30: 10.15 | X30: 10.1515 | AA30: 44089 | AB30: 10.526002 | AC30: 10.304572 | AD30: 9.717253 | AE30: 9.853331 | AI30: 44089 | AJ30: 73 | AK30: 59.5 | AL30: 54.75 | AM30: 48.5 | AO30: 43774 | AP30: 107.375 | AQ30: 103 | AR30: 97.75 | AS30: 94.219 | AT30: 100.5 | AU30: 99.375 | AV30: 95.895 | AW30: 91.5 | AX30: 103.5 | AY30: 98.04 | BB30: 43774 | BC30: 7.32 | BD30: 7.77 | BE30: 8.55 | BF30: 9.26 | BG30: 9.55 | BH30: 9.74 | BI30: 9.62 | BJ30: 9.38 | BK30: 10.15 | BL30: 9.8 | BO30: 44089 | BP30: 10.53 | BQ30: 10.3 | BR30: 9.72 | BS30: 10.1 | BW30: 44089 | BX30: 73 | BY30: 59.5 | BZ30: 54.75 | CA30: 48.5
A31: 43775 | B31: 107.375 | C31: 102.625 | D31: 98.125 | E31: 94.221 | F31: 100.25 | G31: 99.25 | H31: 95.25 | I31: 91.375 | J31: 103 | K31: 95.8565 | N31: 43775 | O31: 7.32185 | P31: 7.8886 | Q31: 8.44 | R31: 9.2581 | S31: 9.6 | T31: 9.76525 | U31: 9.7455 | V31: 9.4027 | W31: 10.23 | X31: 10.15155 | AA31: 44090 | AB31: 10.530456 | AC31: 10.307369 | AD31: 9.719325 | AE31: 9.857108 | AI31: 44090 | AJ31: 73 | AK31: 59.5 | AL31: 54.75 | AM31: 48.5 | AO31: 43775 | AP31: 107.375 | AQ31: 102.625 | AR31: 98.125 | AS31: 94.221 | AT31: 100.25 | AU31: 99.25 | AV31: 95.25 | AW31: 91.375 | AX31: 103 | AY31: 97.725 | BB31: 43775 | BC31: 7.32 | BD31: 7.89 | BE31: 8.44 | BF31: 9.26 | BG31: 9.6 | BH31: 9.77 | BI31: 9.75 | BJ31: 9.4 | BK31: 10.23 | BL31: 9.85 | BO31: 44090 | BP31: 10.53 | BQ31: 10.31 | BR31: 9.72 | BS31: 10.1 | BW31: 44090 | BX31: 73 | BY31: 59.5 | BZ31: 54.75 | CA31: 48.5
A32: 43776 | B32: 107 | C32: 102 | D32: 97.5 | E32: 94.2295 | F32: 99.5 | G32: 98.375 | H32: 94.375 | I32: 90.5 | J32: 102 | K32: 95.858 | N32: 43776 | O32: 7.47445 | P32: 8.08915 | Q32: 8.62 | R32: 9.258 | S32: 9.75 | T32: 9.93395 | U32: 9.9128 | V32: 9.56985 | W32: 10.4 | X32: 10.1515 | AA32: 44091 | AB32: 10.543843 | AC32: 10.31577 | AD32: 9.72555 | AE32: 9.868458 | AI32: 44091 | AJ32: 73 | AK32: 59.5 | AL32: 54.75 | AM32: 48.5 | AO32: 43776 | AP32: 107 | AQ32: 102 | AR32: 97.5 | AS32: 94.229 | AT32: 99.5 | AU32: 98.375 | AV32: 94.375 | AW32: 90.5 | AX32: 102 | AY32: 97.025 | BB32: 43776 | BC32: 7.47 | BD32: 8.09 | BE32: 8.62 | BF32: 9.26 | BG32: 9.75 | BH32: 9.93 | BI32: 9.91 | BJ32: 9.57 | BK32: 10.4 | BL32: 9.96 | BO32: 44091 | BP32: 10.54435 | BQ32: 10.31625 | BR32: 9.726 | BS32: 10.11285 | BW32: 44091 | BX32: 73 | BY32: 59.5 | BZ32: 54.75 | CA32: 48.5
A33: 43777 | B33: 107 | C33: 102.125 | D33: 97.25 | E33: 94.2315 | F33: 99.375 | G33: 98.375 | H33: 94.375 | I33: 90.25 | J33: 101.875 | K33: 95.8585 | N33: 43777 | O33: 7.47095 | P33: 8.0482 | Q33: 8.68 | R33: 9.258 | S33: 9.77 | T33: 9.93415 | U33: 9.913 | V33: 9.61805 | W33: 10.42 | X33: 10.1515 | AA33: 44092 | AB33: 10.548314 | AC33: 10.318574 | AD33: 9.727626 | AE33: 9.872247 | AI33: 44092 | AJ33: 73 | AK33: 59.5 | AL33: 54.75 | AM33: 48.5 | AO33: 43777 | AP33: 107 | AQ33: 102.125 | AR33: 97.25 | AS33: 94.231 | AT33: 99.353 | AU33: 98.375 | AV33: 94.375 | AW33: 90.25 | AX33: 101.875 | AY33: 96.62 | BB33: 43777 | BC33: 7.47 | BD33: 8.05 | BE33: 8.68 | BF33: 9.26 | BG33: 9.78 | BH33: 9.93 | BI33: 9.91 | BJ33: 9.62 | BK33: 10.42 | BL33: 10.03 | BO33: 44092 | BP33: 10.5488 | BQ33: 10.31905 | BR33: 9.7281 | BS33: 10.1168 | BW33: 44092 | BX33: 73 | BY33: 59.5 | BZ33: 54.75 | CA33: 48.5
A34: 43780 | B34: 106.875 | C34: 102.75 | D34: 97.75 | E34: 94.2315 | F34: 99.625 | G34: 98.25 | H34: 94.375 | I34: 90.625 | J34: 101.75 | K34: 95.8585 | N34: 43780 | O34: 7.52685 | P34: 7.846 | Q34: 8.55 | R34: 9.258 | S34: 9.72 | T34: 9.9583 | U34: 9.913 | V34: 9.5465 | W34: 10.44 | X34: 10.1515 | AA34: 44095 | AB34: 10.552789 | AC34: 10.32138 | AD34: 9.729704 | AE34: 9.876039 | AI34: 44095 | AJ34: 73 | AK34: 59.5 | AL34: 54.75 | AM34: 48.5 | AO34: 43780 | AP34: 106.875 | AQ34: 102.75 | AR34: 97.75 | AS34: 94.231 | AT34: 99.625 | AU34: 98.25 | AV34: 94.268 | AW34: 90.625 | AX34: 101.75 | AY34: 96.63 | BB34: 43780 | BC34: 7.53 | BD34: 7.85 | BE34: 8.55 | BF34: 9.26 | BG34: 9.72 | BH34: 9.96 | BI34: 9.93 | BJ34: 9.55 | BK34: 10.44 | BL34: 10.03 | BO34: 44095 | BP34: 10.55 | BQ34: 10.32 | BR34: 9.73 | BS34: 10.12 | BW34: 44095 | BX34: 73 | BY34: 59.5 | BZ34: 54.75 | CA34: 48.5
A35: 43781 | B35: 106.625 | C35: 101.5 | D35: 96.375 | E35: 94.2335 | F35: 98.625 | G35: 97.5 | H35: 93.375 | I35: 89.25 | J35: 100.625 | K35: 95.8585 | N35: 43781 | O35: 7.6356 | P35: 8.2518 | Q35: 8.92 | R35: 9.258 | S35: 9.92 | T35: 10.1045 | U35: 10.10635 | V35: 9.81115 | W35: 10.64 | X35: 10.1515 | AA35: 44096 | AB35: 11.265027 | AC35: 10.652081 | AD35: 9.731783 | AE35: 10.17542 | AI35: 44096 | AJ35: 70 | AK35: 57.75 | AL35: 54.75 | AM35: 47.5 | AO35: 43781 | AP35: 106.625 | AQ35: 101.5 | AR35: 96.375 | AS35: 94.233 | AT35: 98.625 | AU35: 97.5 | AV35: 93.375 | AW35: 89.25 | AX35: 100.625 | AY35: 96 | BB35: 43781 | BC35: 7.63 | BD35: 8.25 | BE35: 8.92 | BF35: 9.26 | BG35: 9.92 | BH35: 10.1 | BI35: 10.11 | BJ35: 9.81 | BK35: 10.64 | BL35: 10.13 | BO35: 44096 | BP35: 11.27 | BQ35: 10.65 | BR35: 9.73 | BS35: 10.12 | BW35: 44096 | BX35: 70 | BY35: 57.75 | BZ35: 54.75 | CA35: 48.5
A36: 43782 | B36: 105.625 | C36: 101.125 | D36: 95.125 | E36: 94.2355 | F36: 97.25 | G36: 95.75 | H36: 92.125 | I36: 88.125 | J36: 99.5 | K36: 95.8585 | N36: 43782 | O36: 8.0849 | P36: 8.37485 | Q36: 9.27 | R36: 9.25805 | S36: 10.2 | T36: 10.45125 | U36: 10.352 | V36: 10.03175 | W36: 10.83 | X36: 10.15155 | AA36: 44097 | AB36: 11.269852 | AC36: 10.654994 | AD36: 10.101295 | AE36: 10.179337 | AI36: 44097 | AJ36: 70 | AK36: 57.75 | AL36: 52.5 | AM36: 47.5 | AO36: 43782 | AP36: 105.625 | AQ36: 101.125 | AR36: 95.125 | AS36: 94.235 | AT36: 97.25 | AU36: 95.75 | AV36: 92.125 | AW36: 88.125 | AX36: 99.5 | AY36: 94.605 | BB36: 43782 | BC36: 8.08 | BD36: 8.37 | BE36: 9.27 | BF36: 9.26 | BG36: 10.2 | BH36: 10.45 | BI36: 10.35 | BJ36: 10.03 | BK36: 10.83 | BL36: 10.36 | BO36: 44097 | BP36: 11.27 | BQ36: 10.65 | BR36: 10.1 | BS36: 10.43935 | BW36: 44097 | BX36: 70 | BY36: 57.75 | BZ36: 52.5 | CA36: 47.5
... A313: 44169 | B313: 51.5 | C313: 51.75 | D313: 51.5 | E313: 51.75 | F313: 51.75 | G313: 51.75 | H313: 51.5 | I313: 51.75 | J313: 51.75 | K313: 51.75 | N313: 44169 | O313: 10.4346 | P313: 10.39205 | Q313: 10.43 | R313: 10.39225 | S313: 10.55 | T313: 10.5555 | U313: 10.435 | V313: 10.3922 | W313: 10.57 | X313: 10.5537 | AA313: 44484 | AB313: 9.061178 | AC313: 9.777326 | AD313: 9.431253 | AE313: 9.580679 | AI313: 44484 | AJ313: 86.25 | AK313: 68.625 | AL313: 62 | AM313: 54.75 | AO313: 44169 | AP313: 51.5 | AQ313: 51.75 | AR313: 51.5 | AS313: 51.75 | AT313: 51.75 | AU313: 51.75 | AV313: 51.5 | AW313: 51.75 | AX313: 51.75 | AY313: 51.75 | BB313: 44169 | BC313: 10.43 | BD313: 10.39 | BE313: 10.43 | BF313: 10.39 | BG313: 10.55 | BH313: 10.55 | BI313: 10.43 | BJ313: 10.39 | BK313: 10.57 | BL313: 10.55 | BO313: 44484 | BP313: 9.06 | BQ313: 9.78 | BR313: 9.43 | BS313: 9.81 | BW313: 44484 | BX313: 86.25 | BY313: 68.625 | BZ313: 62 | CA313: 54.75
A314: 44172 | B314: 52 | C314: 52.25 | D314: 52 | E314: 52.25 | F314: 52.25 | G314: 52.25 | H314: 52 | I314: 52.25 | J314: 52.25 | K314: 52.25 | N314: 44172 | O314: 10.34995 | P314: 10.30785 | Q314: 10.35 | R314: 10.30805 | S314: 10.47 | T314: 10.46965 | U314: 10.35035 | V314: 10.30805 | W314: 10.49 | X314: 10.46785 | AO314: 44172 | AP314: 52 | AQ314: 52.25 | AR314: 52 | AS314: 52.25 | AT314: 52.25 | AU314: 52.25 | AV314: 52 | AW314: 52.25 | AX314: 52.25 | AY314: 52.25 | BB314: 44172 | BC314: 10.35 | BD314: 10.31 | BE314: 10.35 | BF314: 10.31 | BG314: 10.47 | BH314: 10.47 | BI314: 10.35 | BJ314: 10.31 | BK314: 10.49 | BL314: 10.47
A315: 44173 | B315: 52.25 | C315: 52.5 | D315: 52.25 | E315: 52.5 | F315: 52.5 | G315: 52.5 | H315: 52.25 | I315: 52.5 | J315: 52.5 | K315: 52.5 | N315: 44173 | O315: 10.30915 | P315: 10.2673 | Q315: 10.31 | R315: 10.2675 | S315: 10.43 | T315: 10.4284 | U315: 10.3095 | V315: 10.26745 | W315: 10.44 | X315: 10.4266 | AO315: 44173 | AP315: 52.25 | AQ315: 52.5 | AR315: 52.25 | AS315: 52.5 | AT315: 52.5 | AU315: 52.5 | AV315: 52.25 | AW315: 52.5 | AX315: 52.5 | AY315: 52.5 | BB315: 44173 | BC315: 10.31 | BD315: 10.27 | BE315: 10.31 | BF315: 10.27 | BG315: 10.43 | BH315: 10.43 | BI315: 10.31 | BJ315: 10.27 | BK315: 10.44 | BL315: 10.43
A316: 44174 | B316: 52.875 | C316: 53.125 | D316: 52.875 | E316: 53.125 | F316: 53.125 | G316: 53.125 | H316: 52.875 | I316: 53.125 | J316: 53.125 | K316: 53.125 | N316: 44174 | O316: 10.20475 | P316: 10.1635 | Q316: 10.2 | R316: 10.1637 | S316: 10.32 | T316: 10.3225 | U316: 10.2051 | V316: 10.1636 | W316: 10.34 | X316: 10.3207 | AO316: 44174 | AP316: 52.875 | AQ316: 53.125 | AR316: 52.875 | AS316: 53.125 | AT316: 53.125 | AU316: 53.125 | AV316: 52.875 | AW316: 53.125 | AX316: 53.125 | AY316: 53.125 | BB316: 44174 | BC316: 10.2 | BD316: 10.16 | BE316: 10.2 | BF316: 10.16 | BG316: 10.32 | BH316: 10.32 | BI316: 10.2 | BJ316: 10.16 | BK316: 10.34 | BL316: 10.32
A317: 44175 | B317: 52.625 | C317: 52.875 | D317: 52.625 | E317: 52.875 | F317: 52.875 | G317: 52.875 | H317: 52.625 | I317: 52.875 | J317: 52.875 | K317: 52.875 | N317: 44175 | O317: 10.25415 | P317: 10.21265 | Q317: 10.25 | R317: 10.21275 | S317: 10.37 | T317: 10.3734 | U317: 10.2545 | V317: 10.21275 | W317: 10.39 | X317: 10.37165 | AO317: 44175 | AP317: 52.625 | AQ317: 52.875 | AR317: 52.625 | AS317: 52.875 | AT317: 52.875 | AU317: 52.875 | AV317: 52.625 | AW317: 52.875 | AX317: 52.875 | AY317: 52.875 | BB317: 44175 | BC317: 10.25 | BD317: 10.21 | BE317: 10.25 | BF317: 10.21 | BG317: 10.37 | BH317: 10.37 | BI317: 10.25 | BJ317: 10.21 | BK317: 10.39 | BL317: 10.37
A318: 44176 | B318: 52.25 | C318: 52.5 | D318: 52.25 | E318: 52.5 | F318: 52.5 | G318: 52.5 | H318: 52.25 | I318: 52.5 | J318: 52.5 | K318: 52.5 | N318: 44176 | O318: 10.3208 | P318: 10.2788 | Q318: 10.32 | R318: 10.279 | S318: 10.44 | T318: 10.4414 | U318: 10.3211 | V318: 10.279 | W318: 10.46 | X318: 10.4396 | AO318: 44176 | AP318: 52.25 | AQ318: 52.5 | AR318: 52.25 | AS318: 52.5 | AT318: 52.5 | AU318: 52.5 | AV318: 52.25 | AW318: 52.5 | AX318: 52.5 | AY318: 52.5 | BB318: 44176 | BC318: 10.32 | BD318: 10.28 | BE318: 10.32 | BF318: 10.28 | BG318: 10.44 | BH318: 10.44 | BI318: 10.32 | BJ318: 10.28 | BK318: 10.46 | BL318: 10.44
A319: 44179 | B319: 52.25 | C319: 52.5 | D319: 52.25 | E319: 52.5 | F319: 52.5 | G319: 52.5 | H319: 52.25 | I319: 52.5 | J319: 52.5 | K319: 52.5 | N319: 44179 | O319: 10.3231 | P319: 10.28115 | Q319: 10.32 | R319: 10.28125 | S319: 10.44 | T319: 10.444 | U319: 10.32345 | V319: 10.28125 | W319: 10.46 | X319: 10.44215 | AO319: 44179 | AP319: 52.25 | AQ319: 52.5 | AR319: 52.25 | AS319: 52.5 | AT319: 52.5 | AU319: 52.5 | AV319: 52.25 | AW319: 52.5 | AX319: 52.5 | AY319: 52.5 | BB319: 44179 | BC319: 10.32 | BD319: 10.28 | BE319: 10.32 | BF319: 10.28 | BG319: 10.44 | BH319: 10.44 | BI319: 10.32 | BJ319: 10.28 | BK319: 10.46 | BL319: 10.44
A320: 44180 | B320: 51.75 | C320: 52 | D320: 51.75 | E320: 52 | F320: 52 | G320: 52 | H320: 51.75 | I320: 52 | J320: 52 | K320: 52 | N320: 44180 | O320: 10.4121 | P320: 10.36965 | Q320: 10.41 | R320: 10.3698 | S320: 10.53 | T320: 10.53475 | U320: 10.4124 | V320: 10.36975 | W320: 10.55 | X320: 10.5329 | AO320: 44180 | AP320: 51.75 | AQ320: 52 | AR320: 51.75 | AS320: 52 | AT320: 52 | AU320: 52 | AV320: 51.75 | AW320: 52 | AX320: 52 | AY320: 52 | BB320: 44180 | BC320: 10.41 | BD320: 10.37 | BE320: 10.41 | BF320: 10.37 | BG320: 10.53 | BH320: 10.53 | BI320: 10.41 | BJ320: 10.37 | BK320: 10.55 | BL320: 10.53
A321: 44181 | B321: 52.125 | C321: 52.375 | D321: 52.125 | E321: 52.375 | F321: 52.375 | G321: 52.375 | H321: 52.125 | I321: 52.375 | J321: 52.375 | K321: 52.375 | N321: 44181 | O321: 10.34935 | P321: 10.3072 | Q321: 10.35 | R321: 10.30735 | S321: 10.47 | T321: 10.47115 | U321: 10.34965 | V321: 10.30735 | W321: 10.49 | X321: 10.46935 | AO321: 44181 | AP321: 52.125 | AQ321: 52.375 | AR321: 52.125 | AS321: 52.375 | AT321: 52.375 | AU321: 52.375 | AV321: 52.125 | AW321: 52.375 | AX321: 52.375 | AY321: 52.375 | BB321: 44181 | BC321: 10.35 | BD321: 10.31 | BE321: 10.35 | BF321: 10.31 | BG321: 10.47 | BH321: 10.47 | BI321: 10.35 | BJ321: 10.31 | BK321: 10.49 | BL321: 10.47
A322: 44182 | B322: 56.75 | C322: 57 | D322: 56.75 | E322: 57 | F322: 57 | G322: 57 | H322: 56.75 | I322: 57 | J322: 57 | K322: 57 | N322: 44182 | O322: 9.59745 | P322: 9.55945 | Q322: 9.6 | R322: 9.55955 | S322: 9.71 | T322: 9.70765 | U322: 9.59765 | V322: 9.55955 | W322: 9.72 | X322: 9.70605 | AO322: 44182 | AP322: 56.75 | AQ322: 57 | AR322: 56.75 | AS322: 57 | AT322: 57 | AU322: 57 | AV322: 56.75 | AW322: 57 | AX322: 57 | AY322: 57 | BB322: 44182 | BC322: 9.6 | BD322: 9.56 | BE322: 9.6 | BF322: 9.56 | BG322: 9.71 | BH322: 9.71 | BI322: 9.6 | BJ322: 9.56 | BK322: 9.72 | BL322: 9.7
A323: 44183 | B323: 52.5 | C323: 52.75 | D323: 52.5 | E323: 52.75 | F323: 52.75 | G323: 52.75 | H323: 52.5 | I323: 52.75 | J323: 52.75 | K323: 52.75 | N323: 44183 | O323: 10.29405 | P323: 10.2522 | Q323: 10.29 | R323: 10.2524 | S323: 10.41 | T323: 10.41585 | U323: 10.29435 | V323: 10.25235 | W323: 10.43 | X323: 10.4141 | AO323: 44183 | AP323: 52.5 | AQ323: 52.75 | AR323: 52.5 | AS323: 52.75 | AT323: 52.75 | AU323: 52.75 | AV323: 52.5 | AW323: 52.75 | AX323: 52.75 | AY323: 52.75 | BB323: 44183 | BC323: 10.29 | BD323: 10.25 | BE323: 10.29 | BF323: 10.25 | BG323: 10.41 | BH323: 10.41 | BI323: 10.29 | BJ323: 10.25 | BK323: 10.43 | BL323: 10.41
A324: 44186 | B324: 51.75 | C324: 52 | D324: 51.75 | E324: 52 | F324: 52 | G324: 52 | H324: 51.75 | I324: 52 | J324: 52 | K324: 52 | N324: 44186 | O324: 10.42625 | P324: 10.38365 | Q324: 10.43 | R324: 10.38375 | S324: 10.55 | T324: 10.5506 | U324: 10.42655 | V324: 10.38375 | W324: 10.57 | X324: 10.54875 | AO324: 44186 | AP324: 51.75 | AQ324: 52 | AR324: 51.75 | AS324: 52 | AT324: 52 | AU324: 52 | AV324: 51.75 | AW324: 52 | AX324: 52 | AY324: 52 | BB324: 44186 | BC324: 10.43 | BD324: 10.38 | BE324: 10.43 | BF324: 10.38 | BG324: 10.55 | BH324: 10.55 | BI324: 10.43 | BJ324: 10.38 | BK324: 10.57 | BL324: 10.55
A325: 44187 | B325: 51 | C325: 51.25 | D325: 51 | E325: 51.25 | F325: 51.25 | G325: 51.25 | H325: 51 | I325: 51.25 | J325: 51.25 | K325: 51.25 | N325: 44187 | O325: 10.5609 | P325: 10.5175 | Q325: 10.56 | R325: 10.51765 | S325: 10.69 | T325: 10.6878 | U325: 10.5612 | V325: 10.5176 | W325: 10.7 | X325: 10.68595 | AO325: 44187 | AP325: 51 | AQ325: 51.25 | AR325: 51 | AS325: 51.25 | AT325: 51.25 | AU325: 51.25 | AV325: 51 | AW325: 51.25 | AX325: 51.25 | AY325: 51.25 | BB325: 44187 | BC325: 10.56 | BD325: 10.52 | BE325: 10.56 | BF325: 10.52 | BG325: 10.69 | BH325: 10.69 | BI325: 10.56 | BJ325: 10.52 | BK325: 10.7 | BL325: 10.68
... A538: 44484 | B538: 62 | C538: 62.25 | D538: 62 | E538: 62.25 | F538: 62.25 | G538: 62.25 | H538: 62.25 | I538: 62.25 | J538: 62.25 | K538: 62.25 | N538: 44484 | O538: 9.43165 | P538: 9.39435 | Q538: 9.43 | R538: 9.39435 | S538: 9.41 | T538: 9.4109 | U538: 9.39435 | V538: 9.39435 | W538: 9.41 | X538: 9.4109 | AO538: 44484 | AP538: 62 | AQ538: 62.25 | AR538: 62 | AS538: 62.25 | AT538: 62.25 | AU538: 62.25 | AV538: 62.25 | AW538: 62.25 | AX538: 62.25 | AY538: 62.25 | BB538: 44484 | BC538: 9.43 | BD538: 9.39 | BE538: 9.43 | BF538: 9.39 | BG538: 9.41 | BH538: 9.41 | BI538: 9.39 | BJ538: 9.39 | BK538: 9.41 | BL538: 9.41
