Workbook
Name chfeur_exit: 'NBs List'!$P$5
Name chfeur_offer: 'Exchange Offer'!$B$4
Name chfusd_exit: 'NBs List'!$P$4
Name chfusd_offer: 'Exchange Offer'!$B$3
Name ds_oldbonds_123: #REF!
Name ds_oldbonds_data: #REF!
Name eurusd_exit: 'NBs List'!$P$3
Name eurusd_offer: 'Exchange Offer'!$B$2
Name exit_newbonds: 'NBs List'!$A$3:$A$14
Name exit_prices: 'NBs List'!$M$3:$M$14
Name exit_yields: 'NBs List'!$N$3:$N$14
Name key_date: #REF!
Name new_bond_ref: #REF!
Name NPVs_oldbonds_durations: 'EBs NPVs'!$E$121:$E$145
Name NPVs_oldbonds_names: 'EBs NPVs'!$A$121:$A$145
Name NPVs_oldbonds_vals: 'EBs NPVs'!$F$121:$F$145
Name offer_adj_newbonds: 'Exchange Offer'!$D$37:$O$37
Name offer_adj_notender_newbonds: 'Exchange Offer'!$Q$37:$AB$37
Name offer_adj_notender_vals: 'Exchange Offer'!$Q$38:$AB$62
Name offer_adj_oldbonds: 'Exchange Offer'!$A$38:$A$62
Name offer_adj_oldbonds_alt: 'Exchange Offer'!$C$38:$C$62
Name offer_adj_vals: 'Exchange Offer'!$D$38:$O$62
Name offer_raw_newbonds: 'Exchange Offer'!$D$8:$O$8
Name offer_raw_oldbonds: 'Exchange Offer'!$A$9:$A$33
Name offer_raw_vals: 'Exchange Offer'!$D$9:$O$33
Name old_bond_ref: #REF!
Name OldBonds: #REF!
Name oldbonds_prices_dates: #REF!
Name oldbonds_prices_names: #REF!
Name oldbonds_prices_vals: #REF!
Name orders_afterAPPs_newbonds: 'Exchange Results'!$AM$3:$AV$3
Name orders_afterAPPs_vals: 'Exchange Results'!$AM$4:$AV$28
Name orders_beforeAPPs_newbonds: 'Exchange Results'!$AC$3:$AL$3
Name orders_beforeAPPs_vals: 'Exchange Results'!$AC$4:$AL$28
Name orders_oldbonds: 'Exchange Results'!$A$4:$A$28
Name results_names: 'Exchange Results'!$C$3:$C$28
Name results_vals: 'Exchange Results'!$C$3:$AV$28
Name RRs_adj_oldbonds: 'Exchange Results'!$A$64:$A$88
Name RRs_mkt_newbonds: 'Exchange Results'!$D$32:$M$32
Name RRs_mkt_vals: 'Exchange Results'!$D$33:$M$57
Name RRs_mktadj_newbonds: 'Exchange Results'!$D$63:$M$63
Name RRs_mktadj_vals: 'Exchange Results'!$D$64:$M$88
Name RRs_oldbonds: 'Exchange Results'!$A$33:$A$57
Name RRs_sz_newbonds: 'Exchange Results'!$R$32:$AA$32
Name RRs_sz_vals: 'Exchange Results'!$R$33:$AA$57
Name RRs_szadj_newbonds: 'Exchange Results'!$N$63:$W$63
Name RRs_szadj_vals: 'Exchange Results'!$N$64:$W$88

Sheet README
A1: Companion Spreadsheet for
A2: "Majority Voting in Sovereign Restructurings: The Aggregation Dilemma"
A3: by Carlo Galli and Stephane Guibaud
A5: Abbreviations
A6: EB | B6: Eligible Bonds
A7: NB | B7: New Bonds
A8: NPV | B8: Net Present Value
A9: PA | B9: Principal Amount
A10: FV | B10: Face Value
A13: List of Sheets | B13: Description
A14: EBs List | B14: Details on Kirchner and Macri EBs
A15: Kirchner EBs Cashflows | B15: Detailed cashflows, principal capitalization, and amortization structures of the Kirchner bonds
A16: EBs NPVs | B16: NPV and duration calculations for the EBs
A17: EBs Prices | B17: Historical prices and yields of the EBs. Source: LSEG Workspace
A18: Exchange Offer | B18: Details on the exchange conversion rates
A19: Exchange Results | B19: Details on the exchange recovery rates
... A22: NBs Prices | B22: Historical prices and yields of the NBs. Source: LSEG Workspace
A26: Notes regarding Kirchner "Discount" Bonds
A27: - We denote by "Effective FV" the actual capitalised notional as of the exchange offer date (i.e., approx 140 USD and 138 EUR), and by the "Nominal" FV the theoretical notional that would appear in the Bond Prospectus at issuance.
A28: - In the "Exhange Results" sheet, the Tendered Amounts must be multiplied by the Effective/Nominal FV ratio (approx 1.4) in order to reconcile the quantities with the "PA that consented" column.
A29: - In the "EBs List" and "Exchange Results" sheets, the PA outstanding is measured in Effective FV (i.e. if there was 1 bond outstanding, the PA outsanding would be approx 140 USD or 138 EUR).
A30: - In the "Exchange Offer" sheet, the offers are expressed in Nominal FV (i.e. 100), so we adjust them using the Effective/Nominal FV ratio.
A31: - In the "EBs Prices" sheet, we assume that the historical bond prices from LSEG Workspace are per 100 USD of Effective FV.
A32: - In the "EBs List" sheet, coupon rates are abusted by the Effective/Nominal FV ratio.
A34: Other Notes
A35: - In the "Exchange Results" sheet, "PA that consented" = "Sum of Tender Orders" - " PA controlled by Argentina", and "Consent share" = "PA that consented" / "PA Outstanding"

Sheet EBs List
A1: Lookup name | B1: Short Name | C1: Bond Description (Exchange Offer terminology) | D1: Defined Term (Exchange Offer Terminology) | E1: Indenture | F1: Issue date | G1: ISIN (SEC) | H1: ISIN (Reg S) | I1: ISIN (144A) | J1: Coupon rate | K1: Coupon Frequency (months) | L1: Maturity date | M1: Amortization terms | N1: Total PA outstanding | O1: PA controlled by ARG | P1: Effective Face Value on Valuation Date
A2: USD 2033 Discount I | B2: USD 2033 Discount I | C2: U.S. dollar-denominated Discounts due 2033 (New York law) issued in 2005 (the “USD 2033 Discount Bonds I”) | D2: USD Discount Bonds | E2: 2005 | F2: 38626 | G2: US040114GL81 | J2: 0.0828 | K2: =ROUND(('EBs NPVs'!E9-'EBs NPVs'!D9)/30,0) -> 6 | L2: 48944 | M2: twenty equal semi-annual payments on June 30 and December 31 of each year,commencing on June 30, 2024 | N2: 3857694.7 | O2: 403847.7 | P2: ='Kirchner EBs Cashflows'!$AI$5 -> 140.20421
A3: USD 2033 Discount II and III | B3: USD 2033 Discount II | C3: U.S. dollar-denominated Discounts due 2033 (New York law) issued in 2010 (the “USD 2033 Discount Bonds II”) | D3: USD Discount Bonds | E3: 2005 | F3: 40296 | G3: XS0501194756 | J3: 0.0828 | K3: =ROUND(('EBs NPVs'!E10-'EBs NPVs'!D10)/30,0) -> 6 | L3: 48944 | M3: twenty equal semi-annual payments on June 30 and December 31 of each year,commencing on June 30, 2024 | N3: 1242697.5 | O3: 68982.757 | P3: ='Kirchner EBs Cashflows'!$AI$5 -> 140.20421
A4: USD Par 2038 I | B4: USD Par 2038 I | C4: U.S. dollar-denominated Pars due 2038 (New York law) issued in 2005 (the “USD Par 2038 Bonds I”) | D4: USD Par Bonds | E4: 2005 | F4: 38626 | G4: US040114GK09 | J4: 1.33% to 3/31/2009; 2.5% to 3/31/2019; 3.75% to 3/31/2029; 5.25% to 12/31/2038 | K4: =ROUND(('EBs NPVs'!E11-'EBs NPVs'!D11)/30,0) -> 6 | L4: 50770 | M4: twenty equal semi-annual payments; the first nineteen installments on March 31 and September 30 of each year, commencing on September 30, 2029, and will pay the last installment on December 31, 2038 | N4: 4938659.9 | O4: 358029.25 | P4: 100
A5: USD Par 2038 II and III | B5: USD Par 2038 II and III | C5: U.S. dollar-denominated Pars due 2038 (New York law) issued in 2010 (the “USD Par 2038 Bonds II”) | D5: USD Par Bonds | E5: 2005 | F5: 40296 | G5: XS0501195647 | J5: 2.5% to 3/31/2019; 3.75% to 3/31/2029; 5.25% to 12/31/2038 | K5: =ROUND(('EBs NPVs'!E12-'EBs NPVs'!D12)/30,0) -> 6 | L5: 50770 | M5: twenty equal semi-annual payments; the first nineteen installments on March 31 and September 30 of each year, commencing on September 30, 2029, and will pay the last installment on December 31, 2038 | N5: 94939.179 | O5: 0 | P5: 100
A6: Euro 2033 Discount I | B6: Euro 2033 Discount I | C6: Euro-denominated Discounts due 2033 (English law) issued in 2005 (the “Euro 2033 Discount Bonds I”) | D6: Euro Discount Bonds | E6: 2005 | F6: 38626 | G6: XS0205545840 | J6: 0.0782 | K6: =ROUND(('EBs NPVs'!E13-'EBs NPVs'!D13)/30,0) -> 6 | L6: 48944 | M6: twenty equal semi-annual payments on June 30 and December 31 of each year, commencing on June 30, 2024 | N6: 3107582.4 | O6: 7241.919 | P6: ='Kirchner EBs Cashflows'!$AK$23 -> 137.96394
A7: Euro 2033 Discount II and III | B7: Euro 2033 Discount II and III | C7: Euro-denominated Discounts due 2033 (English law) issued in 2010 (the “Euro 2033 Discount Bonds II”) | D7: Euro Discount Bonds | E7: 2005 | F7: 40350 | G7: XS0501195134 | J7: 0.0782 | K7: =ROUND(('EBs NPVs'!E14-'EBs NPVs'!D14)/30,0) -> 6 | L7: 48944 | M7: twenty equal semi-annual payments on June 30 and December 31 of each year, commencing on June 30, 2024 | N7: 2661472.4 | O7: 0 | P7: ='Kirchner EBs Cashflows'!$AK$23 -> 137.96394
A8: Euro Par 2038 I | B8: Euro Par 2038 I | C8: Euro-denominated Pars due 2038 (English law) issued in 2005 (the “Euro Par 2038 Bonds I”) | D8: Euro Par Bonds | E8: 2005 | F8: 38626 | G8: XS0205537581 | J8: 1.2% to 3/31/2009; 2.26% to 3/31/2019; 3.38% to 3/31/2029; 4.74% to 12/31/2038 | K8: =ROUND(('EBs NPVs'!E15-'EBs NPVs'!D15)/30,0) -> 6 | L8: 50770 | M8: twenty equal semi-annual payments; the first nineteen installments on March 31 and September 30 of each year, commencing on September 30, 2029, and will pay the last installment on December 31, 2038 | N8: 5034912.2 | O8: 0 | P8: 100
A9: Euro Par 2038 II and III | B9: Euro Par 2038 II and III | C9: Euro-denominated Pars due 2038 (English law) issued in 2010 (the “Euro Par 2038 Bonds II”) | D9: Euro Par Bonds | E9: 2005 | F9: 40296 | G9: XS0501195993 | J9: 2.26% to 3/31/2019; 3.38% to 3/31/2029; 4.74% to 12/31/2038 | K9: =ROUND(('EBs NPVs'!E16-'EBs NPVs'!D16)/30,0) -> 6 | L9: 50770 | M9: twenty equal semi-annual payments; the first nineteen installments on March 31 and September 30 of each year, commencing on September 30, 2029, and will pay the last installment on December 31, 2038 | N9: 1438310.9 | O9: 0 | P9: 100
A10: USD 2021 | B10: USD 2021 | C10: U.S. dollar-denominated 6.875 per cent. International Bonds due 2021 (the “USD 2021 Bonds”) | D10: USD Bonds due 2021-2023 | E10: 2016 | F10: 42482 | G10: US040114GW47 | H10: USP04808AA23 | J10: 0.06875 | K10: =ROUND(('EBs NPVs'!E17-'EBs NPVs'!D17)/30,0) -> 6 | L10: 44308 | M10: bullet | N10: 4484000 | O10: 16000 | P10: 100
A11: USD 2022 | B11: USD 2022 | C11: U.S. dollar-denominated 5.625 per cent. International Bonds due 2022 (the “USD 2022 Bonds”) | D11: USD Bonds due 2021-2023 | E11: 2016 | F11: 42761 | G11: US040114HK99 | H11: USP04808AL87 | J11: 0.05625 | K11: =ROUND(('EBs NPVs'!E18-'EBs NPVs'!D18)/30,0) -> 6 | L11: 44587 | M11: bullet | N11: 3250000 | O11: 0 | P11: 100
A12: USD 2023 | B12: USD 2023 | C12: U.S. dollar-denominated 4.625 per cent. International Bonds due 2023 (the “USD 2023 Bonds”) | D12: USD Bonds due 2021-2023 | E12: 2016 | F12: 43111 | G12: US040114HP86 | J12: 0.04625 | K12: =ROUND(('EBs NPVs'!E19-'EBs NPVs'!D19)/30,0) -> 6 | L12: 44937 | M12: bullet | N12: 1750000 | O12: 0 | P12: 100
A13: USD 2026 | B13: USD 2026 | C13: U.S. dollar-denominated 7.500 per cent. International Bonds due 2026 (the “USD 2026 Bonds”) | D13: USD Bonds due 2026-2036 | E13: 2016 | F13: 42482 | G13: US040114GX20 | H13: USP04808AC88 | I13: US040114GS35 | J13: 0.075 | K13: =ROUND(('EBs NPVs'!E20-'EBs NPVs'!D20)/30,0) -> 6 | L13: 46134 | M13: bullet | N13: 6454850 | O13: 45150 | P13: 100
A14: USD 2027 | B14: USD 2027 | C14: U.S. dollar-denominated 6.875 per cent. International Bonds due 2027 (the “USD 2027 Bonds”) | D14: USD Bonds due 2026-2036 | E14: 2016 | F14: 42761 | G14: US040114HL72 | H14: USP04808AM60 | J14: 0.06875 | K14: =ROUND(('EBs NPVs'!E21-'EBs NPVs'!D21)/30,0) -> 6 | L14: 46413 | M14: bullet | N14: 3750000 | O14: 0 | P14: 100
A15: USD 5.875% 2028 | B15: USD 5.875% 2028 | C15: U.S. dollar-denominated 5.875 per cent. International Bonds due 2028 (the “USD 5.875% 2028 Bonds”) | D15: USD Bonds due 2026-2036 | E15: 2016 | F15: 43111 | G15: US040114HQ69 | J15: 0.05875 | K15: =ROUND(('EBs NPVs'!E22-'EBs NPVs'!D22)/30,0) -> 6 | L15: 46763 | M15: bullet | N15: 4250000 | O15: 0 | P15: 100
A16: USD 6.625% 2028 | B16: USD 6.625% 2028 | C16: U.S. dollar-denominated 6.625 per cent. International Bonds due 2028 (the “USD 6.625% 2028 Bonds”) | D16: USD Bonds due 2026-2036 | E16: 2016 | F16: 42557 | G16: US040114HF05 | H16: USP04808AJ32 | J16: 0.06625 | K16: =ROUND(('EBs NPVs'!E23-'EBs NPVs'!D23)/30,0) -> 6 | L16: 46940 | M16: bullet | N16: 965000 | O16: 35000 | P16: 100
A17: USD 2036 | B17: USD 2036 | C17: U.S. dollar-denominated 7.125 per cent. International Bonds due 2036 (the “USD 2036 Bonds”) | D17: USD Bonds due 2026-2036 | E17: 2016 | F17: 42557 | G17: US040114HG87 | H17: USP04808AK05 | I17: US040114HE30 | J17: 0.07125 | K17: =ROUND(('EBs NPVs'!E24-'EBs NPVs'!D24)/30,0) -> 6 | L17: 49862 | M17: bullet | N17: 1727000 | O17: 23000 | P17: 100
A18: USD 2046 | B18: USD 2046 | C18: U.S. dollar-denominated 7.625 per cent. International Bonds due 2046 (the “USD 2046 Bonds”) | D18: USD Bonds due 2046-2117 | E18: 2016 | F18: 42482 | G18: US040114GY03 | H18: USP04808AE45 | I18: US040114GU80 | J18: 0.07625 | K18: =ROUND(('EBs NPVs'!E25-'EBs NPVs'!D25)/30,0) -> 6 | L18: 53439 | M18: bullet | N18: 2617685 | O18: 132315 | P18: 100
A19: USD 2048 | B19: USD 2048 | C19: U.S. dollar-denominated 6.875 per cent. International Bonds due 2048 (the “USD 2048 Bonds”) | D19: USD Bonds due 2046-2117 | E19: 2016 | F19: 43111 | G19: US040114HR43 | J19: 0.06875 | K19: =ROUND(('EBs NPVs'!E26-'EBs NPVs'!D26)/30,0) -> 6 | L19: 54068 | M19: bullet | N19: 3000000 | O19: 0 | P19: 100
A20: USD 2117 | B20: USD 2117 | C20: U.S. dollar-denominated 7.125 per cent. International Bonds due 2117 (the “USD 2117 Bonds”) | D20: USD Bonds due 2046-2117 | E20: 2016 | F20: 42914 | G20: USP04808AN44 | H20: US040114HM55 | I20: US040114HN39 | J20: 0.07125 | K20: =ROUND(('EBs NPVs'!E27-'EBs NPVs'!D27)/30,0) -> 6 | L20: 79438 | M20: bullet | N20: 2689176 | O20: 60824 | P20: 100
A21: Euro 2022 | B21: Euro 2022 | C21: Euro-denominated 3.875 per cent. International Bonds due 2022 (the “Euro 2022 Bonds”) | D21: Euro Bonds due 2022-2023 | E21: 2016 | F21: 42655 | G21: XS1503160225 | J21: 0.03875 | K21: =ROUND(('EBs NPVs'!E28-'EBs NPVs'!D28)/30,0) -> 12 | L21: 44576 | M21: bullet | N21: 1250000 | O21: 0 | P21: 100
A22: Euro 2023 | B22: Euro 2023 | C22: Euro-denominated 3.375 per cent. International Bonds due 2023 (the “Euro 2023 Bonds”) | D22: Euro Bonds due 2022-2023 | E22: 2016 | F22: 43048 | G22: XS1715303340 | J22: 0.03375 | K22: =ROUND(('EBs NPVs'!E29-'EBs NPVs'!D29)/30,0) -> 12 | L22: 44941 | M22: bullet | N22: 1000000 | O22: 0 | P22: 100
A23: Euro 2027 | B23: Euro 2027 | C23: Euro-denominated 5.000 per cent. International Bonds due 2027 (the “Euro 2027 Bonds”) | D23: Euro Bonds due 2027-2028 | E23: 2016 | F23: 42655 | G23: XS1503160498 | J23: 0.05 | K23: =ROUND(('EBs NPVs'!E30-'EBs NPVs'!D30)/30,0) -> 12 | L23: 46402 | M23: bullet | N23: 1250000 | O23: 0 | P23: 100
A24: Euro 2028 | B24: Euro 2028 | C24: Euro-denominated 5.250 per cent. International Bonds due 2028 (the “Euro 2028 Bonds”) | D24: Euro Bonds due 2027-2028 | E24: 2016 | F24: 43048 | G24: XS1715303779 | J24: 0.0525 | K24: =ROUND(('EBs NPVs'!E31-'EBs NPVs'!D31)/30,0) -> 12 | L24: 46767 | M24: bullet | N24: 1000000 | O24: 0 | P24: 100
A25: Euro 2047 | B25: Euro 2047 | C25: Euro-denominated 6.250 per cent. International Bonds due 2047 (the “Euro 2047 Bonds”) | D25: Euro Bonds due 2047 | E25: 2016 | F25: 43048 | G25: XS1715535123 | J25: 0.0625 | K25: =ROUND(('EBs NPVs'!E32-'EBs NPVs'!D32)/30,0) -> 12 | L25: 54005 | M25: bullet | N25: 750000 | O25: 0 | P25: 100
A26: CHF 2020 | B26: CHF 2020 | C26: Swiss Franc-denominated 3.375 per cent. International Bonds due 2020 (the “CHF 2020 Bonds”) | D26: CHF 2020 Bonds | E26: 2016 | F26: 42837 | G26: CH0361824458 | J26: 0.03375 | K26: =ROUND(('EBs NPVs'!E33-'EBs NPVs'!D33)/30,0) -> 12 | L26: 44116 | M26: bullet | N26: 400000 | O26: 0 | P26: 100

Sheet Kirchner EBs Cashflows
A1: USD Discounts | AQ1: Here you start repaying principal | BY1: Here you start repaying principal
A2: Dates | B2: 37986 | C2: =EDATE(B2,6) -> 38168 | D2: =EDATE(B2,12) -> 38352 | E2: =EDATE(C2,12) -> 38533 | F2: =EDATE(D2,12) -> 38717 | G2: =EDATE(E2,12) -> 38898 | H2: =EDATE(F2,12) -> 39082 | I2: =EDATE(G2,12) -> 39263 | J2: =EDATE(H2,12) -> 39447 | K2: =EDATE(I2,12) -> 39629 | ... BJ2: =EDATE(BH2,12) -> 48944
A3: Cash rate (t-1 to t) | B3: =3.97 -> 3.97 | C3: =3.97 -> 3.97 | D3: =3.97 -> 3.97 | E3: =3.97 -> 3.97 | F3: =3.97 -> 3.97 | G3: =3.97 -> 3.97 | H3: =3.97 -> 3.97 | I3: =3.97 -> 3.97 | ... L3: =3.97 -> 3.97 | M3: =5.77 -> 5.77 | N3: =5.77 -> 5.77 | O3: =5.77 -> 5.77 | P3: =5.77 -> 5.77 | Q3: =5.77 -> 5.77 | R3: =5.77 -> 5.77 | S3: =5.77 -> 5.77 | T3: =5.77 -> 5.77 | ... V3: =5.77 -> 5.77 | W3: 8.28 | X3: 8.28 | Y3: 8.28 | Z3: 8.28 | AA3: 8.28 | AB3: 8.28 | AC3: 8.28 | AD3: 8.28 | AE3: 8.28 | AF3: 8.28 | AG3: 8.28 | AH3: 8.28 | AI3: 8.28 | AJ3: 8.28 | AK3: 8.28 | AL3: 8.28 | AM3: 8.28 | AN3: 8.28 | AO3: 8.28 | AP3: 8.28 | AQ3: 8.28 | AR3: 8.28 | AS3: 8.28 | AT3: 8.28 | AU3: 8.28 | AV3: 8.28 | AW3: 8.28 | AX3: 8.28 | AY3: 8.28 | AZ3: 8.28 | BA3: 8.28 | BB3: 8.28 | BC3: 8.28 | BD3: 8.28 | BE3: 8.28 | BF3: 8.28 | BG3: 8.28 | BH3: 8.28 | BI3: 8.28 | BJ3: 8.28
A4: Cap.ed rate (t-1 to t) | B4: =4.31 -> 4.31 | C4: =4.31 -> 4.31 | D4: =4.31 -> 4.31 | E4: =4.31 -> 4.31 | F4: =4.31 -> 4.31 | G4: =4.31 -> 4.31 | H4: =4.31 -> 4.31 | I4: =4.31 -> 4.31 | ... L4: =4.31 -> 4.31 | M4: =2.51 -> 2.51 | N4: =2.51 -> 2.51 | O4: =2.51 -> 2.51 | P4: =2.51 -> 2.51 | Q4: =2.51 -> 2.51 | R4: =2.51 -> 2.51 | S4: =2.51 -> 2.51 | T4: =2.51 -> 2.51 | ... V4: =2.51 -> 2.51 | W4: 0 | X4: 0 | Y4: 0 | Z4: 0 | AA4: 0 | AB4: 0 | AC4: 0 | AD4: 0 | AE4: 0 | AF4: 0 | AG4: 0 | AH4: 0 | AI4: 0 | AJ4: 0 | AK4: 0 | AL4: 0 | AM4: 0 | AN4: 0 | AO4: 0 | AP4: 0 | AQ4: 0 | AR4: 0 | AS4: 0 | AT4: 0 | AU4: 0 | AV4: 0 | AW4: 0 | AX4: 0 | AY4: 0 | AZ4: 0 | BA4: 0 | BB4: 0 | BC4: 0 | BD4: 0 | BE4: 0 | BF4: 0 | BG4: 0 | BH4: 0 | BI4: 0 | BJ4: 0
A5: PA (on which to compute stuff) | B5: 100 | C5: =B5+B7-B8 -> 100 | D5: =C5+C7-C8 -> 102.155 | E5: =D5+D7-D8 -> 104.35644 | F5: =E5+E7-E8 -> 106.60532 | G5: =F5+F7-F8 -> 108.90267 | H5: =G5+G7-G8 -> 111.24952 | I5: =H5+H7-H8 -> 113.64695 | J5: =I5+I7-I8 -> 116.09604 | ... BJ5: =BI5+BI7-BI8 -> 7.0102106
A6: S/A Coupon payment | B6: 0 | C6: =C3/2*C5/100 -> 1.985 | D6: =D3/2*D5/100 -> 2.0277768 | E6: =E3/2*E5/100 -> 2.0714753 | F6: =F3/2*F5/100 -> 2.1161156 | G6: =G3/2*G5/100 -> 2.1617179 | H6: =H3/2*H5/100 -> 2.2083029 | I6: =I3/2*I5/100 -> 2.2558919 | J6: =J3/2*J5/100 -> 2.3045063 | ... BJ6: =BJ3/2*BJ5/100 -> 0.29022272
A7: Cap.ed amount | B7: 0 | C7: =C$5*C4/2/100 -> 2.155 | D7: =D$5*D4/2/100 -> 2.2014402 | E7: =E$5*E4/2/100 -> 2.2488813 | F7: =F$5*F4/2/100 -> 2.2973447 | G7: =G$5*G4/2/100 -> 2.3468525 | H7: =H$5*H4/2/100 -> 2.3974271 | I7: =I$5*I4/2/100 -> 2.4490917 | J7: =J$5*J4/2/100 -> 2.5018696 | ... BJ7: =BJ$5*BJ4/2/100 -> 0
A8: PA Amortization payment | B8: 0 | C8: 0 | D8: 0 | E8: 0 | F8: 0 | G8: 0 | H8: 0 | I8: 0 | J8: 0 | K8: 0 | L8: 0 | M8: 0 | N8: 0 | O8: 0 | P8: 0 | Q8: 0 | R8: 0 | S8: 0 | T8: 0 | U8: 0 | V8: 0 | W8: 0 | X8: 0 | Y8: 0 | Z8: 0 | AA8: 0 | AB8: 0 | AC8: 0 | AD8: 0 | AE8: 0 | AF8: 0 | AG8: 0 | AH8: 0 | AI8: 0 | AJ8: 0 | AK8: 0 | AL8: 0 | AM8: 0 | AN8: 0 | AO8: 0 | AP8: 0 | AQ8: =AQ5/20 -> 7.0102106 | AR8: =AQ8 -> 7.0102106 | AS8: =AR8 -> 7.0102106 | AT8: =AS8 -> 7.0102106 | AU8: =AT8 -> 7.0102106 | AV8: =AU8 -> 7.0102106 | AW8: =AV8 -> 7.0102106 | AX8: =AW8 -> 7.0102106 | AY8: =AX8 -> 7.0102106 | ... BJ8: =BI8 -> 7.0102106
A9: Total Cash Flow | B9: =B8+B6 -> 0 | C9: =C8+C6 -> 1.985 | D9: =D8+D6 -> 2.0277768 | E9: =E8+E6 -> 2.0714753 | F9: =F8+F6 -> 2.1161156 | G9: =G8+G6 -> 2.1617179 | H9: =H8+H6 -> 2.2083029 | I9: =I8+I6 -> 2.2558919 | ... BJ9: =BJ8+BJ6 -> 7.3004333
A11: USD Pars | C11: First cpn /2 because of 3 months period | M11: x | BU11: Last cpn /2 because of 3 months period
A12: Dates | B12: 37986 | C12: =EDATE(B12,3) -> 38077 | D12: =EDATE(C12,6) -> 38260 | E12: =EDATE(C12,12) -> 38442 | F12: =EDATE(D12,12) -> 38625 | G12: =EDATE(E12,12) -> 38807 | H12: =EDATE(F12,12) -> 38990 | I12: =EDATE(G12,12) -> 39172 | J12: =EDATE(H12,12) -> 39355 | K12: =EDATE(I12,12) -> 39538 | L12: =EDATE(J12,12) -> 39721 | ... BT12: =EDATE(BR12,12) -> 50678 | BU12: 50770
A13: ANNUAL Coupon rate (t-1 to t) | B13: 1.33 | C13: 1.33 | D13: 1.33 | E13: 1.33 | F13: 1.33 | G13: 1.33 | H13: 1.33 | I13: 1.33 | J13: 1.33 | K13: 1.33 | L13: 1.33 | M13: 1.33 | N13: 2.5 | O13: 2.5 | P13: 2.5 | Q13: 2.5 | R13: 2.5 | S13: 2.5 | T13: 2.5 | U13: 2.5 | V13: 2.5 | W13: 2.5 | X13: 2.5 | Y13: 2.5 | Z13: 2.5 | AA13: 2.5 | AB13: 2.5 | AC13: 2.5 | AD13: 2.5 | AE13: 2.5 | AF13: 2.5 | AG13: 2.5 | AH13: 3.75 | AI13: 3.75 | AJ13: 3.75 | AK13: 3.75 | AL13: 3.75 | AM13: 3.75 | AN13: 3.75 | AO13: 3.75 | AP13: 3.75 | AQ13: 3.75 | AR13: 3.75 | AS13: 3.75 | AT13: 3.75 | AU13: 3.75 | AV13: 3.75 | AW13: 3.75 | AX13: 3.75 | AY13: 3.75 | AZ13: 3.75 | BA13: 3.75 | BB13: 5.25 | BC13: 5.25 | BD13: 5.25 | BE13: 5.25 | BF13: 5.25 | BG13: 5.25 | BH13: 5.25 | BI13: 5.25 | BJ13: 5.25 | BK13: 5.25 | BL13: 5.25 | BM13: 5.25 | BN13: 5.25 | BO13: 5.25 | BP13: 5.25 | BQ13: 5.25 | BR13: 5.25 | BS13: 5.25 | BT13: 5.25 | BU13: 5.25
A14: PA (on which to compute stuff) | B14: 100 | C14: =B14-B16 -> 100 | D14: =C14-C16 -> 100 | E14: =D14-D16 -> 100 | F14: =E14-E16 -> 100 | G14: =F14-F16 -> 100 | H14: =G14-G16 -> 100 | I14: =H14-H16 -> 100 | J14: =I14-I16 -> 100 | ... BU14: =BT14-BT16 -> 5
A15: S/A Coupon payment | B15: 0 | C15: =C14*C13/2/100/2 -> 0.3325 | D15: =D14*D13/2/100 -> 0.665 | E15: =E14*E13/2/100 -> 0.665 | F15: =F14*F13/2/100 -> 0.665 | G15: =G14*G13/2/100 -> 0.665 | H15: =H14*H13/2/100 -> 0.665 | I15: =I14*I13/2/100 -> 0.665 | J15: =J14*J13/2/100 -> 0.665 | K15: =K14*K13/2/100 -> 0.665 | ... BT15: =BT14*BT13/2/100 -> 0.2625 | BU15: =BU14*BU13/2/100/2 -> 0.065625
A16: PA Amortization payment | B16: 0 | C16: 0 | D16: 0 | E16: 0 | F16: 0 | G16: 0 | H16: 0 | I16: 0 | J16: 0 | K16: 0 | L16: 0 | M16: 0 | N16: 0 | O16: 0 | P16: 0 | Q16: 0 | R16: 0 | S16: 0 | T16: 0 | U16: 0 | V16: 0 | W16: 0 | X16: 0 | Y16: 0 | Z16: 0 | AA16: 0 | AB16: 0 | AC16: 0 | AD16: 0 | AE16: 0 | AF16: 0 | AG16: 0 | AH16: 0 | AI16: 0 | AJ16: 0 | AK16: 0 | AL16: 0 | AM16: 0 | AN16: 0 | AO16: 0 | AP16: 0 | AQ16: 0 | AR16: 0 | AS16: 0 | AT16: 0 | AU16: 0 | AV16: 0 | AW16: 0 | AX16: 0 | AY16: 0 | AZ16: 0 | BA16: 0 | BB16: =BA14/20 -> 5 | BC16: =BB16 -> 5 | BD16: =BC16 -> 5 | BE16: =BD16 -> 5 | BF16: =BE16 -> 5 | BG16: =BF16 -> 5 | BH16: =BG16 -> 5 | BI16: =BH16 -> 5 | BJ16: =BI16 -> 5 | ... BU16: =BT16 -> 5
A17: Total Cash Flow | B17: =B16+B15 -> 0 | C17: =C16+C15 -> 0.3325 | D17: =D16+D15 -> 0.665 | E17: =E16+E15 -> 0.665 | F17: =F16+F15 -> 0.665 | G17: =G16+G15 -> 0.665 | H17: =H16+H15 -> 0.665 | I17: =I16+I15 -> 0.665 | ... BU17: =BU16+BU15 -> 5.065625
A19: EUR Discounts | AQ19: Here you start repaying principal
A20: Dates | B20: 37986 | C20: =EDATE(B20,6) -> 38168 | D20: =EDATE(B20,12) -> 38352 | E20: =EDATE(C20,12) -> 38533 | F20: =EDATE(D20,12) -> 38717 | G20: =EDATE(E20,12) -> 38898 | H20: =EDATE(F20,12) -> 39082 | I20: =EDATE(G20,12) -> 39263 | J20: =EDATE(H20,12) -> 39447 | K20: =EDATE(I20,12) -> 39629 | ... BJ20: =EDATE(BH20,12) -> 48944
A21: Cash rate (t-1 to t) | B21: 3.75 | C21: 3.75 | D21: 3.75 | E21: 3.75 | F21: 3.75 | G21: 3.75 | H21: 3.75 | I21: 3.75 | J21: 3.75 | K21: 3.75 | L21: 3.75 | M21: 5.45 | N21: 5.45 | O21: 5.45 | P21: 5.45 | Q21: 5.45 | R21: 5.45 | S21: 5.45 | T21: 5.45 | U21: 5.45 | V21: 5.45 | W21: 7.82 | X21: 7.82 | Y21: 7.82 | Z21: 7.82 | AA21: 7.82 | AB21: 7.82 | AC21: 7.82 | AD21: 7.82 | AE21: 7.82 | AF21: 7.82 | AG21: 7.82 | AH21: 7.82 | AI21: 7.82 | AJ21: 7.82 | AK21: 7.82 | AL21: 7.82 | AM21: 7.82 | AN21: 7.82 | AO21: 7.82 | AP21: 7.82 | AQ21: 7.82 | AR21: 7.82 | AS21: 7.82 | AT21: 7.82 | AU21: 7.82 | AV21: 7.82 | AW21: 7.82 | AX21: 7.82 | AY21: 7.82 | AZ21: 7.82 | BA21: 7.82 | BB21: 7.82 | BC21: 7.82 | BD21: 7.82 | BE21: 7.82 | BF21: 7.82 | BG21: 7.82 | BH21: 7.82 | BI21: 7.82 | BJ21: 7.82
A22: Cap.ed rate (t-1 to t) | B22: 4.07 | C22: 4.07 | D22: 4.07 | E22: 4.07 | F22: 4.07 | G22: 4.07 | H22: 4.07 | I22: 4.07 | J22: 4.07 | K22: 4.07 | L22: 4.07 | M22: 2.37 | N22: 2.37 | O22: 2.37 | P22: 2.37 | Q22: 2.37 | R22: 2.37 | S22: 2.37 | T22: 2.37 | U22: 2.37 | V22: 2.37 | W22: 0 | X22: 0 | Y22: 0 | Z22: 0 | AA22: 0 | AB22: 0 | AC22: 0 | AD22: 0 | AE22: 0 | AF22: 0 | AG22: 0 | AH22: 0 | AI22: 0 | AJ22: 0 | AK22: 0 | AL22: 0 | AM22: 0 | AN22: 0 | AO22: 0 | AP22: 0 | AQ22: 0 | AR22: 0 | AS22: 0 | AT22: 0 | AU22: 0 | AV22: 0 | AW22: 0 | AX22: 0 | AY22: 0 | AZ22: 0 | BA22: 0 | BB22: 0 | BC22: 0 | BD22: 0 | BE22: 0 | BF22: 0 | BG22: 0 | BH22: 0 | BI22: 0 | BJ22: 0
A23: PA (on which to compute stuff) | B23: 100 | C23: =B23+B25-B26 -> 100 | D23: =C23+C25-C26 -> 102.035 | E23: =D23+D25-D26 -> 104.11385 | F23: =E23+E25-E26 -> 106.23751 | G23: =F23+F25-F26 -> 108.40693 | H23: =G23+G25-G26 -> 110.6231 | I23: =H23+H25-H26 -> 112.88702 | J23: =I23+I25-I26 -> 115.19974 | ... BJ23: =BI23+BI25-BI26 -> 6.8981971
A24: S/A Coupon payment | B24: 0 | C24: =C21/2*C23/100 -> 1.875 | D24: =D21/2*D23/100 -> 1.9131562 | E24: =E21/2*E23/100 -> 1.9521348 | F24: =F21/2*F23/100 -> 1.9919533 | G24: =G21/2*G23/100 -> 2.0326299 | H24: =H21/2*H23/100 -> 2.074183 | I24: =I21/2*I23/100 -> 2.1166317 | J24: =J21/2*J23/100 -> 2.1599951 | ... BJ24: =BJ21/2*BJ23/100 -> 0.26971951
A25: Cap.ed amount | B25: 0 | C25: =C$5*C22/2/100 -> 2.035 | D25: =D$5*D22/2/100 -> 2.0788543 | E25: =E$5*E22/2/100 -> 2.1236536 | F25: =F$5*F22/2/100 -> 2.1694183 | G25: =G$5*G22/2/100 -> 2.2161693 | H25: =H$5*H22/2/100 -> 2.2639277 | I25: =I$5*I22/2/100 -> 2.3127153 | J25: =J$5*J22/2/100 -> 2.3625544 | ... BJ25: =BJ$5*BJ22/2/100 -> 0
A26: PA Amortization payment | B26: 0 | C26: 0 | D26: 0 | E26: 0 | F26: 0 | G26: 0 | H26: 0 | I26: 0 | J26: 0 | K26: 0 | L26: 0 | M26: 0 | N26: 0 | O26: 0 | P26: 0 | Q26: 0 | R26: 0 | S26: 0 | T26: 0 | U26: 0 | V26: 0 | W26: 0 | X26: 0 | Y26: 0 | Z26: 0 | AA26: 0 | AB26: 0 | AC26: 0 | AD26: 0 | AE26: 0 | AF26: 0 | AG26: 0 | AH26: 0 | AI26: 0 | AJ26: 0 | AK26: 0 | AL26: 0 | AM26: 0 | AN26: 0 | AO26: 0 | AP26: 0 | AQ26: =AQ23/20 -> 6.8981971 | AR26: =AQ26 -> 6.8981971 | AS26: =AR26 -> 6.8981971 | AT26: =AS26 -> 6.8981971 | AU26: =AT26 -> 6.8981971 | AV26: =AU26 -> 6.8981971 | AW26: =AV26 -> 6.8981971 | AX26: =AW26 -> 6.8981971 | AY26: =AX26 -> 6.8981971 | ... BJ26: =BI26 -> 6.8981971
A27: Total Cash Flow | B27: =B26+B24 -> 0 | C27: =C26+C24 -> 1.875 | D27: =D26+D24 -> 1.9131562 | E27: =E26+E24 -> 1.9521348 | F27: =F26+F24 -> 1.9919533 | G27: =G26+G24 -> 2.0326299 | H27: =H26+H24 -> 2.074183 | I27: =I26+I24 -> 2.1166317 | ... BJ27: =BJ26+BJ24 -> 7.1679167
A29: EUR Pars | C29: First cpn /2 because of 3 months period | M29: x | BU29: Last cpn /2 because of 3 months period
A30: Dates | B30: 37986 | C30: =EDATE(B30,3) -> 38077 | D30: =EDATE(C30,6) -> 38260 | E30: =EDATE(C30,12) -> 38442 | F30: =EDATE(D30,12) -> 38625 | G30: =EDATE(E30,12) -> 38807 | H30: =EDATE(F30,12) -> 38990 | I30: =EDATE(G30,12) -> 39172 | J30: =EDATE(H30,12) -> 39355 | K30: =EDATE(I30,12) -> 39538 | L30: =EDATE(J30,12) -> 39721 | ... BT30: =EDATE(BR30,12) -> 50678 | BU30: 50770
A31: ANNUAL Coupon rate (t-1 to t) | B31: 1.2 | C31: 1.2 | D31: 1.2 | E31: 1.2 | F31: 1.2 | G31: 1.2 | H31: 1.2 | I31: 1.2 | J31: 1.2 | K31: 1.2 | L31: 1.2 | M31: 1.2 | N31: 2.26 | O31: 2.26 | P31: 2.26 | Q31: 2.26 | R31: 2.26 | S31: 2.26 | T31: 2.26 | U31: 2.26 | V31: 2.26 | W31: 2.26 | X31: 2.26 | Y31: 2.26 | Z31: 2.26 | AA31: 2.26 | AB31: 2.26 | AC31: 2.26 | AD31: 2.26 | AE31: 2.26 | AF31: 2.26 | AG31: 2.26 | AH31: 3.38 | AI31: 3.38 | AJ31: 3.38 | AK31: 3.38 | AL31: 3.38 | AM31: 3.38 | AN31: 3.38 | AO31: 3.38 | AP31: 3.38 | AQ31: 3.38 | AR31: 3.38 | AS31: 3.38 | AT31: 3.38 | AU31: 3.38 | AV31: 3.38 | AW31: 3.38 | AX31: 3.38 | AY31: 3.38 | AZ31: 3.38 | BA31: 3.38 | BB31: 4.74 | BC31: 4.74 | BD31: 4.74 | BE31: 4.74 | BF31: 4.74 | BG31: 4.74 | BH31: 4.74 | BI31: 4.74 | BJ31: 4.74 | BK31: 4.74 | BL31: 4.74 | BM31: 4.74 | BN31: 4.74 | BO31: 4.74 | BP31: 4.74 | BQ31: 4.74 | BR31: 4.74 | BS31: 4.74 | BT31: 4.74 | BU31: 4.74
A32: PA (on which to compute stuff) | B32: 100 | C32: =B32-B34 -> 100 | D32: =C32-C34 -> 100 | E32: =D32-D34 -> 100 | F32: =E32-E34 -> 100 | G32: =F32-F34 -> 100 | H32: =G32-G34 -> 100 | I32: =H32-H34 -> 100 | J32: =I32-I34 -> 100 | ... BU32: =BT32-BT34 -> 5
A33: S/A Coupon payment | B33: 0 | C33: =C32*C31/2/100/2 -> 0.3 | D33: =D32*D31/2/100 -> 0.6 | E33: =E32*E31/2/100 -> 0.6 | F33: =F32*F31/2/100 -> 0.6 | G33: =G32*G31/2/100 -> 0.6 | H33: =H32*H31/2/100 -> 0.6 | I33: =I32*I31/2/100 -> 0.6 | J33: =J32*J31/2/100 -> 0.6 | K33: =K32*K31/2/100 -> 0.6 | ... BT33: =BT32*BT31/2/100 -> 0.237 | BU33: =BU32*BU31/2/100/2 -> 0.05925
A34: PA Amortization payment | B34: 0 | C34: 0 | D34: 0 | E34: 0 | F34: 0 | G34: 0 | H34: 0 | I34: 0 | J34: 0 | K34: 0 | L34: 0 | M34: 0 | N34: 0 | O34: 0 | P34: 0 | Q34: 0 | R34: 0 | S34: 0 | T34: 0 | U34: 0 | V34: 0 | W34: 0 | X34: 0 | Y34: 0 | Z34: 0 | AA34: 0 | AB34: 0 | AC34: 0 | AD34: 0 | AE34: 0 | AF34: 0 | AG34: 0 | AH34: 0 | AI34: 0 | AJ34: 0 | AK34: 0 | AL34: 0 | AM34: 0 | AN34: 0 | AO34: 0 | AP34: 0 | AQ34: 0 | AR34: 0 | AS34: 0 | AT34: 0 | AU34: 0 | AV34: 0 | AW34: 0 | AX34: 0 | AY34: 0 | AZ34: 0 | BA34: 0 | BB34: =BA32/20 -> 5 | BC34: =BB34 -> 5 | BD34: =BC34 -> 5 | BE34: =BD34 -> 5 | BF34: =BE34 -> 5 | BG34: =BF34 -> 5 | BH34: =BG34 -> 5 | BI34: =BH34 -> 5 | BJ34: =BI34 -> 5 | ... BU34: =BT34 -> 5
A35: Total Cash Flow | B35: =B34+B33 -> 0 | C35: =C34+C33 -> 0.3 | D35: =D34+D33 -> 0.6 | E35: =E34+E33 -> 0.6 | F35: =F34+F33 -> 0.6 | G35: =G34+G33 -> 0.6 | H35: =H34+H33 -> 0.6 | I35: =I34+I33 -> 0.6 | ... BU35: =BU34+BU33 -> 5.05925

Sheet EBs NPVs
B1: Valuation date | C1: 44089 | GQ1: x
B2: Exit yields (Principal Amount-weighted averages)
B3: USD2005 | C3: ='NBs Prices'!G49 -> 11.341845
B4: EUR2005 | C4: ='NBs Prices'!G50 -> 13.393885
B5: USD2016 | C5: ='NBs Prices'!G51 -> 11.513868 | E5: Max date | F5: Min date
B6: EUR2016 | C6: ='NBs Prices'!G52 -> 14.151281 | E6: =MAX(E9:E33) -> 44038 | F6: =MIN(F9:F33) -> 44104
B8: ISIN | C8: Short Name | E8: Payment dates
B9: US040114GL81 | C9: USD 2033 Discount I | D9: =EDATE(E9,-ROUND((F9-E9)/30,0)) -> 43829 | E9: 44012 | F9: 44196 | G9: 44377 | H9: 44561 | I9: 44742 | J9: 44926 | K9: 45107 | L9: 45291 | M9: 45473 | N9: 45657 | O9: 45838 | P9: 46022 | Q9: 46203 | R9: 46387 | S9: 46568 | T9: 46752 | U9: 46934 | V9: 47118 | W9: 47299 | X9: 47483 | Y9: 47664 | Z9: 47848 | AA9: 48029 | AB9: 48213 | AC9: 48395 | AD9: 48579 | AE9: 48760 | AF9: 48944
B10: XS0501194756 | C10: USD 2033 Discount II and III | D10: =EDATE(E10,-ROUND((F10-E10)/30,0)) -> 43829 | E10: 44012 | F10: 44196 | G10: 44377 | H10: 44561 | I10: 44742 | J10: 44926 | K10: 45107 | L10: 45291 | M10: 45473 | N10: 45657 | O10: 45838 | P10: 46022 | Q10: 46203 | R10: 46387 | S10: 46568 | T10: 46752 | U10: 46934 | V10: 47118 | W10: 47299 | X10: 47483 | Y10: 47664 | Z10: 47848 | AA10: 48029 | AB10: 48213 | AC10: 48395 | AD10: 48579 | AE10: 48760 | AF10: 48944
B11: US040114GK09 | C11: USD Par 2038 I | D11: =EDATE(E11,-ROUND((F11-E11)/30,0)) -> 43738 | E11: 43921 | F11: 44104 | G11: 44286 | H11: 44469 | I11: 44651 | J11: 44834 | K11: 45016 | L11: 45199 | M11: 45382 | N11: 45565 | O11: 45747 | P11: 45930 | Q11: 46112 | R11: 46295 | S11: 46477 | T11: 46660 | U11: 46843 | V11: 47026 | W11: 47208 | X11: 47391 | Y11: 47573 | Z11: 47756 | AA11: 47938 | AB11: 48121 | AC11: 48304 | AD11: 48487 | AE11: 48669 | AF11: 48852 | AG11: 49034 | AH11: 49217 | AI11: 49399 | AJ11: 49582 | AK11: 49765 | AL11: 49948 | AM11: 50130 | AN11: 50313 | AO11: 50495 | AP11: 50678 | AQ11: 50770
B12: XS0501195647 | C12: USD Par 2038 II and III | D12: =EDATE(E12,-ROUND((F12-E12)/30,0)) -> 43738 | E12: 43921 | F12: 44104 | G12: 44286 | H12: 44469 | I12: 44651 | J12: 44834 | K12: 45016 | L12: 45199 | M12: 45382 | N12: 45565 | O12: 45747 | P12: 45930 | Q12: 46112 | R12: 46295 | S12: 46477 | T12: 46660 | U12: 46843 | V12: 47026 | W12: 47208 | X12: 47391 | Y12: 47573 | Z12: 47756 | AA12: 47938 | AB12: 48121 | AC12: 48304 | AD12: 48487 | AE12: 48669 | AF12: 48852 | AG12: 49034 | AH12: 49217 | AI12: 49399 | AJ12: 49582 | AK12: 49765 | AL12: 49948 | AM12: 50130 | AN12: 50313 | AO12: 50495 | AP12: 50678 | AQ12: 50770
B13: XS0205545840 | C13: Euro 2033 Discount I | D13: =EDATE(E13,-ROUND((F13-E13)/30,0)) -> 43829 | E13: 44012 | F13: 44196 | G13: 44377 | H13: 44561 | I13: 44742 | J13: 44926 | K13: 45107 | L13: 45291 | M13: 45473 | N13: 45657 | O13: 45838 | P13: 46022 | Q13: 46203 | R13: 46387 | S13: 46568 | T13: 46752 | U13: 46934 | V13: 47118 | W13: 47299 | X13: 47483 | Y13: 47664 | Z13: 47848 | AA13: 48029 | AB13: 48213 | AC13: 48395 | AD13: 48579 | AE13: 48760 | AF13: 48944
B14: XS0501195134 | C14: Euro 2033 Discount II and III | D14: =EDATE(E14,-ROUND((F14-E14)/30,0)) -> 43829 | E14: 44012 | F14: 44196 | G14: 44377 | H14: 44561 | I14: 44742 | J14: 44926 | K14: 45107 | L14: 45291 | M14: 45473 | N14: 45657 | O14: 45838 | P14: 46022 | Q14: 46203 | R14: 46387 | S14: 46568 | T14: 46752 | U14: 46934 | V14: 47118 | W14: 47299 | X14: 47483 | Y14: 47664 | Z14: 47848 | AA14: 48029 | AB14: 48213 | AC14: 48395 | AD14: 48579 | AE14: 48760 | AF14: 48944
B15: XS0205537581 | C15: Euro Par 2038 I | D15: =EDATE(E15,-ROUND((F15-E15)/30,0)) -> 43738 | E15: 43921 | F15: 44104 | G15: 44286 | H15: 44469 | I15: 44651 | J15: 44834 | K15: 45016 | L15: 45199 | M15: 45382 | N15: 45565 | O15: 45747 | P15: 45930 | Q15: 46112 | R15: 46295 | S15: 46477 | T15: 46660 | U15: 46843 | V15: 47026 | W15: 47208 | X15: 47391 | Y15: 47573 | Z15: 47756 | AA15: 47938 | AB15: 48121 | AC15: 48304 | AD15: 48487 | AE15: 48669 | AF15: 48852 | AG15: 49034 | AH15: 49217 | AI15: 49399 | AJ15: 49582 | AK15: 49765 | AL15: 49948 | AM15: 50130 | AN15: 50313 | AO15: 50495 | AP15: 50678 | AQ15: 50770
B16: XS0501195993 | C16: Euro Par 2038 II and III | D16: =EDATE(E16,-ROUND((F16-E16)/30,0)) -> 43738 | E16: 43921 | F16: 44104 | G16: 44286 | H16: 44469 | I16: 44651 | J16: 44834 | K16: 45016 | L16: 45199 | M16: 45382 | N16: 45565 | O16: 45747 | P16: 45930 | Q16: 46112 | R16: 46295 | S16: 46477 | T16: 46660 | U16: 46843 | V16: 47026 | W16: 47208 | X16: 47391 | Y16: 47573 | Z16: 47756 | AA16: 47938 | AB16: 48121 | AC16: 48304 | AD16: 48487 | AE16: 48669 | AF16: 48852 | AG16: 49034 | AH16: 49217 | AI16: 49399 | AJ16: 49582 | AK16: 49765 | AL16: 49948 | AM16: 50130 | AN16: 50313 | AO16: 50495 | AP16: 50678 | AQ16: 50770
B17: US040114GW47 | C17: USD 2021 | D17: =EDATE(E17,-ROUND((F17-E17)/30,0)) -> 43760 | E17: 43943 | F17: 44126 | G17: 44308
B18: US040114HK99 | C18: USD 2022 | D18: =EDATE(E18,-ROUND((F18-E18)/30,0)) -> 43856 | E18: 44038 | F18: 44222 | G18: 44403 | H18: 44587
B19: US040114HP86 | C19: USD 2023 | D19: =EDATE(E19,-ROUND((F19-E19)/30,0)) -> 43841 | E19: 44023 | F19: 44207 | G19: 44388 | H19: 44572 | I19: 44753 | J19: 44937
B20: US040114GX20 | C20: USD 2026 | D20: =EDATE(E20,-ROUND((F20-E20)/30,0)) -> 43760 | E20: 43943 | F20: 44126 | G20: 44308 | H20: 44491 | I20: 44673 | J20: 44856 | K20: 45038 | L20: 45221 | M20: 45404 | N20: 45587 | O20: 45769 | P20: 45952 | Q20: 46134
B21: US040114HL72 | C21: USD 2027 | D21: =EDATE(E21,-ROUND((F21-E21)/30,0)) -> 43856 | E21: 44038 | F21: 44222 | G21: 44403 | H21: 44587 | I21: 44768 | J21: 44952 | K21: 45133 | L21: 45317 | M21: 45499 | N21: 45683 | O21: 45864 | P21: 46048 | Q21: 46229 | R21: 46413
B22: US040114HQ69 | C22: USD 5.875% 2028 | D22: =EDATE(E22,-ROUND((F22-E22)/30,0)) -> 43841 | E22: 44023 | F22: 44207 | G22: 44388 | H22: 44572 | I22: 44753 | J22: 44937 | K22: 45118 | L22: 45302 | M22: 45484 | N22: 45668 | O22: 45849 | P22: 46033 | Q22: 46214 | R22: 46398 | S22: 46579 | T22: 46763
B23: US040114HF05 | C23: USD 6.625% 2028 | D23: =EDATE(E23,-ROUND((F23-E23)/30,0)) -> 43836 | E23: 44018 | F23: =EDATE(E23,6) -> 44202 | G23: =EDATE(F23,6) -> 44383 | H23: =EDATE(G23,6) -> 44567 | I23: =EDATE(H23,6) -> 44748 | J23: =EDATE(I23,6) -> 44932 | K23: =EDATE(J23,6) -> 45113 | L23: =EDATE(K23,6) -> 45297 | M23: =EDATE(L23,6) -> 45479 | ... U23: =EDATE(T23,6) -> 46940
B24: US040114HG87 | C24: USD 2036 | D24: =EDATE(E24,-ROUND((F24-E24)/30,0)) -> 43836 | E24: 44018 | F24: 44202 | G24: 44383 | H24: 44567 | I24: 44748 | J24: 44932 | K24: 45113 | L24: 45297 | M24: 45479 | N24: 45663 | O24: 45844 | P24: 46028 | Q24: 46209 | R24: 46393 | S24: 46574 | T24: 46758 | U24: 46940 | V24: 47124 | W24: 47305 | X24: 47489 | Y24: 47670 | Z24: 47854 | AA24: 48035 | AB24: 48219 | AC24: 48401 | AD24: 48585 | AE24: 48766 | AF24: 48950 | AG24: 49131 | AH24: 49315 | AI24: 49496 | AJ24: 49680 | AK24: 49862
B25: US040114GY03 | C25: USD 2046 | D25: =EDATE(E25,-ROUND((F25-E25)/30,0)) -> 43760 | E25: 43943 | F25: 44126 | G25: 44308 | H25: 44491 | I25: 44673 | J25: 44856 | K25: 45038 | L25: 45221 | M25: 45404 | N25: 45587 | O25: 45769 | P25: 45952 | Q25: 46134 | R25: 46317 | S25: 46499 | T25: 46682 | U25: 46865 | V25: 47048 | W25: 47230 | X25: 47413 | Y25: 47595 | Z25: 47778 | AA25: 47960 | AB25: 48143 | AC25: 48326 | AD25: 48509 | AE25: 48691 | AF25: 48874 | AG25: 49056 | AH25: 49239 | AI25: 49421 | AJ25: 49604 | AK25: 49787 | AL25: 49970 | AM25: 50152 | AN25: 50335 | AO25: 50517 | AP25: 50700 | AQ25: 50882 | AR25: 51065 | AS25: 51248 | AT25: 51431 | AU25: 51613 | AV25: 51796 | AW25: 51978 | AX25: 52161 | AY25: 52343 | AZ25: 52526 | BA25: 52709 | BB25: 52892 | BC25: 53074 | BD25: 53257 | BE25: 53439
B26: US040114HR43 | C26: USD 2048 | D26: =EDATE(E26,-ROUND((F26-E26)/30,0)) -> 43841 | E26: 44023 | F26: 44207 | G26: 44388 | H26: 44572 | I26: 44753 | J26: 44937 | K26: 45118 | L26: 45302 | M26: 45484 | N26: 45668 | O26: 45849 | P26: 46033 | Q26: 46214 | R26: 46398 | S26: 46579 | T26: 46763 | U26: 46945 | V26: 47129 | W26: 47310 | X26: 47494 | Y26: 47675 | Z26: 47859 | AA26: 48040 | AB26: 48224 | AC26: 48406 | AD26: 48590 | AE26: 48771 | AF26: 48955 | AG26: 49136 | AH26: 49320 | AI26: 49501 | AJ26: 49685 | AK26: 49867 | AL26: 50051 | AM26: 50232 | AN26: 50416 | AO26: 50597 | AP26: 50781 | AQ26: 50962 | AR26: 51146 | AS26: 51328 | AT26: 51512 | AU26: 51693 | AV26: 51877 | AW26: 52058 | AX26: 52242 | AY26: 52423 | AZ26: 52607 | BA26: 52789 | BB26: 52973 | BC26: 53154 | BD26: 53338 | BE26: 53519 | BF26: 53703 | BG26: 53884 | BH26: 54068
B27: USP04808AN44 | C27: USD 2117 | D27: =EDATE(E27,-ROUND((F27-E27)/30,0)) -> 43827 | E27: 44010 | F27: =EDATE(E27,6) -> 44193 | G27: =EDATE(F27,6) -> 44375 | H27: =EDATE(G27,6) -> 44558 | I27: =EDATE(H27,6) -> 44740 | J27: =EDATE(I27,6) -> 44923 | K27: =EDATE(J27,6) -> 45105 | L27: =EDATE(K27,6) -> 45288 | M27: =EDATE(L27,6) -> 45471 | ... GQ27: =EDATE(GP27,6) -> 79438
B28: XS1503160225 | C28: Euro 2022 | D28: =EDATE(E28,-ROUND((F28-E28)/30,0)) -> 43480 | E28: 43845 | F28: =EDATE(E28,12) -> 44211 | G28: =EDATE(F28,12) -> 44576
B29: XS1715303340 | C29: Euro 2023 | D29: =EDATE(E29,-ROUND((F29-E29)/30,0)) -> 43480 | E29: 43845 | F29: =EDATE(E29,12) -> 44211 | G29: =EDATE(F29,12) -> 44576 | H29: =EDATE(G29,12) -> 44941
B30: XS1503160498 | C30: Euro 2027 | D30: =EDATE(E30,-ROUND((F30-E30)/30,0)) -> 43480 | E30: 43845 | F30: =EDATE(E30,12) -> 44211 | G30: =EDATE(F30,12) -> 44576 | H30: =EDATE(G30,12) -> 44941 | I30: =EDATE(H30,12) -> 45306 | J30: =EDATE(I30,12) -> 45672 | K30: =EDATE(J30,12) -> 46037 | L30: =EDATE(K30,12) -> 46402
B31: XS1715303779 | C31: Euro 2028 | D31: =EDATE(E31,-ROUND((F31-E31)/30,0)) -> 43480 | E31: 43845 | F31: =EDATE(E31,12) -> 44211 | G31: =EDATE(F31,12) -> 44576 | H31: =EDATE(G31,12) -> 44941 | I31: =EDATE(H31,12) -> 45306 | J31: =EDATE(I31,12) -> 45672 | K31: =EDATE(J31,12) -> 46037 | L31: =EDATE(K31,12) -> 46402 | M31: =EDATE(L31,12) -> 46767
B32: XS1715535123 | C32: Euro 2047 | D32: =EDATE(E32,-ROUND((F32-E32)/30,0)) -> 43413 | E32: 43778 | F32: =EDATE(E32,12) -> 44144 | G32: =EDATE(F32,12) -> 44509 | H32: =EDATE(G32,12) -> 44874 | I32: =EDATE(H32,12) -> 45239 | J32: =EDATE(I32,12) -> 45605 | K32: =EDATE(J32,12) -> 45970 | L32: =EDATE(K32,12) -> 46335 | M32: =EDATE(L32,12) -> 46700 | ... AG32: =EDATE(AF32,12) -> 54005
B33: CH0361824458 | C33: CHF 2020 | D33: =EDATE(E33,-ROUND((F33-E33)/30,0)) -> 43385 | E33: 43750 | F33: =EDATE(E33,12) -> 44116
E35: Note on below: First column is in the past so assuming no CF there. Second column is in less than 1 payment period, so we compute the accrued coupon.
B36: ISIN | C36: Short Name | E36: Cash Flows (Coupons + Redemptions) for 100 USD Notional.
B37: US040114GL81 | C37: =C9 -> USD 2033 Discount I | F37: ='Kirchner EBs Cashflows'!AJ9 -> 5.8044544 | G37: ='Kirchner EBs Cashflows'!AK9 -> 5.8044544 | H37: ='Kirchner EBs Cashflows'!AL9 -> 5.8044544 | I37: ='Kirchner EBs Cashflows'!AM9 -> 5.8044544 | J37: ='Kirchner EBs Cashflows'!AN9 -> 5.8044544 | K37: ='Kirchner EBs Cashflows'!AO9 -> 5.8044544 | L37: ='Kirchner EBs Cashflows'!AP9 -> 5.8044544 | M37: ='Kirchner EBs Cashflows'!AQ9 -> 12.814665 | ... AQ37: ='Kirchner EBs Cashflows'!BU9 -> 0
B38: XS0501194756 | C38: =C10 -> USD 2033 Discount II and III | F38: =F37 -> 5.8044544 | G38: =G37 -> 5.8044544 | H38: =H37 -> 5.8044544 | I38: =I37 -> 5.8044544 | J38: =J37 -> 5.8044544 | K38: =K37 -> 5.8044544 | L38: =L37 -> 5.8044544 | M38: =M37 -> 12.814665 | ... AQ38: =AQ37 -> 0
B39: US040114GK09 | C39: =C11 -> USD Par 2038 I | F39: ='Kirchner EBs Cashflows'!AJ17 -> 1.875 | G39: ='Kirchner EBs Cashflows'!AK17 -> 1.875 | H39: ='Kirchner EBs Cashflows'!AL17 -> 1.875 | I39: ='Kirchner EBs Cashflows'!AM17 -> 1.875 | J39: ='Kirchner EBs Cashflows'!AN17 -> 1.875 | K39: ='Kirchner EBs Cashflows'!AO17 -> 1.875 | L39: ='Kirchner EBs Cashflows'!AP17 -> 1.875 | M39: ='Kirchner EBs Cashflows'!AQ17 -> 1.875 | ... AQ39: ='Kirchner EBs Cashflows'!BU17 -> 5.065625
B40: XS0501195647 | C40: =C12 -> USD Par 2038 II and III | F40: =F39 -> 1.875 | G40: =G39 -> 1.875 | H40: =H39 -> 1.875 | I40: =I39 -> 1.875 | J40: =J39 -> 1.875 | K40: =K39 -> 1.875 | L40: =L39 -> 1.875 | M40: =M39 -> 1.875 | ... AQ40: =AQ39 -> 5.065625
B41: XS0205545840 | C41: =C13 -> Euro 2033 Discount I | F41: ='Kirchner EBs Cashflows'!AJ27 -> 5.3943902 | G41: ='Kirchner EBs Cashflows'!AK27 -> 5.3943902 | H41: ='Kirchner EBs Cashflows'!AL27 -> 5.3943902 | I41: ='Kirchner EBs Cashflows'!AM27 -> 5.3943902 | J41: ='Kirchner EBs Cashflows'!AN27 -> 5.3943902 | K41: ='Kirchner EBs Cashflows'!AO27 -> 5.3943902 | L41: ='Kirchner EBs Cashflows'!AP27 -> 5.3943902 | M41: ='Kirchner EBs Cashflows'!AQ27 -> 12.292587 | ... AQ41: ='Kirchner EBs Cashflows'!BU27 -> 0
B42: XS0501195134 | C42: =C14 -> Euro 2033 Discount II and III | F42: =F41 -> 5.3943902 | G42: =G41 -> 5.3943902 | H42: =H41 -> 5.3943902 | I42: =I41 -> 5.3943902 | J42: =J41 -> 5.3943902 | K42: =K41 -> 5.3943902 | L42: =L41 -> 5.3943902 | M42: =M41 -> 12.292587 | ... AQ42: =AQ41 -> 0
B43: XS0205537581 | C43: =C15 -> Euro Par 2038 I | F43: ='Kirchner EBs Cashflows'!AJ35 -> 1.69 | G43: ='Kirchner EBs Cashflows'!AK35 -> 1.69 | H43: ='Kirchner EBs Cashflows'!AL35 -> 1.69 | I43: ='Kirchner EBs Cashflows'!AM35 -> 1.69 | J43: ='Kirchner EBs Cashflows'!AN35 -> 1.69 | K43: ='Kirchner EBs Cashflows'!AO35 -> 1.69 | L43: ='Kirchner EBs Cashflows'!AP35 -> 1.69 | M43: ='Kirchner EBs Cashflows'!AQ35 -> 1.69 | ... AQ43: ='Kirchner EBs Cashflows'!BU35 -> 5.05925
B44: XS0501195993 | C44: =C16 -> Euro Par 2038 II and III | F44: =F43 -> 1.69 | G44: =G43 -> 1.69 | H44: =H43 -> 1.69 | I44: =I43 -> 1.69 | J44: =J43 -> 1.69 | K44: =K43 -> 1.69 | L44: =L43 -> 1.69 | M44: =M43 -> 1.69 | ... AQ44: =AQ43 -> 5.05925
B45: US040114GW47 | C45: =C17 -> USD 2021 | F45: 3.4375 | G45: 103.4375
B46: US040114HK99 | C46: =C18 -> USD 2022 | F46: 2.8125 | G46: 2.8125 | H46: 102.8125
B47: US040114HP86 | C47: =C19 -> USD 2023 | F47: 2.3125 | G47: 2.3125 | H47: 2.3125 | I47: 2.3125 | J47: 102.3125
B48: US040114GX20 | C48: =C20 -> USD 2026 | F48: 3.75 | G48: 3.75 | H48: 3.75 | I48: 3.75 | J48: 3.75 | K48: 3.75 | L48: 3.75 | M48: 3.75 | N48: 3.75 | O48: 3.75 | P48: 3.75 | Q48: 103.75
B49: US040114HL72 | C49: =C21 -> USD 2027 | F49: 3.4375 | G49: 3.4375 | H49: 3.4375 | I49: 3.4375 | J49: 3.4375 | K49: 3.4375 | L49: 3.4375 | M49: 3.4375 | N49: 3.4375 | O49: 3.4375 | P49: 3.4375 | Q49: 3.4375 | R49: 103.4375
B50: US040114HQ69 | C50: =C22 -> USD 5.875% 2028 | F50: 2.9375 | G50: 2.9375 | H50: 2.9375 | I50: 2.9375 | J50: 2.9375 | K50: 2.9375 | L50: 2.9375 | M50: 2.9375 | N50: 2.9375 | O50: 2.9375 | P50: 2.9375 | Q50: 2.9375 | R50: 2.9375 | S50: 2.9375 | T50: 102.9375
B51: US040114HF05 | C51: =C23 -> USD 6.625% 2028 | F51: 3.3125 | G51: 3.3125 | H51: 3.3125 | I51: 3.3125 | J51: 3.3125 | K51: 3.3125 | L51: 3.3125 | M51: 3.3125 | N51: 3.3125 | O51: 3.3125 | P51: 3.3125 | Q51: 3.3125 | R51: 3.3125 | S51: 3.3125 | T51: 3.3125 | U51: 103.3125
B52: US040114HG87 | C52: =C24 -> USD 2036 | F52: 3.5625 | G52: 3.5625 | H52: 3.5625 | I52: 3.5625 | J52: 3.5625 | K52: 3.5625 | L52: 3.5625 | M52: 3.5625 | N52: 3.5625 | O52: 3.5625 | P52: 3.5625 | Q52: 3.5625 | R52: 3.5625 | S52: 3.5625 | T52: 3.5625 | U52: 3.5625 | V52: 3.5625 | W52: 3.5625 | X52: 3.5625 | Y52: 3.5625 | Z52: 3.5625 | AA52: 3.5625 | AB52: 3.5625 | AC52: 3.5625 | AD52: 3.5625 | AE52: 3.5625 | AF52: 3.5625 | AG52: 3.5625 | AH52: 3.5625 | AI52: 3.5625 | AJ52: 3.5625 | AK52: 103.5625
B53: US040114GY03 | C53: =C25 -> USD 2046 | F53: 3.8125 | G53: 3.8125 | H53: 3.8125 | I53: 3.8125 | J53: 3.8125 | K53: 3.8125 | L53: 3.8125 | M53: 3.8125 | N53: 3.8125 | O53: 3.8125 | P53: 3.8125 | Q53: 3.8125 | R53: 3.8125 | S53: 3.8125 | T53: 3.8125 | U53: 3.8125 | V53: 3.8125 | W53: 3.8125 | X53: 3.8125 | Y53: 3.8125 | Z53: 3.8125 | AA53: 3.8125 | AB53: 3.8125 | AC53: 3.8125 | AD53: 3.8125 | AE53: 3.8125 | AF53: 3.8125 | AG53: 3.8125 | AH53: 3.8125 | AI53: 3.8125 | AJ53: 3.8125 | AK53: 3.8125 | AL53: 3.8125 | AM53: 3.8125 | AN53: 3.8125 | AO53: 3.8125 | AP53: 3.8125 | AQ53: 3.8125 | AR53: 3.8125 | AS53: 3.8125 | AT53: 3.8125 | AU53: 3.8125 | AV53: 3.8125 | AW53: 3.8125 | AX53: 3.8125 | AY53: 3.8125 | AZ53: 3.8125 | BA53: 3.8125 | BB53: 3.8125 | BC53: 3.8125 | BD53: 3.8125 | BE53: 103.8125
B54: US040114HR43 | C54: =C26 -> USD 2048 | F54: 3.4375 | G54: 3.4375 | H54: 3.4375 | I54: 3.4375 | J54: 3.4375 | K54: 3.4375 | L54: 3.4375 | M54: 3.4375 | N54: 3.4375 | O54: 3.4375 | P54: 3.4375 | Q54: 3.4375 | R54: 3.4375 | S54: 3.4375 | T54: 3.4375 | U54: 3.4375 | V54: 3.4375 | W54: 3.4375 | X54: 3.4375 | Y54: 3.4375 | Z54: 3.4375 | AA54: 3.4375 | AB54: 3.4375 | AC54: 3.4375 | AD54: 3.4375 | AE54: 3.4375 | AF54: 3.4375 | AG54: 3.4375 | AH54: 3.4375 | AI54: 3.4375 | AJ54: 3.4375 | AK54: 3.4375 | AL54: 3.4375 | AM54: 3.4375 | AN54: 3.4375 | AO54: 3.4375 | AP54: 3.4375 | AQ54: 3.4375 | AR54: 3.4375 | AS54: 3.4375 | AT54: 3.4375 | AU54: 3.4375 | AV54: 3.4375 | AW54: 3.4375 | AX54: 3.4375 | AY54: 3.4375 | AZ54: 3.4375 | BA54: 3.4375 | BB54: 3.4375 | BC54: 3.4375 | BD54: 3.4375 | BE54: 3.4375 | BF54: 3.4375 | BG54: 3.4375 | BH54: 103.4375
B55: USP04808AN44 | C55: =C27 -> USD 2117 | F55: =7.125/2 -> 3.5625 | G55: =7.125/2 -> 3.5625 | H55: =7.125/2 -> 3.5625 | I55: =7.125/2 -> 3.5625 | J55: =7.125/2 -> 3.5625 | K55: =7.125/2 -> 3.5625 | L55: =7.125/2 -> 3.5625 | M55: =7.125/2 -> 3.5625 | ... GP55: =7.125/2 -> 3.5625 | GQ55: =100+7.125/2 -> 103.5625
B56: XS1503160225 | C56: =C28 -> Euro 2022 | F56: =3.875 -> 3.875 | G56: =100+3.875 -> 103.875
B57: XS1715303340 | C57: =C29 -> Euro 2023 | F57: 3.375 | G57: 3.375 | H57: =3.375+100 -> 103.375
B58: XS1503160498 | C58: =C30 -> Euro 2027 | F58: =5 -> 5 | G58: =5 -> 5 | H58: =5 -> 5 | I58: =5 -> 5 | J58: =5 -> 5 | K58: =5 -> 5 | L58: =100+5 -> 105
B59: XS1715303779 | C59: =C31 -> Euro 2028 | F59: 5.25 | G59: 5.25 | H59: 5.25 | I59: 5.25 | J59: 5.25 | K59: 5.25 | L59: 5.25 | M59: =100+5.25 -> 105.25
B60: XS1715535123 | C60: =C32 -> Euro 2047 | F60: 6.25 | G60: 6.25 | H60: 6.25 | I60: 6.25 | J60: 6.25 | K60: 6.25 | L60: 6.25 | M60: 6.25 | N60: 6.25 | O60: 6.25 | P60: 6.25 | Q60: 6.25 | R60: 6.25 | S60: 6.25 | T60: 6.25 | U60: 6.25 | V60: 6.25 | W60: 6.25 | X60: 6.25 | Y60: 6.25 | Z60: 6.25 | AA60: 6.25 | AB60: 6.25 | AC60: 6.25 | AD60: 6.25 | AE60: 6.25 | AF60: 6.25 | AG60: =100+6.25 -> 106.25
B61: CH0361824458 | C61: =C33 -> CHF 2020 | F61: =100+3.375 -> 103.375
B63: ISIN | C63: Short Name | E63: Time (years) between Payment Date and Current/Valuation Data. First column is zero if Accrued Interest is immediately due.
B64: US040114GL81 | C64: =C37 -> USD 2033 Discount I | F64: =IF(F9="","",(MAX(F9-$C$1,0)/365)) -> 0.29315068 | G64: =IF(G9="","",(MAX(G9-$C$1,0)/365)) -> 0.7890411 | H64: =IF(H9="","",(MAX(H9-$C$1,0)/365)) -> 1.2931507 | I64: =IF(I9="","",(MAX(I9-$C$1,0)/365)) -> 1.7890411 | J64: =IF(J9="","",(MAX(J9-$C$1,0)/365)) -> 2.2931507 | K64: =IF(K9="","",(MAX(K9-$C$1,0)/365)) -> 2.7890411 | L64: =IF(L9="","",(MAX(L9-$C$1,0)/365)) -> 3.2931507 | M64: =IF(M9="","",(MAX(M9-$C$1,0)/365)) -> 3.7917808 | ... GQ64: =IF(GQ9="","",(MAX(GQ9-$C$1,0)/365))
B65: XS0501194756 | C65: =C38 -> USD 2033 Discount II and III | F65: =IF(F10="","",(MAX(F10-$C$1,0)/365)) -> 0.29315068 | G65: =IF(G10="","",(MAX(G10-$C$1,0)/365)) -> 0.7890411 | H65: =IF(H10="","",(MAX(H10-$C$1,0)/365)) -> 1.2931507 | I65: =IF(I10="","",(MAX(I10-$C$1,0)/365)) -> 1.7890411 | J65: =IF(J10="","",(MAX(J10-$C$1,0)/365)) -> 2.2931507 | K65: =IF(K10="","",(MAX(K10-$C$1,0)/365)) -> 2.7890411 | L65: =IF(L10="","",(MAX(L10-$C$1,0)/365)) -> 3.2931507 | M65: =IF(M10="","",(MAX(M10-$C$1,0)/365)) -> 3.7917808 | ... GQ65: =IF(GQ10="","",(MAX(GQ10-$C$1,0)/365))
B66: US040114GK09 | C66: =C39 -> USD Par 2038 I | F66: =IF(F11="","",(MAX(F11-$C$1,0)/365)) -> 0.04109589 | G66: =IF(G11="","",(MAX(G11-$C$1,0)/365)) -> 0.53972603 | H66: =IF(H11="","",(MAX(H11-$C$1,0)/365)) -> 1.0410959 | I66: =IF(I11="","",(MAX(I11-$C$1,0)/365)) -> 1.539726 | J66: =IF(J11="","",(MAX(J11-$C$1,0)/365)) -> 2.0410959 | K66: =IF(K11="","",(MAX(K11-$C$1,0)/365)) -> 2.539726 | L66: =IF(L11="","",(MAX(L11-$C$1,0)/365)) -> 3.0410959 | M66: =IF(M11="","",(MAX(M11-$C$1,0)/365)) -> 3.5424658 | ... GQ66: =IF(GQ11="","",(MAX(GQ11-$C$1,0)/365))
B67: XS0501195647 | C67: =C40 -> USD Par 2038 II and III | F67: =IF(F12="","",(MAX(F12-$C$1,0)/365)) -> 0.04109589 | G67: =IF(G12="","",(MAX(G12-$C$1,0)/365)) -> 0.53972603 | H67: =IF(H12="","",(MAX(H12-$C$1,0)/365)) -> 1.0410959 | I67: =IF(I12="","",(MAX(I12-$C$1,0)/365)) -> 1.539726 | J67: =IF(J12="","",(MAX(J12-$C$1,0)/365)) -> 2.0410959 | K67: =IF(K12="","",(MAX(K12-$C$1,0)/365)) -> 2.539726 | L67: =IF(L12="","",(MAX(L12-$C$1,0)/365)) -> 3.0410959 | M67: =IF(M12="","",(MAX(M12-$C$1,0)/365)) -> 3.5424658 | ... GQ67: =IF(GQ12="","",(MAX(GQ12-$C$1,0)/365))
B68: XS0205545840 | C68: =C41 -> Euro 2033 Discount I | F68: =IF(F13="","",(MAX(F13-$C$1,0)/365)) -> 0.29315068 | G68: =IF(G13="","",(MAX(G13-$C$1,0)/365)) -> 0.7890411 | H68: =IF(H13="","",(MAX(H13-$C$1,0)/365)) -> 1.2931507 | I68: =IF(I13="","",(MAX(I13-$C$1,0)/365)) -> 1.7890411 | J68: =IF(J13="","",(MAX(J13-$C$1,0)/365)) -> 2.2931507 | K68: =IF(K13="","",(MAX(K13-$C$1,0)/365)) -> 2.7890411 | L68: =IF(L13="","",(MAX(L13-$C$1,0)/365)) -> 3.2931507 | M68: =IF(M13="","",(MAX(M13-$C$1,0)/365)) -> 3.7917808 | ... GQ68: =IF(GQ13="","",(MAX(GQ13-$C$1,0)/365))
B69: XS0501195134 | C69: =C42 -> Euro 2033 Discount II and III | F69: =IF(F14="","",(MAX(F14-$C$1,0)/365)) -> 0.29315068 | G69: =IF(G14="","",(MAX(G14-$C$1,0)/365)) -> 0.7890411 | H69: =IF(H14="","",(MAX(H14-$C$1,0)/365)) -> 1.2931507 | I69: =IF(I14="","",(MAX(I14-$C$1,0)/365)) -> 1.7890411 | J69: =IF(J14="","",(MAX(J14-$C$1,0)/365)) -> 2.2931507 | K69: =IF(K14="","",(MAX(K14-$C$1,0)/365)) -> 2.7890411 | L69: =IF(L14="","",(MAX(L14-$C$1,0)/365)) -> 3.2931507 | M69: =IF(M14="","",(MAX(M14-$C$1,0)/365)) -> 3.7917808 | ... GQ69: =IF(GQ14="","",(MAX(GQ14-$C$1,0)/365))
B70: XS0205537581 | C70: =C43 -> Euro Par 2038 I | F70: =IF(F15="","",(MAX(F15-$C$1,0)/365)) -> 0.04109589 | G70: =IF(G15="","",(MAX(G15-$C$1,0)/365)) -> 0.53972603 | H70: =IF(H15="","",(MAX(H15-$C$1,0)/365)) -> 1.0410959 | I70: =IF(I15="","",(MAX(I15-$C$1,0)/365)) -> 1.539726 | J70: =IF(J15="","",(MAX(J15-$C$1,0)/365)) -> 2.0410959 | K70: =IF(K15="","",(MAX(K15-$C$1,0)/365)) -> 2.539726 | L70: =IF(L15="","",(MAX(L15-$C$1,0)/365)) -> 3.0410959 | M70: =IF(M15="","",(MAX(M15-$C$1,0)/365)) -> 3.5424658 | ... GQ70: =IF(GQ15="","",(MAX(GQ15-$C$1,0)/365))
B71: XS0501195993 | C71: =C44 -> Euro Par 2038 II and III | F71: =IF(F16="","",(MAX(F16-$C$1,0)/365)) -> 0.04109589 | G71: =IF(G16="","",(MAX(G16-$C$1,0)/365)) -> 0.53972603 | H71: =IF(H16="","",(MAX(H16-$C$1,0)/365)) -> 1.0410959 | I71: =IF(I16="","",(MAX(I16-$C$1,0)/365)) -> 1.539726 | J71: =IF(J16="","",(MAX(J16-$C$1,0)/365)) -> 2.0410959 | K71: =IF(K16="","",(MAX(K16-$C$1,0)/365)) -> 2.539726 | L71: =IF(L16="","",(MAX(L16-$C$1,0)/365)) -> 3.0410959 | M71: =IF(M16="","",(MAX(M16-$C$1,0)/365)) -> 3.5424658 | ... GQ71: =IF(GQ16="","",(MAX(GQ16-$C$1,0)/365))
B72: =B45 -> US040114GW47 | C72: =C45 -> USD 2021 | F72: =IF(F17="","",(MAX(F17-$C$1,0)/365)) -> 0.10136986 | G72: =IF(G17="","",(MAX(G17-$C$1,0)/365)) -> 0.6 | H72: =IF(H17="","",(MAX(H17-$C$1,0)/365)) | I72: =IF(I17="","",(MAX(I17-$C$1,0)/365)) | J72: =IF(J17="","",(MAX(J17-$C$1,0)/365)) | K72: =IF(K17="","",(MAX(K17-$C$1,0)/365)) | L72: =IF(L17="","",(MAX(L17-$C$1,0)/365)) | M72: =IF(M17="","",(MAX(M17-$C$1,0)/365)) | ... GQ72: =IF(GQ17="","",(MAX(GQ17-$C$1,0)/365))
B73: =B46 -> US040114HK99 | C73: =C46 -> USD 2022 | F73: =IF(F18="","",(MAX(F18-$C$1,0)/365)) -> 0.36438356 | G73: =IF(G18="","",(MAX(G18-$C$1,0)/365)) -> 0.86027397 | H73: =IF(H18="","",(MAX(H18-$C$1,0)/365)) -> 1.3643836 | I73: =IF(I18="","",(MAX(I18-$C$1,0)/365)) | J73: =IF(J18="","",(MAX(J18-$C$1,0)/365)) | K73: =IF(K18="","",(MAX(K18-$C$1,0)/365)) | L73: =IF(L18="","",(MAX(L18-$C$1,0)/365)) | M73: =IF(M18="","",(MAX(M18-$C$1,0)/365)) | ... GQ73: =IF(GQ18="","",(MAX(GQ18-$C$1,0)/365))
B74: =B47 -> US040114HP86 | C74: =C47 -> USD 2023 | F74: =IF(F19="","",(MAX(F19-$C$1,0)/365)) -> 0.32328767 | G74: =IF(G19="","",(MAX(G19-$C$1,0)/365)) -> 0.81917808 | H74: =IF(H19="","",(MAX(H19-$C$1,0)/365)) -> 1.3232877 | I74: =IF(I19="","",(MAX(I19-$C$1,0)/365)) -> 1.8191781 | J74: =IF(J19="","",(MAX(J19-$C$1,0)/365)) -> 2.3232877 | K74: =IF(K19="","",(MAX(K19-$C$1,0)/365)) | L74: =IF(L19="","",(MAX(L19-$C$1,0)/365)) | M74: =IF(M19="","",(MAX(M19-$C$1,0)/365)) | ... GQ74: =IF(GQ19="","",(MAX(GQ19-$C$1,0)/365))
B75: =B48 -> US040114GX20 | C75: =C48 -> USD 2026 | F75: =IF(F20="","",(MAX(F20-$C$1,0)/365)) -> 0.10136986 | G75: =IF(G20="","",(MAX(G20-$C$1,0)/365)) -> 0.6 | H75: =IF(H20="","",(MAX(H20-$C$1,0)/365)) -> 1.1013699 | I75: =IF(I20="","",(MAX(I20-$C$1,0)/365)) -> 1.6 | J75: =IF(J20="","",(MAX(J20-$C$1,0)/365)) -> 2.1013699 | K75: =IF(K20="","",(MAX(K20-$C$1,0)/365)) -> 2.6 | L75: =IF(L20="","",(MAX(L20-$C$1,0)/365)) -> 3.1013699 | M75: =IF(M20="","",(MAX(M20-$C$1,0)/365)) -> 3.6027397 | ... GQ75: =IF(GQ20="","",(MAX(GQ20-$C$1,0)/365))
B76: =B49 -> US040114HL72 | C76: =C49 -> USD 2027 | F76: =IF(F21="","",(MAX(F21-$C$1,0)/365)) -> 0.36438356 | G76: =IF(G21="","",(MAX(G21-$C$1,0)/365)) -> 0.86027397 | H76: =IF(H21="","",(MAX(H21-$C$1,0)/365)) -> 1.3643836 | I76: =IF(I21="","",(MAX(I21-$C$1,0)/365)) -> 1.860274 | J76: =IF(J21="","",(MAX(J21-$C$1,0)/365)) -> 2.3643836 | K76: =IF(K21="","",(MAX(K21-$C$1,0)/365)) -> 2.860274 | L76: =IF(L21="","",(MAX(L21-$C$1,0)/365)) -> 3.3643836 | M76: =IF(M21="","",(MAX(M21-$C$1,0)/365)) -> 3.8630137 | ... GQ76: =IF(GQ21="","",(MAX(GQ21-$C$1,0)/365))
B77: =B50 -> US040114HQ69 | C77: =C50 -> USD 5.875% 2028 | F77: =IF(F22="","",(MAX(F22-$C$1,0)/365)) -> 0.32328767 | G77: =IF(G22="","",(MAX(G22-$C$1,0)/365)) -> 0.81917808 | H77: =IF(H22="","",(MAX(H22-$C$1,0)/365)) -> 1.3232877 | I77: =IF(I22="","",(MAX(I22-$C$1,0)/365)) -> 1.8191781 | J77: =IF(J22="","",(MAX(J22-$C$1,0)/365)) -> 2.3232877 | K77: =IF(K22="","",(MAX(K22-$C$1,0)/365)) -> 2.8191781 | L77: =IF(L22="","",(MAX(L22-$C$1,0)/365)) -> 3.3232877 | M77: =IF(M22="","",(MAX(M22-$C$1,0)/365)) -> 3.8219178 | ... GQ77: =IF(GQ22="","",(MAX(GQ22-$C$1,0)/365))
B78: =B51 -> US040114HF05 | C78: =C51 -> USD 6.625% 2028 | F78: =IF(F23="","",(MAX(F23-$C$1,0)/365)) -> 0.30958904 | G78: =IF(G23="","",(MAX(G23-$C$1,0)/365)) -> 0.80547945 | H78: =IF(H23="","",(MAX(H23-$C$1,0)/365)) -> 1.309589 | I78: =IF(I23="","",(MAX(I23-$C$1,0)/365)) -> 1.8054795 | J78: =IF(J23="","",(MAX(J23-$C$1,0)/365)) -> 2.309589 | K78: =IF(K23="","",(MAX(K23-$C$1,0)/365)) -> 2.8054795 | L78: =IF(L23="","",(MAX(L23-$C$1,0)/365)) -> 3.309589 | M78: =IF(M23="","",(MAX(M23-$C$1,0)/365)) -> 3.8082192 | ... GQ78: =IF(GQ23="","",(MAX(GQ23-$C$1,0)/365))
B79: =B52 -> US040114HG87 | C79: =C52 -> USD 2036 | F79: =IF(F24="","",(MAX(F24-$C$1,0)/365)) -> 0.30958904 | G79: =IF(G24="","",(MAX(G24-$C$1,0)/365)) -> 0.80547945 | H79: =IF(H24="","",(MAX(H24-$C$1,0)/365)) -> 1.309589 | I79: =IF(I24="","",(MAX(I24-$C$1,0)/365)) -> 1.8054795 | J79: =IF(J24="","",(MAX(J24-$C$1,0)/365)) -> 2.309589 | K79: =IF(K24="","",(MAX(K24-$C$1,0)/365)) -> 2.8054795 | L79: =IF(L24="","",(MAX(L24-$C$1,0)/365)) -> 3.309589 | M79: =IF(M24="","",(MAX(M24-$C$1,0)/365)) -> 3.8082192 | ... GQ79: =IF(GQ24="","",(MAX(GQ24-$C$1,0)/365))
B80: =B53 -> US040114GY03 | C80: =C53 -> USD 2046 | F80: =IF(F25="","",(MAX(F25-$C$1,0)/365)) -> 0.10136986 | G80: =IF(G25="","",(MAX(G25-$C$1,0)/365)) -> 0.6 | H80: =IF(H25="","",(MAX(H25-$C$1,0)/365)) -> 1.1013699 | I80: =IF(I25="","",(MAX(I25-$C$1,0)/365)) -> 1.6 | J80: =IF(J25="","",(MAX(J25-$C$1,0)/365)) -> 2.1013699 | K80: =IF(K25="","",(MAX(K25-$C$1,0)/365)) -> 2.6 | L80: =IF(L25="","",(MAX(L25-$C$1,0)/365)) -> 3.1013699 | M80: =IF(M25="","",(MAX(M25-$C$1,0)/365)) -> 3.6027397 | ... GQ80: =IF(GQ25="","",(MAX(GQ25-$C$1,0)/365))
B81: =B54 -> US040114HR43 | C81: =C54 -> USD 2048 | F81: =IF(F26="","",(MAX(F26-$C$1,0)/365)) -> 0.32328767 | G81: =IF(G26="","",(MAX(G26-$C$1,0)/365)) -> 0.81917808 | H81: =IF(H26="","",(MAX(H26-$C$1,0)/365)) -> 1.3232877 | I81: =IF(I26="","",(MAX(I26-$C$1,0)/365)) -> 1.8191781 | J81: =IF(J26="","",(MAX(J26-$C$1,0)/365)) -> 2.3232877 | K81: =IF(K26="","",(MAX(K26-$C$1,0)/365)) -> 2.8191781 | L81: =IF(L26="","",(MAX(L26-$C$1,0)/365)) -> 3.3232877 | M81: =IF(M26="","",(MAX(M26-$C$1,0)/365)) -> 3.8219178 | ... GQ81: =IF(GQ26="","",(MAX(GQ26-$C$1,0)/365))
B82: =B55 -> USP04808AN44 | C82: =C55 -> USD 2117 | F82: =IF(F27="","",(MAX(F27-$C$1,0)/365)) -> 0.28493151 | G82: =IF(G27="","",(MAX(G27-$C$1,0)/365)) -> 0.78356164 | H82: =IF(H27="","",(MAX(H27-$C$1,0)/365)) -> 1.2849315 | I82: =IF(I27="","",(MAX(I27-$C$1,0)/365)) -> 1.7835616 | J82: =IF(J27="","",(MAX(J27-$C$1,0)/365)) -> 2.2849315 | K82: =IF(K27="","",(MAX(K27-$C$1,0)/365)) -> 2.7835616 | L82: =IF(L27="","",(MAX(L27-$C$1,0)/365)) -> 3.2849315 | M82: =IF(M27="","",(MAX(M27-$C$1,0)/365)) -> 3.7863014 | ... GQ82: =IF(GQ27="","",(MAX(GQ27-$C$1,0)/365)) -> 96.846575
B83: XS1503160225 | C83: =C56 -> Euro 2022 | F83: =IF(F28="","",(MAX(F28-$C$1,0)/365)) -> 0.33424658 | G83: =IF(G28="","",(MAX(G28-$C$1,0)/365)) -> 1.3342466 | H83: =IF(H28="","",(MAX(H28-$C$1,0)/365)) | I83: =IF(I28="","",(MAX(I28-$C$1,0)/365)) | J83: =IF(J28="","",(MAX(J28-$C$1,0)/365)) | K83: =IF(K28="","",(MAX(K28-$C$1,0)/365)) | L83: =IF(L28="","",(MAX(L28-$C$1,0)/365)) | M83: =IF(M28="","",(MAX(M28-$C$1,0)/365)) | ... GQ83: =IF(GQ28="","",(MAX(GQ28-$C$1,0)/365))
B84: XS1715303340 | C84: =C57 -> Euro 2023 | F84: =IF(F29="","",(MAX(F29-$C$1,0)/365)) -> 0.33424658 | G84: =IF(G29="","",(MAX(G29-$C$1,0)/365)) -> 1.3342466 | H84: =IF(H29="","",(MAX(H29-$C$1,0)/365)) -> 2.3342466 | I84: =IF(I29="","",(MAX(I29-$C$1,0)/365)) | J84: =IF(J29="","",(MAX(J29-$C$1,0)/365)) | K84: =IF(K29="","",(MAX(K29-$C$1,0)/365)) | L84: =IF(L29="","",(MAX(L29-$C$1,0)/365)) | M84: =IF(M29="","",(MAX(M29-$C$1,0)/365)) | ... GQ84: =IF(GQ29="","",(MAX(GQ29-$C$1,0)/365))
B85: XS1503160498 | C85: =C58 -> Euro 2027 | F85: =IF(F30="","",(MAX(F30-$C$1,0)/365)) -> 0.33424658 | G85: =IF(G30="","",(MAX(G30-$C$1,0)/365)) -> 1.3342466 | H85: =IF(H30="","",(MAX(H30-$C$1,0)/365)) -> 2.3342466 | I85: =IF(I30="","",(MAX(I30-$C$1,0)/365)) -> 3.3342466 | J85: =IF(J30="","",(MAX(J30-$C$1,0)/365)) -> 4.3369863 | K85: =IF(K30="","",(MAX(K30-$C$1,0)/365)) -> 5.3369863 | L85: =IF(L30="","",(MAX(L30-$C$1,0)/365)) -> 6.3369863 | M85: =IF(M30="","",(MAX(M30-$C$1,0)/365)) | ... GQ85: =IF(GQ30="","",(MAX(GQ30-$C$1,0)/365))
B86: XS1715303779 | C86: =C59 -> Euro 2028 | F86: =IF(F31="","",(MAX(F31-$C$1,0)/365)) -> 0.33424658 | G86: =IF(G31="","",(MAX(G31-$C$1,0)/365)) -> 1.3342466 | H86: =IF(H31="","",(MAX(H31-$C$1,0)/365)) -> 2.3342466 | I86: =IF(I31="","",(MAX(I31-$C$1,0)/365)) -> 3.3342466 | J86: =IF(J31="","",(MAX(J31-$C$1,0)/365)) -> 4.3369863 | K86: =IF(K31="","",(MAX(K31-$C$1,0)/365)) -> 5.3369863 | L86: =IF(L31="","",(MAX(L31-$C$1,0)/365)) -> 6.3369863 | M86: =IF(M31="","",(MAX(M31-$C$1,0)/365)) -> 7.3369863 | ... GQ86: =IF(GQ31="","",(MAX(GQ31-$C$1,0)/365))
B87: XS1715535123 | C87: =C60 -> Euro 2047 | F87: =IF(F32="","",(MAX(F32-$C$1,0)/365)) -> 0.15068493 | G87: =IF(G32="","",(MAX(G32-$C$1,0)/365)) -> 1.1506849 | H87: =IF(H32="","",(MAX(H32-$C$1,0)/365)) -> 2.1506849 | I87: =IF(I32="","",(MAX(I32-$C$1,0)/365)) -> 3.1506849 | J87: =IF(J32="","",(MAX(J32-$C$1,0)/365)) -> 4.1534247 | K87: =IF(K32="","",(MAX(K32-$C$1,0)/365)) -> 5.1534247 | L87: =IF(L32="","",(MAX(L32-$C$1,0)/365)) -> 6.1534247 | M87: =IF(M32="","",(MAX(M32-$C$1,0)/365)) -> 7.1534247 | ... GQ87: =IF(GQ32="","",(MAX(GQ32-$C$1,0)/365))
B88: CH0361824458 | C88: =C61 -> CHF 2020 | F88: =IF(F33="","",(MAX(F33-$C$1,0)/365)) -> 0.073972603 | G88: =IF(G33="","",(MAX(G33-$C$1,0)/365)) | H88: =IF(H33="","",(MAX(H33-$C$1,0)/365)) | I88: =IF(I33="","",(MAX(I33-$C$1,0)/365)) | J88: =IF(J33="","",(MAX(J33-$C$1,0)/365)) | K88: =IF(K33="","",(MAX(K33-$C$1,0)/365)) | L88: =IF(L33="","",(MAX(L33-$C$1,0)/365)) | M88: =IF(M33="","",(MAX(M33-$C$1,0)/365)) | ... GQ88: =IF(GQ33="","",(MAX(GQ33-$C$1,0)/365))
H89: =INDEX($C$3:$C$6,MATCH($A91,$B$3:$B$6,0)) -> 11.341845
B90: ISIN | C90: Short Name | E90: Discounted Cash Flows | G90: Computing accrued only for first payment (if t<0.5 for seminannual, or if t<1 for annual)
A91: USD2005 | B91: US040114GL81 | C91: =C64 -> USD 2033 Discount I | E91: =IF(E64="","",E37/(1+ INDEX($C$3:$C$6,MATCH($A91,$B$3:$B$6,0))/100)^E64) | F91: =IF(F64="","",F37*MIN(F64/0.5,1)/(1+ INDEX($C$3:$C$6,MATCH($A91,$B$3:$B$6,0))/100)^F64) -> 3.2976485 | G91: =IF(G64="","",G37/(1+ INDEX($C$3:$C$6,MATCH($A91,$B$3:$B$6,0))/100)^G64) -> 5.3326858 | H91: =IF(H64="","",H37/(1+ INDEX($C$3:$C$6,MATCH($A91,$B$3:$B$6,0))/100)^H64) -> 5.0515545 | I91: =IF(I64="","",I37/(1+ INDEX($C$3:$C$6,MATCH($A91,$B$3:$B$6,0))/100)^I64) -> 4.7894714 | J91: =IF(J64="","",J37/(1+ INDEX($C$3:$C$6,MATCH($A91,$B$3:$B$6,0))/100)^J64) -> 4.5369776 | K91: =IF(K64="","",K37/(1+ INDEX($C$3:$C$6,MATCH($A91,$B$3:$B$6,0))/100)^K64) -> 4.3015916 | L91: =IF(L64="","",L37/(1+ INDEX($C$3:$C$6,MATCH($A91,$B$3:$B$6,0))/100)^L64) -> 4.074818 | M91: =IF(M64="","",M37/(1+ INDEX($C$3:$C$6,MATCH($A91,$B$3:$B$6,0))/100)^M64) -> 8.5268531 | N91: =IF(N64="","",N37/(1+ INDEX($C$3:$C$6,MATCH($A91,$B$3:$B$6,0))/100)^N64) -> 7.8943971 | ... GQ91: =IF(GQ64="","",GQ37/(1+ INDEX($C$3:$C$6,MATCH($A91,$B$3:$B$6,0))/100)^GQ64)
A92: USD2005 | B92: XS0501194756 | C92: =C65 -> USD 2033 Discount II and III | E92: =IF(E65="","",E38/(1+ INDEX($C$3:$C$6,MATCH($A92,$B$3:$B$6,0))/100)^E65) | F92: =IF(F65="","",F38*MIN(F65/0.5,1)/(1+ INDEX($C$3:$C$6,MATCH($A92,$B$3:$B$6,0))/100)^F65) -> 3.2976485 | G92: =IF(G65="","",G38/(1+ INDEX($C$3:$C$6,MATCH($A92,$B$3:$B$6,0))/100)^G65) -> 5.3326858 | H92: =IF(H65="","",H38/(1+ INDEX($C$3:$C$6,MATCH($A92,$B$3:$B$6,0))/100)^H65) -> 5.0515545 | I92: =IF(I65="","",I38/(1+ INDEX($C$3:$C$6,MATCH($A92,$B$3:$B$6,0))/100)^I65) -> 4.7894714 | J92: =IF(J65="","",J38/(1+ INDEX($C$3:$C$6,MATCH($A92,$B$3:$B$6,0))/100)^J65) -> 4.5369776 | K92: =IF(K65="","",K38/(1+ INDEX($C$3:$C$6,MATCH($A92,$B$3:$B$6,0))/100)^K65) -> 4.3015916 | L92: =IF(L65="","",L38/(1+ INDEX($C$3:$C$6,MATCH($A92,$B$3:$B$6,0))/100)^L65) -> 4.074818 | M92: =IF(M65="","",M38/(1+ INDEX($C$3:$C$6,MATCH($A92,$B$3:$B$6,0))/100)^M65) -> 8.5268531 | N92: =IF(N65="","",N38/(1+ INDEX($C$3:$C$6,MATCH($A92,$B$3:$B$6,0))/100)^N65) -> 7.8943971 | ... GQ92: =IF(GQ65="","",GQ38/(1+ INDEX($C$3:$C$6,MATCH($A92,$B$3:$B$6,0))/100)^GQ65)
A93: USD2005 | B93: US040114GK09 | C93: =C66 -> USD Par 2038 I | E93: =IF(E66="","",E39/(1+ INDEX($C$3:$C$6,MATCH($A93,$B$3:$B$6,0))/100)^E66) | F93: =IF(F66="","",F39*MIN(F66/0.5,1)/(1+ INDEX($C$3:$C$6,MATCH($A93,$B$3:$B$6,0))/100)^F66) -> 0.15343067 | G93: =IF(G66="","",G39/(1+ INDEX($C$3:$C$6,MATCH($A93,$B$3:$B$6,0))/100)^G66) -> 1.7693694 | H93: =IF(H66="","",H39/(1+ INDEX($C$3:$C$6,MATCH($A93,$B$3:$B$6,0))/100)^H66) -> 1.6765843 | I93: =IF(I66="","",I39/(1+ INDEX($C$3:$C$6,MATCH($A93,$B$3:$B$6,0))/100)^I66) -> 1.5891325 | J93: =IF(J66="","",J39/(1+ INDEX($C$3:$C$6,MATCH($A93,$B$3:$B$6,0))/100)^J66) -> 1.5057989 | K93: =IF(K66="","",K39/(1+ INDEX($C$3:$C$6,MATCH($A93,$B$3:$B$6,0))/100)^K66) -> 1.4272554 | L93: =IF(L66="","",L39/(1+ INDEX($C$3:$C$6,MATCH($A93,$B$3:$B$6,0))/100)^L66) -> 1.3524106 | M93: =IF(M66="","",M39/(1+ INDEX($C$3:$C$6,MATCH($A93,$B$3:$B$6,0))/100)^M66) -> 1.2814906 | N93: =IF(N66="","",N39/(1+ INDEX($C$3:$C$6,MATCH($A93,$B$3:$B$6,0))/100)^N66) -> 1.2142897 | ... GQ93: =IF(GQ66="","",GQ39/(1+ INDEX($C$3:$C$6,MATCH($A93,$B$3:$B$6,0))/100)^GQ66)
A94: USD2005 | B94: XS0501195647 | C94: =C67 -> USD Par 2038 II and III | E94: =IF(E67="","",E40/(1+ INDEX($C$3:$C$6,MATCH($A94,$B$3:$B$6,0))/100)^E67) | F94: =IF(F67="","",F40*MIN(F67/0.5,1)/(1+ INDEX($C$3:$C$6,MATCH($A94,$B$3:$B$6,0))/100)^F67) -> 0.15343067 | G94: =IF(G67="","",G40/(1+ INDEX($C$3:$C$6,MATCH($A94,$B$3:$B$6,0))/100)^G67) -> 1.7693694 | H94: =IF(H67="","",H40/(1+ INDEX($C$3:$C$6,MATCH($A94,$B$3:$B$6,0))/100)^H67) -> 1.6765843 | I94: =IF(I67="","",I40/(1+ INDEX($C$3:$C$6,MATCH($A94,$B$3:$B$6,0))/100)^I67) -> 1.5891325 | J94: =IF(J67="","",J40/(1+ INDEX($C$3:$C$6,MATCH($A94,$B$3:$B$6,0))/100)^J67) -> 1.5057989 | K94: =IF(K67="","",K40/(1+ INDEX($C$3:$C$6,MATCH($A94,$B$3:$B$6,0))/100)^K67) -> 1.4272554 | L94: =IF(L67="","",L40/(1+ INDEX($C$3:$C$6,MATCH($A94,$B$3:$B$6,0))/100)^L67) -> 1.3524106 | M94: =IF(M67="","",M40/(1+ INDEX($C$3:$C$6,MATCH($A94,$B$3:$B$6,0))/100)^M67) -> 1.2814906 | N94: =IF(N67="","",N40/(1+ INDEX($C$3:$C$6,MATCH($A94,$B$3:$B$6,0))/100)^N67) -> 1.2142897 | ... GQ94: =IF(GQ67="","",GQ40/(1+ INDEX($C$3:$C$6,MATCH($A94,$B$3:$B$6,0))/100)^GQ67)
A95: EUR2005 | B95: XS0205545840 | C95: =C68 -> Euro 2033 Discount I | E95: =IF(E68="","",E41/(1+ INDEX($C$3:$C$6,MATCH($A95,$B$3:$B$6,0))/100)^E68) | F95: =IF(F68="","",F41*MIN(F68/0.5,1)/(1+ INDEX($C$3:$C$6,MATCH($A95,$B$3:$B$6,0))/100)^F68) -> 3.048318 | G95: =IF(G68="","",G41/(1+ INDEX($C$3:$C$6,MATCH($A95,$B$3:$B$6,0))/100)^G68) -> 4.8850486 | H95: =IF(H68="","",H41/(1+ INDEX($C$3:$C$6,MATCH($A95,$B$3:$B$6,0))/100)^H68) -> 4.5851097 | I95: =IF(I68="","",I41/(1+ INDEX($C$3:$C$6,MATCH($A95,$B$3:$B$6,0))/100)^I68) -> 4.3080353 | J95: =IF(J68="","",J41/(1+ INDEX($C$3:$C$6,MATCH($A95,$B$3:$B$6,0))/100)^J68) -> 4.0435247 | K95: =IF(K68="","",K41/(1+ INDEX($C$3:$C$6,MATCH($A95,$B$3:$B$6,0))/100)^K68) -> 3.7991779 | L95: =IF(L68="","",L41/(1+ INDEX($C$3:$C$6,MATCH($A95,$B$3:$B$6,0))/100)^L68) -> 3.5659107 | M95: =IF(M68="","",M41/(1+ INDEX($C$3:$C$6,MATCH($A95,$B$3:$B$6,0))/100)^M68) -> 7.6322287 | N95: =IF(N68="","",N41/(1+ INDEX($C$3:$C$6,MATCH($A95,$B$3:$B$6,0))/100)^N68) -> 7.0064333 | ... GQ95: =IF(GQ68="","",GQ41/(1+ INDEX($C$3:$C$6,MATCH($A95,$B$3:$B$6,0))/100)^GQ68)
A96: EUR2005 | B96: XS0501195134 | C96: =C69 -> Euro 2033 Discount II and III | E96: =IF(E69="","",E42/(1+ INDEX($C$3:$C$6,MATCH($A96,$B$3:$B$6,0))/100)^E69) | F96: =IF(F69="","",F42*MIN(F69/0.5,1)/(1+ INDEX($C$3:$C$6,MATCH($A96,$B$3:$B$6,0))/100)^F69) -> 3.048318 | G96: =IF(G69="","",G42/(1+ INDEX($C$3:$C$6,MATCH($A96,$B$3:$B$6,0))/100)^G69) -> 4.8850486 | H96: =IF(H69="","",H42/(1+ INDEX($C$3:$C$6,MATCH($A96,$B$3:$B$6,0))/100)^H69) -> 4.5851097 | I96: =IF(I69="","",I42/(1+ INDEX($C$3:$C$6,MATCH($A96,$B$3:$B$6,0))/100)^I69) -> 4.3080353 | J96: =IF(J69="","",J42/(1+ INDEX($C$3:$C$6,MATCH($A96,$B$3:$B$6,0))/100)^J69) -> 4.0435247 | K96: =IF(K69="","",K42/(1+ INDEX($C$3:$C$6,MATCH($A96,$B$3:$B$6,0))/100)^K69) -> 3.7991779 | L96: =IF(L69="","",L42/(1+ INDEX($C$3:$C$6,MATCH($A96,$B$3:$B$6,0))/100)^L69) -> 3.5659107 | M96: =IF(M69="","",M42/(1+ INDEX($C$3:$C$6,MATCH($A96,$B$3:$B$6,0))/100)^M69) -> 7.6322287 | N96: =IF(N69="","",N42/(1+ INDEX($C$3:$C$6,MATCH($A96,$B$3:$B$6,0))/100)^N69) -> 7.0064333 | ... GQ96: =IF(GQ69="","",GQ42/(1+ INDEX($C$3:$C$6,MATCH($A96,$B$3:$B$6,0))/100)^GQ69)
A97: EUR2005 | B97: XS0205537581 | C97: =C70 -> Euro Par 2038 I | E97: =IF(E70="","",E43/(1+ INDEX($C$3:$C$6,MATCH($A97,$B$3:$B$6,0))/100)^E70) | F97: =IF(F70="","",F43*MIN(F70/0.5,1)/(1+ INDEX($C$3:$C$6,MATCH($A97,$B$3:$B$6,0))/100)^F70) -> 0.13818843 | G97: =IF(G70="","",G43/(1+ INDEX($C$3:$C$6,MATCH($A97,$B$3:$B$6,0))/100)^G70) -> 1.5791495 | H97: =IF(H70="","",H43/(1+ INDEX($C$3:$C$6,MATCH($A97,$B$3:$B$6,0))/100)^H70) -> 1.4827013 | I97: =IF(I70="","",I43/(1+ INDEX($C$3:$C$6,MATCH($A97,$B$3:$B$6,0))/100)^I70) -> 1.3926232 | J97: =IF(J70="","",J43/(1+ INDEX($C$3:$C$6,MATCH($A97,$B$3:$B$6,0))/100)^J70) -> 1.3075672 | K97: =IF(K70="","",K43/(1+ INDEX($C$3:$C$6,MATCH($A97,$B$3:$B$6,0))/100)^K70) -> 1.228129 | L97: =IF(L70="","",L43/(1+ INDEX($C$3:$C$6,MATCH($A97,$B$3:$B$6,0))/100)^L70) -> 1.1531197 | M97: =IF(M70="","",M43/(1+ INDEX($C$3:$C$6,MATCH($A97,$B$3:$B$6,0))/100)^M70) -> 1.0826917 | N97: =IF(N70="","",N43/(1+ INDEX($C$3:$C$6,MATCH($A97,$B$3:$B$6,0))/100)^N70) -> 1.0165651 | ... GQ97: =IF(GQ70="","",GQ43/(1+ INDEX($C$3:$C$6,MATCH($A97,$B$3:$B$6,0))/100)^GQ70)
A98: EUR2005 | B98: XS0501195993 | C98: =C71 -> Euro Par 2038 II and III | E98: =IF(E71="","",E44/(1+ INDEX($C$3:$C$6,MATCH($A98,$B$3:$B$6,0))/100)^E71) | F98: =IF(F71="","",F44*MIN(F71/0.5,1)/(1+ INDEX($C$3:$C$6,MATCH($A98,$B$3:$B$6,0))/100)^F71) -> 0.13818843 | G98: =IF(G71="","",G44/(1+ INDEX($C$3:$C$6,MATCH($A98,$B$3:$B$6,0))/100)^G71) -> 1.5791495 | H98: =IF(H71="","",H44/(1+ INDEX($C$3:$C$6,MATCH($A98,$B$3:$B$6,0))/100)^H71) -> 1.4827013 | I98: =IF(I71="","",I44/(1+ INDEX($C$3:$C$6,MATCH($A98,$B$3:$B$6,0))/100)^I71) -> 1.3926232 | J98: =IF(J71="","",J44/(1+ INDEX($C$3:$C$6,MATCH($A98,$B$3:$B$6,0))/100)^J71) -> 1.3075672 | K98: =IF(K71="","",K44/(1+ INDEX($C$3:$C$6,MATCH($A98,$B$3:$B$6,0))/100)^K71) -> 1.228129 | L98: =IF(L71="","",L44/(1+ INDEX($C$3:$C$6,MATCH($A98,$B$3:$B$6,0))/100)^L71) -> 1.1531197 | M98: =IF(M71="","",M44/(1+ INDEX($C$3:$C$6,MATCH($A98,$B$3:$B$6,0))/100)^M71) -> 1.0826917 | N98: =IF(N71="","",N44/(1+ INDEX($C$3:$C$6,MATCH($A98,$B$3:$B$6,0))/100)^N71) -> 1.0165651 | ... GQ98: =IF(GQ71="","",GQ44/(1+ INDEX($C$3:$C$6,MATCH($A98,$B$3:$B$6,0))/100)^GQ71)
A99: USD2016 | B99: =B72 -> US040114GW47 | C99: =C72 -> USD 2021 | E99: =IF(E72="","",E45/(1+ INDEX($C$3:$C$6,MATCH($A99,$B$3:$B$6,0))/100)^E72) | F99: =IF(F72="","",F45*MIN(F72/0.5,1)/(1+ INDEX($C$3:$C$6,MATCH($A99,$B$3:$B$6,0))/100)^F72) -> 0.68926121 | G99: =IF(G72="","",G45/(1+ INDEX($C$3:$C$6,MATCH($A99,$B$3:$B$6,0))/100)^G72) -> 96.890386 | H99: =IF(H72="","",H45/(1+ INDEX($C$3:$C$6,MATCH($A99,$B$3:$B$6,0))/100)^H72) | I99: =IF(I72="","",I45/(1+ INDEX($C$3:$C$6,MATCH($A99,$B$3:$B$6,0))/100)^I72) | J99: =IF(J72="","",J45/(1+ INDEX($C$3:$C$6,MATCH($A99,$B$3:$B$6,0))/100)^J72) | K99: =IF(K72="","",K45/(1+ INDEX($C$3:$C$6,MATCH($A99,$B$3:$B$6,0))/100)^K72) | L99: =IF(L72="","",L45/(1+ INDEX($C$3:$C$6,MATCH($A99,$B$3:$B$6,0))/100)^L72) | M99: =IF(M72="","",M45/(1+ INDEX($C$3:$C$6,MATCH($A99,$B$3:$B$6,0))/100)^M72) | N99: =IF(N72="","",N45/(1+ INDEX($C$3:$C$6,MATCH($A99,$B$3:$B$6,0))/100)^N72) | ... GQ99: =IF(GQ72="","",GQ45/(1+ INDEX($C$3:$C$6,MATCH($A99,$B$3:$B$6,0))/100)^GQ72)
A100: USD2016 | B100: =B73 -> US040114HK99 | C100: =C73 -> USD 2022 | E100: =IF(E73="","",E46/(1+ INDEX($C$3:$C$6,MATCH($A100,$B$3:$B$6,0))/100)^E73) | F100: =IF(F73="","",F46*MIN(F73/0.5,1)/(1+ INDEX($C$3:$C$6,MATCH($A100,$B$3:$B$6,0))/100)^F73) -> 1.9698603 | G100: =IF(G73="","",G46/(1+ INDEX($C$3:$C$6,MATCH($A100,$B$3:$B$6,0))/100)^G73) -> 2.5608063 | H100: =IF(H73="","",H46/(1+ INDEX($C$3:$C$6,MATCH($A100,$B$3:$B$6,0))/100)^H73) -> 88.607641 | I100: =IF(I73="","",I46/(1+ INDEX($C$3:$C$6,MATCH($A100,$B$3:$B$6,0))/100)^I73) | J100: =IF(J73="","",J46/(1+ INDEX($C$3:$C$6,MATCH($A100,$B$3:$B$6,0))/100)^J73) | K100: =IF(K73="","",K46/(1+ INDEX($C$3:$C$6,MATCH($A100,$B$3:$B$6,0))/100)^K73) | L100: =IF(L73="","",L46/(1+ INDEX($C$3:$C$6,MATCH($A100,$B$3:$B$6,0))/100)^L73) | M100: =IF(M73="","",M46/(1+ INDEX($C$3:$C$6,MATCH($A100,$B$3:$B$6,0))/100)^M73) | N100: =IF(N73="","",N46/(1+ INDEX($C$3:$C$6,MATCH($A100,$B$3:$B$6,0))/100)^N73) | ... GQ100: =IF(GQ73="","",GQ46/(1+ INDEX($C$3:$C$6,MATCH($A100,$B$3:$B$6,0))/100)^GQ73)
A101: USD2016 | B101: =B74 -> US040114HP86 | C101: =C74 -> USD 2023 | E101: =IF(E74="","",E47/(1+ INDEX($C$3:$C$6,MATCH($A101,$B$3:$B$6,0))/100)^E74) | F101: =IF(F74="","",F47*MIN(F74/0.5,1)/(1+ INDEX($C$3:$C$6,MATCH($A101,$B$3:$B$6,0))/100)^F74) -> 1.4434443 | G101: =IF(G74="","",G47/(1+ INDEX($C$3:$C$6,MATCH($A101,$B$3:$B$6,0))/100)^G74) -> 2.1150029 | H101: =IF(H74="","",H47/(1+ INDEX($C$3:$C$6,MATCH($A101,$B$3:$B$6,0))/100)^H74) -> 2.0019444 | I101: =IF(I74="","",I47/(1+ INDEX($C$3:$C$6,MATCH($A101,$B$3:$B$6,0))/100)^I74) -> 1.8966277 | J101: =IF(J74="","",J47/(1+ INDEX($C$3:$C$6,MATCH($A101,$B$3:$B$6,0))/100)^J74) -> 79.427353 | K101: =IF(K74="","",K47/(1+ INDEX($C$3:$C$6,MATCH($A101,$B$3:$B$6,0))/100)^K74) | L101: =IF(L74="","",L47/(1+ INDEX($C$3:$C$6,MATCH($A101,$B$3:$B$6,0))/100)^L74) | M101: =IF(M74="","",M47/(1+ INDEX($C$3:$C$6,MATCH($A101,$B$3:$B$6,0))/100)^M74) | N101: =IF(N74="","",N47/(1+ INDEX($C$3:$C$6,MATCH($A101,$B$3:$B$6,0))/100)^N74) | ... GQ101: =IF(GQ74="","",GQ47/(1+ INDEX($C$3:$C$6,MATCH($A101,$B$3:$B$6,0))/100)^GQ74)
A102: USD2016 | B102: =B75 -> US040114GX20 | C102: =C75 -> USD 2026 | E102: =IF(E75="","",E48/(1+ INDEX($C$3:$C$6,MATCH($A102,$B$3:$B$6,0))/100)^E75) | F102: =IF(F75="","",F48*MIN(F75/0.5,1)/(1+ INDEX($C$3:$C$6,MATCH($A102,$B$3:$B$6,0))/100)^F75) -> 0.75192132 | G102: =IF(G75="","",G48/(1+ INDEX($C$3:$C$6,MATCH($A102,$B$3:$B$6,0))/100)^G75) -> 3.5126424 | H102: =IF(H75="","",H48/(1+ INDEX($C$3:$C$6,MATCH($A102,$B$3:$B$6,0))/100)^H75) -> 3.3258654 | I102: =IF(I75="","",I48/(1+ INDEX($C$3:$C$6,MATCH($A102,$B$3:$B$6,0))/100)^I75) -> 3.1499601 | J102: =IF(J75="","",J48/(1+ INDEX($C$3:$C$6,MATCH($A102,$B$3:$B$6,0))/100)^J75) -> 2.9824679 | K102: =IF(K75="","",K48/(1+ INDEX($C$3:$C$6,MATCH($A102,$B$3:$B$6,0))/100)^K75) -> 2.824725 | L102: =IF(L75="","",L48/(1+ INDEX($C$3:$C$6,MATCH($A102,$B$3:$B$6,0))/100)^L75) -> 2.6745265 | M102: =IF(M75="","",M48/(1+ INDEX($C$3:$C$6,MATCH($A102,$B$3:$B$6,0))/100)^M75) -> 2.5323144 | N102: =IF(N75="","",N48/(1+ INDEX($C$3:$C$6,MATCH($A102,$B$3:$B$6,0))/100)^N75) -> 2.3976642 | ... GQ102: =IF(GQ75="","",GQ48/(1+ INDEX($C$3:$C$6,MATCH($A102,$B$3:$B$6,0))/100)^GQ75)
A103: USD2016 | B103: =B76 -> US040114HL72 | C103: =C76 -> USD 2027 | E103: =IF(E76="","",E49/(1+ INDEX($C$3:$C$6,MATCH($A103,$B$3:$B$6,0))/100)^E76) | F103: =IF(F76="","",F49*MIN(F76/0.5,1)/(1+ INDEX($C$3:$C$6,MATCH($A103,$B$3:$B$6,0))/100)^F76) -> 2.4076071 | G103: =IF(G76="","",G49/(1+ INDEX($C$3:$C$6,MATCH($A103,$B$3:$B$6,0))/100)^G76) -> 3.1298743 | H103: =IF(H76="","",H49/(1+ INDEX($C$3:$C$6,MATCH($A103,$B$3:$B$6,0))/100)^H76) -> 2.9625655 | I103: =IF(I76="","",I49/(1+ INDEX($C$3:$C$6,MATCH($A103,$B$3:$B$6,0))/100)^I76) -> 2.8067131 | J103: =IF(J76="","",J49/(1+ INDEX($C$3:$C$6,MATCH($A103,$B$3:$B$6,0))/100)^J76) -> 2.656679 | K103: =IF(K76="","",K49/(1+ INDEX($C$3:$C$6,MATCH($A103,$B$3:$B$6,0))/100)^K76) -> 2.5169184 | L103: =IF(L76="","",L49/(1+ INDEX($C$3:$C$6,MATCH($A103,$B$3:$B$6,0))/100)^L76) -> 2.3823754 | M103: =IF(M76="","",M49/(1+ INDEX($C$3:$C$6,MATCH($A103,$B$3:$B$6,0))/100)^M76) -> 2.2563714 | N103: =IF(N76="","",N49/(1+ INDEX($C$3:$C$6,MATCH($A103,$B$3:$B$6,0))/100)^N76) -> 2.1357561 | ... GQ103: =IF(GQ76="","",GQ49/(1+ INDEX($C$3:$C$6,MATCH($A103,$B$3:$B$6,0))/100)^GQ76)
...

Sheet EBs Prices
GH1: -6 months | JV1: -3 months | KY1: -2 months | ME1: -1 month | MO1: xxx | NJ1: exchange settlement date
D2: (Composite Mid Price)
A3: Short Name | B3: Issue date | C3: ISIN (SEC) | D3: (CMPM) | E3: 43709 | F3: 43710 | G3: 43711 | H3: 43712 | I3: 43713 | J3: 43714 | K3: 43715 | L3: 43716 | M3: 43717 | N3: 43718 | O3: 43719 | P3: 43720 | Q3: 43721 | R3: 43722 | S3: 43723 | T3: 43724 | U3: 43725 | V3: 43726 | W3: 43727 | X3: 43728 | Y3: 43729 | Z3: 43730 | AA3: 43731 | AB3: 43732 | AC3: 43733 | AD3: 43734 | AE3: 43735 | AF3: 43736 | AG3: 43737 | AH3: 43738 | AI3: 43739 | AJ3: 43740 | AK3: 43741 | AL3: 43742 | AM3: 43743 | AN3: 43744 | AO3: 43745 | AP3: 43746 | AQ3: 43747 | AR3: 43748 | AS3: 43749 | AT3: 43750 | AU3: 43751 | AV3: 43752 | AW3: 43753 | AX3: 43754 | AY3: 43755 | AZ3: 43756 | BA3: 43757 | BB3: 43758 | BC3: 43759 | BD3: 43760 | BE3: 43761 | BF3: 43762 | BG3: 43763 | BH3: 43764 | BI3: 43765 | BJ3: 43766 | BK3: 43767 | BL3: 43768 | BM3: 43769 | BN3: 43770 | BO3: 43771 | BP3: 43772 | BQ3: 43773 | BR3: 43774 | BS3: 43775 | BT3: 43776 | BU3: 43777 | BV3: 43778 | BW3: 43779 | BX3: 43780 | BY3: 43781 | BZ3: 43782 | CA3: 43783 | CB3: 43784 | CC3: 43785 | CD3: 43786 | CE3: 43787 | CF3: 43788 | CG3: 43789 | CH3: 43790 | CI3: 43791 | CJ3: 43792 | CK3: 43793 | CL3: 43794 | CM3: 43795 | CN3: 43796 | CO3: 43797 | CP3: 43798 | CQ3: 43799 | CR3: 43800 | CS3: 43801 | CT3: 43802 | CU3: 43803 | CV3: 43804 | CW3: 43805 | CX3: 43806 | CY3: 43807 | CZ3: 43808 | DA3: 43809 | DB3: 43810 | DC3: 43811 | DD3: 43812 | DE3: 43813 | DF3: 43814 | DG3: 43815 | DH3: 43816 | DI3: 43817 | DJ3: 43818 | DK3: 43819 | DL3: 43820 | DM3: 43821 | DN3: 43822 | DO3: 43823 | DP3: 43824 | DQ3: 43825 | DR3: 43826 | DS3: 43827 | DT3: 43828 | DU3: 43829 | DV3: 43830 | DW3: 43831 | DX3: 43832 | DY3: 43833 | DZ3: 43834 | EA3: 43835 | EB3: 43836 | EC3: 43837 | ED3: 43838 | EE3: 43839 | EF3: 43840 | EG3: 43841 | EH3: 43842 | EI3: 43843 | EJ3: 43844 | EK3: 43845 | EL3: 43846 | EM3: 43847 | EN3: 43848 | EO3: 43849 | EP3: 43850 | EQ3: 43851 | ER3: 43852 | ES3: 43853 | ET3: 43854 | EU3: 43855 | EV3: 43856 | EW3: 43857 | EX3: 43858 | EY3: 43859 | EZ3: 43860 | FA3: 43861 | FB3: 43862 | FC3: 43863 | FD3: 43864 | FE3: 43865 | FF3: 43866 | FG3: 43867 | FH3: 43868 | FI3: 43869 | FJ3: 43870 | FK3: 43871 | FL3: 43872 | FM3: 43873 | FN3: 43874 | FO3: 43875 | FP3: 43876 | FQ3: 43877 | FR3: 43878 | FS3: 43879 | FT3: 43880 | FU3: 43881 | FV3: 43882 | FW3: 43883 | FX3: 43884 | FY3: 43885 | FZ3: 43886 | GA3: 43887 | GB3: 43888 | GC3: 43889 | GD3: 43890 | GE3: 43891 | GF3: 43892 | GG3: 43893 | GH3: 43894 | GI3: 43895 | GJ3: 43896 | GK3: 43897 | GL3: 43898 | GM3: 43899 | GN3: 43900 | GO3: 43901 | GP3: 43902 | GQ3: 43903 | GR3: 43904 | GS3: 43905 | GT3: 43906 | GU3: 43907 | GV3: 43908 | GW3: 43909 | GX3: 43910 | GY3: 43911 | GZ3: 43912 | HA3: 43913 | HB3: 43914 | HC3: 43915 | HD3: 43916 | HE3: 43917 | HF3: 43918 | HG3: 43919 | HH3: 43920 | HI3: 43921 | HJ3: 43922 | HK3: 43923 | HL3: 43924 | HM3: 43925 | HN3: 43926 | HO3: 43927 | HP3: 43928 | HQ3: 43929 | HR3: 43930 | HS3: 43931 | HT3: 43932 | HU3: 43933 | HV3: 43934 | HW3: 43935 | HX3: 43936 | HY3: 43937 | HZ3: 43938 | IA3: 43939 | IB3: 43940 | IC3: 43941 | ID3: 43942 | IE3: 43943 | IF3: 43944 | IG3: 43945 | IH3: 43946 | II3: 43947 | IJ3: 43948 | IK3: 43949 | IL3: 43950 | IM3: 43951 | IN3: 43952 | IO3: 43953 | IP3: 43954 | IQ3: 43955 | IR3: 43956 | IS3: 43957 | IT3: 43958 | IU3: 43959 | IV3: 43960 | IW3: 43961 | IX3: 43962 | IY3: 43963 | IZ3: 43964 | JA3: 43965 | JB3: 43966 | JC3: 43967 | JD3: 43968 | JE3: 43969 | JF3: 43970 | JG3: 43971 | JH3: 43972 | JI3: 43973 | JJ3: 43974 | JK3: 43975 | JL3: 43976 | JM3: 43977 | JN3: 43978 | JO3: 43979 | JP3: 43980 | JQ3: 43981 | JR3: 43982 | JS3: 43983 | JT3: 43984 | JU3: 43985 | JV3: 43986 | JW3: 43987 | JX3: 43988 | JY3: 43989 | JZ3: 43990 | KA3: 43991 | KB3: 43992 | KC3: 43993 | KD3: 43994 | KE3: 43995 | KF3: 43996 | KG3: 43997 | KH3: 43998 | KI3: 43999 | KJ3: 44000 | KK3: 44001 | KL3: 44002 | KM3: 44003 | KN3: 44004 | KO3: 44005 | KP3: 44006 | KQ3: 44007 | KR3: 44008 | KS3: 44009 | KT3: 44010 | KU3: 44011 | KV3: 44012 | KW3: 44013 | KX3: 44014 | KY3: 44015 | KZ3: 44016 | LA3: 44017 | LB3: 44018 | LC3: 44019 | LD3: 44020 | LE3: 44021 | LF3: 44022 | LG3: 44023 | LH3: 44024 | LI3: 44025 | LJ3: 44026 | LK3: 44027 | LL3: 44028 | LM3: 44029 | LN3: 44030 | LO3: 44031 | LP3: 44032 | LQ3: 44033 | LR3: 44034 | LS3: 44035 | LT3: 44036 | LU3: 44037 | LV3: 44038 | LW3: 44039 | LX3: 44040 | LY3: 44041 | LZ3: 44042 | MA3: 44043 | MB3: 44044 | MC3: 44045 | MD3: 44046 | ME3: 44047 | MF3: 44048 | MG3: 44049 | MH3: 44050 | MI3: 44051 | MJ3: 44052 | MK3: 44053 | ML3: 44054 | MM3: 44055 | MN3: 44056 | MO3: 44057 | MP3: 44058 | MQ3: 44059 | MR3: 44060 | MS3: 44061 | MT3: 44062 | MU3: 44063 | MV3: 44064 | MW3: 44065 | MX3: 44066 | MY3: 44067 | MZ3: 44068 | NA3: 44069 | NB3: 44070 | NC3: 44071 | ND3: 44072 | NE3: 44073 | NF3: 44074 | NG3: 44075 | NH3: 44076 | NI3: 44077 | NJ3: 44078 | NK3: 44079 | NL3: 44080 | NM3: 44081 | NN3: 44082 | NO3: 44083 | NP3: 44084 | NQ3: 44085 | NR3: 44086 | NS3: 44087 | NT3: 44088 | NU3: 44089 | NV3: 44090 | NW3: 44091 | NX3: 44092 | NY3: 44093 | NZ3: 44094 | OA3: 44095 | OB3: 44096 | OC3: 44097 | OD3: 44098 | OE3: 44099 | OF3: 44100 | OG3: 44101 | OH3: 44102 | OI3: 44103 | OJ3: 44104 | OK3: 44105 | OL3: 44106 | OM3: 44107 | ON3: 44108 | OO3: 44109 | OP3: 44110 | OQ3: 44111 | OR3: 44112 | OS3: 44113 | OT3: 44114 | OU3: 44115 | OV3: 44116 | OW3: 44117 | OX3: 44118 | OY3: 44119 | OZ3: 44120 | PA3: 44121 | PB3: 44122 | PC3: 44123 | PD3: 44124 | PE3: 44125 | PF3: 44126 | PG3: 44127 | PH3: 44128 | PI3: 44129 | PJ3: 44130 | PK3: 44131 | PL3: 44132 | PM3: 44133 | PN3: 44134 | PO3: 44135 | PP3: 44136 | PQ3: 44137 | PR3: 44138 | PS3: 44139 | PT3: 44140 | PU3: 44141 | PV3: 44142 | PW3: 44143 | PX3: 44144 | PY3: 44145 | PZ3: 44146 | QA3: 44147 | QB3: 44148 | QC3: 44149 | QD3: 44150 | QE3: 44151 | QF3: 44152 | QG3: 44153 | QH3: 44154 | QI3: 44155 | QJ3: 44156 | QK3: 44157 | QL3: 44158 | QM3: 44159 | QN3: 44160 | QO3: 44161
A4: USD 2033 Discount I | B4: 38626 | C4: US040114GL81 | F4: 41.5 | G4: 41.4375 | H4: 44.3125 | I4: 46 | J4: 48.5 | M4: 50.2745 | N4: 48.4375 | O4: 48.625 | P4: 48 | Q4: 47.4175 | T4: 46.6945 | U4: 47.5245 | V4: 48.761 | W4: 48.4375 | X4: 49.125 | AA4: 48.4375 | AB4: 48 | AC4: 47.7115 | AD4: 48.25 | AE4: 49.375 | AH4: 49.6875 | AI4: 49.5625 | AJ4: 49.6875 | AK4: 49.9375 | AL4: 50.4375 | AO4: 51.375 | AP4: 51.128 | AQ4: 52.625 | AR4: 54 | AS4: 55 | AV4: 55.415 | AW4: 55.75 | AX4: 54.75 | AY4: 55.5 | AZ4: 54.5 | BC4: 53.125 | BD4: 52.3125 | BE4: 52.75 | BF4: 53.825 | BG4: 53.016 | BJ4: 51.25 | BK4: 51.58 | BL4: 51 | BM4: 51.3675 | BN4: 51.572 | BQ4: 51.475 | BR4: 51.241 | BS4: 51.355 | BT4: 50.5 | BU4: 48.91 | BX4: 49.0625 | BY4: 46.6875 | BZ4: 46.8125 | CA4: 47.64 | CB4: 46.375 | CE4: 47.12 | CF4: 48.5625 | CG4: 49 | CH4: 50.25 | CI4: 50 | CL4: 48.5 | CM4: 49.625 | CN4: 49.511 | CO4: 49.75 | CP4: 49.648 | CS4: 49 | CT4: 47.86 | CU4: 48.75 | CV4: 48.625 | CW4: 49 | CZ4: 51.03 | DA4: 51.5 | DB4: 51.717 | DC4: 53.375 | DD4: 53.3125 | DG4: 53.625 | DH4: 56.0625 | DI4: 58.0625 | DJ4: 57.4375 | DK4: 56.75 | DN4: 58.252 | DO4: 57.75 | DP4: 57.75 | DQ4: 57.75 | DR4: 62.775 | DU4: 61.0225 | DV4: 61.125 | DW4: 61.125 | DX4: 61.375 | DY4: 61.495 | EB4: 59 | EC4: 60.95 | ED4: 62 | EE4: 62.5 | EF4: 62.27 | EI4: 62.375 | EJ4: 62.0305 | EK4: 61.75 | EL4: 63 | EM4: 61.993 | EP4: 61.5 | EQ4: 60.0625 | ER4: 59.0265 | ES4: 58.5 | ET4: 57.7595 | EW4: 55.125 | EX4: 55.111 | EY4: 55.875 | EZ4: 56.125 | FA4: 56 | FD4: 56.625 | FE4: 58.4465 | FF4: 59.25 | FG4: 59 | FH4: 60.1875 | FK4: 60.125 | FL4: 58.0625 | FM4: 58.857 | FN4: 58 | FO4: 57.8125 | FR4: 57.6975 | FS4: 57.5 | FT4: 57.5165 | FU4: 56.5 | FV4: 56.6215 | FY4: 57 | FZ4: 56.8195 | GA4: 57 | GB4: 56.8035 | GC4: 53.9375 | GF4: 54.1875 | GG4: 55.0625 | GH4: 55.25 | GI4: 54.5 | GJ4: 50.6875 | GM4: 51.197 | GN4: 45.5 | GO4: 44.6475 | GP4: 40.625 | GQ4: 40.4375 | GT4: 39.5665 | GU4: 38.25 | GV4: 37.48 | GW4: 34.25 | GX4: 34.5 | HA4: 33.875 | HB4: 33.702 | HC4: 32.8835 | HD4: 33.125 | HE4: 34.04 | HH4: 34.3195 | HI4: 34.5 | HJ4: 35.5425 | HK4: 35.909 | HL4: 37.0305 | HO4: 38.164 | HP4: 37.25 | HQ4: 36.625 | HR4: 37.4445 | HS4: 36.375 | HV4: 36.75 | HW4: 36.25 | HX4: 35.75 | HY4: 35.5 | HZ4: 36.125 | IC4: 36.9925 | ID4: 37.396 | IE4: 36.375 | IF4: 34.875 | IG4: 34.5 | IJ4: 35.125 | IK4: 35.812 | IL4: 36.859 | IM4: 35.375 | IN4: 34.5 | IQ4: 33.25 | IR4: 33 | IS4: 33.25 | IT4: 33.5 | IU4: 34.375 | IX4: 35 | IY4: 38.125 | IZ4: 37.5 | JA4: 37.4635 | JB4: 39.9685 | JE4: 41.163 | JF4: 42.2085 | JG4: 42.687 | JH4: 42 | JI4: 41.7935 | JL4: 41.355 | JM4: 41.449 | JN4: 41.449 | JO4: 45.295 | JP4: 45.3995 | JS4: 45.3995 | JT4: 46.25 | JU4: 48.094 | JV4: 48.375 | JW4: 48.125 | JZ4: 47.75 | KA4: 47.9075 | KB4: 46.5 | KC4: 46 | KD4: 46 | KG4: 45.375 | KH4: 46.125 | KI4: 45.8075 | KJ4: 44.848 | KK4: 46 | KN4: 46.125 | KO4: 46.875 | KP4: 45.875 | KQ4: 45.8595 | KR4: 45.25 | KU4: 45.774 | KV4: 45.25 | KW4: 44.875 | KX4: 45.5 | KY4: 45.5 | LB4: 47.5 | LC4: 48 | LD4: 49.375 | LE4: 48.375 | LF4: 48.875 | LI4: 49.24 | LJ4: 48.631 | LK4: 48.875 | LL4: 49.625 | LM4: 49.625 | LP4: 49.6305 | LQ4: 49.75 | LR4: 50.375 | LS4: 51.985 | LT4: 51.4875 | LW4: 51.25 | LX4: 50.75 | LY4: 49.875 | LZ4: 50.5 | MA4: 51 | MD4: 50.955 | ME4: 54.875 | MF4: 54.974 | MG4: 54.875 | MH4: 55.125 | MK4: 53.5 | ML4: 54.5 | MM4: 54.75 | MN4: 54.5515 | MO4: 53.875 | MR4: 53.5 | MS4: 53.375 | MT4: 53.167 | MU4: 52.75 | MV4: 53.0385 | MY4: 53.0435 | MZ4: 52.86 | NA4: 49.94 | NB4: 49.94 | NC4: 49.94 | NF4: 51.38 | NG4: 51.145 | NH4: 51.145 | NI4: 51.145 | NJ4: 51.145
A5: USD 2033 Discount II and III | B5: 40296 | C5: XS0501194756 | F5: 39.75 | G5: 39.75 | H5: 39.75 | I5: 44 | J5: 45.5 | M5: 49.5 | N5: 45 | O5: 47.25 | P5: 48 | Q5: 48 | T5: 45.5 | U5: 45.5 | V5: 47.5 | W5: 47.5 | X5: 47.5 | AA5: 47.5 | AB5: 46.75 | AC5: 46.75 | AD5: 48.125 | AE5: 48 | AH5: 49.125 | AI5: 48.5 | AJ5: 49.5 | AK5: 49.5 | AL5: 49.5 | AO5: 49.5 | AP5: 49.5 | AQ5: 49.5 | AR5: 49.5 | AS5: 49.5 | AV5: 49.5 | AW5: 49.5 | AX5: 49.5 | AY5: 49.5 | AZ5: 49.5 | BC5: 49.5 | BD5: 52.25 | BE5: 52.625 | BF5: 53.5 | BG5: 52.125 | BJ5: 51.5 | BK5: 50.375 | BL5: 51 | BM5: 51 | BN5: 50.5 | BQ5: 50.5 | BR5: 50.5 | BS5: 50 | BT5: 50.5 | BU5: 50.5 | BX5: 50.5 | BY5: 50.5 | BZ5: 50.5 | CA5: 50.5 | CB5: 50.5 | CE5: 50.5 | CF5: 50.5 | CG5: 50.5 | CH5: 50.5 | CI5: 50.5 | CL5: 50.5 | CM5: 50.5 | CN5: 50.5 | CO5: 50.5 | CP5: 50.5 | CS5: 50.5 | CT5: 50.5 | CU5: 50.5 | CV5: 50.5 | CW5: 50.5 | CZ5: 50.5 | DA5: 50.5 | DB5: 50.5 | DC5: 50.5 | DD5: 50.5 | DG5: 50.5 | DH5: 50.5 | DI5: 50.5 | DJ5: 50.5 | DK5: 50.5 | DN5: 57.75 | DO5: 57.75 | DP5: 56.75 | DQ5: 59.25 | DR5: 60.625 | DU5: 61.125 | DV5: 61.125 | DW5: 61.125 | DX5: 61.375 | DY5: 59.75 | EB5: 59 | EC5: 58.5 | ED5: 60.25 | EE5: 61.5 | EF5: 62.5 | EI5: 62.375 | EJ5: 59.25 | EK5: 61.5 | EL5: 62.25 | EM5: 60.5 | EP5: 61.25 | EQ5: 59.375 | ER5: 58.25 | ES5: 57.875 | ET5: 56.75 | EW5: 55 | EX5: 55.125 | EY5: 55.875 | EZ5: 55.25 | FA5: 55.25 | FD5: 56.25 | FE5: 57 | FF5: 58.75 | FG5: 58.5 | FH5: 59.625 | FK5: 59.5 | FL5: 59.25 | FM5: 58.5 | FN5: 57.125 | FO5: 57.375 | FR5: 58.375 | FS5: 57.25 | FT5: 57.375 | FU5: 56 | FV5: 57.375 | FY5: 56.75 | FZ5: 56 | GA5: 56.75 | GB5: 54.25 | GC5: 53.625 | GF5: 53.5 | GG5: 54.75 | GH5: 54.5 | GI5: 53.125 | GJ5: 50.875 | GM5: 46 | GN5: 44.75 | GO5: 42.25 | GP5: 40.375 | GQ5: 40.125 | GT5: 36.25 | GU5: 37.25 | GV5: 34.125 | GW5: 34.25 | GX5: 34.5 | HA5: 31.25 | HB5: 30.875 | HC5: 32.25 | HD5: 33.125 | HE5: 33.375 | HH5: 33.5 | HI5: 34.5 | HJ5: 34.375 | HK5: 35.25 | HL5: 35.625 | HO5: 37.5 | HP5: 37.25 | HQ5: 36.625 | HR5: 36.375 | HS5: 36.375 | HV5: 36.75 | HW5: 35.5 | HX5: 35.75 | HY5: 34.5 | HZ5: 34.25 | IC5: 34.25 | ID5: 37.875 | IE5: 36.375 | IF5: 34.875 | IG5: 34.5 | IJ5: 34.875 | IK5: 35.375 | IL5: 35.75 | IM5: 35.375 | IN5: 33.5 | IQ5: 31.5 | IR5: 33 | IS5: 33.875 | IT5: 34.875 | IU5: 34.375 | IX5: 36.625 | IY5: 38.125 | IZ5: 37.5 | JA5: 37 | JB5: 38.125 | JE5: 40.125 | JF5: 40.75 | JG5: 40.625 | JH5: 42 | JI5: 41.875 | JL5: 41.875 | JM5: 45 | JN5: 44.75 | JO5: 44 | JP5: 46.375 | JS5: 46.125 | JT5: 46.25 | JU5: 46.625 | JV5: 46.5 | JW5: 48.125 | JZ5: 47.75 | KA5: 44.875 | KB5: 46.5 | KC5: 46 | KD5: 46 | KG5: 45.375 | KH5: 46.125 | KI5: 46 | KJ5: 45 | KK5: 46 | KN5: 46.125 | KO5: 46.875 | KP5: 45.75 | KQ5: 45.75 | KR5: 45.25 | KU5: 44.125 | KV5: 45.25 | KW5: 45.375 | KX5: 45.5 | KY5: 45.5 | LB5: 47.5 | LC5: 48 | LD5: 49.375 | LE5: 48.375 | LF5: 48.875 | LI5: 48.875 | LJ5: 48.875 | LK5: 48.875 | LL5: 49.625 | LM5: 49.625 | LP5: 49.5 | LQ5: 49.75 | LR5: 50.375 | LS5: 51.375 | LT5: 51.625 | LW5: 51.25 | LX5: 50.75 | LY5: 49.875 | LZ5: 50.5 | MA5: 51 | MD5: 50.625 | ME5: 54.875 | MF5: 54.625 | MG5: 54.875 | MH5: 52.75 | MK5: 52.375 | ML5: 54.5 | MM5: 54.75 | MN5: 52 | MO5: 53.875 | MR5: 53.5 | MS5: 53.375 | MT5: 53.125 | MU5: 52.75 | MV5: 52.75 | MY5: 52.75 | MZ5: 52.75 | NA5: 53 | NB5: 50.25 | NC5: 52.5 | NF5: 52.625 | NG5: 53.75 | NH5: 52.125 | NI5: 50.75 | NJ5: 50.5
A6: USD 2033 Discount III | B6: 40296 | C6: XS0501195050 | F6: 38.25 | G6: 38.5 | H6: 40 | I6: 43.25 | J6: 46.25 | M6: 47 | N6: 45.25 | O6: 46.75 | P6: 47.75 | Q6: 47.75 | T6: 47.75 | U6: 47.75 | V6: 47.25 | W6: 47.25 | X6: 47.25 | AA6: 47.25 | AB6: 47.25 | AC6: 47.25 | AD6: 47.25 | AE6: 47.25 | AH6: 48.875 | AI6: 48.25 | AJ6: 48.75 | AK6: 48.75 | AL6: 48.75 | AO6: 48.75 | AP6: 48.75 | AQ6: 48.75 | AR6: 48.75 | AS6: 48.75 | AV6: 48.75 | AW6: 48.75 | AX6: 48.75 | AY6: 48.75 | AZ6: 48.75 | BC6: 48.75 | BD6: 52 | BE6: 52.375 | BF6: 53.375 | BG6: 51.875 | BJ6: 51.25 | BK6: 51.25 | BL6: 50.75 | BM6: 50.75 | BN6: 51 | BQ6: 51 | BR6: 51 | BS6: 51 | BT6: 50.25 | BU6: 50.5 | BX6: 50.5 | BY6: 50.5 | BZ6: 50.5 | CA6: 50.5 | CB6: 50.5 | CE6: 50.5 | CF6: 50.5 | CG6: 50.5 | CH6: 50.5 | CI6: 50.5 | CL6: 50.5 | CM6: 50.5 | CN6: 48.5 | CO6: 48.5 | CP6: 48.5 | CS6: 48.5 | CT6: 48.5 | CU6: 48.5 | CV6: 48.5 | CW6: 48.5 | CZ6: 48.5 | DA6: 48.5 | DB6: 48.5 | DC6: 48.5 | DD6: 48.5 | DG6: 48.5 | DH6: 48.5 | DI6: 48.5 | DJ6: 48.5 | DK6: 48.5 | DN6: 57.5 | DO6: 57.5 | DP6: 56.5 | DQ6: 59 | DR6: 60.375 | DU6: 60.875 | DV6: 60.875 | DW6: 60.875 | DX6: 61.125 | DY6: 59.5 | EB6: 58.75 | EC6: 58.25 | ED6: 60.5 | EE6: 61.25 | EF6: 62.25 | EI6: 62.125 | EJ6: 59 | EK6: 61.25 | EL6: 62 | EM6: 60.25 | EP6: 61 | EQ6: 59.125 | ER6: 58 | ES6: 57.625 | ET6: 56.5 | EW6: 54.75 | EX6: 54.875 | EY6: 55.625 | EZ6: 55 | FA6: 55 | FD6: 56 | FE6: 56.75 | FF6: 58.5 | FG6: 58.25 | FH6: 59.375 | FK6: 59.25 | FL6: 59 | FM6: 58.25 | FN6: 56.875 | FO6: 57.125 | FR6: 58.125 | FS6: 57 | FT6: 57.125 | FU6: 55.75 | FV6: 57.125 | FY6: 56.5 | FZ6: 55.75 | GA6: 56.5 | GB6: 54 | GC6: 53.375 | GF6: 53.25 | GG6: 54.5 | GH6: 54.25 | GI6: 52.875 | GJ6: 50.625 | GM6: 45.75 | GN6: 44.5 | GO6: 42 | GP6: 40.125 | GQ6: 39.875 | GT6: 36 | GU6: 37 | GV6: 33.875 | GW6: 34 | GX6: 34.25 | HA6: 31 | HB6: 30.625 | HC6: 32 | HD6: 32.875 | HE6: 33.125 | HH6: 33.25 | HI6: 34.25 | HJ6: 34.125 | HK6: 35 | HL6: 35.375 | HO6: 37.25 | HP6: 37 | HQ6: 36.375 | HR6: 36.125 | HS6: 36.125 | HV6: 36.5 | HW6: 35.25 | HX6: 35.5 | HY6: 34.25 | HZ6: 34 | IC6: 34 | ID6: 37.625 | IE6: 36.125 | IF6: 34.625 | IG6: 34.25 | IJ6: 34.625 | IK6: 35.125 | IL6: 35.5 | IM6: 35.125 | IN6: 33.25 | IQ6: 31.25 | IR6: 32.75 | IS6: 33.625 | IT6: 34.625 | IU6: 34.125 | IX6: 36.375 | IY6: 37.875 | IZ6: 37.25 | JA6: 36.75 | JB6: 37.875 | JE6: 39.875 | JF6: 40.5 | JG6: 40.375 | JH6: 41.75 | JI6: 41.625 | JL6: 41.625 | JM6: 44.75 | JN6: 44.5 | JO6: 43.75 | JP6: 46.125 | JS6: 45.875 | JT6: 46 | JU6: 46.375 | JV6: 46.25 | JW6: 47.875 | JZ6: 47.5 | KA6: 44.625 | KB6: 46.25 | KC6: 45.75 | KD6: 45.75 | KG6: 45.125 | KH6: 45.875 | KI6: 45.75 | KJ6: 44.75 | KK6: 45.75 | KN6: 45.875 | KO6: 46.625 | KP6: 45.5 | KQ6: 45.375 | KR6: 45 | KU6: 43.625 | KV6: 45 | KW6: 44.625 | KX6: 45.25 | KY6: 45.25 | LB6: 47.25 | LC6: 47.75 | LD6: 49.125 | LE6: 48.125 | LF6: 48.625 | LI6: 48.625 | LJ6: 48.625 | LK6: 48.625 | LL6: 49.375 | LM6: 49.375 | LP6: 49.25 | LQ6: 49.5 | LR6: 50.125 | LS6: 51.125 | LT6: 51.375 | LW6: 51 | LX6: 50.5 | LY6: 49.625 | LZ6: 50.25 | MA6: 50.75 | MD6: 50.375 | ME6: 54.625 | MF6: 54.375 | MG6: 54.625 | MH6: 52.5 | MK6: 52.125 | ML6: 54.25 | MM6: 54.5 | MN6: 51.75 | MO6: 53.625 | MR6: 53.25 | MS6: 53.125 | MT6: 52.875 | MU6: 52.5 | MV6: 52.5 | MY6: 52.5 | MZ6: 52.5 | NA6: 52.75 | NB6: 50 | NC6: 52.25 | NF6: 52.375 | NG6: 53.5 | NH6: 51.875 | NI6: 50.5 | NJ6: 50.25
A7: USD Par 2038 I | B7: 38626 | C7: US040114GK09 | F7: 33.25 | G7: 36.1875 | H7: 38.3125 | I7: 39.9375 | J7: 41.625 | M7: 40.8125 | N7: 40.3125 | O7: 40.3125 | P7: 39.8125 | Q7: 39.0625 | T7: 38.75 | U7: 38.8 | V7: 40 | W7: 39.9375 | X7: 40.25 | AA7: 39.5625 | AB7: 39.0625 | AC7: 38.75 | AD7: 39.375 | AE7: 40 | AH7: 39.8125 | AI7: 39.8125 | AJ7: 39.375 | AK7: 39.375 | AL7: 39.5 | AO7: 40.5625 | AP7: 40.75 | AQ7: 41.5625 | AR7: 43.75 | AS7: 42.5 | AV7: 43.265 | AW7: 42.5625 | AX7: 41 | AY7: 41.7 | AZ7: 41.25 | BC7: 40.625 | BD7: 40.1875 | BE7: 41.0625 | BF7: 41.5 | BG7: 41.965 | BJ7: 40.0625 | BK7: 41.125 | BL7: 40.5 | BM7: 40.61 | BN7: 40.625 | BQ7: 40.125 | BR7: 40.57 | BS7: 40.555 | BT7: 39.625 | BU7: 39.405 | BX7: 39.1875 | BY7: 38.6875 | BZ7: 38.875 | CA7: 39.435 | CB7: 39.4375 | CE7: 39.42 | CF7: 40 | CG7: 40.8125 | CH7: 41 | CI7: 40.8125 | CL7: 39.875 | CM7: 39.375 | CN7: 39.25 | CO7: 38.875 | CP7: 39.375 | CS7: 38.3125 | CT7: 38.5 | CU7: 38.6875 | CV7: 38.5 | CW7: 38.9375 | CZ7: 39.995 | DA7: 39.8125 | DB7: 40.5 | DC7: 41.5625 | DD7: 41.375 | DG7: 41.625 | DH7: 43.6875 | DI7: 45.6875 | DJ7: 45.0625 | DK7: 45.525 | DN7: 46.125 | DO7: 45.25 | DP7: 45.25 | DQ7: 45 | DR7: 48.875 | DU7: 46.125 | DV7: 49.125 | DW7: 49.125 | DX7: 48.25 | DY7: 45.625 | EB7: 44.5 | EC7: 45.8 | ED7: 45.25 | EE7: 47.605 | EF7: 46.5 | EI7: 46.44 | EJ7: 45.405 | EK7: 45.75 | EL7: 46.25 | EM7: 47.25 | EP7: 45.5 | EQ7: 44.375 | ER7: 43.5625 | ES7: 43.0625 | ET7: 42.8125 | EW7: 41.9375 | EX7: 43.375 | EY7: 43.475 | EZ7: 42.625 | FA7: 42.905 | FD7: 43 | FE7: 40.875 | FF7: 44.25 | FG7: 44.0625 | FH7: 44.4375 | FK7: 44.375 | FL7: 43.125 | FM7: 43.375 | FN7: 42.75 | FO7: 43.25 | FR7: 43.3125 | FS7: 43 | FT7: 43.5 | FU7: 44 | FV7: 44.875 | FY7: 44.125 | FZ7: 44.25 | GA7: 43.8125 | GB7: 41.5625 | GC7: 41.0625 | GF7: 41.125 | GG7: 41.75 | GH7: 41.9375 | GI7: 41 | GJ7: 39.625 | GM7: 37.5 | GN7: 37.625 | GO7: 35.31 | GP7: 34.9375 | GQ7: 35.3125 | GT7: 31.32 | GU7: 32 | GV7: 26.455 | GW7: 29.355 | GX7: 29.15 | HA7: 28 | HB7: 26.75 | HC7: 26.85 | HD7: 27.5 | HE7: 27.945 | HH7: 28.182 | HI7: 28.25 | HJ7: 29.529 | HK7: 28.27 | HL7: 29.75 | HO7: 29.73 | HP7: 30 | HQ7: 29.875 | HR7: 28.79 | HS7: 29.125 | HV7: 30 | HW7: 29.625 | HX7: 27.875 | HY7: 28.125 | HZ7: 30.625 | IC7: 33.5 | ID7: 32.75 | IE7: 32 | IF7: 31.5 | IG7: 31.25 | IJ7: 31.5 | IK7: 31.375 | IL7: 31.75 | IM7: 31.25 | IN7: 30.75 | IQ7: 29.315 | IR7: 30.625 | IS7: 31.75 | IT7: 31.75 | IU7: 31.29 | IX7: 32 | IY7: 34.25 | IZ7: 34 | JA7: 33.375 | JB7: 35 | JE7: 36.22 | JF7: 36.065 | JG7: 35.375 | JH7: 36 | JI7: 36.095 | JL7: 36 | JM7: 36.215 | JN7: 38.375 | JO7: 37.875 | JP7: 38.125 | JS7: 38.25 | JT7: 38.5 | JU7: 39.375 | JV7: 39 | JW7: 38.125 | JZ7: 38.875 | KA7: 36.375 | KB7: 37.875 | KC7: 37.75 | KD7: 38.125 | KG7: 37.375 | KH7: 38.25 | KI7: 38.525 | KJ7: 38 | KK7: 38.5 | KN7: 38.625 | KO7: 39.25 | KP7: 38.375 | KQ7: 38.625 | KR7: 38.5 | KU7: 38 | KV7: 39.125 | KW7: 39.25 | KX7: 39.395 | KY7: 39 | LB7: 41.375 | LC7: 40.5 | LD7: 41.875 | LE7: 41.375 | LF7: 41.25 | LI7: 40.775 | LJ7: 40.514 | LK7: 40.7365 | LL7: 40.985 | LM7: 40.8935 | LP7: 40.835 | LQ7: 40.9005 | LR7: 41.417 | LS7: 42.6945 | LT7: 42.8135 | LW7: 43.033 | LX7: 42.7025 | LY7: 42.0775 | LZ7: 41.671 | MA7: 42.1335 | MD7: 41.9015 | ME7: 46.1685 | MF7: 46.3095 | MG7: 45.0195 | MH7: 44.899 | MK7: 44.9095 | ML7: 44.9745 | MM7: 44.882 | MN7: 44.705 | MO7: 44.557 | MR7: 44.5905 | MS7: 44.207 | MT7: 44.4055 | MU7: 43.829 | MV7: 43.6145 | MY7: 42.0115 | MZ7: 41.278 | NA7: 42.3685 | NB7: 43.343 | NC7: 43.3405 | NF7: 44.1675 | NG7: 42.7915 | NH7: 44.9165 | NI7: 43.625 | NJ7: 44.4905
A8: USD Par 2038 II and III | B8: 40296 | C8: XS0501195647 | F8: 33.75 | G8: 36.25 | H8: 34.25 | I8: 37.25 | J8: 38.25 | M8: 40.25 | N8: 38.25 | O8: 38.25 | P8: 40.25 | Q8: 40.25 | T8: 38.25 | U8: 38.25 | V8: 38.25 | W8: 38.25 | X8: 38.25 | AA8: 38.25 | AB8: 37.25 | AC8: 37.25 | AD8: 38.25 | AE8: 38.25 | AH8: 38.25 | AI8: 38.25 | AJ8: 38.25 | AK8: 39.125 | AL8: 39.25 | AO8: 40.25 | AP8: 40.25 | AQ8: 41.375 | AR8: 42.75 | AS8: 43.125 | AV8: 43.25 | AW8: 43.25 | AX8: 43.25 | AY8: 43.25 | AZ8: 43.25 | BC8: 43.25 | BD8: 40.25 | BE8: 40 | BF8: 40.75 | BG8: 40.75 | BJ8: 40.75 | BK8: 40.25 | BL8: 40.25 | BM8: 40.25 | BN8: 40.25 | BQ8: 40.125 | BR8: 38.375 | BS8: 39.75 | BT8: 39.75 | BU8: 39.75 | BX8: 39 | BY8: 38.875 | BZ8: 38.75 | CA8: 37.5 | CB8: 36.75 | CE8: 36.75 | CF8: 36.75 | CG8: 37.375 | CH8: 37.375 | CI8: 37.375 | CL8: 40 | CM8: 39.375 | CN8: 39.25 | CO8: 38.875 | CP8: 39.375 | CS8: 38.875 | CT8: 38.5 | CU8: 38.75 | CV8: 38.5 | CW8: 36.25 | CZ8: 38.5 | DA8: 40 | DB8: 39.75 | DC8: 41.375 | DD8: 41.25 | DG8: 41.375 | DH8: 43.75 | DI8: 44.25 | DJ8: 42.25 | DK8: 45 | DN8: 46.125 | DO8: 45.25 | DP8: 45.25 | DQ8: 45 | DR8: 45.375 | DU8: 45.875 | DV8: 45.875 | DW8: 45.875 | DX8: 48.25 | DY8: 45.625 | EB8: 44.5 | EC8: 43.75 | ED8: 45.625 | EE8: 45.75 | EF8: 46.5 | EI8: 46.5 | EJ8: 46.5 | EK8: 44.25 | EL8: 46.25 | EM8: 46.125 | EP8: 46.125 | EQ8: 46.125 | ER8: 46.125 | ES8: 43.125 | ET8: 43.5 | EW8: 41.75 | EX8: 42.25 | EY8: 43.5 | EZ8: 42.625 | FA8: 42.5 | FD8: 41.25 | FE8: 40.875 | FF8: 44.25 | FG8: 42.25 | FH8: 44.75 | FK8: 44.75 | FL8: 44 | FM8: 43.375 | FN8: 42.75 | FO8: 43.125 | FR8: 43.125 | FS8: 43 | FT8: 43.25 | FU8: 43.25 | FV8: 44.5 | FY8: 44.125 | FZ8: 44.25 | GA8: 44 | GB8: 42.375 | GC8: 40.25 | GF8: 41.25 | GG8: 41.375 | GH8: 41.875 | GI8: 41 | GJ8: 39.625 | GM8: 37.5 | GN8: 37.75 | GO8: 37.25 | GP8: 34.75 | GQ8: 35 | GT8: 32.375 | GU8: 32.75 | GV8: 27.875 | GW8: 29.125 | GX8: 29.125 | HA8: 28 | HB8: 26.75 | HC8: 26.875 | HD8: 27.5 | HE8: 27.375 | HH8: 27.125 | HI8: 28.25 | HJ8: 28.25 | HK8: 29.375 | HL8: 29.75 | HO8: 30.5 | HP8: 30 | HQ8: 29.875 | HR8: 29.125 | HS8: 29.125 | HV8: 29.125 | HW8: 29.125 | HX8: 29.125 | HY8: 29.125 | HZ8: 30.625 | IC8: 30.625 | ID8: 30.625 | IE8: 30.625 | IF8: 30.625 | IG8: 30.625 | IJ8: 30.625 | IK8: 30.625 | IL8: 30.625 | IM8: 30.625 | IN8: 30.75 | IQ8: 30.875 | IR8: 30.625 | IS8: 31.75 | IT8: 31.75 | IU8: 31.75 | IX8: 33.875 | IY8: 33.875 | IZ8: 33.875 | JA8: 33.875 | JB8: 33.875 | JE8: 35.5 | JF8: 36 | JG8: 35.375 | JH8: 36 | JI8: 36 | JL8: 36 | JM8: 38.5 | JN8: 38.375 | JO8: 37.875 | JP8: 37.875 | JS8: 37.875 | JT8: 37.875 | JU8: 37.875 | JV8: 37.875 | JW8: 37.875 | JZ8: 37.875 | KA8: 37.875 | KB8: 37.875 | KC8: 37.875 | KD8: 37.875 | KG8: 37.875 | KH8: 37.875 | KI8: 37.875 | KJ8: 37.875 | KK8: 37.875 | KN8: 37.875 | KO8: 37.875 | KP8: 37.875 | KQ8: 37.875 | KR8: 37.875 | KU8: 38 | KV8: 39.125 | KW8: 39.25 | KX8: 39.25 | KY8: 39 | LB8: 41.375 | LC8: 40.5 | LD8: 40.5 | LE8: 40.5 | LF8: 40.5 | LI8: 40.5 | LJ8: 40.5 | LK8: 40.5 | LL8: 40.5 | LM8: 40.5 | LP8: 40.5 | LQ8: 40.75 | LR8: 41.625 | LS8: 42.25 | LT8: 41.75 | LW8: 42.75 | LX8: 42.5 | LY8: 41.75 | LZ8: 41.75 | MA8: 41.875 | MD8: 41.875 | ME8: 45.25 | MF8: 45 | MG8: 44.625 | MH8: 44 | MK8: 43.25 | ML8: 44.375 | MM8: 44.375 | MN8: 44.375 | MO8: 44.375 | MR8: 44.375 | MS8: 44.375 | MT8: 44.375 | MU8: 44.375 | MV8: 44.375 | MY8: 44.375 | MZ8: 44.375 | NA8: 44.375 | NB8: 44.375 | NC8: 44.375 | NF8: 44.375 | NG8: 44.375 | NH8: 44.875 | NI8: 43.625 | NJ8: 42.75 | NM8: 42.75 | NN8: 41.25 | NO8: 43.25 | NP8: 43.375 | NQ8: 43.375 | NT8: 43.375 | NU8: 43.375 | NV8: 43.375 | NW8: 43.375 | NX8: 43.375 | OA8: 43.375 | OB8: 43.375 | OC8: 43.375 | OD8: 38.25 | OE8: 38.5 | OH8: 39 | OI8: 40.25 | OJ8: 40.25 | OK8: 40.25 | OL8: 40.25 | OO8: 40.25 | OP8: 40.25 | OQ8: 40.25 | OR8: 40.25 | OS8: 40.25 | OV8: 40.25 | OW8: 40.25 | OX8: 40.25 | OY8: 40.25 | OZ8: 40.25 | PC8: 40.25 | PD8: 40.25 | PE8: 38.25 | PF8: 38.25 | PG8: 38.25 | PJ8: 38.25 | PK8: 38.25 | PL8: 38.25 | PM8: 38.25 | PN8: 38.25
A9: USD Par 2038 III | B9: 40296 | C9: XS0501195720
A10: Euro 2033 Discount I | B10: 38626 | C10: XS0205545840 | F10: 45.197 | G10: 38.008 | H10: 38.222 | I10: 43.238 | J10: 47.213 | M10: 47.002 | N10: 45.405 | O10: 46.526 | P10: 46.148 | Q10: 44.506 | T10: 45.275 | U10: 45.506 | V10: 48.562 | W10: 48.463 | X10: 48.568 | AA10: 48.113 | AB10: 47.051 | AC10: 46.319 | AD10: 47.533 | AE10: 48.648 | AH10: 48.478 | AI10: 48.517 | AJ10: 49.032 | AK10: 49.092 | AL10: 48.754 | AO10: 49.493 | AP10: 50.054 | AQ10: 50.444 | AR10: 52.102 | AS10: 55.914 | AV10: 54.759 | AW10: 53.92 | AX10: 53.445 | AY10: 52.542 | AZ10: 52.433 | BC10: 52.263 | BD10: 50.568 | BE10: 50.071 | BF10: 52.029 | BG10: 51.006 | BJ10: 49.479 | BK10: 48.906 | BL10: 49.016 | BM10: 49.117 | BN10: 49.172 | BQ10: 48.899 | BR10: 49.423 | BS10: 49.175 | BT10: 48.645 | BU10: 48.521 | BX10: 46.983 | BY10: 46.528 | BZ10: 47.199 | CA10: 46.797 | CB10: 46.984 | CE10: 47.148 | CF10: 46.78 | CG10: 48.98 | CH10: 48.717 | CI10: 48.755 | CL10: 48.244 | CM10: 47.601 | CN10: 47.599 | CO10: 47.623 | CP10: 47.618 | CS10: 47.478 | CT10: 47.616 | CU10: 47.557 | CV10: 47.488 | CW10: 47.487 | CZ10: 47.515 | DA10: 47.509 | DB10: 47.563 | DC10: 48.148 | DD10: 48.216 | DG10: 48.181 | DH10: 48.228 | DI10: 48.158 | DJ10: 54.24 | DK10: 54.523 | DN10: 54.61 | DO10: 54.643 | DP10: 54.643 | DQ10: 54.643 | DR10: 55.695 | DU10: 58.029 | DV10: 58.001 | DW10: 58.001 | DX10: 58.006 | DY10: 57.762 | EB10: 57.527 | EC10: 57.039 | ED10: 57.975 | EE10: 59.005 | EF10: 59.95 | EI10: 59.206 | EJ10: 59.005 | EK10: 59.231 | EL10: 59.814 | EM10: 59.512 | EP10: 59.308 | EQ10: 58.56 | ER10: 56.646 | ES10: 55.728 | ET10: 55.421 | EW10: 53.471 | EX10: 53.174 | EY10: 53.761 | EZ10: 53.759 | FA10: 53.92 | FD10: 54.522 | FE10: 55.251 | FF10: 56.758 | FG10: 57.023 | FH10: 59.24 | FK10: 58.274 | FL10: 58.225 | FM10: 58.151 | FN10: 56.344 | FO10: 56.726 | FR10: 56.001 | FS10: 56.25 | FT10: 56.25 | FU10: 54.75 | FV10: 56 | FY10: 55.425 | FZ10: 55.45 | GA10: 55.325 | GB10: 52.25 | GC10: 52.325 | GF10: 51.95 | GG10: 53 | GH10: 53 | GI10: 52.46 | GJ10: 48.03 | GM10: 46 | GN10: 44.005 | GO10: 41.75 | GP10: 38.5 | GQ10: 38 | GT10: 37 | GU10: 36.5 | GV10: 35.677 | GW10: 32.85 | GX10: 32.631 | HA10: 32 | HB10: 32 | HC10: 32 | HD10: 32.7 | HE10: 32 | HH10: 31.5 | HI10: 33 | HJ10: 33.5 | HK10: 35 | HL10: 35.25 | HO10: 35.85 | HP10: 36.25 | HQ10: 35.581 | HR10: 34.8 | HS10: 34.804 | HV10: 34.804 | HW10: 35.5 | HX10: 33.125 | HY10: 33 | HZ10: 32.5 | IC10: 36 | ID10: 36 | IE10: 34.497 | IF10: 33 | IG10: 32 | IJ10: 30.47 | IK10: 28.72 | IL10: 29.5 | IM10: 31.35 | IN10: 31.35 | IQ10: 27.07 | IR10: 29 | IS10: 30.5 | IT10: 31 | IU10: 30.745 | IX10: 30.75 | IY10: 34.225 | IZ10: 33.95 | JA10: 33.025 | JB10: 36 | JE10: 37.375 | JF10: 37.95 | JG10: 36.75 | JH10: 36.57 | JI10: 35.47 | JL10: 35.47 | JM10: 35.47 | JN10: 35.47 | JO10: 35.47 | JP10: 35.47 | JS10: 44.75 | JT10: 46.05 | JU10: 46.85 | JV10: 45.61 | JW10: 44.89 | JZ10: 44.88 | KA10: 44.47 | KB10: 43.48 | KC10: 43.63 | KD10: 43.63 | KG10: 42.79 | KH10: 43.25 | KI10: 44.01 | KJ10: 42.18 | KK10: 43.32 | KN10: 44.75 | KO10: 44.95 | KP10: 45.25 | KQ10: 44.5 | KR10: 44.25 | KU10: 44.25 | KV10: 43.625 | KW10: 43.375 | KX10: 43.375 | KY10: 43.25 | LB10: 45.25 | LC10: 45.45 | LD10: 46.35 | LE10: 46.2 | LF10: 45.625 | LI10: 46 | LJ10: 46.125 | LK10: 45.375 | LL10: 46.5 | LM10: 46.5 | LP10: 46.25 | LQ10: 46.25 | LR10: 46.25 | LS10: 48.6 | LT10: 48.875 | LW10: 48.9 | LX10: 48.94 | LY10: 48.94 | LZ10: 48.94 | MA10: 48.94 | MD10: 48.94 | ME10: 50.08 | MF10: 51.71 | MG10: 52.56 | MH10: 52.53 | MK10: 52.53 | ML10: 52.5 | MM10: 51.61 | MN10: 51.24 | MO10: 51.23 | MR10: 50.91 | MS10: 50.72 | MT10: 50.7 | MU10: 50.65 | MV10: 50.7 | MY10: 50.45 | MZ10: 46.95 | NA10: 47.45 | NB10: 45.5 | NC10: 45.68 | NF10: 45.68 | NG10: 51 | NH10: 51 | NI10: 51 | NJ10: 51.436
A11: Euro 2033 Discount II and III | B11: 40350 | C11: XS0501195134
A12: Euro 2033 Discount III | B12: 40350 | C12: XS0501195308
A13: Euro Par 2038 I | B13: 38626 | C13: XS0205537581 | F13: 33.775 | G13: 34.831 | H13: 34.898 | I13: 38.408 | J13: 40.221 | M13: 40.238 | N13: 38.798 | O13: 39.395 | P13: 39.193 | Q13: 37.52 | T13: 37.99 | U13: 37.467 | V13: 39.147 | W13: 38.704 | X13: 39.049 | AA13: 38.676 | AB13: 37.934 | AC13: 36.98 | AD13: 37.652 | AE13: 38.747 | AH13: 38.842 | AI13: 39.075 | AJ13: 38.842 | AK13: 38.64 | AL13: 38.456 | AO13: 38.953 | AP13: 39.154 | AQ13: 39.382 | AR13: 40.748 | AS13: 41.76 | AV13: 41.357 | AW13: 41.255 | AX13: 40.301 | AY13: 40.222 | AZ13: 39.814 | BC13: 39.57 | BD13: 39.446 | BE13: 39.786 | BF13: 41.264 | BG13: 40.372 | BJ13: 40.071 | BK13: 40.062 | BL13: 39.624 | BM13: 39.665 | BN13: 39.237 | BQ13: 39.327 | BR13: 39.606 | BS13: 39.645 | BT13: 39.052 | BU13: 38.607 | BX13: 37.804 | BY13: 37.701 | BZ13: 38.15 | CA13: 38.992 | CB13: 38.949 | CE13: 39.244 | CF13: 38.876 | CG13: 40.413 | CH13: 40.196 | CI13: 40.269 | CL13: 39.728 | CM13: 39.409 | CN13: 39.398 | CO13: 39.4 | CP13: 39.025 | CS13: 38.743 | CT13: 38.96 | CU13: 38.832 | CV13: 38.786 | CW13: 38.769 | CZ13: 38.806 | DA13: 38.798 | DB13: 38.872 | DC13: 40.294 | DD13: 40.43 | DG13: 40.375 | DH13: 40.463 | DI13: 40.338 | DJ13: 43.842 | DK13: 42.999 | DN13: 42.862 | DO13: 42.885 | DP13: 42.9 | DQ13: 42.916 | DR13: 43.985 | DU13: 45.273 | DV13: 45.418 | DW13: 45.435 | DX13: 46.003 | DY13: 44.63 | EB13: 43.968 | EC13: 44.259 | ED13: 43.898 | EE13: 44.831 | EF13: 45.063 | EI13: 44.046 | EJ13: 44.021 | EK13: 44.235 | EL13: 44.876 | EM13: 44.428 | EP13: 44.2 | EQ13: 44.002 | ER13: 42.906 | ES13: 42.576 | ET13: 42.516 | EW13: 41.227 | EX13: 41.347 | EY13: 42.027 | EZ13: 41.847 | FA13: 41.532 | FD13: 42.005 | FE13: 42.592 | FF13: 43.301 | FG13: 42.747 | FH13: 43.247 | FK13: 42.85 | FL13: 42.782 | FM13: 42.607 | FN13: 41.862 | FO13: 42.301 | FR13: 41.503 | FS13: 41.422 | FT13: 41.657 | FU13: 40.437 | FV13: 42.281 | FY13: 41.522 | FZ13: 42.107 | GA13: 41.517 | GB13: 39.95 | GC13: 39.154 | GF13: 38.743 | GG13: 39.547 | GH13: 39.722 | GI13: 39.672 | GJ13: 37.732 | GM13: 34.88 | GN13: 35.174 | GO13: 33.572 | GP13: 30.727 | GQ13: 30.197 | GT13: 29.332 | GU13: 28.977 | GV13: 28.5 | GW13: 25.45 | GX13: 25.5 | HA13: 25.402 | HB13: 25.5 | HC13: 25.372 | HD13: 25.163 | HE13: 24.6 | HH13: 24.5 | HI13: 26.297 | HJ13: 26.5 | HK13: 27.547 | HL13: 27.672 | HO13: 27.802 | HP13: 28.372 | HQ13: 27.582 | HR13: 27.5 | HS13: 27.505 | HV13: 27.505 | HW13: 27.447 | HX13: 27.122 | HY13: 26.622 | HZ13: 27.691 | IC13: 30.147 | ID13: 28.992 | IE13: 28.252 | IF13: 27.927 | IG13: 26.997 | IJ13: 26 | IK13: 25.413 | IL13: 26.322 | IM13: 25.964 | IN13: 25.964 | IQ13: 23.747 | IR13: 24.489 | IS13: 25 | IT13: 25.5 | IU13: 25.893 | IX13: 26.5 | IY13: 29.463 | IZ13: 28.172 | JA13: 28.402 | JB13: 29.639 | JE13: 30.524 | JF13: 31.082 | JG13: 30.386 | JH13: 30.515 | JI13: 29.707 | JL13: 29.707 | JM13: 29.707 | JN13: 29.707 | JO13: 29.707 | JP13: 29.707 | JS13: 35.75 | JT13: 36.5 | JU13: 37.4 | JV13: 37.35 | JW13: 36.36 | JZ13: 37.11 | KA13: 36.36 | KB13: 35.81 | KC13: 36.01 | KD13: 36.38 | KG13: 35.81 | KH13: 36.16 | KI13: 36.56 | KJ13: 35.23 | KK13: 36.711 | KN13: 36.87 | KO13: 37.46 | KP13: 37.01 | KQ13: 36.527 | KR13: 37.093 | KU13: 37.253 | KV13: 37.8 | KW13: 37.16 | KX13: 35.5 | KY13: 36.17 | LB13: 38.26 | LC13: 38.96 | LD13: 39.75 | LE13: 39.12 | LF13: 38.16 | LI13: 38.42 | LJ13: 38.01 | LK13: 38.21 | LL13: 38.47 | LM13: 38.21 | LP13: 37.86 | LQ13: 37.928 | LR13: 38.75 | LS13: 39.832 | LT13: 39.943 | LW13: 40.5 | LX13: 39.875 | LY13: 39.638 | LZ13: 39.115 | MA13: 39.87 | MD13: 39.61 | ME13: 44.75 | MF13: 44.05 | MG13: 43.71 | MH13: 43.28 | MK13: 43.28 | ML13: 43.27 | MM13: 43.7 | MN13: 43.85 | MO13: 43.85 | MR13: 43.13 | MS13: 42.92 | MT13: 42.76 | MU13: 42.31 | MV13: 41.76 | MY13: 41.74 | MZ13: 41.26 | NA13: 40.5 | NB13: 39 | NC13: 37.65 | NF13: 39.55 | NG13: 44 | NH13: 45.25 | NI13: 45.25 | NJ13: 45.75
A14: Euro Par 2038 II and III | B14: 40296 | C14: XS0501195993 | F14: 34.63 | G14: 34.847 | H14: 35.143 | I14: 38.76 | J14: 40.337 | M14: 40.075 | N14: 38.816 | O14: 39.586 | P14: 39.203 | Q14: 37.763 | T14: 38.227 | U14: 37.825 | V14: 39.098 | W14: 38.783 | X14: 39.214 | AA14: 39.238 | AB14: 38.114 | AC14: 37.005 | AD14: 37.409 | AE14: 38.148 | AH14: 38.327 | AI14: 38.58 | AJ14: 38.474 | AK14: 38.426 | AL14: 37.957 | AO14: 38.346 | AP14: 38.569 | AQ14: 38.847 | AR14: 40.313 | AS14: 41.228 | AV14: 40.93 | AW14: 40.903 | AX14: 39.699 | AY14: 39.563 | AZ14: 39.568 | BC14: 39.514 | BD14: 39.424 | BE14: 39.726 | BF14: 41.009 | BG14: 39.924 | BJ14: 40.225 | BK14: 39.589 | BL14: 39.69 | BM14: 39.639 | BN14: 39.257 | BQ14: 39.391 | BR14: 39.383 | BS14: 39.347 | BT14: 38.949 | BU14: 38.547 | BX14: 37.947 | BY14: 37.376 | BZ14: 37.61 | CA14: 38.951 | CB14: 39.124 | CE14: 39.265 | CF14: 38.958 | CG14: 39.544 | CH14: 39.775 | CI14: 40.184 | CL14: 39.717 | CM14: 39.27 | CN14: 39.269 | CO14: 39.28 | CP14: 39.286 | CS14: 39.013 | CT14: 39.237 | CU14: 39.116 | CV14: 39.062 | CW14: 39.048 | CZ14: 39.088 | DA14: 39.074 | DB14: 39.153 | DC14: 38.984 | DD14: 39.108 | DG14: 39.055 | DH14: 39.122 | DI14: 39.008 | DJ14: 44.045 | DK14: 43.905 | DN14: 43.943 | DO14: 43.958 | DP14: 43.964 | DQ14: 43.98 | DR14: 44.086 | DU14: 45.009 | DV14: 45.003 | DW14: 45.02 | DX14: 45.798 | DY14: 44.505 | EB14: 44.454 | EC14: 44.635 | ED14: 44.262 | EE14: 45.109 | EF14: 45.037 | EI14: 44.619 | EJ14: 44.302 | EK14: 44.248 | EL14: 44.992 | EM14: 44.92 | EP14: 44.508 | EQ14: 44.307 | ER14: 43.743 | ES14: 43.759 | ET14: 43.855 | EW14: 43.745 | EX14: 41.206 | EY14: 42.087 | EZ14: 41.787 | FA14: 41.46 | FD14: 41.844 | FE14: 42.597 | FF14: 43.235 | FG14: 42.812 | FH14: 43.297 | FK14: 42.977 | FL14: 43.072 | FM14: 43.082 | FN14: 41.955 | FO14: 42.4 | FR14: 41.664 | FS14: 41.787 | FT14: 41.751 | FU14: 40.902 | FV14: 42.35 | FY14: 41.647 | FZ14: 42.397 | GA14: 41.997 | GB14: 40.517 | GC14: 39.841 | GF14: 39.227 | GG14: 40.092 | GH14: 40.092 | GI14: 40.227 | GJ14: 38.232 | GM14: 35.421 | GN14: 35.735 | GO14: 34.122 | GP14: 30.952 | GQ14: 30.887 | GT14: 29.872 | GU14: 29.632 | GV14: 29 | GW14: 25.95 | GX14: 26.392 | HA14: 25.977 | HB14: 26.137 | HC14: 25.877 | HD14: 25.872 | HE14: 24.95 | HH14: 24.627 | HI14: 26.422 | HJ14: 26.684 | HK14: 27.447 | HL14: 28.297 | HO14: 28.344 | HP14: 28.525 | HQ14: 28.005 | HR14: 28 | HS14: 28.005 | HV14: 28.005 | HW14: 28.272 | HX14: 28.127 | HY14: 27.447 | HZ14: 28.418 | IC14: 30.662 | ID14: 29.522 | IE14: 28.755 | IF14: 28.622 | IG14: 27.632 | IJ14: 26.622 | IK14: 26.007 | IL14: 26.727 | IM14: 25.972 | IN14: 25.972 | IQ14: 24.122 | IR14: 24.289 | IS14: 24.987 | IT14: 25.5 | IU14: 26.112 | IX14: 26 | IY14: 28.297 | IZ14: 28.294 | JA14: 28.182 | JB14: 29.472 | JE14: 30.728 | JF14: 30.752 | JG14: 30.532 | JH14: 30.651 | JI14: 30.042 | JL14: 30.042 | JM14: 30.042 | JN14: 30.042 | JO14: 30.042 | JP14: 30.042 | JS14: 30.042 | JT14: 30.042 | JU14: 30.042 | JV14: 30.042 | JW14: 30.042 | JZ14: 30.042 | KA14: 37.46 | KB14: 36.86 | KC14: 36.67 | KD14: 37.25 | KG14: 37 | KH14: 36.9 | KI14: 37.3 | KJ14: 35.92 | KK14: 36.79 | KN14: 37.5 | KO14: 38 | KP14: 37.94 | KQ14: 37 | KR14: 37.62 | KU14: 37.75 | KV14: 38.2 | KW14: 37.61 | KX14: 37 | KY14: 36.93 | LB14: 38.55 | LC14: 39 | LD14: 39.56 | LE14: 39 | LF14: 38.65 | LI14: 38.7 | LJ14: 38.51 | LK14: 39 | LL14: 38.96 | LM14: 38.5 | LP14: 38.13 | LQ14: 38.5 | LR14: 39.5 | LS14: 40.5 | LT14: 40.3 | LW14: 41.2 | LX14: 40.55 | LY14: 40.4 | LZ14: 39.7 | MA14: 40.6 | MD14: 40 | ME14: 45.75 | MF14: 44.61 | MG14: 44.45 | MH14: 43.88 | MK14: 43.88 | ML14: 43.79 | MM14: 43.87 | MN14: 44.05 | MO14: 44 | MR14: 44.04 | MS14: 44.03 | MT14: 43.91 | MU14: 43.25 | MV14: 42.03 | MY14: 42 | MZ14: 41.71 | NA14: 41.3 | NB14: 40.25 | NC14: 39.5 | NF14: 40.55 | NG14: 44.5 | NH14: 45.75 | NI14: 45.75 | NJ14: 46.25 | NM14: 47 | NN14: 46.875 | NO14: 48.333 | NP14: 46.938 | NQ14: 46.938 | NT14: 46.938 | NU14: 46.938 | NV14: 46.938 | NW14: 46.938 | NX14: 46.938 | OA14: 46.938 | OB14: 46.938 | OC14: 46.938 | OD14: 46.938 | OE14: 46.938 | OH14: 46.938 | OI14: 46.938 | OJ14: 46.938 | OK14: 46.938 | OL14: 46.938 | OO14: 46.938 | OP14: 46.938 | OQ14: 46.938 | OR14: 46.938 | OS14: 46.938 | OV14: 46.938 | OW14: 46.938 | OX14: 46.938 | OY14: 46.938 | OZ14: 46.938 | PC14: 46.938 | PD14: 46.938 | PE14: 46.938 | PF14: 46.938 | PG14: 46.938 | PJ14: 46.938 | PK14: 46.938 | PL14: 46.938 | PM14: 46.938 | PN14: 46.938
A15: Euro Par 2038 III | B15: 40296 | C15: XS0501196025 | F15: 34.637 | G15: 34.826 | H15: 35.177 | I15: 39.036 | J15: 40.121 | M15: 40.241 | N15: 38.857 | O15: 39.561 | P15: 39.209 | Q15: 37.851 | T15: 38.116 | U15: 37.856 | V15: 38.951 | W15: 38.86 | X15: 39.175 | AA15: 39.071 | AB15: 38.167 | AC15: 36.945 | AD15: 37.367 | AE15: 38.178 | AH15: 38.333 | AI15: 38.63 | AJ15: 38.61 | AK15: 38.291 | AL15: 37.972 | AO15: 38.394 | AP15: 38.466 | AQ15: 38.931 | AR15: 40.551 | AS15: 41.346 | AV15: 40.843 | AW15: 40.832 | AX15: 39.703 | AY15: 39.585 | AZ15: 39.618 | BC15: 39.604 | BD15: 39.351 | BE15: 39.588 | BF15: 41.058 | BG15: 39.977 | BJ15: 40.378 | BK15: 39.467 | BL15: 39.636 | BM15: 39.486 | BN15: 39.274 | BQ15: 39.419 | BR15: 39.487 | BS15: 39.283 | BT15: 39.144 | BU15: 38.629 | BX15: 37.924 | BY15: 37.401 | BZ15: 37.682 | CA15: 38.951 | CB15: 39.124 | CE15: 39.24 | CF15: 38.963 | CG15: 39.549 | CH15: 39.78 | CI15: 40.157 | CL15: 39.722 | CM15: 39.248 | CN15: 39.244 | CO15: 39.255 | CP15: 39.26 | CS15: 38.988 | CT15: 39.212 | CU15: 39.091 | CV15: 39.037 | CW15: 39.023 | CZ15: 39.063 | DA15: 39.049 | DB15: 39.128 | DC15: 38.96 | DD15: 39.083 | DG15: 39.03 | DH15: 39.097 | DI15: 38.983 | DJ15: 38.935 | DK15: 43.91 | DN15: 43.948 | DO15: 43.963 | DP15: 43.969 | DQ15: 43.985 | DR15: 44.091 | DU15: 45.014 | DV15: 45.008 | DW15: 45.025 | DX15: 45.775 | DY15: 44.511 | EB15: 44.423 | EC15: 44.641 | ED15: 44.267 | EE15: 45.114 | EF15: 45.042 | EI15: 44.588 | EJ15: 44.307 | EK15: 44.253 | EL15: 44.997 | EM15: 44.925 | EP15: 44.477 | EQ15: 44.313 | ER15: 43.748 | ES15: 43.764 | ET15: 43.86 | EW15: 43.75 | EX15: 43.661 | EY15: 42.087 | EZ15: 41.787 | FA15: 41.46 | FD15: 41.844 | FE15: 42.597 | FF15: 43.235 | FG15: 42.812 | FH15: 43.297 | FK15: 42.977 | FL15: 43.072 | FM15: 43.082 | FN15: 41.955 | FO15: 42.4 | FR15: 41.664 | FS15: 41.787 | FT15: 41.751 | FU15: 40.902 | FV15: 42.35 | FY15: 41.647 | FZ15: 42.397 | GA15: 41.997 | GB15: 40.517 | GC15: 39.841 | GF15: 39.227 | GG15: 40.092 | GH15: 40.092 | GI15: 40.227 | GJ15: 38.232 | GM15: 35.421 | GN15: 35.735 | GO15: 34.122 | GP15: 30.952 | GQ15: 30.887 | GT15: 29.872 | GU15: 29.632 | GV15: 29 | GW15: 25.95 | GX15: 26.392 | HA15: 25.977 | HB15: 26.137 | HC15: 25.877 | HD15: 25.872 | HE15: 24.95 | HH15: 24.627 | HI15: 26.422 | HJ15: 26.684 | HK15: 27.447 | HL15: 28.297 | HO15: 28.344 | HP15: 28.525 | HQ15: 28.005 | HR15: 28 | HS15: 28.005 | HV15: 28.005 | HW15: 28.272 | HX15: 28.127 | HY15: 27.447 | HZ15: 28.418 | IC15: 30.662 | ID15: 29.522 | IE15: 28.755 | IF15: 28.622 | IG15: 27.632 | IJ15: 26.622 | IK15: 26.007 | IL15: 26.727 | IM15: 25.972 | IN15: 25.972 | IQ15: 24.122 | IR15: 24.289 | IS15: 24.987 | IT15: 25.5 | IU15: 26.112 | IX15: 26 | IY15: 28.297 | IZ15: 28.294 | JA15: 28.182 | JB15: 29.472 | JE15: 30.728 | JF15: 30.752 | JG15: 30.532 | JH15: 30.651 | JI15: 30.042 | JL15: 30.042 | JM15: 30.042 | JN15: 30.042 | JO15: 30.042 | JP15: 30.042 | JS15: 30.042 | JT15: 30.042 | JU15: 30.042 | JV15: 30.042 | JW15: 30.042 | JZ15: 30.042 | KA15: 37.46 | KB15: 36.86 | KC15: 36.67 | KD15: 37.25 | KG15: 37 | KH15: 36.9 | KI15: 37.3 | KJ15: 35.92 | KK15: 36.79 | KN15: 37.5 | KO15: 38 | KP15: 37.94 | KQ15: 37 | KR15: 37.62 | KU15: 37.75 | KV15: 38.2 | KW15: 37.61 | KX15: 37 | KY15: 36.93 | LB15: 38.55 | LC15: 39 | LD15: 39.56 | LE15: 39 | LF15: 38.65 | LI15: 38.7 | LJ15: 38.51 | LK15: 39 | LL15: 38.96 | LM15: 38.5 | LP15: 38.13 | LQ15: 38.5 | LR15: 39.5 | LS15: 40.5 | LT15: 40.3 | LW15: 41.2 | LX15: 40.55 | LY15: 40.4 | LZ15: 39.7 | MA15: 40.6 | MD15: 40 | ME15: 45.75 | MF15: 44.61 | MG15: 44.45 | MH15: 43.88 | MK15: 43.88 | ML15: 43.79 | MM15: 43.87 | MN15: 44.05 | MO15: 44 | MR15: 44.04 | MS15: 44.03 | MT15: 43.91 | MU15: 43.25 | MV15: 42.03 | MY15: 42 | MZ15: 41.71 | NA15: 41.3 | NB15: 40.25 | NC15: 39.5 | NF15: 40.55 | NG15: 44.5 | NH15: 45.75 | NI15: 45.75 | NJ15: 46.25 | NM15: 47 | NN15: 46.875 | NO15: 48.333 | NP15: 46.938 | NQ15: 46.938 | NT15: 46.938 | NU15: 46.938 | NV15: 46.938 | NW15: 46.938 | NX15: 46.938 | OA15: 46.938 | OB15: 46.938 | OC15: 46.938 | OD15: 46.938 | OE15: 46.938 | OH15: 46.938 | OI15: 46.938 | OJ15: 46.938 | OK15: 46.938 | OL15: 46.938 | OO15: 46.938 | OP15: 46.938 | OQ15: 46.938 | OR15: 46.938 | OS15: 46.938 | OV15: 46.938 | OW15: 46.938 | OX15: 46.938 | OY15: 46.938 | OZ15: 46.938 | PC15: 46.938 | PD15: 46.938 | PE15: 46.938 | PF15: 46.938 | PG15: 46.938 | PJ15: 46.938 | PK15: 46.938 | PL15: 46.938 | PM15: 46.938 | PN15: 46.938
A16: USD 2021 | B16: 42482 | C16: US040114GW47 | F16: 41.75 | G16: 41.7875 | H16: 44.8355 | I16: 47.6085 | J16: 47.375 | M16: 50.8125 | N16: 50.6255 | O16: 51.325 | P16: 50.96 | Q16: 49.6415 | T16: 48.5 | U16: 50.1425 | V16: 51.25 | W16: 50.735 | X16: 50.5 | AA16: 49.017 | AB16: 47.6335 | AC16: 47.245 | AD16: 47.239 | AE16: 48.2125 | AH16: 49.244 | AI16: 49.075 | AJ16: 49.0785 | AK16: 49 | AL16: 49.95 | AO16: 50.955 | AP16: 51.616 | AQ16: 52.25 | AR16: 54.85 | AS16: 54 | AV16: 53.4015 | AW16: 53.5 | AX16: 52.15 | AY16: 52.5765 | AZ16: 51.05 | BC16: 49.195 | BD16: 46.6915 | BE16: 47.1785 | BF16: 47.8045 | BG16: 46.8765 | BJ16: 45 | BK16: 46.4185 | BL16: 45.919 | BM16: 45.152 | BN16: 45.071 | BQ16: 45.0625 | BR16: 45.0315 | BS16: 44.1275 | BT16: 44.1225 | BU16: 43.301 | BX16: 43.125 | BY16: 42.0875 | BZ16: 42.0125 | CA16: 42.623 | CB16: 42.2 | CE16: 41.7195 | CF16: 43.5565 | CG16: 44.488 | CH16: 46.3035 | CI16: 45.242 | CL16: 44.75 | CM16: 45.3695 | CN16: 45.366 | CO16: 45 | CP16: 45.625 | CS16: 43.3835 | CT16: 44.029 | CU16: 44.925 | CV16: 44.317 | CW16: 45.628 | CZ16: 48.6 | DA16: 48.95 | DB16: 49.259 | DC16: 49.74 | DD16: 49.781 | DG16: 48.8005 | DH16: 51.607 | DI16: 52.679 | DJ16: 51.9195 | DK16: 51.6475 | DN16: 51.949 | DO16: 52.5805 | DP16: 52.6115 | DQ16: 53.118 | DR16: 54.1345 | DU16: 54 | DV16: 54.1875 | DW16: 53.75 | DX16: 52.8805 | DY16: 53.327 | EB16: 51.025 | EC16: 51.7085 | ED16: 52.175 | EE16: 53.378 | EF16: 53.125 | EI16: 54 | EJ16: 53.6 | EK16: 54.7 | EL16: 54.625 | EM16: 54.2235 | EP16: 54 | EQ16: 53.175 | ER16: 52.608 | ES16: 52.8445 | ET16: 52.116 | EW16: 50.872 | EX16: 52.245 | EY16: 53.869 | EZ16: 53.855 | FA16: 53.432 | FD16: 54.833 | FE16: 56.675 | FF16: 57.125 | FG16: 56.625 | FH16: 57.756 | FK16: 57.1195 | FL16: 54.744 | FM16: 55.006 | FN16: 55.1785 | FO16: 54.6225 | FR16: 54.8595 | FS16: 54.8575 | FT16: 54.883 | FU16: 54.884 | FV16: 54.884 | FY16: 54.884 | FZ16: 54.8925 | GA16: 54.8925 | GB16: 54.8835 | GC16: 54.8835 | GF16: 54.8835 | GG16: 54.8665 | GH16: 54.8665 | GI16: 54.8585 | GJ16: 54.8585 | GM16: 54.8585 | GN16: 41.612 | GO16: 40.9885 | GP16: 37.8035 | GQ16: 37.211 | GT16: 33.966 | GU16: 33.7505 | GV16: 28.647 | GW16: 28.445 | GX16: 28.0925 | HA16: 26.3 | HB16: 26.012 | HC16: 26.474 | HD16: 27.5705 | HE16: 27.4345 | HH16: 28.036 | HI16: 29.198 | HJ16: 29.2945 | HK16: 30.133 | HL16: 30.658 | HO16: 32.381 | HP16: 32.2435 | HQ16: 31.2965 | HR16: 30.9185 | HS16: 30.9185 | HV16: 30.75 | HW16: 30.7135 | HX16: 30.0345 | HY16: 29.93 | HZ16: 32.577 | IC16: 33.2985 | ID16: 32.373 | IE16: 31.6015 | IF16: 31.163 | IG16: 29.042 | IJ16: 29.3515 | IK16: 29.6185 | IL16: 29.7705 | IM16: 28.9875 | IN16: 28.738 | IQ16: 28.2865 | IR16: 29.529 | IS16: 30.293 | IT16: 30.6425 | IU16: 30.606 | IX16: 32.651 | IY16: 34.762 | IZ16: 35.01 | JA16: 35.3805 | JB16: 38.499 | JE16: 40.2015 | JF16: 38.963 | JG16: 38.141 | JH16: 38.4515 | JI16: 38.573 | JL16: 38.798 | JM16: 39.8645 | JN16: 41.2045 | JO16: 39.9215 | JP16: 40.418 | JS16: 41.625 | JT16: 41.0965 | JU16: 41.7305 | JV16: 41.274 | JW16: 40.8705 | JZ16: 41.572 | KA16: 40.1835 | KB16: 40.815 | KC16: 41.165 | KD16: 41.646 | KG16: 41.0425 | KH16: 42.2495 | KI16: 41.9765 | KJ16: 41.251 | KK16: 41.879 | KN16: 42.2045 | KO16: 42.87 | KP16: 42.3285 | KQ16: 42.5365 | KR16: 41.482 | KU16: 42.3715 | KV16: 41.9945 | KW16: 41.947 | KX16: 41.7955 | KY16: 41.662 | LB16: 43.4135 | LC16: 43.8395 | LD16: 44.5675 | LE16: 44.692 | LF16: 44.305 | LI16: 44.5005 | LJ16: 43.9005 | LK16: 43.6495 | LL16: 43.934 | LM16: 43.6495 | LP16: 43.688 | LQ16: 43.69 | LR16: 44.962 | LS16: 45.7235 | LT16: 45.7255 | LW16: 45.858 | LX16: 45.8395 | LY16: 45.393 | LZ16: 45.354 | MA16: 45.5565 | MD16: 45.2765 | ME16: 49.208 | MF16: 49.8535 | MG16: 49.777 | MH16: 49.151 | MK16: 49.086 | ML16: 49.2275 | MM16: 49.087 | MN16: 49.1505 | MO16: 49.043 | MR16: 48.853 | MS16: 48.6765 | MT16: 48.929 | MU16: 48.6665 | MV16: 48.678 | MY16: 48.77 | MZ16: 48.7985 | NA16: 48.8595 | NB16: 48.842 | NC16: 48.8655 | NF16: 48.807 | NG16: 49.408 | NH16: 49.362 | NI16: 51 | NJ16: 49.5475
A17: USD 2022 | B17: 42761 | C17: US040114HK99 | F17: 39.9965 | G17: 39.793 | H17: 41.306 | I17: 43.9855 | J17: 44.9235 | M17: 47.592 | N17: 47.131 | O17: 46.896 | P17: 46.359 | Q17: 45.0235 | T17: 44.187 | U17: 44.503 | V17: 45.7335 | W17: 44.838 | X17: 45.284 | AA17: 44.155 | AB17: 42.614 | AC17: 42.2745 | AD17: 42.465 | AE17: 43.1965 | AH17: 43.5105 | AI17: 43.4725 | AJ17: 43.327 | AK17: 43.181 | AL17: 43.462 | AO17: 44.4925 | AP17: 44.7715 | AQ17: 45.7615 | AR17: 47.667 | AS17: 48.069 | AV17: 48.128 | AW17: 47.4975 | AX17: 46.59 | AY17: 46.722 | AZ17: 46.2175 | BC17: 45.028 | BD17: 44.0245 | BE17: 43.9675 | BF17: 45.258 | BG17: 45.0245 | BJ17: 43.1615 | BK17: 43.1395 | BL17: 43.205 | BM17: 42.8235 | BN17: 42.665 | BQ17: 42.3155 | BR17: 42.3545 | BS17: 42.1165 | BT17: 41.446 | BU17: 40.633 | BX17: 41.061 | BY17: 39.495 | BZ17: 39.0625 | CA17: 40.4385 | CB17: 40.134 | CE17: 40.1125 | CF17: 40.514 | CG17: 42.355 | CH17: 43.704 | CI17: 43.4215 | CL17: 42.922 | CM17: 42.8305 | CN17: 42.929 | CO17: 42.5555 | CP17: 42.8115 | CS17: 42.2765 | CT17: 41.5535 | CU17: 42.1345 | CV17: 41.997 | CW17: 42.5755 | CZ17: 45.4465 | DA17: 46.582 | DB17: 46.702 | DC17: 48.2325 | DD17: 47.834 | DG17: 47.352 | DH17: 47.534 | DI17: 50.4375 | DJ17: 49.6215 | DK17: 49.0645 | DN17: 49.152 | DO17: 50 | DP17: 50 | DQ17: 50.5 | DR17: 52.3905 | DU17: 52.6365 | DV17: 52.327 | DW17: 51.875 | DX17: 51.53 | DY17: 50.4095 | EB17: 48.8495 | EC17: 49.997 | ED17: 49.71 | EE17: 51.867 | EF17: 51.4915 | EI17: 51.5885 | EJ17: 50.804 | EK17: 51.3925 | EL17: 52.514 | EM17: 51.6475 | EP17: 51.936 | EQ17: 50.6305 | ER17: 49.5515 | ES17: 49.357 | ET17: 49.1285 | EW17: 47.2665 | EX17: 48.2725 | EY17: 50.064 | EZ17: 50.115 | FA17: 49.664 | FD17: 50.888 | FE17: 52.098 | FF17: 53.247 | FG17: 52.5505 | FH17: 54.1195 | FK17: 53.5545 | FL17: 52.676 | FM17: 51.992 | FN17: 49.9905 | FO17: 50.599 | FR17: 50.1155 | FS17: 50.282 | FT17: 49.7885 | FU17: 48.8115 | FV17: 49.8925 | FY17: 49.5055 | FZ17: 49.9265 | GA17: 50.0135 | GB17: 48.9845 | GC17: 47.0525 | GF17: 46.9255 | GG17: 48.435 | GH17: 48.8235 | GI17: 47.7325 | GJ17: 47.0315 | GM17: 47.0315 | GN17: 39.535 | GO17: 38.985 | GP17: 35.9115 | GQ17: 36.189 | GT17: 33.0375 | GU17: 31.031 | GV17: 31.2895 | GW17: 27.824 | GX17: 28.5785 | HA17: 26.4845 | HB17: 26.7955 | HC17: 27.062 | HD17: 27.8465 | HE17: 27.773 | HH17: 28.0015 | HI17: 29.0735 | HJ17: 29.434 | HK17: 30.027 | HL17: 30.9705 | HO17: 32.4785 | HP17: 32.2315 | HQ17: 31.5355 | HR17: 30.0135 | HS17: 30.0135 | HV17: 30.0135 | HW17: 30.438 | HX17: 30.4745 | HY17: 30.4745 | HZ17: 30.4745 | IC17: 33.2355 | ID17: 31.3125 | IE17: 30.6635 | IF17: 29.349 | IG17: 28.5615 | IJ17: 28.3705 | IK17: 28.687 | IL17: 29.491 | IM17: 28.4245 | IN17: 28.1375 | IQ17: 26.9555 | IR17: 27.939 | IS17: 29.7905 | IT17: 29.455 | IU17: 29.289 | IX17: 30.289 | IY17: 33.829 | IZ17: 33.9975 | JA17: 33.542 | JB17: 36.432 | JE17: 38.7405 | JF17: 38.8265 | JG17: 37.2985 | JH17: 37.0855 | JI17: 36.667 | JL17: 36.2645 | JM17: 36.3385 | JN17: 36.3385 | JO17: 37.6995 | JP17: 38.927 | JS17: 39.3705 | JT17: 40.443 | JU17: 40.6895 | JV17: 41.7145 | JW17: 41.182 | JZ17: 41.35 | KA17: 41.019 | KB17: 40.9975 | KC17: 41.2245 | KD17: 41.032 | KG17: 40.5855 | KH17: 41.465 | KI17: 41.464 | KJ17: 40.4975 | KK17: 41.0435 | KN17: 41.595 | KO17: 42.3895 | KP17: 41.67 | KQ17: 41.557 | KR17: 40.6365 | KU17: 41.494 | KV17: 41.518 | KW17: 41.672 | KX17: 41.3035 | KY17: 41.3085 | LB17: 42.0565 | LC17: 42.555 | LD17: 44.0315 | LE17: 43.2055 | LF17: 43.219 | LI17: 43.8775 | LJ17: 42.859 | LK17: 42.6675 | LL17: 43.0625 | LM17: 42.8675 | LP17: 42.6975 | LQ17: 43.018 | LR17: 43.6565 | LS17: 45.119 | LT17: 44.4425 | LW17: 45.1895 | LX17: 44.7595 | LY17: 44.493 | LZ17: 44.2635 | MA17: 44.1095 | MD17: 44.2115 | ME17: 49.5435 | MF17: 49.632 | MG17: 49.471 | MH17: 49.0595 | MK17: 49.123 | ML17: 49.0535 | MM17: 48.8125 | MN17: 48.8045 | MO17: 48.406 | MR17: 48.468 | MS17: 48.197 | MT17: 48.5315 | MU17: 48.3195 | MV17: 48.2565 | MY17: 46.504 | MZ17: 45.3905 | NA17: 46.1165 | NB17: 46.1165 | NC17: 48.0945 | NF17: 48.3175 | NG17: 47.935 | NH17: 47.935 | NI17: 47.935 | NJ17: 47.935
A18: USD 2023 | B18: 43111 | C18: US040114HP86 | F18: 39.375 | G18: 38.625 | H18: 40.091 | I18: 41.8125 | J18: 45.082 | M18: 45.5315 | N18: 43.75 | O18: 44.8865 | P18: 44.5155 | Q18: 41.9375 | T18: 42.3725 | U18: 98.875 | V18: 44.0775 | W18: 43.125 | X18: 43.375 | AA18: 41.875 | AB18: 41.1875 | AC18: 40.765 | AD18: 41.49 | AE18: 42.337 | AH18: 42.375 | AI18: 42.556 | AJ18: 42.3345 | AK18: 42.125 | AL18: 42.635 | AO18: 43.5005 | AP18: 43.6875 | AQ18: 44.375 | AR18: 46.6875 | AS18: 46.5 | AV18: 46.4775 | AW18: 45.75 | AX18: 44.625 | AY18: 44.75 | AZ18: 44.4575 | BC18: 43 | BD18: 42.125 | BE18: 43.125 | BF18: 44.125 | BG18: 43 | BJ18: 40.75 | BK18: 41.625 | BL18: 41 | BM18: 40.25 | BN18: 41.225 | BQ18: 40.6695 | BR18: 40.385 | BS18: 39.75 | BT18: 39.5 | BU18: 38.25 | BX18: 39.268 | BY18: 37.5625 | BZ18: 37.8125 | CA18: 38.5 | CB18: 38.25 | CE18: 38 | CF18: 39.375 | CG18: 40.7785 | CH18: 41.4195 | CI18: 41.167 | CL18: 40.668 | CM18: 40.738 | CN18: 40.8035 | CO18: 40.47 | CP18: 40.563 | CS18: 38.625 | CT18: 47.8725 | CU18: 39.4375 | CV18: 39.6655 | CW18: 40.3125 | CZ18: 42.565 | DA18: 43.8125 | DB18: 44.25 | DC18: 46.1425 | DD18: 45.843 | DG18: 45.3395 | DH18: 47.4375 | DI18: 48.1875 | DJ18: 47.621 | DK18: 47 | DN18: 47.25 | DO18: 48 | DP18: 48 | DQ18: 48.5 | DR18: 49.875 | DU18: 50.7575 | DV18: 49.625 | DW18: 49.625 | DX18: 49.625 | DY18: 47.875 | EB18: 47 | EC18: 47.625 | ED18: 47.5 | EE18: 48.625 | EF18: 49 | EI18: 49 | EJ18: 48.04 | EK18: 48 | EL18: 49.47 | EM18: 48.375 | EP18: 48.2715 | EQ18: 47.125 | ER18: 46.7355 | ES18: 46.346 | ET18: 45.727 | EW18: 44.2365 | EX18: 44.5 | EY18: 45.875 | EZ18: 46.6285 | FA18: 45.875 | FD18: 47.375 | FE18: 48.75 | FF18: 49.25 | FG18: 49.375 | FH18: 50.5625 | FK18: 50.25 | FL18: 49.789 | FM18: 48.625 | FN18: 47.25 | FO18: 48.3915 | FR18: 48.4655 | FS18: 47.75 | FT18: 47.375 | FU18: 46.666 | FV18: 47.4375 | FY18: 47.87 | FZ18: 46.75 | GA18: 47 | GB18: 44.75 | GC18: 43.75 | GF18: 44.375 | GG18: 45.375 | GH18: 46.0585 | GI18: 43.985 | GJ18: 42.6715 | GM18: 37.375 | GN18: 37.7245 | GO18: 35.625 | GP18: 33.625 | GQ18: 36.0205 | GT18: 31 | GU18: 31.375 | GV18: 28.0735 | GW18: 26.875 | GX18: 27.125 | HA18: 25.5 | HB18: 27.2025 | HC18: 26.5 | HD18: 26.75 | HE18: 26.625 | HH18: 28.6865 | HI18: 28 | HJ18: 28.7675 | HK18: 28.25 | HL18: 29.75 | HO18: 30.25 | HP18: 31.359 | HQ18: 29.875 | HR18: 29.6985 | HS18: 28.75 | HV18: 29.125 | HW18: 30.125 | HX18: 28.875 | HY18: 29.1975 | HZ18: 33.125 | IC18: 32.25 | ID18: 32 | IE18: 30.625 | IF18: 29.5 | IG18: 29 | IJ18: 28.75 | IK18: 29.25 | IL18: 29.125 | IM18: 28.625 | IN18: 27.75 | IQ18: 40.269 | IR18: 29.5 | IS18: 30.3395 | IT18: 30.125 | IU18: 30.125 | IX18: 32.375 | IY18: 33.5 | IZ18: 33.75 | JA18: 55.01 | JB18: 36.4405 | JE18: 38 | JF18: 38.706 | JG18: 37.25 | JH18: 37.5 | JI18: 37.1175 | JL18: 57.345 | JM18: 40.625 | JN18: 40 | JO18: 38.8605 | JP18: 40.125 | JS18: 39.875 | JT18: 40.25 | JU18: 41.25 | JV18: 40.75 | JW18: 40.597 | JZ18: 41.5 | KA18: 39.5 | KB18: 40.875 | KC18: 40.25 | KD18: 41.375 | KG18: 40.75 | KH18: 41.75 | KI18: 41.5 | KJ18: 40.75 | KK18: 41.875 | KN18: 42.125 | KO18: 42.5 | KP18: 41.6335 | KQ18: 41.875 | KR18: 41 | KU18: 42.25 | KV18: 42 | KW18: 41.75 | KX18: 41.6255 | KY18: 41.616 | LB18: 42.9895 | LC18: 43.375 | LD18: 44.5 | LE18: 43.75 | LF18: 44.125 | LI18: 44.355 | LJ18: 42.858 | LK18: 43.232 | LL18: 43.584 | LM18: 42.9655 | LP18: 42.631 | LQ18: 43.25 | LR18: 44.181 | LS18: 45.334 | LT18: 45.0045 | LW18: 45.23 | LX18: 44.444 | LY18: 44.05 | LZ18: 44.0235 | MA18: 44.626 | MD18: 44.1875 | ME18: 49.52 | MF18: 49.9175 | MG18: 48.765 | MH18: 48.553 | MK18: 48.6435 | ML18: 48.6885 | MM18: 48.5735 | MN18: 48.4725 | MO18: 48.407 | MR18: 48.2915 | MS18: 47.988 | MT18: 48.3075 | MU18: 48.0015 | MV18: 48.04 | MY18: 45.959 | MZ18: 46.3275 | NA18: 46.03 | NB18: 46.8225 | NC18: 45.509 | NF18: 46.609 | NG18: 47.5085 | NH18: 47.635 | NI18: 47.7635 | NJ18: 47.7635
A19: USD 2026 | B19: 42482 | C19: US040114GX20 | F19: 38.25 | G19: 38.759 | H19: 40.99 | I19: 43.477 | J19: 45.426 | M19: 46.0235 | N19: 44.1265 | O19: 45.567 | P19: 45.282 | Q19: 43.901 | T19: 43.2685 | U19: 43.989 | V19: 45.4235 | W19: 44.953 | X19: 45.3085 | AA19: 44.41 | AB19: 43.261 | AC19: 42.753 | AD19: 42.9865 | AE19: 43.8565 | AH19: 43.947 | AI19: 44.335 | AJ19: 44.298 | AK19: 43.9915 | AL19: 44.0355 | AO19: 44.9875 | AP19: 45.182 | AQ19: 45.986 | AR19: 48.263 | AS19: 48.262 | AV19: 48.5515 | AW19: 47.757 | AX19: 46.701 | AY19: 46.766 | AZ19: 46.0005 | BC19: 45.219 | BD19: 43.7715 | BE19: 44.4455 | BF19: 45.3955 | BG19: 44.9595 | BJ19: 43.0035 | BK19: 42.7325 | BL19: 43.063 | BM19: 42.6395 | BN19: 42.4475 | BQ19: 42.4485 | BR19: 42.1335 | BS19: 41.583 | BT19: 41.4205 | BU19: 40.461 | BX19: 40.34 | BY19: 39.4835 | BZ19: 39.132 | CA19: 40.07 | CB19: 40.1395 | CE19: 40.26 | CF19: 40.783 | CG19: 42.93 | CH19: 44.15 | CI19: 43.6895 | CL19: 42.6575 | CM19: 42.9725 | CN19: 43.701 | CO19: 43.982 | CP19: 43.777 | CS19: 42.6335 | CT19: 41.5465 | CU19: 42.729 | CV19: 42.022 | CW19: 42.916 | CZ19: 45.544 | DA19: 45.707 | DB19: 45.6715 | DC19: 46.381 | DD19: 46.0455 | DG19: 46.185 | DH19: 47.5835 | DI19: 49.944 | DJ19: 48.8915 | DK19: 48.9985 | DN19: 49.5655 | DO19: 50.1485 | DP19: 50.3615 | DQ19: 51.306 | DR19: 52.1665 | DU19: 52.7565 | DV19: 52.1935 | DW19: 52.1875 | DX19: 51.4475 | DY19: 51.2225 | EB19: 48.273 | EC19: 48.9465 | ED19: 48.535 | EE19: 49.7135 | EF19: 50.0945 | EI19: 50.188 | EJ19: 50.217 | EK19: 50.6485 | EL19: 51.2375 | EM19: 50.786 | EP19: 50.656 | EQ19: 49.571 | ER19: 47.901 | ES19: 47.468 | ET19: 46.326 | EW19: 44.6395 | EX19: 45.055 | EY19: 46.5335 | EZ19: 46.329 | FA19: 46.144 | FD19: 47.313 | FE19: 48.813 | FF19: 49.5515 | FG19: 48.965 | FH19: 51.1035 | FK19: 50.364 | FL19: 49.357 | FM19: 48.8455 | FN19: 47.9285 | FO19: 47.46 | FR19: 47.281 | FS19: 47.998 | FT19: 47.2825 | FU19: 46.331 | FV19: 46.7055 | FY19: 46.8385 | FZ19: 46.831 | GA19: 46.8565 | GB19: 45.5885 | GC19: 44.03 | GF19: 44.2335 | GG19: 45.645 | GH19: 45.93 | GI19: 44.8205 | GJ19: 42.615 | GM19: 41.286 | GN19: 37.073 | GO19: 36.4535 | GP19: 33.7145 | GQ19: 33.986 | GT19: 33.2905 | GU19: 30.023 | GV19: 28.873 | GW19: 26.411 | GX19: 27.009 | HA19: 24.844 | HB19: 25.4525 | HC19: 25.409 | HD19: 26.196 | HE19: 26.563 | HH19: 26.7705 | HI19: 27.906 | HJ19: 28.1125 | HK19: 28.443 | HL19: 29.0515 | HO19: 30.115 | HP19: 29.7975 | HQ19: 28.2895 | HR19: 28 | HS19: 27.9035 | HV19: 27.6875 | HW19: 27.903 | HX19: 27.111 | HY19: 26.5575 | HZ19: 29.7575 | IC19: 32.4825 | ID19: 30.609 | IE19: 29.5475 | IF19: 28.0075 | IG19: 27.523 | IJ19: 27.5895 | IK19: 27.827 | IL19: 28.208 | IM19: 27.3055 | IN19: 26.6585 | IQ19: 26.0835 | IR19: 27.356 | IS19: 28.2785 | IT19: 28.2405 | IU19: 28.215 | IX19: 30.161 | IY19: 32.114 | IZ19: 31.884 | JA19: 31.424 | JB19: 34.11 | JE19: 35.6745 | JF19: 35.114 | JG19: 34.4395 | JH19: 34.6665 | JI19: 34.964 | JL19: 35.0765 | JM19: 37.763 | JN19: 38.3385 | JO19: 37.3085 | JP19: 38.1625 | JS19: 38.3125 | JT19: 38.1915 | JU19: 39.6555 | JV19: 39.4795 | JW19: 39.18 | JZ19: 39.7725 | KA19: 39.0635 | KB19: 39.219 | KC19: 38.9175 | KD19: 39.151 | KG19: 38.7195 | KH19: 40.31 | KI19: 40.2485 | KJ19: 39.1795 | KK19: 40.245 | KN19: 41.0635 | KO19: 42.0375 | KP19: 41.24 | KQ19: 41.021 | KR19: 40.126 | KU19: 40.8945 | KV19: 40.667 | KW19: 40.831 | KX19: 40.4065 | KY19: 40.1995 | LB19: 41.5415 | LC19: 41.8575 | LD19: 42.86 | LE19: 41.9335 | LF19: 42.15 | LI19: 42.284 | LJ19: 41.4585 | LK19: 41.4045 | LL19: 41.987 | LM19: 41.402 | LP19: 41.304 | LQ19: 41.7255 | LR19: 43.084 | LS19: 43.863 | LT19: 43.9045 | LW19: 43.974 | LX19: 43.465 | LY19: 42.8555 | LZ19: 42.7275 | MA19: 43.2975 | MD19: 42.8165 | ME19: 47.944 | MF19: 48.34 | MG19: 47.602 | MH19: 47.2025 | MK19: 47.1475 | ML19: 47.234 | MM19: 46.9465 | MN19: 46.73 | MO19: 46.66 | MR19: 46.579 | MS19: 46.381 | MT19: 46.4395 | MU19: 46.279 | MV19: 46.1985 | MY19: 46.1725 | MZ19: 46.087 | NA19: 46.077 | NB19: 46.0755 | NC19: 45.8195 | NF19: 45.7875 | NG19: 46.685 | NH19: 46.441 | NI19: 45.894 | NJ19: 46.235
A20: USD 2027 | B20: 42761 | C20: US040114HL72 | F20: 37.75 | G20: 37.533 | H20: 39.3125 | I20: 41.8125 | J20: 44.375 | M20: 44.3125 | N20: 43.1875 | O20: 43.5625 | P20: 43.25 | Q20: 41.625 | T20: 41.25 | U20: 41.5 | V20: 43.48 | W20: 42.6875 | X20: 43 | AA20: 42.125 | AB20: 41.375 | AC20: 40.857 | AD20: 41.1875 | AE20: 42.1875 | AH20: 42.375 | AI20: 42.3125 | AJ20: 42.125 | AK20: 42.0625 | AL20: 42.25 | AO20: 43.375 | AP20: 43.5 | AQ20: 44.1875 | AR20: 47 | AS20: 46.75 | AV20: 46.5 | AW20: 46.25 | AX20: 45 | AY20: 45.125 | AZ20: 44.5 | BC20: 43.625 | BD20: 41.5625 | BE20: 42.375 | BF20: 43.375 | BG20: 42.125 | BJ20: 40.5 | BK20: 40.75 | BL20: 40.485 | BM20: 40.11 | BN20: 39.5 | BQ20: 39.5 | BR20: 39 | BS20: 38.5 | BT20: 38.3125 | BU20: 37.632 | BX20: 37.375 | BY20: 36.375 | BZ20: 36.375 | CA20: 37.0025 | CB20: 37.375 | CE20: 37.25 | CF20: 38.875 | CG20: 40.4375 | CH20: 41.25 | CI20: 41.125 | CL20: 40.4375 | CM20: 40.75 | CN20: 40.9325 | CO20: 40.75 | CP20: 40.87 | CS20: 40.5 | CT20: 38.7165 | CU20: 38.949 | CV20: 39.4375 | CW20: 39.875 | CZ20: 40.231 | DA20: 40.231 | DB20: 40.231 | DC20: 40.231 | DD20: 43.8125 | DG20: 43.8125 | DH20: 44.02 | DI20: 47.3125 | DJ20: 46.875 | DK20: 46.5 | DN20: 47.375 | DO20: 47.875 | DP20: 47.875 | DQ20: 47.875 | DR20: 50.1875 | DU20: 50.125 | DV20: 50 | DW20: 50 | DX20: 49.5 | DY20: 48.46 | EB20: 46.125 | EC20: 46.5 | ED20: 46.52 | EE20: 47.75 | EF20: 48.125 | EI20: 48.25 | EJ20: 48 | EK20: 48.375 | EL20: 49.125 | EM20: 48.625 | EP20: 48.125 | EQ20: 47.0625 | ER20: 46.125 | ES20: 45.625 | ET20: 44.5625 | EW20: 45 | EX20: 43.125 | EY20: 45.375 | EZ20: 45.625 | FA20: 45.3925 | FD20: 46.75 | FE20: 48.25 | FF20: 48.8125 | FG20: 48.8125 | FH20: 49.6875 | FK20: 49.4375 | FL20: 48.948 | FM20: 47.625 | FN20: 47.625 | FO20: 46.375 | FR20: 46.4375 | FS20: 45.625 | FT20: 45.875 | FU20: 45.125 | FV20: 45.5625 | FY20: 45.75 | FZ20: 46 | GA20: 45.5625 | GB20: 44.375 | GC20: 43.0625 | GF20: 43.8125 | GG20: 44.5 | GH20: 44.875 | GI20: 43.625 | GJ20: 41.875 | GM20: 39.125 | GN20: 36.9375 | GO20: 35.875 | GP20: 32.875 | GQ20: 34.25 | GT20: 31 | GU20: 29.8125 | GV20: 26.625 | GW20: 26.375 | GX20: 26.375 | HA20: 24.5 | HB20: 25.125 | HC20: 25.375 | HD20: 25.875 | HE20: 25.875 | HH20: 26.9335 | HI20: 27.75 | HJ20: 27.949 | HK20: 28.625 | HL20: 29.375 | HO20: 29.875 | HP20: 29.75 | HQ20: 29.375 | HR20: 29.385 | HS20: 28.375 | HV20: 28.125 | HW20: 28.125 | HX20: 27.5 | HY20: 27.375 | HZ20: 31.125 | IC20: 31.25 | ID20: 30.25 | IE20: 28.375 | IF20: 27.375 | IG20: 26 | IJ20: 26.125 | IK20: 26.375 | IL20: 26.25 | IM20: 25.625 | IN20: 25 | IQ20: 24.375 | IR20: 25.625 | IS20: 26.5 | IT20: 27 | IU20: 26.6525 | IX20: 28.875 | IY20: 30 | IZ20: 29.25 | JA20: 29 | JB20: 30.875 | JE20: 32.375 | JF20: 32.25 | JG20: 31.625 | JH20: 32.75 | JI20: 32.405 | JL20: 32.625 | JM20: 36.75 | JN20: 36.125 | JO20: 35.298 | JP20: 36.25 | JS20: 37.25 | JT20: 37.25 | JU20: 39.5 | JV20: 38.75 | JW20: 38.25 | JZ20: 39.625 | KA20: 38.125 | KB20: 39.375 | KC20: 38.5 | KD20: 39 | KG20: 38.75 | KH20: 40.125 | KI20: 40 | KJ20: 39.125 | KK20: 40.125 | KN20: 40.75 | KO20: 41.625 | KP20: 40.375 | KQ20: 40.25 | KR20: 39.8375 | KU20: 40.25 | KV20: 39.875 | KW20: 40.2985 | KX20: 40.0555 | KY20: 39.875 | LB20: 41.25 | LC20: 41.875 | LD20: 42.25 | LE20: 41.625 | LF20: 41.625 | LI20: 42.01 | LJ20: 41.4375 | LK20: 40.9575 | LL20: 41.271 | LM20: 40.74 | LP20: 40.515 | LQ20: 40.8375 | LR20: 41.87 | LS20: 42.8875 | LT20: 42.745 | LW20: 42.8825 | LX20: 42.5285 | LY20: 42.1 | LZ20: 41.909 | MA20: 42.3355 | MD20: 41.78 | ME20: 46.6625 | MF20: 46.8 | MG20: 46.2675 | MH20: 45.893 | MK20: 45.638 | ML20: 45.7275 | MM20: 45.639 | MN20: 45.5195 | MO20: 45.5875 | MR20: 45.652 | MS20: 45.4525 | MT20: 45.555 | MU20: 45.1375 | MV20: 43.46 | MY20: 43.676 | MZ20: 43.5905 | NA20: 44.75 | NB20: 42.875 | NC20: 43.375 | NF20: 44.625 | NG20: 46 | NH20: 46 | NI20: 47 | NJ20: 47
A21: USD 5.875% 2028 | B21: 43111 | C21: US040114HQ69 | F21: 37.925 | G21: 37.125 | H21: 39.375 | I21: 41 | J21: 43.5625 | M21: 43.25 | N21: 41.875 | O21: 42.4375 | P21: 41.9375 | Q21: 40.125 | T21: 40.343 | U21: 40.5745 | V21: 42.1865 | W21: 41.5 | X21: 41.8125 | AA21: 40.875 | AB21: 40.25 | AC21: 40 | AD21: 39.875 | AE21: 40.625 | AH21: 41.25 | AI21: 41 | AJ21: 40.875 | AK21: 40.625 | AL21: 40.875 | AO21: 41.5 | AP21: 41.75 | AQ21: 42.375 | AR21: 44.9375 | AS21: 44.9375 | AV21: 44.8665 | AW21: 44.3125 | AX21: 43.125 | AY21: 43.32 | AZ21: 42.375 | BC21: 40.875 | BD21: 40.375 | BE21: 41.375 | BF21: 41.875 | BG21: 40.875 | BJ21: 38.6875 | BK21: 39.375 | BL21: 38.5445 | BM21: 38.25 | BN21: 38.375 | BQ21: 38.4295 | BR21: 38.179 | BS21: 37.625 | BT21: 37.5 | BU21: 36.5455 | BX21: 36.5625 | BY21: 35.6875 | BZ21: 36.125 | CA21: 36.875 | CB21: 36.875 | CE21: 36.795 | CF21: 38 | CG21: 39.8125 | CH21: 40.5 | CI21: 40.375 | CL21: 39.5 | CM21: 39.875 | CN21: 39.625 | CO21: 40.075 | CP21: 39.985 | CS21: 37.875 | CT21: 38.25 | CU21: 38.6875 | CV21: 38.5 | CW21: 38.8125 | CZ21: 40.7575 | DA21: 40.5 | DB21: 40.895 | DC21: 42.0625 | DD21: 41.9375 | DG21: 41.625 | DH21: 44 | DI21: 44.8125 | DJ21: 44.1875 | DK21: 43.625 | DN21: 44.875 | DO21: 45.5 | DP21: 45.5 | DQ21: 45.75 | DR21: 47.1875 | DU21: 48.155 | DV21: 47.25 | DW21: 47.25 | DX21: 46.875 | DY21: 44.625 | EB21: 44.25 | EC21: 45.375 | ED21: 44.75 | EE21: 46.1055 | EF21: 46.75 | EI21: 46.5 | EJ21: 46.134 | EK21: 46.625 | EL21: 47.4035 | EM21: 46.685 | EP21: 46.1115 | EQ21: 45.125 | ER21: 44.375 | ES21: 44.125 | ET21: 43.1875 | EW21: 42.0625 | EX21: 42.5 | EY21: 44.375 | EZ21: 44.4375 | FA21: 43.875 | FD21: 45.375 | FE21: 46.875 | FF21: 47.25 | FG21: 47.0625 | FH21: 47.9375 | FK21: 47.5625 | FL21: 45.375 | FM21: 45.75 | FN21: 44.25 | FO21: 44.625 | FR21: 44.75 | FS21: 43.875 | FT21: 43.875 | FU21: 43.0625 | FV21: 43.8125 | FY21: 43.875 | FZ21: 43.75 | GA21: 42.9375 | GB21: 41.3125 | GC21: 41 | GF21: 41.4375 | GG21: 42.1875 | GH21: 42.5 | GI21: 40.6875 | GJ21: 39.5625 | GM21: 35.25 | GN21: 35.2625 | GO21: 35.184 | GP21: 31.852 | GQ21: 32.1755 | GT21: 32.1755 | GU21: 32.1755 | GV21: 32.1755 | GW21: 26.1225 | GX21: 26.4675 | HA21: 24.3085 | HB21: 24.7465 | HC21: 24.745 | HD21: 25.245 | HE21: 25.1885 | HH21: 25.322 | HI21: 26.47 | HJ21: 26.7995 | HK21: 27.461 | HL21: 28.112 | HO21: 29.305 | HP21: 29.609 | HQ21: 28.6065 | HR21: 28.071 | HS21: 27.6315 | HV21: 27.25 | HW21: 27.908 | HX21: 27.287 | HY21: 27.5725 | HZ21: 28.893 | IC21: 31.018 | ID21: 29.6865 | IE21: 28.646 | IF21: 27.4795 | IG21: 26.4755 | IJ21: 26.195 | IK21: 25.985 | IL21: 26.566 | IM21: 26.0985 | IN21: 24.625 | IQ21: 24.1145 | IR21: 25.1255 | IS21: 26.572 | IT21: 26.764 | IU21: 26.573 | IX21: 27.111 | IY21: 30.409 | IZ21: 29.7395 | JA21: 29.061 | JB21: 31.6245 | JE21: 32.959 | JF21: 33.113 | JG21: 32.2305 | JH21: 32.4645 | JI21: 32.027 | JL21: 32.7265 | JM21: 36.313 | JN21: 36.5625 | JO21: 34.755 | JP21: 36.13 | JS21: 37.156 | JT21: 37.257 | JU21: 38.659 | JV21: 39.571 | JW21: 38.5585 | JZ21: 39.1975 | KA21: 38.968 | KB21: 39.302 | KC21: 39.188 | KD21: 38.8515 | KG21: 38.1765 | KH21: 39.86 | KI21: 39.7935 | KJ21: 38.7515 | KK21: 39.3635 | KN21: 39.9665 | KO21: 41.82 | KP21: 40.773 | KQ21: 40.5865 | KR21: 39.8125 | KU21: 40.3565 | KV21: 40.234 | KW21: 40.246 | KX21: 39.436 | KY21: 39.4995 | LB21: 41.1535 | LC21: 41.247 | LD21: 42.2 | LE21: 41.6065 | LF21: 41.5285 | LI21: 41.839 | LJ21: 40.948 | LK21: 40.7975 | LL21: 41.02 | LM21: 40.827 | LP21: 40.465 | LQ21: 40.678 | LR21: 41.643 | LS21: 42.8265 | LT21: 42.66 | LW21: 42.9085 | LX21: 42.478 | LY21: 41.88 | LZ21: 41.6715 | MA21: 42.449 | MD21: 42.157 | ME21: 47.5955 | MF21: 47.5275 | MG21: 45.7915 | MH21: 45.3465 | MK21: 45.564 | ML21: 45.5365 | MM21: 45.4085 | MN21: 45.438 | MO21: 45.36 | MR21: 45.285 | MS21: 45.062 | MT21: 45.2585 | MU21: 44.8865 | MV21: 44.803 | MY21: 43.68 | MZ21: 43.809 | NA21: 44.165 | NB21: 44.2415 | NC21: 39.8035 | NF21: 40.2115 | NG21: 43.9265 | NH21: 46.0015 | NI21: 45.875 | NJ21: 45.375
A22: USD 6.625% 2028 | B22: 42557 | C22: US040114HF05 | F22: 38.5 | G22: 37.489 | H22: 39.2395 | I22: 41.768 | J22: 43.325 | M22: 43.218 | N22: 42.444 | O22: 42.875 | P22: 42.6555 | Q22: 40.839 | T22: 40.512 | U22: 41.5 | V22: 42.261 | W22: 42 | X22: 42.011 | AA22: 41.3095 | AB22: 40.941 | AC22: 40.5755 | AD22: 40.8005 | AE22: 41.761 | AH22: 41.5 | AI22: 41.767 | AJ22: 41.875 | AK22: 41.725 | AL22: 41.675 | AO22: 42.54 | AP22: 42.9055 | AQ22: 43.625 | AR22: 46.142 | AS22: 46.46 | AV22: 46.5 | AW22: 44.987 | AX22: 44.043 | AY22: 43.5785 | AZ22: 42.8585 | BC22: 42.125 | BD22: 40.9115 | BE22: 41.85 | BF22: 42.25 | BG22: 41.989 | BJ22: 39.393 | BK22: 40.125 | BL22: 39.663 | BM22: 39.213 | BN22: 39.26 | BQ22: 39.01 | BR22: 39.1765 | BS22: 38.4335 | BT22: 38.2745 | BU22: 37.045 | BX22: 37.125 | BY22: 36.2015 | BZ22: 36.425 | CA22: 36.925 | CB22: 37.131 | CE22: 37.1275 | CF22: 38.5625 | CG22: 40.4 | CH22: 40.6175 | CI22: 40.407 | CL22: 39.744 | CM22: 40.2 | CN22: 40.31 | CO22: 40.305 | CP22: 40.325 | CS22: 39.0525 | CT22: 38.725 | CU22: 39.2 | CV22: 38.7975 | CW22: 39.222 | CZ22: 42.041 | DA22: 41.909 | DB22: 42.1825 | DC22: 42.5 | DD22: 42.4625 | DG22: 42.125 | DH22: 44.275 | DI22: 45.495 | DJ22: 44.75 | DK22: 45 | DN22: 45.9255 | DO22: 46.125 | DP22: 46.125 | DQ22: 46.5 | DR22: 47.255 | DU22: 48.125 | DV22: 47.875 | DW22: 47.875 | DX22: 47.8775 | DY22: 47.92 | EB22: 45.25 | EC22: 46.125 | ED22: 45.598 | EE22: 46.625 | EF22: 47.409 | EI22: 47.25 | EJ22: 47.125 | EK22: 47.375 | EL22: 48 | EM22: 47.625 | EP22: 47.4195 | EQ22: 46.0625 | ER22: 45.25 | ES22: 44.9375 | ET22: 44.0625 | EW22: 42.9375 | EX22: 43.125 | EY22: 45.125 | EZ22: 45 | FA22: 44.75 | FD22: 46 | FE22: 47.5 | FF22: 48.0625 | FG22: 47.9375 | FH22: 48.625 | FK22: 48.5 | FL22: 46.4375 | FM22: 47.125 | FN22: 45.8255 | FO22: 46 | FR22: 46.245 | FS22: 46.25 | FT22: 45.75 | FU22: 44.25 | FV22: 44.875 | FY22: 45.375 | FZ22: 46 | GA22: 45.6875 | GB22: 46.125 | GC22: 43 | GF22: 43.625 | GG22: 44.375 | GH22: 44.625 | GI22: 44.375 | GJ22: 41.125 | GM22: 41.1085 | GN22: 41.1085 | GO22: 41.1085 | GP22: 32.8125 | GQ22: 34.5625 | GT22: 31.8005 | GU22: 30.3125 | GV22: 27 | GW22: 25.805 | GX22: 27.375 | HA22: 24.196 | HB22: 25.25 | HC22: 25.75 | HD22: 25.7965 | HE22: 21.736 | HH22: 26.4585 | HI22: 28.25 | HJ22: 27.274 | HK22: 28.75 | HL22: 29.5 | HO22: 30 | HP22: 29.875 | HQ22: 27.875 | HR22: 27.961 | HS22: 28.375 | HV22: 28.125 | HW22: 28.625 | HX22: 27.375 | HY22: 27.344 | HZ22: 29.125 | IC22: 31.25 | ID22: 29.0415 | IE22: 28.75 | IF22: 27 | IG22: 27 | IJ22: 27 | IK22: 26.546 | IL22: 26.875 | IM22: 26.75 | IN22: 25.5 | IQ22: 24.625 | IR22: 25.875 | IS22: 26.625 | IT22: 27.25 | IU22: 26.875 | IX22: 29.25 | IY22: 29.875 | IZ22: 29.25 | JA22: 28.9355 | JB22: 31.125 | JE22: 33.625 | JF22: 32.5 | JG22: 32.25 | JH22: 32.5 | JI22: 32.9775 | JL22: 32.7355 | JM22: 37.75 | JN22: 35.875 | JO22: 35.137 | JP22: 36.625 | JS22: 37.5 | JT22: 37.625 | JU22: 39.5 | JV22: 39.25 | JW22: 38.375 | JZ22: 39.875 | KA22: 38.125 | KB22: 39.375 | KC22: 38.625 | KD22: 38.875 | KG22: 38.75 | KH22: 40.25 | KI22: 39.875 | KJ22: 39.25 | KK22: 40.125 | KN22: 40.875 | KO22: 41.875 | KP22: 40.754 | KQ22: 40.875 | KR22: 40 | KU22: 40.625 | KV22: 40 | KW22: 40.2325 | KX22: 39.5875 | KY22: 39.6435 | LB22: 41.325 | LC22: 42.125 | LD22: 42.5 | LE22: 41.75 | LF22: 41.875 | LI22: 41.8465 | LJ22: 40.891 | LK22: 40.9205 | LL22: 41.1425 | LM22: 40.592 | LP22: 40.4705 | LQ22: 40.973 | LR22: 41.9805 | LS22: 43.064 | LT22: 42.968 | LW22: 43.097 | LX22: 42.591 | LY22: 41.8985 | LZ22: 41.925 | MA22: 42.5325 | MD22: 41.777 | ME22: 47.344 | MF22: 47.032 | MG22: 46.3 | MH22: 45.9065 | MK22: 46.01 | ML22: 46.103 | MM22: 45.9315 | MN22: 45.805 | MO22: 45.6215 | MR22: 45.5115 | MS22: 45.215 | MT22: 45.453 | MU22: 45.195 | MV22: 45.087 | MY22: 44.992 | MZ22: 45.055 | NA22: 45.103 | NB22: 44.2115 | NC22: 45.077 | NF22: 45.013 | NG22: 46.4435 | NH22: 46.767 | NI22: 46.647 | NJ22: 46.647
A23: USD 2036 | B23: 42557 | C23: US040114HG87 | F23: 37.521 | G23: 37.396 | H23: 40.25 | I23: 42 | J23: 44.75 | M23: 44.5625 | N23: 43.625 | O23: 43.9375 | P23: 43.6875 | Q23: 42 | T23: 41.365 | U23: 42.25 | V23: 44.2895 | W23: 43.6875 | X23: 43.875 | AA23: 43.0625 | AB23: 42.3125 | AC23: 42.0575 | AD23: 42 | AE23: 43 | AH23: 43.1875 | AI23: 43.1875 | AJ23: 43.125 | AK23: 42.9375 | AL23: 43.125 | AO23: 43.6875 | AP23: 43.9375 | AQ23: 44.5625 | AR23: 47.375 | AS23: 47.0625 | AV23: 47.07 | AW23: 46.375 | AX23: 44.25 | AY23: 44.875 | AZ23: 43.875 | BC23: 42.125 | BD23: 40.75 | BE23: 41.4375 | BF23: 42.375 | BG23: 41.125 | BJ23: 39.5 | BK23: 40 | BL23: 40.125 | BM23: 39.25 | BN23: 39.5 | BQ23: 39.5 | BR23: 39.25 | BS23: 38.75 | BT23: 38.5 | BU23: 37.5 | BX23: 37.625 | BY23: 37.5 | BZ23: 36.5 | CA23: 37.625 | CB23: 37.75 | CE23: 37.625 | CF23: 38.25 | CG23: 40 | CH23: 41.5 | CI23: 41.125 | CL23: 40.75 | CM23: 40.125 | CN23: 40.625 | CO23: 40.25 | CP23: 40.625 | CS23: 38.75 | CT23: 38.125 | CU23: 39.375 | CV23: 38.375 | CW23: 38.375 | CZ23: 41 | DA23: 40.25 | DB23: 40.125 | DC23: 40.375 | DD23: 40.25 | DG23: 40.5 | DH23: 42.625 | DI23: 44.25 | DJ23: 44.125 | DK23: 44.125 | DN23: 45.75 | DO23: 46.625 | DP23: 46.625 | DQ23: 48 | DR23: 47.75 | DU23: 48.125 | DV23: 48.125 | DW23: 48.125 | DX23: 48.125 | DY23: 45.375 | EB23: 44.625 | EC23: 45.875 | ED23: 45.25 | EE23: 46.625 | EF23: 46.875 | EI23: 47.125 | EJ23: 46.75 | EK23: 47.25 | EL23: 47.875 | EM23: 47.5 | EP23: 47.25 | EQ23: 46.25 | ER23: 45.25 | ES23: 44.875 | ET23: 44.75 | EW23: 42.125 | EX23: 42.625 | EY23: 44 | EZ23: 44 | FA23: 43.375 | FD23: 44.875 | FE23: 46.5 | FF23: 46.75 | FG23: 46.125 | FH23: 46.75 | FK23: 46.25 | FL23: 45.5 | FM23: 44.625 | FN23: 43 | FO23: 43.375 | FR23: 45 | FS23: 42.625 | FT23: 43.125 | FU23: 42.125 | FV23: 43.125 | FY23: 43 | FZ23: 43.25 | GA23: 43.375 | GB23: 42 | GC23: 41.5 | GF23: 40.875 | GG23: 42.625 | GH23: 42.75 | GI23: 42.25 | GJ23: 41.375 | GM23: 38.625 | GN23: 36.75 | GO23: 34.5 | GP23: 33.125 | GQ23: 31.75 | GT23: 29.625 | GU23: 29.125 | GV23: 27.75 | GW23: 25.5 | GX23: 25.875 | HA23: 24.5 | HB23: 24.625 | HC23: 25.125 | HD23: 24.625 | HE23: 25 | HH23: 25.25 | HI23: 26.25 | HJ23: 26.125 | HK23: 26.5 | HL23: 27.125 | HO23: 27.875 | HP23: 28 | HQ23: 26.625 | HR23: 26.375 | HS23: 26.375 | HV23: 27 | HW23: 27.125 | HX23: 26.25 | HY23: 26.5 | HZ23: 30.25 | IC23: 29.25 | ID23: 30.125 | IE23: 28.25 | IF23: 26.625 | IG23: 26 | IJ23: 26.25 | IK23: 25.75 | IL23: 26 | IM23: 25.375 | IN23: 24.5 | IQ23: 24 | IR23: 25.625 | IS23: 26.625 | IT23: 26.875 | IU23: 26.875 | IX23: 28.75 | IY23: 30 | IZ23: 29.375 | JA23: 29 | JB23: 29.75 | JE23: 31.875 | JF23: 31.625 | JG23: 31.25 | JH23: 31.625 | JI23: 31.5 | JL23: 31.5 | JM23: 36.375 | JN23: 36.125 | JO23: 35.75 | JP23: 37 | JS23: 37.5 | JT23: 37.875 | JU23: 39.75 | JV23: 39.375 | JW23: 38.75 | JZ23: 40 | KA23: 38.25 | KB23: 39.5 | KC23: 38.625 | KD23: 38.75 | KG23: 38.875 | KH23: 39.75 | KI23: 39.375 | KJ23: 38.625 | KK23: 40 | KN23: 40.375 | KO23: 41.375 | KP23: 40.375 | KQ23: 40.375 | KR23: 39.625 | KU23: 40.375 | KV23: 39.75 | KW23: 39.75 | KX23: 39.625 | KY23: 39.625 | LB23: 41.5 | LC23: 41.75 | LD23: 42.125 | LE23: 41.75 | LF23: 42 | LI23: 42 | LJ23: 40.9465 | LK23: 41.0035 | LL23: 41.1245 | LM23: 40.465 | LP23: 40.5255 | LQ23: 40.9855 | LR23: 42.0265 | LS23: 43.388 | LT23: 42.9665 | LW23: 43.26 | LX23: 42.89 | LY23: 42.797 | LZ23: 42.0065 | MA23: 42.9365 | MD23: 42.715 | ME23: 48.0915 | MF23: 47.5125 | MG23: 46.685 | MH23: 46.1425 | MK23: 46.2785 | ML23: 46.285 | MM23: 45.835 | MN23: 45.6785 | MO23: 45.31 | MR23: 45.2825 | MS23: 45.0325 | MT23: 45.095 | MU23: 44.9175 | MV23: 44.965 | MY23: 44.6065 | MZ23: 44.4705 | NA23: 44.5665 | NB23: 43.746 | NC23: 44.875 | NF23: 44.875 | NG23: 46.375 | NH23: 46.375 | NI23: 46.375 | NJ23: 47.875
A24: USD 2046 | B24: 42482 | C24: US040114GY03 | F24: 38.634 | G24: 38.8025 | H24: 40.9735 | I24: 43.284 | J24: 45.6095 | M24: 46.028 | N24: 43.994 | O24: 44.6905 | P24: 44.6995 | Q24: 43.6245 | T24: 42.2335 | U24: 42.8785 | V24: 44.676 | W24: 44.3955 | X24: 44.879 | AA24: 44.2635 | AB24: 43.005 | AC24: 42.709 | AD24: 43.1665 | AE24: 43.621 | AH24: 43.75 | AI24: 43.907 | AJ24: 43.6745 | AK24: 43.522 | AL24: 43.9015 | AO24: 44.6825 | AP24: 44.7895 | AQ24: 45.52 | AR24: 48.4175 | AS24: 48.1795 | AV24: 48.0975 | AW24: 47.5075 | AX24: 45.8565 | AY24: 45.488 | AZ24: 44.654 | BC24: 43.336 | BD24: 42.045 | BE24: 42.316 | BF24: 43.972 | BG24: 42.9695 | BJ24: 40.496 | BK24: 40.8015 | BL24: 41.0275 | BM24: 40.6495 | BN24: 40.6325 | BQ24: 40.3775 | BR24: 40.4835 | BS24: 39.741 | BT24: 39.4065 | BU24: 38.972 | BX24: 38.6825 | BY24: 38.2205 | BZ24: 38.138 | CA24: 39.537 | CB24: 39.433 | CE24: 39.639 | CF24: 39.9515 | CG24: 42.184 | CH24: 43.1795 | CI24: 43.0425 | CL24: 42.2575 | CM24: 42.3545 | CN24: 42.5615 | CO24: 42.5625 | CP24: 42.7095 | CS24: 41.0955 | CT24: 40.3905 | CU24: 41.312 | CV24: 40.6595 | CW24: 41.2625 | CZ24: 43.2405 | DA24: 42.7425 | DB24: 42.6615 | DC24: 43.4005 | DD24: 43.203 | DG24: 43.1775 | DH24: 44.0155 | DI24: 47.317 | DJ24: 46.7185 | DK24: 46.744 | DN24: 47.984 | DO24: 49.2795 | DP24: 49.3015 | DQ24: 49.757 | DR24: 50.0985 | DU24: 50.734 | DV24: 50.6745 | DW24: 50.6945 | DX24: 50.118 | DY24: 49.7945 | EB24: 46.3655 | EC24: 47.5545 | ED24: 46.6635 | EE24: 48.1955 | EF24: 48.7385 | EI24: 48.3715 | EJ24: 48.262 | EK24: 48.096 | EL24: 48.5825 | EM24: 47.977 | EP24: 48.121 | EQ24: 46.74 | ER24: 45.26 | ES24: 44.914 | ET24: 44.281 | EW24: 42.01 | EX24: 42.3255 | EY24: 43.8345 | EZ24: 43.426 | FA24: 43.3225 | FD24: 44.182 | FE24: 45.011 | FF24: 45.9505 | FG24: 45.067 | FH24: 45.815 | FK24: 45.4815 | FL24: 44.481 | FM24: 43.679 | FN24: 42.901 | FO24: 42.9375 | FR24: 43.035 | FS24: 42.5075 | FT24: 42.626 | FU24: 42.223 | FV24: 42.9405 | FY24: 43.0795 | FZ24: 43.2755 | GA24: 43.1595 | GB24: 42.6165 | GC24: 41.9825 | GF24: 41.9825 | GG24: 42.2835 | GH24: 42.8215 | GI24: 42.141 | GJ24: 41.6365 | GM24: 36.718 | GN24: 35.9565 | GO24: 35.7675 | GP24: 35.7675 | GQ24: 30.9265 | GT24: 30.9265 | GU24: 30.9265 | GV24: 30.9265 | GW24: 24.96 | GX24: 25.062 | HA24: 23.403 | HB24: 24.17 | HC24: 24.233 | HD24: 24.595 | HE24: 24.625 | HH24: 24.895 | HI24: 25.9295 | HJ24: 25.5735 | HK24: 26.2015 | HL24: 26.8605 | HO24: 27.88 | HP24: 28.445 | HQ24: 26.859 | HR24: 26.1375 | HS24: 25.632 | HV24: 26.375 | HW24: 26.7035 | HX24: 25.57 | HY24: 25.352 | HZ24: 27.851 | IC24: 31.0475 | ID24: 30.2815 | IE24: 28.383 | IF24: 26.27 | IG24: 25.8715 | IJ24: 25.6485 | IK24: 25.9165 | IL24: 26.0685 | IM24: 24.9785 | IN24: 24.783 | IQ24: 23.65 | IR24: 25.4775 | IS24: 26.8085 | IT24: 27.088 | IU24: 27.533 | IX24: 28.528 | IY24: 30.8735 | IZ24: 30.3315 | JA24: 29.579 | JB24: 32.7125 | JE24: 33.97 | JF24: 33.3515 | JG24: 32.499 | JH24: 32.366 | JI24: 32.5265 | JL24: 32.8675 | JM24: 36.1155 | JN24: 36.725 | JO24: 35.985 | JP24: 37.0965 | JS24: 37.25 | JT24: 37.3425 | JU24: 38.11 | JV24: 38.1635 | JW24: 37.7025 | JZ24: 38.689 | KA24: 38.303 | KB24: 38.2355 | KC24: 37.976 | KD24: 37.655 | KG24: 37.179 | KH24: 38.1035 | KI24: 37.7265 | KJ24: 36.8415 | KK24: 38.063 | KN24: 38.7485 | KO24: 40.081 | KP24: 39.201 | KQ24: 39.1525 | KR24: 38.486 | KU24: 39.321 | KV24: 39.372 | KW24: 39.3135 | KX24: 38.8515 | KY24: 38.8035 | LB24: 40.51 | LC24: 40.739 | LD24: 41.901 | LE24: 41.129 | LF24: 41.5005 | LI24: 41.675 | LJ24: 40.7705 | LK24: 40.69 | LL24: 40.9815 | LM24: 40.5065 | LP24: 40.3765 | LQ24: 40.8275 | LR24: 41.693 | LS24: 42.8655 | LT24: 42.8635 | LW24: 43.1515 | LX24: 42.9515 | LY24: 42.5515 | LZ24: 42.278 | MA24: 42.9075 | MD24: 42.5585 | ME24: 47.826 | MF24: 47.6125 | MG24: 46.8175 | MH24: 46.1815 | MK24: 46.205 | ML24: 46.0685 | MM24: 45.765 | MN24: 45.3365 | MO24: 45.256 | MR24: 45.0355 | MS24: 44.8875 | MT24: 45.1915 | MU24: 44.9075 | MV24: 45.105 | MY24: 44.4685 | MZ24: 44.3765 | NA24: 44.1215 | NB24: 43.9765 | NC24: 44.122 | NF24: 44.2165 | NG24: 45.182 | NH24: 45.303 | NI24: 45.449 | NJ24: 46.75
A25: USD 2048 | B25: 43111 | C25: US040114HR43 | F25: 37.625 | G25: 37.8625 | H25: 39.814 | I25: 42.39 | J25: 42.511 | M25: 44.1545 | N25: 43.0915 | O25: 43.592 | P25: 43.377 | Q25: 41.011 | T25: 40.273 | U25: 42.01 | V25: 42.6415 | W25: 42.59 | X25: 42.9355 | AA25: 42.275 | AB25: 41.625 | AC25: 41.625 | AD25: 41.3505 | AE25: 41.878 | AH25: 42.75 | AI25: 42.2115 | AJ25: 42.055 | AK25: 42.125 | AL25: 42.6345 | AO25: 43.35 | AP25: 43.5545 | AQ25: 44.4885 | AR25: 46.7355 | AS25: 46.2385 | AV25: 46.4535 | AW25: 45.255 | AX25: 43.725 | AY25: 43.662 | AZ25: 42.967 | BC25: 41.375 | BD25: 40.225 | BE25: 40.957 | BF25: 41.825 | BG25: 41.05 | BJ25: 40.0565 | BK25: 40.133 | BL25: 39.7055 | BM25: 39.587 | BN25: 39.3535 | BQ25: 39.13 | BR25: 39.098 | BS25: 38.175 | BT25: 37.9005 | BU25: 36.954 | BX25: 37.273 | BY25: 36.128 | BZ25: 36.6635 | CA25: 37.449 | CB25: 37.7 | CE25: 37.3 | CF25: 38.8175 | CG25: 40.7245 | CH25: 40.9 | CI25: 40.585 | CL25: 39.9195 | CM25: 40.2605 | CN25: 40.25 | CO25: 40.07 | CP25: 40.455 | CS25: 38.9885 | CT25: 37.8625 | CU25: 38.5425 | CV25: 37.997 | CW25: 38.036 | CZ25: 39.735 | DA25: 39.4975 | DB25: 39.872 | DC25: 40.369 | DD25: 40.225 | DG25: 39.798 | DH25: 42.325 | DI25: 43.934 | DJ25: 43.7095 | DK25: 44.318 | DN25: 45.3835 | DO25: 45.75 | DP25: 45.8815 | DQ25: 47.1325 | DR25: 47.02 | DU25: 48.38 | DV25: 47.9825 | DW25: 47.375 | DX25: 47.7415 | DY25: 47.708 | EB25: 43.6425 | EC25: 44.625 | ED25: 44.375 | EE25: 45.5 | EF25: 45.7105 | EI25: 46.5 | EJ25: 46.125 | EK25: 46.25 | EL25: 46.79 | EM25: 46.375 | EP25: 45.875 | EQ25: 44.6875 | ER25: 43.8125 | ES25: 43.8125 | ET25: 42.9375 | EW25: 42.3105 | EX25: 41.625 | EY25: 43.5 | EZ25: 42.585 | FA25: 42.625 | FD25: 43.625 | FE25: 45.375 | FF25: 45.125 | FG25: 44.4375 | FH25: 44.875 | FK25: 44.8125 | FL25: 42.9375 | FM25: 43.4165 | FN25: 42.309 | FO25: 42.375 | FR25: 42.4375 | FS25: 42.158 | FT25: 42.158 | FU25: 42.158 | FV25: 42.375 | FY25: 42.375 | FZ25: 42.625 | GA25: 42.438 | GB25: 42.438 | GC25: 42.438 | GF25: 42.438 | GG25: 42.438 | GH25: 42.438 | GI25: 39.75 | GJ25: 39.75 | GM25: 39.75 | GN25: 39.75 | GO25: 34.784 | GP25: 34.784 | GQ25: 30.625 | GT25: 30.625 | GU25: 30.625 | GV25: 30.625 | GW25: 30.625 | GX25: 25.625 | HA25: 25.48 | HB25: 23.375 | HC25: 24.125 | HD25: 24.75 | HE25: 24.625 | HH25: 25.175 | HI25: 26.125 | HJ25: 25.9915 | HK25: 26.125 | HL25: 27 | HO25: 27.553 | HP25: 27.5 | HQ25: 26.625 | HR25: 26.7145 | HS25: 26.25 | HV25: 26.125 | HW25: 26.375 | HX25: 26 | HY25: 25.875 | HZ25: 26.505 | IC25: 29.875 | ID25: 29.875 | IE25: 28.75 | IF25: 28.75 | IG25: 28.75 | IJ25: 28.75 | IK25: 24.5 | IL25: 24.375 | IM25: 24.125 | IN25: 23 | IQ25: 22.875 | IR25: 24.5 | IS25: 25.375 | IT25: 25.5 | IU25: 25.875 | IX25: 27.5 | IY25: 28.5 | IZ25: 27.875 | JA25: 27.375 | JB25: 29.25 | JE25: 31.125 | JF25: 29.75 | JG25: 29.5 | JH25: 30.25 | JI25: 30.125 | JL25: 30.125 | JM25: 35.625 | JN25: 34.75 | JO25: 34.25 | JP25: 36.25 | JS25: 36.125 | JT25: 36.5 | JU25: 38.125 | JV25: 37.625 | JW25: 37.375 | JZ25: 38.875 | KA25: 37.375 | KB25: 38.375 | KC25: 37.25 | KD25: 37.5 | KG25: 37.375 | KH25: 38.125 | KI25: 37.75 | KJ25: 36.875 | KK25: 38.125 | KN25: 38.875 | KO25: 39.875 | KP25: 39 | KQ25: 38.5 | KR25: 38 | KU25: 39.375 | KV25: 39.125 | KW25: 39 | KX25: 39 | KY25: 39 | LB25: 40.375 | LC25: 40.875 | LD25: 41.375 | LE25: 41 | LF25: 40.875 | LI25: 40.875 | LJ25: 40.8365 | LK25: 40.021 | LL25: 40.404 | LM25: 40.199 | LP25: 40.165 | LQ25: 40.325 | LR25: 41.5935 | LS25: 42.5465 | LT25: 42.243 | LW25: 42.3465 | LX25: 41.905 | LY25: 41.3785 | LZ25: 41.3635 | MA25: 41.4985 | MD25: 41.682 | ME25: 46.2235 | MF25: 46.603 | MG25: 45.403 | MH25: 45.2585 | MK25: 44.6915 | ML25: 45.332 | MM25: 44.955 | MN25: 44.547 | MO25: 44.2435 | MR25: 44.0945 | MS25: 43.912 | MT25: 43.455 | MU25: 43.8625 | MV25: 43.2515 | MY25: 42.933 | MZ25: 42.625 | NA25: 43.16 | NB25: 42.832 | NC25: 42.603 | NF25: 42.9375 | NG25: 43.5 | NH25: 44.625 | NI25: 45.4845 | NJ25: 44.7725
A26: USD 2117 | B26: 42914 | C26: USP04808AN44 | F26: 37.75 | G26: 38.25 | H26: 41 | I26: 42 | J26: 45.25 | M26: 47.25 | N26: 43.25 | O26: 44.75 | P26: 44.25 | Q26: 42.25 | T26: 42 | U26: 42.25 | V26: 44.25 | W26: 43.5 | X26: 43.5 | AA26: 43.25 | AB26: 42 | AC26: 41.5 | AD26: 42.25 | AE26: 43 | AH26: 43.5 | AI26: 43.25 | AJ26: 43.5 | AK26: 42.875 | AL26: 43.375 | AO26: 44.25 | AP26: 43.875 | AQ26: 44.75 | AR26: 47.5 | AS26: 47.25 | AV26: 46.75 | AW26: 46.25 | AX26: 44.5 | AY26: 44.625 | AZ26: 43.875 | BC26: 42.75 | BD26: 41.75 | BE26: 42.125 | BF26: 43.25 | BG26: 42.375 | BJ26: 40 | BK26: 40.75 | BL26: 40.625 | BM26: 40 | BN26: 40.25 | BQ26: 40 | BR26: 39.875 | BS26: 39.5 | BT26: 38.75 | BU26: 38.125 | BX26: 37.875 | BY26: 37.75 | BZ26: 37 | CA26: 38.625 | CB26: 38.375 | CE26: 38.25 | CF26: 38.375 | CG26: 41.25 | CH26: 42.25 | CI26: 42.375 | CL26: 41.125 | CM26: 40.75 | CN26: 41.5 | CO26: 41 | CP26: 41.25 | CS26: 40.25 | CT26: 39.25 | CU26: 40.5 | CV26: 39.375 | CW26: 39.375 | CZ26: 41.875 | DA26: 41.125 | DB26: 41.625 | DC26: 41.625 | DD26: 41.5 | DG26: 41.5 | DH26: 43.5 | DI26: 45.375 | DJ26: 45.625 | DK26: 45.75 | DN26: 46.75 | DO26: 48.25 | DP26: 48.25 | DQ26: 48.25 | DR26: 49.625 | DU26: 50.25 | DV26: 50.25 | DW26: 50.25 | DX26: 49 | DY26: 47.25 | EB26: 45.875 | EC26: 47.375 | ED26: 46.625 | EE26: 48 | EF26: 48.875 | EI26: 48.5 | EJ26: 47.75 | EK26: 48 | EL26: 48.5 | EM26: 47.875 | EP26: 47.875 | EQ26: 46.5 | ER26: 44.625 | ES26: 44.75 | ET26: 44.625 | EW26: 43.25 | EX26: 42.625 | EY26: 44.25 | EZ26: 43.75 | FA26: 43.25 | FD26: 44.875 | FE26: 45.5 | FF26: 46.375 | FG26: 45.25 | FH26: 45.75 | FK26: 45.375 | FL26: 44.375 | FM26: 43.875 | FN26: 42.5 | FO26: 43.125 | FR26: 43.5 | FS26: 42.5 | FT26: 42.875 | FU26: 42 | FV26: 43.125 | FY26: 43.25 | FZ26: 43.625 | GA26: 43.125 | GB26: 41.5 | GC26: 40.375 | GF26: 40.5 | GG26: 41.75 | GH26: 42.25 | GI26: 40.375 | GJ26: 38.625 | GM26: 35.5 | GN26: 35.5 | GO26: 34.75 | GP26: 31.5 | GQ26: 31 | GT26: 30.25 | GU26: 28.75 | GV26: 26.5 | GW26: 24.75 | GX26: 25.75 | HA26: 24 | HB26: 24 | HC26: 24.375 | HD26: 25 | HE26: 24.625 | HH26: 24.625 | HI26: 25.5 | HJ26: 25.75 | HK26: 26.25 | HL26: 27 | HO26: 28.125 | HP26: 28.125 | HQ26: 26.25 | HR26: 26 | HS26: 26 | HV26: 26.25 | HW26: 26.5 | HX26: 25.375 | HY26: 25.875 | HZ26: 28.375 | IC26: 30 | ID26: 29.125 | IE26: 27 | IF26: 26.25 | IG26: 24.5 | IJ26: 24.5 | IK26: 24.625 | IL26: 24.5 | IM26: 24.5 | IN26: 23.25 | IQ26: 22.75 | IR26: 24.5 | IS26: 25.25 | IT26: 25.75 | IU26: 25.75 | IX26: 27.5 | IY26: 29 | IZ26: 28 | JA26: 27.25 | JB26: 29.25 | JE26: 30.625 | JF26: 30 | JG26: 29.125 | JH26: 29.625 | JI26: 29.75 | JL26: 29.75 | JM26: 35.25 | JN26: 34.625 | JO26: 34.375 | JP26: 36.125 | JS26: 36 | JT26: 36.5 | JU26: 38.25 | JV26: 38 | JW26: 37.5 | JZ26: 39.125 | KA26: 37.5 | KB26: 38.375 | KC26: 37.25 | KD26: 37.625 | KG26: 37.25 | KH26: 38.125 | KI26: 37.625 | KJ26: 36.875 | KK26: 38 | KN26: 38.875 | KO26: 39.75 | KP26: 38.75 | KQ26: 38.75 | KR26: 37.875 | KU26: 39.25 | KV26: 38.875 | KW26: 38.625 | KX26: 39 | KY26: 39 | LB26: 40.25 | LC26: 40.625 | LD26: 41.75 | LE26: 41.25 | LF26: 41.125 | LI26: 41.125 | LJ26: 41.125 | LK26: 39.75 | LL26: 40.5 | LM26: 40.125 | LP26: 40 | LQ26: 40.875 | LR26: 41.625 | LS26: 42.5 | LT26: 41.875 | LW26: 42.375 | LX26: 41.5 | LY26: 41.25 | LZ26: 41 | MA26: 41.5 | MD26: 41.375 | ME26: 46 | MF26: 46 | MG26: 45.25 | MH26: 45.25 | MK26: 44.75 | ML26: 44.75 | MM26: 44.625 | MN26: 44.125 | MO26: 43.875 | MR26: 44 | MS26: 43.625 | MT26: 43.75 | MU26: 43.25 | MV26: 43.25 | MY26: 43.25 | MZ26: 43.25 | NA26: 43.125 | NB26: 41.125 | NC26: 43.25 | NF26: 43.375 | NG26: 43.5 | NH26: 43.5 | NI26: 43.375 | NJ26: 42.375
A27: Euro 2022 | B27: 42655 | C27: XS1503160225 | F27: 37.18 | G27: 37.25 | H27: 37.9245 | I27: 40.25 | J27: 42.4375 | M27: 42.5 | N27: 40.8125 | O27: 41.4375 | P27: 41.1875 | Q27: 40.0625 | T27: 39.5 | U27: 40 | V27: 41.245 | W27: 40.625 | X27: 41.03 | AA27: 40.125 | AB27: 39.1875 | AC27: 38.73 | AD27: 38.9375 | AE27: 39.9 | AH27: 39.875 | AI27: 40.25 | AJ27: 40.1875 | AK27: 40.25 | AL27: 40.375 | AO27: 41.25 | AP27: 41.75 | AQ27: 42.25 | AR27: 43.996 | AS27: 44.625 | AV27: 44.56 | AW27: 43.9375 | AX27: 43.567 | AY27: 42.749 | AZ27: 42.375 | BC27: 42.015 | BD27: 40.3125 | BE27: 41 | BF27: 42.25 | BG27: 42.5755 | BJ27: 39.75 | BK27: 40.375 | BL27: 40.44 | BM27: 40.24 | BN27: 40.175 | BQ27: 39.75 | BR27: 40.315 | BS27: 40.25 | BT27: 38.9375 | BU27: 39.06 | BX27: 38.25 | BY27: 37.6875 | BZ27: 36.875 | CA27: 37.75 | CB27: 37.8125 | CE27: 37.86 | CF27: 38.4375 | CG27: 40.25 | CH27: 39.5 | CI27: 39.875 | CL27: 39.55 | CM27: 39 | CN27: 39.55 | CO27: 40.06 | CP27: 40.075 | CS27: 38.9 | CT27: 39.7775 | CU27: 39.966 | CV27: 40.534 | CW27: 40.143 | CZ27: 42.14 | DA27: 42.665 | DB27: 42.2195 | DC27: 41.093 | DD27: 41.143 | DG27: 42.327 | DH27: 41.246 | DI27: 41.246 | DJ27: 47.7155 | DK27: 45.8785 | DN27: 47 | DO27: 45.8 | DP27: 46.644 | DQ27: 46.644 | DR27: 48.35 | DU27: 48.75 | DV27: 48.74 | DW27: 48.75 | DX27: 48.15 | DY27: 48.487 | EB27: 47.047 | EC27: 47.5935 | ED27: 47.239 | EE27: 48.247 | EF27: 49.42 | EI27: 49.026 | EJ27: 48.581 | EK27: 48.9 | EL27: 49.22 | EM27: 49.157 | EP27: 49.157 | EQ27: 48.491 | ER27: 46.76 | ES27: 45.9695 | ET27: 46.1345 | EW27: 44.3755 | EX27: 45.16 | EY27: 46.91 | EZ27: 46.745 | FA27: 46.7795 | FD27: 47.5 | FE27: 48.9365 | FF27: 50.875 | FG27: 49.25 | FH27: 50.4 | FK27: 50.64 | FL27: 50.035 | FM27: 49.6 | FN27: 48.525 | FO27: 48.955 | FR27: 47.975 | FS27: 47.4 | FT27: 48.575 | FU27: 46.585 | FV27: 47.4 | FY27: 48 | FZ27: 48.04 | GA27: 47.45 | GB27: 48.24 | GC27: 45 | GF27: 44.95 | GG27: 46.1 | GH27: 46.1315 | GI27: 46.025 | GJ27: 46.75 | GM27: 43.41 | GN27: 39.475 | GO27: 37.85 | GP27: 35.21 | GQ27: 36.85 | GT27: 36.35 | GU27: 35.25 | GV27: 33.85 | GW27: 33.85 | GX27: 28.85 | HA27: 24.5 | HB27: 24.316 | HC27: 23.05 | HD27: 23.5405 | HE27: 22.56 | HH27: 23.059 | HI27: 24.48 | HJ27: 24.687 | HK27: 25.145 | HL27: 26.48 | HO27: 27.61 | HP27: 26.8855 | HQ27: 26.789 | HR27: 27.23 | HS27: 28.75 | HV27: 28.75 | HW27: 27.59 | HX27: 26.172 | HY27: 27.5145 | HZ27: 29.1 | IC27: 30.325 | ID27: 29.177 | IE27: 28.77 | IF27: 26.948 | IG27: 27.25 | IJ27: 24.99 | IK27: 25.66 | IL27: 25.35 | IM27: 24.57 | IN27: 26.75 | IQ27: 22.2685 | IR27: 23.459 | IS27: 26.105 | IT27: 26.526 | IU27: 26.171 | IX27: 27.3005 | IY27: 29.318 | IZ27: 29.299 | JA27: 29.9575 | JB27: 30.6975 | JE27: 33.192 | JF27: 32.762 | JG27: 32.629 | JH27: 32.946 | JI27: 32.409 | JL27: 32.409 | JM27: 34 | JN27: 36.275 | JO27: 33.902 | JP27: 38.247 | JS27: 36.4 | JT27: 38.4425 | JU27: 39.391 | JV27: 39.3205 | JW27: 38.929 | JZ27: 39.2025 | KA27: 39.182 | KB27: 38.991 | KC27: 38.9925 | KD27: 38.954 | KG27: 38.402 | KH27: 39.1255 | KI27: 38.4235 | KJ27: 37.5255 | KK27: 38.995 | KN27: 39.455 | KO27: 40.515 | KP27: 40.1545 | KQ27: 40.314 | KR27: 39.312 | KU27: 39.948 | KV27: 39.664 | KW27: 40.0905 | KX27: 39.416 | KY27: 39.5265 | LB27: 40.845 | LC27: 41.093 | LD27: 41.543 | LE27: 41.2745 | LF27: 41.2635 | LI27: 41.583 | LJ27: 40.317 | LK27: 40.4455 | LL27: 40.7035 | LM27: 40.574 | LP27: 39.675 | LQ27: 40.456 | LR27: 41.316 | LS27: 43.19 | LT27: 43.718 | LW27: 43.71 | LX27: 43.1255 | LY27: 42.7245 | LZ27: 42.581 | MA27: 42.7075 | MD27: 42.37 | ME27: 48.04 | MF27: 48.22 | MG27: 48.065 | MH27: 48.455 | MK27: 47.925 | ML27: 48.12 | MM27: 47.66 | MN27: 47.43 | MO27: 47.3 | MR27: 48.25 | MS27: 46.665 | MT27: 47.185 | MU27: 46.78 | MV27: 46.74 | MY27: 46.7 | MZ27: 49.7 | NA27: 47.595 | NB27: 46.07 | NC27: 46.38 | NF27: 42 | NG27: 47.5 | NH27: 46.635 | NI27: 49.5 | NJ27: 52
... A32: CHF 2020 | B32: 42837 | C32: CH0361824458 | F32: 44.5 | G32: 43.665 | H32: 43.1 | I32: 48.735 | J32: 52.625 | M32: 54.485 | N32: 50.82 | O32: 52.38 | P32: 52.3 | Q32: 50.545 | T32: 50.5 | U32: 50.005 | V32: 52.499 | W32: 52.06 | X32: 51.44 | AA32: 50.875 | AB32: 49.9 | AC32: 49.495 | AD32: 49.25 | AE32: 49.18 | AH32: 50.3 | AI32: 50.975 | AJ32: 50.975 | AK32: 50.75 | AL32: 51.1 | AO32: 51.225 | AP32: 51.675 | AQ32: 52.05 | AR32: 53.6 | AS32: 56.1 | AV32: 55.499 | AW32: 54.531 | AX32: 54.75 | AY32: 54.09 | AZ32: 54.501 | BC32: 54.1 | BD32: 51.655 | BE32: 51.115 | BF32: 51.375 | BG32: 51.025 | BJ32: 52.125 | BK32: 50.75 | BL32: 50.89 | BM32: 50.465 | BN32: 50.51 | BQ32: 49.5 | BR32: 50.975 | BS32: 51.1 | BT32: 49.38 | BU32: 49.26 | BX32: 49.435 | BY32: 49.409 | BZ32: 48.8 | CA32: 49.075 | CB32: 48.975 | CE32: 48.875 | CF32: 48.495 | CG32: 48.555 | CH32: 49.1 | CI32: 50.18 | CL32: 49.25 | CM32: 49.665 | CN32: 49.77 | CO32: 50.405 | CP32: 50.235 | CS32: 50.2 | CT32: 49.93 | CU32: 50.25 | CV32: 50.46 | CW32: 51.005 | CZ32: 52.015 | DA32: 53.625 | DB32: 54.2 | DC32: 55.07 | DD32: 55.105 | DG32: 54.25 | DH32: 54.26 | DI32: 57.375 | DJ32: 57.16 | DK32: 56.45 | DN32: 58.75 | DO32: 58.75 | DP32: 58.75 | DQ32: 58.75 | DR32: 59.475 | DU32: 58.999 | DV32: 58.999 | DW32: 58.999 | DX32: 58.999 | DY32: 59.575 | EB32: 59.04 | EC32: 58.525 | ED32: 57.355 | EE32: 58.9 | EF32: 59.175 | EI32: 59.625 | EJ32: 59.86 | EK32: 59.895 | EL32: 60.5 | EM32: 60.575 | EP32: 60.465 | EQ32: 59.875 | ER32: 58.825 | ES32: 59 | ET32: 59.175 | EW32: 58.23 | EX32: 58.735 | EY32: 59.875 | EZ32: 59.75 | FA32: 59.805 | FD32: 59.775 | FE32: 60.33 | FF32: 60.16 | FG32: 59.63 | FH32: 61.715 | FK32: 61.6 | FL32: 61.045 | FM32: 60.995 | FN32: 60.18 | FO32: 60.265 | FR32: 60.75 | FS32: 60.89 | FT32: 60.925 | FU32: 59.19 | FV32: 60.04 | FY32: 59.51 | FZ32: 60.25 | GA32: 60.025 | GB32: 58.88 | GC32: 58 | GF32: 58.25 | GG32: 59.485 | GH32: 59.615 | GI32: 58.5 | GJ32: 57.379 | GM32: 51.5 | GN32: 48.63 | GO32: 44.805 | GP32: 46.5 | GQ32: 43.9 | GT32: 34.055 | GU32: 37.245 | GV32: 31.265 | GW32: 31.265 | GX32: 31.265 | HA32: 28.75 | HB32: 30.225 | HC32: 30.25 | HD32: 30.05 | HE32: 32.145 | HH32: 32.1 | HI32: 32.825 | HJ32: 32.55 | HK32: 33.75 | HL32: 34.75 | HO32: 36.69 | HP32: 37.49 | HQ32: 38.25 | HR32: 37.4 | HS32: 37.4 | HV32: 37.4 | HW32: 39.005 | HX32: 37.5 | HY32: 37.5 | HZ32: 39.25 | IC32: 36.55 | ID32: 35.025 | IE32: 34.8 | IF32: 33.425 | IG32: 31.5 | IJ32: 29.325 | IK32: 30 | IL32: 29.75 | IM32: 28 | IN32: 28 | IQ32: 26.875 | IR32: 27.495 | IS32: 28.745 | IT32: 27.25 | IU32: 27.625 | IX32: 27.575 | IY32: 29.2 | IZ32: 28.95 | JA32: 28.725 | JB32: 30.745 | JE32: 32.475 | JF32: 33.75 | JG32: 34.65 | JH32: 34.65 | JI32: 34.875 | JL32: 34.875 | JM32: 34 | JN32: 34 | JO32: 35.005 | JP32: 35.755 | JS32: 35.755 | JT32: 35 | JU32: 42.125 | JV32: 38.5 | JW32: 40 | JZ32: 40.05 | KA32: 39.625 | KB32: 39 | KC32: 37.5 | KD32: 37.5 | KG32: 37.5 | KH32: 39.495 | KI32: 37.5 | KJ32: 36.5 | KK32: 36.25 | KN32: 35.5 | KO32: 39.5 | KP32: 39.5 | KQ32: 40.75 | KR32: 40.175 | KU32: 38.5 | KV32: 39 | KW32: 41.87 | KX32: 41.975 | KY32: 41.955 | LB32: 40.855 | LC32: 42.775 | LD32: 42.75 | LE32: 44.1 | LF32: 42.775 | LI32: 43.245 | LJ32: 41.5 | LK32: 41.5 | LL32: 43.1 | LM32: 42.97 | LP32: 40.5 | LQ32: 40.5 | LR32: 40.625 | LS32: 43.25 | LT32: 42.5 | LW32: 40.5 | LX32: 38.5 | LY32: 38.5 | LZ32: 43.145 | MA32: 43.37 | MD32: 44.5 | ME32: 46.5 | MF32: 48.89 | MG32: 48.7 | MH32: 48.1 | MK32: 49.225 | ML32: 47.775 | MM32: 47.65 | MN32: 45.5 | MO32: 46.25 | MR32: 46.25 | MS32: 46.795 | MT32: 48.875 | MU32: 48.875 | MV32: 49.315 | MY32: 49.05 | MZ32: 48.75 | NA32: 45.5 | NB32: 47.75 | NC32: 47.75 | NF32: 41.35 | NG32: 45.5 | NH32: 45.5 | NI32: 45.49 | NJ32: 45.49
D34: (Redemption Yield)
A35: Short Name | B35: Issue date | C35: ISIN (SEC) | D35: (RY) | E35: 43709 | F35: 43710 | G35: 43711 | H35: 43712 | I35: 43713 | J35: 43714 | K35: 43715 | L35: 43716 | M35: 43717 | N35: 43718 | O35: 43719 | P35: 43720 | Q35: 43721 | R35: 43722 | S35: 43723 | T35: 43724 | U35: 43725 | V35: 43726 | W35: 43727 | X35: 43728 | Y35: 43729 | Z35: 43730 | AA35: 43731 | AB35: 43732 | AC35: 43733 | AD35: 43734 | AE35: 43735 | AF35: 43736 | AG35: 43737 | AH35: 43738 | AI35: 43739 | AJ35: 43740 | AK35: 43741 | AL35: 43742 | AM35: 43743 | AN35: 43744 | AO35: 43745 | AP35: 43746 | AQ35: 43747 | AR35: 43748 | AS35: 43749 | AT35: 43750 | AU35: 43751 | AV35: 43752 | AW35: 43753 | AX35: 43754 | AY35: 43755 | AZ35: 43756 | BA35: 43757 | BB35: 43758 | BC35: 43759 | BD35: 43760 | BE35: 43761 | BF35: 43762 | BG35: 43763 | BH35: 43764 | BI35: 43765 | BJ35: 43766 | BK35: 43767 | BL35: 43768 | BM35: 43769 | BN35: 43770 | BO35: 43771 | BP35: 43772 | BQ35: 43773 | BR35: 43774 | BS35: 43775 | BT35: 43776 | BU35: 43777 | BV35: 43778 | BW35: 43779 | BX35: 43780 | BY35: 43781 | BZ35: 43782 | CA35: 43783 | CB35: 43784 | CC35: 43785 | CD35: 43786 | CE35: 43787 | CF35: 43788 | CG35: 43789 | CH35: 43790 | CI35: 43791 | CJ35: 43792 | CK35: 43793 | CL35: 43794 | CM35: 43795 | CN35: 43796 | CO35: 43797 | CP35: 43798 | CQ35: 43799 | CR35: 43800 | CS35: 43801 | CT35: 43802 | CU35: 43803 | CV35: 43804 | CW35: 43805 | CX35: 43806 | CY35: 43807 | CZ35: 43808 | DA35: 43809 | DB35: 43810 | DC35: 43811 | DD35: 43812 | DE35: 43813 | DF35: 43814 | DG35: 43815 | DH35: 43816 | DI35: 43817 | DJ35: 43818 | DK35: 43819 | DL35: 43820 | DM35: 43821 | DN35: 43822 | DO35: 43823 | DP35: 43824 | DQ35: 43825 | DR35: 43826 | DS35: 43827 | DT35: 43828 | DU35: 43829 | DV35: 43830 | DW35: 43831 | DX35: 43832 | DY35: 43833 | DZ35: 43834 | EA35: 43835 | EB35: 43836 | EC35: 43837 | ED35: 43838 | EE35: 43839 | EF35: 43840 | EG35: 43841 | EH35: 43842 | EI35: 43843 | EJ35: 43844 | EK35: 43845 | EL35: 43846 | EM35: 43847 | EN35: 43848 | EO35: 43849 | EP35: 43850 | EQ35: 43851 | ER35: 43852 | ES35: 43853 | ET35: 43854 | EU35: 43855 | EV35: 43856 | EW35: 43857 | EX35: 43858 | EY35: 43859 | EZ35: 43860 | FA35: 43861 | FB35: 43862 | FC35: 43863 | FD35: 43864 | FE35: 43865 | FF35: 43866 | FG35: 43867 | FH35: 43868 | FI35: 43869 | FJ35: 43870 | FK35: 43871 | FL35: 43872 | FM35: 43873 | FN35: 43874 | FO35: 43875 | FP35: 43876 | FQ35: 43877 | FR35: 43878 | FS35: 43879 | FT35: 43880 | FU35: 43881 | FV35: 43882 | FW35: 43883 | FX35: 43884 | FY35: 43885 | FZ35: 43886 | GA35: 43887 | GB35: 43888 | GC35: 43889 | GD35: 43890 | GE35: 43891 | GF35: 43892 | GG35: 43893 | GH35: 43894 | GI35: 43895 | GJ35: 43896 | GK35: 43897 | GL35: 43898 | GM35: 43899 | GN35: 43900 | GO35: 43901 | GP35: 43902 | GQ35: 43903 | GR35: 43904 | GS35: 43905 | GT35: 43906 | GU35: 43907 | GV35: 43908 | GW35: 43909 | GX35: 43910 | GY35: 43911 | GZ35: 43912 | HA35: 43913 | HB35: 43914 | HC35: 43915 | HD35: 43916 | HE35: 43917 | HF35: 43918 | HG35: 43919 | HH35: 43920 | HI35: 43921 | HJ35: 43922 | HK35: 43923 | HL35: 43924 | HM35: 43925 | HN35: 43926 | HO35: 43927 | HP35: 43928 | HQ35: 43929 | HR35: 43930 | HS35: 43931 | HT35: 43932 | HU35: 43933 | HV35: 43934 | HW35: 43935 | HX35: 43936 | HY35: 43937 | HZ35: 43938 | IA35: 43939 | IB35: 43940 | IC35: 43941 | ID35: 43942 | IE35: 43943 | IF35: 43944 | IG35: 43945 | IH35: 43946 | II35: 43947 | IJ35: 43948 | IK35: 43949 | IL35: 43950 | IM35: 43951 | IN35: 43952 | IO35: 43953 | IP35: 43954 | IQ35: 43955 | IR35: 43956 | IS35: 43957 | IT35: 43958 | IU35: 43959 | IV35: 43960 | IW35: 43961 | IX35: 43962 | IY35: 43963 | IZ35: 43964 | JA35: 43965 | JB35: 43966 | JC35: 43967 | JD35: 43968 | JE35: 43969 | JF35: 43970 | JG35: 43971 | JH35: 43972 | JI35: 43973 | JJ35: 43974 | JK35: 43975 | JL35: 43976 | JM35: 43977 | JN35: 43978 | JO35: 43979 | JP35: 43980 | JQ35: 43981 | JR35: 43982 | JS35: 43983 | JT35: 43984 | JU35: 43985 | JV35: 43986 | JW35: 43987 | JX35: 43988 | JY35: 43989 | JZ35: 43990 | KA35: 43991 | KB35: 43992 | KC35: 43993 | KD35: 43994 | KE35: 43995 | KF35: 43996 | KG35: 43997 | KH35: 43998 | KI35: 43999 | KJ35: 44000 | KK35: 44001 | KL35: 44002 | KM35: 44003 | KN35: 44004 | KO35: 44005 | KP35: 44006 | KQ35: 44007 | KR35: 44008 | KS35: 44009 | KT35: 44010 | KU35: 44011 | KV35: 44012 | KW35: 44013 | KX35: 44014 | KY35: 44015 | KZ35: 44016 | LA35: 44017 | LB35: 44018 | LC35: 44019 | LD35: 44020 | LE35: 44021 | LF35: 44022 | LG35: 44023 | LH35: 44024 | LI35: 44025 | LJ35: 44026 | LK35: 44027 | LL35: 44028 | LM35: 44029 | LN35: 44030 | LO35: 44031 | LP35: 44032 | LQ35: 44033 | LR35: 44034 | LS35: 44035 | LT35: 44036 | LU35: 44037 | LV35: 44038 | LW35: 44039 | LX35: 44040 | LY35: 44041 | LZ35: 44042 | MA35: 44043 | MB35: 44044 | MC35: 44045 | MD35: 44046 | ME35: 44047 | MF35: 44048 | MG35: 44049 | MH35: 44050 | MI35: 44051 | MJ35: 44052 | MK35: 44053 | ML35: 44054 | MM35: 44055 | MN35: 44056 | MO35: 44057 | MP35: 44058 | MQ35: 44059 | MR35: 44060 | MS35: 44061 | MT35: 44062 | MU35: 44063 | MV35: 44064 | MW35: 44065 | MX35: 44066 | MY35: 44067 | MZ35: 44068 | NA35: 44069 | NB35: 44070 | NC35: 44071 | ND35: 44072 | NE35: 44073 | NF35: 44074 | NG35: 44075 | NH35: 44076 | NI35: 44077 | NJ35: 44078 | NK35: 44079 | NL35: 44080 | NM35: 44081 | NN35: 44082 | NO35: 44083 | NP35: 44084 | NQ35: 44085 | NR35: 44086 | NS35: 44087 | NT35: 44088 | NU35: 44089 | NV35: 44090 | NW35: 44091 | NX35: 44092 | NY35: 44093 | NZ35: 44094 | OA35: 44095 | OB35: 44096 | OC35: 44097 | OD35: 44098 | OE35: 44099 | OF35: 44100 | OG35: 44101 | OH35: 44102 | OI35: 44103 | OJ35: 44104 | OK35: 44105 | OL35: 44106 | OM35: 44107 | ON35: 44108 | OO35: 44109 | OP35: 44110 | OQ35: 44111 | OR35: 44112 | OS35: 44113 | OT35: 44114 | OU35: 44115 | OV35: 44116 | OW35: 44117 | OX35: 44118 | OY35: 44119 | OZ35: 44120 | PA35: 44121 | PB35: 44122 | PC35: 44123 | PD35: 44124 | PE35: 44125 | PF35: 44126 | PG35: 44127 | PH35: 44128 | PI35: 44129 | PJ35: 44130 | PK35: 44131 | PL35: 44132 | PM35: 44133 | PN35: 44134 | PO35: 44135 | PP35: 44136 | PQ35: 44137 | PR35: 44138 | PS35: 44139 | PT35: 44140 | PU35: 44141 | PV35: 44142 | PW35: 44143 | PX35: 44144 | PY35: 44145 | PZ35: 44146 | QA35: 44147 | QB35: 44148 | QC35: 44149 | QD35: 44150 | QE35: 44151 | QF35: 44152 | QG35: 44153 | QH35: 44154 | QI35: 44155 | QJ35: 44156 | QK35: 44157 | QL35: 44158 | QM35: 44159 | QN35: 44160 | QO35: 44161
A36: USD 2033 Discount I | B36: 38626 | C36: US040114GL81 | F36: 23.1152 | G36: 23.1161 | H36: 21.6532 | I36: 20.8475 | J36: 19.7862 | M36: 19.3641 | N36: 19.8384 | O36: 19.7885 | P36: 20.0469 | Q36: 20.6161 | T36: 20.8098 | U36: 20.5787 | V36: 19.8643 | W36: 19.8472 | X36: 19.5467 | AA36: 19.8488 | AB36: 20.0034 | AC36: 20.3609 | AD36: 19.9039 | AE36: 19.4537 | AH36: 19.3567 | AI36: 19.3576 | AJ36: 19.3586 | AK36: 19.216 | AL36: 19.0738 | AO36: 18.7016 | AP36: 19.0032 | AQ36: 18.211 | AR36: 17.7846 | AS36: 17.4544 | AV36: 17.4091 | AW36: 17.2146 | AX36: 17.5385 | AY36: 17.2975 | AZ36: 17.6244 | BC36: 18.0905 | BD36: 18.4431 | BE36: 18.2228 | BF36: 18.0654 | BG36: 18.3727 | BJ36: 18.8125 | BK36: 18.9523 | BL36: 18.8605 | BM36: 19.0539 | BN36: 18.8258 | BQ36: 18.9287 | BR36: 18.9402 | BS36: 19.0134 | BT36: 19.0579 | BU36: 19.8597 | BX36: 19.5931 | BY36: 20.6352 | BZ36: 20.5278 | CA36: 20.4515 | CB36: 20.7507 | CE36: 20.6662 | CF36: 19.7519 | CG36: 19.6526 | CH36: 19.1199 | CI36: 19.2647 | CL36: 19.8599 | CM36: 19.4124 | CN36: 19.5671 | CO36: 19.6641 | CP36: 19.6599 | CS36: 19.6664 | CT36: 20.3394 | CU36: 19.7691 | CV36: 19.8233 | CW36: 19.6735 | CZ36: 19.1129 | DA36: 18.7183 | DB36: 18.8167 | DC36: 18.0561 | DD36: 18.0571 | DG36: 17.9297 | DH36: 17.151 | DI36: 16.5749 | DJ36: 16.7666 | DK36: 16.96 | DN36: 16.6686 | DO36: 16.6558 | DP36: 16.6566 | DQ36: 16.6597 | DR36: 15.269 | DU36: 15.7293 | DV36: 15.6961 | DW36: 15.6967 | DX36: 15.6295 | DY36: 15.6264 | EB36: 16.3003 | EC36: 15.896 | ED36: 15.4619 | EE36: 15.33 | EF36: 15.5663 | EI36: 15.364 | EJ36: 15.6286 | EK36: 15.5325 | EL36: 15.2014 | EM36: 15.6467 | EP36: 15.6026 | EQ36: 15.9845 | ER36: 16.4937 | ES36: 16.4565 | ET36: 16.8731 | EW36: 17.4666 | EX36: 17.5964 | EY36: 17.266 | EZ36: 17.1884 | FA36: 17.2286 | FD36: 16.9928 | FE36: 16.6175 | FF36: 16.2429 | FG36: 16.3538 | FH36: 15.9946 | FK36: 15.9597 | FL36: 16.5775 | FM36: 16.5621 | FN36: 16.6175 | FO36: 16.6556 | FR36: 16.8413 | FS36: 16.7706 | FT36: 16.9508 | FU36: 17.0826 | FV36: 17.0948 | FY36: 16.9281 | FZ36: 17.0789 | GA36: 16.9682 | GB36: 17.1739 | GC36: 17.9042 | GF36: 17.8626 | GG36: 17.5305 | GH36: 17.4495 | GI36: 17.7401 | GJ36: 19.0731 | GM36: 19.0898 | GN36: 21.2017 | GO36: 21.9997 | GP36: 23.6021 | GQ36: 23.6731 | GT36: 24.6463 | GU36: 25.1657 | GV36: 25.1669 | GW36: 27.9886 | GX36: 27.7947 | HA36: 28.2885 | HB36: 28.9429 | HC36: 29.2864 | HD36: 28.9098 | HE36: 28.5998 | HH36: 28.0843 | HI36: 27.8055 | HJ36: 27.0141 | HK36: 26.9052 | HL36: 26.2414 | HO36: 25.581 | HP36: 25.8397 | HQ36: 26.2644 | HR36: 25.915 | HS36: 26.443 | HV36: 26.185 | HW36: 26.5333 | HX36: 26.8907 | HY36: 27.0769 | HZ36: 26.6283 | IC36: 25.6583 | ID36: 26.1893 | IE36: 26.4569 | IF36: 27.5529 | IG36: 27.8419 | IJ36: 27.3678 | IK36: 26.9518 | IL36: 26.1915 | IM36: 27.19 | IN36: 27.8532 | IQ36: 28.8597 | IR36: 29.0716 | IS36: 28.8632 | IT36: 28.6617 | IU36: 27.9626 | IX36: 27.4847 | IY36: 25.3188 | IZ36: 25.7261 | JA36: 25.7772 | JB36: 24.1861 | JE36: 23.7919 | JF36: 23.2497 | JG36: 23.0124 | JH36: 23.0759 | JI36: 23.3693 | JL36: 23.5077 | JM36: 23.4041 | JN36: 23.4058 | JO36: 21.7022 | JP36: 21.547 | JS36: 21.5483 | JT36: 21.0145 | JU36: 20.4834 | JV36: 20.1054 | JW36: 20.2105 | JZ36: 20.3695 | KA36: 20.4453 | KB36: 20.9143 | KC36: 21.1428 | KD36: 21.1442 | KG36: 21.4322 | KH36: 21.0907 | KI36: 21.3074 | KJ36: 21.8038 | KK36: 21.1547 | KN36: 21.0997 | KO36: 20.7677 | KP36: 21.216 | KQ36: 21.3776 | KR36: 21.5106 | KU36: 21.5922 | KV36: 21.5013 | KW36: 21.6783 | KX36: 21.3877 | KY36: 21.3882 | LB36: 20.4997 | LC36: 20.2884 | LD36: 19.7255 | LE36: 20.1342 | LF36: 19.9297 | LI36: 20.088 | LJ36: 20.3233 | LK36: 19.9315 | LL36: 19.6324 | LM36: 19.633 | LP36: 19.7981 | LQ36: 19.5848 | LR36: 19.3418 | LS36: 19.0034 | LT36: 19.0415 | LW36: 19.0122 | LX36: 19.202 | LY36: 19.5413 | LZ36: 19.3007 | MA36: 19.1108 | MD36: 19.2293 | ME36: 17.7365 | MF36: 17.7974 | MG36: 17.7392 | MH36: 17.6567 | MK36: 18.2093 | ML36: 17.8672 | MM36: 17.7837 | MN36: 17.9538 | MO36: 18.0838 | MR36: 18.2145 | MS36: 18.2589 | MT36: 18.5062 | MU36: 18.4828 | MV36: 18.5741 | MY36: 18.6092 | MZ36: 18.6759 | NA36: 19.7595 | NB36: 19.762 | NC36: 19.763 | NF36: 18.9643 | NG36: 19.2753 | NH36: 18.7173 | NI36: 19.2328 | NJ36: 19.3295
A37: USD 2033 Discount II and III | B37: 40296 | C37: XS0501194756 | F37: 28.0819 | G37: 28.1005 | H37: 28.119 | I37: 25.4568 | J37: 24.6188 | M37: 22.5724 | N37: 24.9286 | O37: 23.7241 | P37: 23.3806 | Q37: 23.3946 | T37: 24.7395 | U37: 24.7547 | V37: 23.6935 | W37: 23.7361 | X37: 23.7506 | AA37: 23.7648 | AB37: 24.1759 | AC37: 24.1906 | AD37: 23.5128 | AE37: 23.5912 | AH37: 23.0368 | AI37: 23.3641 | AJ37: 22.8792 | AK37: 22.92 | AL37: 22.9335 | AO37: 22.9473 | AP37: 22.9608 | AQ37: 22.9746 | AR37: 23.0158 | AS37: 23.0295 | AV37: 23.0433 | AW37: 23.0571 | AX37: 23.071 | AY37: 23.1125 | AZ37: 23.1265 | BC37: 23.1404 | BD37: 21.8426 | BE37: 21.6854 | BF37: 21.3334 | BG37: 21.9642 | BJ37: 22.2674 | BK37: 22.8193 | BL37: 22.531 | BM37: 22.5713 | BN37: 22.827 | BQ37: 22.8407 | BR37: 22.8544 | BS37: 23.1151 | BT37: 22.9098 | BU37: 22.9236 | BX37: 22.9376 | BY37: 22.9515 | BZ37: 22.9654 | CA37: 23.0074 | CB37: 23.0215 | CE37: 23.0355 | CF37: 23.0494 | CG37: 23.0637 | CH37: 23.1059 | CI37: 23.1201 | CL37: 23.1343 | CM37: 23.1487 | CN37: 23.1628 | CO37: 23.2057 | CP37: 23.2201 | CS37: 23.2345 | CT37: 23.2489 | CU37: 23.2633 | CV37: 23.3065 | CW37: 23.3209 | CZ37: 23.3354 | DA37: 23.3499 | DB37: 23.3644 | DC37: 23.4083 | DD37: 23.4229 | DG37: 23.4376 | DH37: 23.4522 | DI37: 23.4671 | DJ37: 23.5113 | DK37: 23.526 | DN37: 20.2352 | DO37: 20.2472 | DP37: 20.6725 | DQ37: 19.6943 | DR37: 17.6978 | DU37: 17.5313 | DV37: 17.5405 | DW37: 17.5493 | DX37: 17.4927 | DY37: 18.0552 | EB37: 18.3282 | EC37: 18.5162 | ED37: 17.9102 | EE37: 17.5139 | EF37: 17.1926 | EI37: 17.2422 | EJ37: 18.3161 | EK37: 17.5502 | EL37: 17.3277 | EM37: 17.9266 | EP37: 17.6798 | EQ37: 18.3392 | ER37: 18.7543 | ES37: 18.9225 | ET37: 19.3562 | EW37: 20.0523 | EX37: 20.0132 | EY37: 19.7267 | EZ37: 20.0069 | FA37: 20.0178 | FD37: 19.6335 | FE37: 19.3544 | FF37: 18.7113 | FG37: 18.8331 | FH37: 18.4346 | FK37: 18.4895 | FL37: 18.5893 | FM37: 18.8734 | FN37: 19.4224 | FO37: 19.3372 | FR37: 18.9708 | FS37: 19.4061 | FT37: 19.3688 | FU37: 19.938 | FV37: 19.4112 | FY37: 19.6639 | FZ37: 19.9713 | GA37: 19.6856 | GB37: 20.7346 | GC37: 21.0122 | GF37: 21.0781 | GG37: 20.5601 | GH37: 20.6761 | GI37: 21.3015 | GJ37: 22.336 | GM37: 24.8433 | GN37: 25.5713 | GO37: 27.1216 | GP37: 28.4364 | GQ37: 28.6319 | GT37: 31.6616 | GU37: 30.8526 | GV37: 33.6266 | GW37: 33.5837 | GX37: 33.3724 | HA37: 36.7623 | HB37: 37.2253 | HC37: 35.7146 | HD37: 34.8804 | HE37: 34.6531 | HH37: 34.5542 | HI37: 33.6016 | HJ37: 33.7469 | HK37: 33.001 | HL37: 32.6843 | HO37: 31.0936 | HP37: 31.323 | HQ37: 31.8752 | HR37: 32.1634 | HS37: 32.1875 | HV37: 31.8858 | HW37: 33.022 | HX37: 32.8186 | HY37: 34.073 | HZ37: 34.3456 | IC37: 34.3728 | ID37: 31.1257 | IE37: 32.4303 | IF37: 33.895 | IG37: 34.2879 | IJ37: 33.9482 | IK37: 33.4967 | IL37: 33.172 | IM37: 33.6014 | IN37: 35.5054 | IQ37: 37.7843 | IR37: 36.1013 | IS37: 35.1992 | IT37: 34.2722 | IU37: 34.7997 | IX37: 32.6786 | IY37: 31.4046 | IZ37: 31.9581 | JA37: 32.4689 | JB37: 31.5225 | JE37: 29.9441 | JF37: 29.4947 | JG37: 29.6091 | JH37: 28.6718 | JI37: 28.7807 | JL37: 28.8011 | JM37: 26.7343 | JN37: 26.9098 | JO37: 27.4487 | JP37: 25.9823 | JS37: 26.1497 | JT37: 26.0921 | JU37: 25.8855 | JV37: 26.012 | JW37: 25.0857 | JZ37: 25.3152 | KA37: 27.0704 | KB37: 26.0818 | KC37: 26.4387 | KD37: 26.4566 | KG37: 26.8641 | KH37: 26.4159 | KI37: 26.5107 | KJ37: 27.1965 | KK37: 26.5835 | KN37: 26.5242 | KO37: 26.0857 | KP37: 26.7943 | KQ37: 26.8499 | KR37: 24.7272 | KU37: 25.3746 | KV37: 24.7573 | KW37: 24.7034 | KX37: 24.6795 | KY37: 24.6944 | LB37: 23.6479 | LC37: 23.4075 | LD37: 22.742 | LE37: 23.274 | LF37: 23.0395 | LI37: 23.0531 | LJ37: 23.0666 | LK37: 23.0802 | LL37: 22.7543 | LM37: 22.7675 | LP37: 22.8415 | LQ37: 22.7338 | LR37: 22.4482 | LS37: 22.0201 | LT37: 21.9182 | LW37: 22.1036 | LX37: 22.3499 | LY37: 22.7805 | LZ37: 22.5206 | MA37: 22.2978 | MD37: 22.4877 | ME37: 20.6067 | MF37: 20.7236 | MG37: 20.6537 | MH37: 21.5861 | MK37: 21.7674 | ML37: 20.8475 | MM37: 20.7534 | MN37: 22.0022 | MO37: 21.1767 | MR37: 21.353 | MS37: 21.4207 | MT37: 21.5441 | MU37: 21.7502 | MV37: 21.763 | MY37: 21.7757 | MZ37: 21.7885 | NA37: 21.6884 | NB37: 23.0208 | NC37: 21.9668 | NF37: 21.9224 | NG37: 21.4294 | NH37: 22.1791 | NI37: 22.8733 | NJ37: 23.0092
A38: USD 2033 Discount III | B38: 40296 | C38: XS0501195050 | F38: 28.9771 | G38: 28.8134 | H38: 27.7742 | I38: 25.7524 | J38: 24.0758 | M38: 23.6956 | N38: 24.6488 | O38: 23.8545 | P38: 23.3806 | Q38: 23.3946 | T38: 23.4085 | U38: 23.4223 | V38: 23.6935 | W38: 23.7361 | X38: 23.7506 | AA38: 23.7648 | AB38: 23.7792 | AC38: 23.7934 | AD38: 23.8367 | AE38: 23.8511 | AH38: 23.0368 | AI38: 23.3641 | AJ38: 23.1265 | AK38: 23.168 | AL38: 22.6896 | AO38: 22.7032 | AP38: 22.5359 | AQ38: 22.5491 | AR38: 20.9468 | AS38: 20.1276 | AV38: 20.5485 | AW38: 20.2007 | AX38: 20.624 | AY38: 20.9234 | AZ38: 20.411 | BC38: 21.0546 | BD38: 21.8426 | BE38: 21.6854 | BF38: 21.2784 | BG38: 21.9642 | BJ38: 22.2674 | BK38: 22.2807 | BL38: 22.531 | BM38: 22.5713 | BN38: 22.4655 | BQ38: 22.4789 | BR38: 22.4923 | BS38: 22.5058 | BT38: 22.9098 | BU38: 22.9236 | BX38: 22.9376 | BY38: 23.8395 | BZ38: 23.8542 | CA38: 25.1302 | CB38: 24.5858 | CE38: 24.8793 | CF38: 24.8252 | CG38: 23.8272 | CH38: 23.6765 | CI38: 23.3081 | CL38: 23.7709 | CM38: 24.2488 | CN38: 24.1972 | CO38: 24.3103 | CP38: 24.2584 | CS38: 24.007 | CT38: 24.9082 | CU38: 24.3046 | CV38: 24.9725 | CW38: 24.4343 | CZ38: 23.7843 | DA38: 23.2869 | DB38: 22.8669 | DC38: 23.1567 | DD38: 23.0467 | DG38: 21.9865 | DH38: 21.8849 | DI38: 20.7451 | DJ38: 20.4164 | DK38: 20.5839 | DN38: 20.2352 | DO38: 20.2472 | DP38: 20.6725 | DQ38: 19.6943 | DR38: 17.6978 | DU38: 17.5313 | DV38: 17.5405 | DW38: 17.5493 | DX38: 17.4927 | DY38: 18.0552 | EB38: 18.3282 | EC38: 18.5162 | ED38: 17.7394 | EE38: 17.5139 | EF38: 17.1926 | EI38: 17.2422 | EJ38: 18.3161 | EK38: 17.5502 | EL38: 17.3277 | EM38: 17.9266 | EP38: 17.6798 | EQ38: 18.3392 | ER38: 18.7543 | ES38: 18.9225 | ET38: 19.3562 | EW38: 20.0523 | EX38: 20.0132 | EY38: 19.7267 | EZ38: 20.0069 | FA38: 20.0178 | FD38: 19.6335 | FE38: 19.3544 | FF38: 18.7113 | FG38: 18.8331 | FH38: 18.4346 | FK38: 18.4895 | FL38: 18.5893 | FM38: 18.8734 | FN38: 19.4224 | FO38: 19.3372 | FR38: 18.9708 | FS38: 19.4061 | FT38: 19.3688 | FU38: 19.938 | FV38: 19.4112 | FY38: 19.6639 | FZ38: 19.9713 | GA38: 19.6856 | GB38: 20.7346 | GC38: 21.0122 | GF38: 21.0781 | GG38: 20.5601 | GH38: 20.6761 | GI38: 21.3015 | GJ38: 22.336 | GM38: 24.8433 | GN38: 25.5713 | GO38: 27.1216 | GP38: 28.4364 | GQ38: 28.6319 | GT38: 31.6616 | GU38: 30.8526 | GV38: 33.6266 | GW38: 33.5837 | GX38: 33.3724 | HA38: 36.7623 | HB38: 37.2253 | HC38: 35.7146 | HD38: 34.8804 | HE38: 34.6531 | HH38: 34.5542 | HI38: 33.6016 | HJ38: 33.7469 | HK38: 33.001 | HL38: 32.6843 | HO38: 31.0936 | HP38: 31.323 | HQ38: 31.8752 | HR38: 32.1634 | HS38: 32.1875 | HV38: 31.8858 | HW38: 33.022 | HX38: 32.8186 | HY38: 34.073 | HZ38: 34.3456 | IC38: 34.3728 | ID38: 31.1257 | IE38: 32.4303 | IF38: 33.895 | IG38: 34.2879 | IJ38: 33.9482 | IK38: 33.4967 | IL38: 33.172 | IM38: 33.6014 | IN38: 35.5054 | IQ38: 37.7843 | IR38: 36.1013 | IS38: 35.1992 | IT38: 34.2722 | IU38: 34.7997 | IX38: 32.6786 | IY38: 31.4046 | IZ38: 31.9581 | JA38: 32.4689 | JB38: 31.5225 | JE38: 29.9441 | JF38: 29.4947 | JG38: 29.6091 | JH38: 28.6718 | JI38: 28.7807 | JL38: 28.8011 | JM38: 26.7343 | JN38: 26.9098 | JO38: 27.4487 | JP38: 25.9823 | JS38: 26.1497 | JT38: 26.0921 | JU38: 25.8855 | JV38: 26.012 | JW38: 25.0857 | JZ38: 25.3152 | KA38: 27.0704 | KB38: 26.0818 | KC38: 26.4387 | KD38: 26.4566 | KG38: 26.8641 | KH38: 26.4159 | KI38: 26.5107 | KJ38: 27.1965 | KK38: 26.5835 | KN38: 26.5242 | KO38: 26.0857 | KP38: 26.7943 | KQ38: 26.9288 | KR38: 24.7272 | KU38: 25.5188 | KV38: 24.7573 | KW38: 24.9804 | KX38: 24.6795 | KY38: 24.6944 | LB38: 23.6479 | LC38: 23.4075 | LD38: 22.742 | LE38: 23.274 | LF38: 23.0395 | LI38: 23.0531 | LJ38: 23.0666 | LK38: 23.0802 | LL38: 22.7543 | LM38: 22.7675 | LP38: 22.8415 | LQ38: 22.7338 | LR38: 22.4482 | LS38: 22.0201 | LT38: 21.9182 | LW38: 22.1036 | LX38: 22.3499 | LY38: 22.7805 | LZ38: 22.5206 | MA38: 22.2978 | MD38: 22.4877 | ME38: 20.6067 | MF38: 20.7236 | MG38: 20.6537 | MH38: 21.5861 | MK38: 21.7674 | ML38: 20.8475 | MM38: 20.7534 | MN38: 22.0022 | MO38: 21.1767 | MR38: 21.353 | MS38: 21.4207 | MT38: 21.5441 | MU38: 21.7502 | MV38: 21.763 | MY38: 21.7757 | MZ38: 21.7885 | NA38: 21.6884 | NB38: 23.0208 | NC38: 21.9668 | NF38: 21.9224 | NG38: 21.4294 | NH38: 22.1791 | NI38: 22.8733 | NJ38: 23.0092
A39: USD Par 2038 I | B39: 38626 | C39: US040114GK09
A40: USD Par 2038 II and III | B40: 40296 | C40: XS0501195647
A41: USD Par 2038 III | B41: 40296 | C41: XS0501195720
A42: Euro 2033 Discount I | B42: 38626 | C42: XS0205545840 | F42: 23.9655 | G42: 28.5226 | H42: 28.3843 | I42: 25.1476 | J42: 22.9892 | M42: 23.11 | N42: 23.966 | O42: 23.3831 | P42: 23.6233 | Q42: 24.5364 | T42: 24.1228 | U42: 24.0108 | V42: 22.4484 | W42: 22.5356 | X42: 22.4972 | AA42: 22.735 | AB42: 23.2881 | AC42: 23.6863 | AD42: 23.0946 | AE42: 22.549 | AH42: 22.6458 | AI42: 22.6397 | AJ42: 22.4001 | AK42: 22.4098 | AL42: 22.5884 | AO42: 22.2415 | AP42: 21.9867 | AQ42: 21.8161 | AR42: 21.0984 | AS42: 19.5142 | AV42: 19.9896 | AW42: 20.3486 | AX42: 20.5611 | AY42: 20.987 | AZ42: 21.047 | BC42: 21.1344 | BD42: 21.9213 | BE42: 22.1698 | BF42: 21.2992 | BG42: 21.7796 | BJ42: 22.5219 | BK42: 22.8191 | BL42: 22.7777 | BM42: 22.7678 | BN42: 22.7538 | BQ42: 22.9041 | BR42: 22.6561 | BS42: 22.7929 | BT42: 23.1017 | BU42: 23.179 | BX42: 24.0053 | BY42: 24.2695 | BZ42: 23.9176 | CA42: 24.181 | CB42: 24.0934 | CE42: 24.0189 | CF42: 24.2352 | CG42: 23.0835 | CH42: 23.2603 | CI42: 23.2548 | CL42: 23.535 | CM42: 23.8919 | CN42: 23.9077 | CO42: 23.939 | CP42: 23.9567 | CS42: 24.0474 | CT42: 23.9875 | CU42: 24.0344 | CV42: 24.1171 | CW42: 24.1325 | CZ42: 24.1323 | DA42: 24.1507 | DB42: 24.1362 | DC42: 23.8639 | DD42: 23.8422 | DG42: 23.8758 | DH42: 23.8656 | DI42: 23.918 | DJ42: 20.9982 | DK42: 20.8863 | DN42: 20.8604 | DO42: 20.8583 | DP42: 20.8704 | DQ42: 20.9069 | DR42: 18.9 | DU42: 18.0459 | DV42: 18.065 | DW42: 18.0743 | DX42: 18.1003 | DY42: 18.1971 | EB42: 18.2912 | EC42: 18.4786 | ED42: 18.1485 | EE42: 17.8117 | EF42: 17.4943 | EI42: 17.7597 | EJ42: 17.8389 | EK42: 17.7692 | EL42: 17.5946 | EM42: 17.708 | EP42: 17.7878 | EQ42: 18.0609 | ER42: 18.7698 | ES42: 19.1489 | ET42: 19.278 | EW42: 20.069 | EX42: 20.2028 | EY42: 19.9716 | EZ42: 20.0048 | FA42: 19.9497 | FD42: 19.7167 | FE42: 19.4372 | FF42: 18.8663 | FG42: 18.7962 | FH42: 17.9968 | FK42: 18.3533 | FL42: 18.3806 | FM42: 18.4174 | FN42: 19.1252 | FO42: 18.9891 | FR42: 19.2784 | FS42: 19.1922 | FT42: 19.2024 | FU42: 19.8277 | FV42: 19.3412 | FY42: 19.5784 | FZ42: 19.579 | GA42: 19.6395 | GB42: 20.9597 | GC42: 20.9386 | GF42: 21.1155 | GG42: 20.669 | GH42: 20.6805 | GI42: 20.9496 | GJ42: 23.0479 | GM42: 24.1279 | GN42: 25.271 | GO42: 26.6734 | GP42: 28.9762 | GQ42: 29.3728 | GT42: 30.1749 | GU42: 30.6021 | GV42: 31.3153 | GW42: 34.0135 | GX42: 34.2611 | HA42: 34.9442 | HB42: 34.9713 | HC42: 34.9986 | HD42: 34.3476 | HE42: 35.1074 | HH42: 35.6789 | HI42: 34.1208 | HJ42: 33.6479 | HK42: 32.3034 | HL42: 32.1012 | HO42: 31.5937 | HP42: 31.2715 | HQ42: 31.8762 | HR42: 32.6548 | HS42: 32.6756 | HV42: 32.6997 | HW42: 32.0885 | HX42: 34.3885 | HY42: 34.5978 | HZ42: 35.1516 | IC42: 31.7853 | ID42: 31.8085 | IE42: 33.2119 | IF42: 34.7881 | IG42: 35.8963 | IJ42: 37.7185 | IK42: 40.0452 | IL42: 39.0213 | IM42: 36.8173 | IN42: 36.8478 | IQ42: 42.7381 | IR42: 39.9056 | IS42: 37.9704 | IT42: 37.452 | IU42: 37.7959 | IX42: 37.8219 | IY42: 33.9949 | IZ42: 34.2987 | JA42: 35.3497 | JB42: 32.4305 | JE42: 31.2449 | JF42: 30.7863 | JG42: 31.8319 | JH42: 32.063 | JI42: 33.0979 | JL42: 33.1234 | JM42: 33.1491 | JN42: 33.1747 | JO42: 33.2521 | JP42: 33.278 | JS42: 26.184 | JT42: 25.4143 | JU42: 24.9651 | JV42: 25.7435 | JW42: 26.2011 | JZ42: 26.2247 | KA42: 26.4994 | KB42: 27.1569 | KC42: 27.1134 | KD42: 27.1319 | KG42: 27.7139 | KH42: 27.4216 | KI42: 26.9384 | KJ42: 28.2344 | KK42: 27.469 | KN42: 26.2395 | KO42: 26.1331 | KP42: 25.966 | KQ42: 26.4848 | KR42: 24.3468 | KU42: 24.3611 | KV42: 24.724 | KW42: 24.8806 | KX42: 24.9252 | KY42: 25.0117 | LB42: 23.918 | LC42: 23.8255 | LD42: 23.3679 | LE42: 23.4867 | LF42: 23.8026 | LI42: 23.6186 | LJ42: 23.5671 | LK42: 23.9781 | LL42: 23.4272 | LM42: 23.4409 | LP42: 23.5849 | LQ42: 23.5987 | LR42: 23.6127 | LS42: 22.4681 | LT42: 22.348 | LW42: 22.3489 | LX42: 22.3425 | LY42: 22.3554 | LZ42: 22.3942 | MA42: 22.407 | MD42: 22.4199 | ME42: 21.891 | MF42: 21.1606 | MG42: 20.8226 | MH42: 20.8473 | MK42: 20.859 | ML42: 20.884 | MM42: 21.2895 | MN42: 21.4933 | MO42: 21.5102 | MR42: 21.669 | MS42: 21.7691 | MT42: 21.7911 | MU42: 21.8521 | MV42: 21.8413 | MY42: 21.9708 | MZ42: 23.7241 | NA42: 23.477 | NB42: 24.5675 | NC42: 24.4828 | NF42: 24.4977 | NG42: 21.8159 | NH42: 21.8286 | NI42: 21.8668 | NJ42: 21.6776
A43: Euro 2033 Discount II and III | B43: 40350 | C43: XS0501195134 | F43: 21.5783 | G43: 28.6982 | H43: 28.3828 | I43: 25.3613 | J43: 23.4534 | M43: 23.219 | N43: 24.8029 | O43: 23.5427 | P43: 23.7442 | Q43: 24.7475 | T43: 24.6635 | U43: 24.4882 | V43: 22.8904 | W43: 22.983 | X43: 22.7564 | AA43: 22.8185 | AB43: 23.5531 | AC43: 24.3375 | AD43: 23.6184 | AE43: 23.2657 | AH43: 23.2859 | AI43: 23.3183 | AJ43: 22.9299 | AK43: 22.9946 | AL43: 23.1439 | AO43: 22.9887 | AP43: 22.5576 | AQ43: 22.6106 | AR43: 21.4769 | AS43: 19.9973 | AV43: 20.5041 | AW43: 21.4558 | AX43: 20.9064 | AY43: 21.2715 | AZ43: 21.65 | BC43: 21.7489 | BD43: 22.5968 | BE43: 23.008 | BF43: 21.8927 | BG43: 22.2847 | BJ43: 22.9525 | BK43: 23.9499 | BL43: 23.6981 | BM43: 23.6731 | BN43: 23.8968 | BQ43: 23.6916 | BR43: 23.4518 | BS43: 23.6258 | BT43: 24.4104 | BU43: 24.0497 | BX43: 24.4469 | BY43: 25.306 | BZ43: 25.2769 | CA43: 24.5398 | CB43: 24.6979 | CE43: 24.7043 | CF43: 25.2153 | CG43: 24.269 | CH43: 23.948 | CI43: 24.0514 | CL43: 24.0663 | CM43: 24.2169 | CN43: 24.2261 | CO43: 24.2697 | CP43: 24.293 | CS43: 24.3745 | CT43: 24.3179 | CU43: 24.3632 | CV43: 24.4467 | CW43: 24.4657 | CZ43: 24.459 | DA43: 24.4799 | DB43: 24.4624 | DC43: 24.5561 | DD43: 24.0486 | DG43: 24.0822 | DH43: 22.9176 | DI43: 21.0894 | DJ43: 20.6139 | DK43: 21.0059 | DN43: 20.9084 | DO43: 20.9206 | DP43: 20.9329 | DQ43: 20.9696 | DR43: 19.4091 | DU43: 18.2352 | DV43: 18.2446 | DW43: 18.2539 | DX43: 18.1382 | DY43: 18.5658 | EB43: 18.6683 | EC43: 18.6036 | ED43: 18.2836 | EE43: 17.8485 | EF43: 17.9987 | EI43: 18.0969 | EJ43: 17.9993 | EK43: 18.0692 | EL43: 17.7899 | EM43: 17.8866 | EP43: 18.0284 | EQ43: 18.1178 | ER43: 18.6842 | ES43: 19.3832 | ET43: 19.3936 | EW43: 20.2645 | EX43: 20.3383 | EY43: 19.9353 | EZ43: 20.0085 | FA43: 19.8156 | FD43: 19.526 | FE43: 19.2811 | FF43: 18.7753 | FG43: 18.5997 | FH43: 18.0822 | FK43: 18.2713 | FL43: 18.1907 | FM43: 18.4728 | FN43: 18.6871 | FO43: 18.9988 | FR43: 18.9898 | FS43: 19 | FT43: 19.0103 | FU43: 19.5771 | FV43: 19.2633 | FY43: 19.4005 | FZ43: 19.5096 | GA43: 19.5202 | GB43: 19.7015 | GC43: 20.9933 | GF43: 21.2246 | GG43: 20.6797 | GH43: 20.7666 | GI43: 21.2845 | GJ43: 22.7225 | GM43: 24.1279 | GN43: 25.271 | GO43: 26.8351 | GP43: 28.9762 | GQ43: 29.3728 | GT43: 30.3765 | GU43: 31.0184 | GV43: 31.8829 | GW43: 34.2669 | GX43: 34.4201 | HA43: 34.9442 | HB43: 34.9713 | HC43: 34.9986 | HD43: 35.4582 | HE43: 35.7891 | HH43: 36.2402 | HI43: 36.2692 | HJ43: 35.1896 | HK43: 33.9981 | HL43: 33.0237 | HO43: 31.9681 | HP43: 31.704 | HQ43: 32.1448 | HR43: 33.0772 | HS43: 33.102 | HV43: 33.1269 | HW43: 33.0092 | HX43: 34.7771 | HY43: 35.1238 | HZ43: 35.9512 | IC43: 32.2308 | ID43: 32.7131 | IE43: 33.7739 | IF43: 33.8517 | IG43: 35.8963 | IJ43: 37.954 | IK43: 39.4479 | IL43: 39.6526 | IM43: 37.7487 | IN43: 37.7807 | IQ43: 42.8826 | IR43: 39.9056 | IS43: 38.2849 | IT43: 37.7574 | IU43: 37.7896 | IX43: 38.1335 | IY43: 34.4756 | IZ43: 34.7357 | JA43: 35.5665 | JB43: 33.3665 | JE43: 32.0049 | JF43: 31.59 | JG43: 32.053 | JH43: 31.5756 | JI43: 32.0604 | JL43: 32.0847 | JM43: 32.1089 | JN43: 32.1332 | JO43: 32.2062 | JP43: 32.2308 | JS43: 32.2554 | JT43: 25.6521 | JU43: 25.3718 | JV43: 25.2159 | JW43: 25.3788 | JZ43: 25.7229 | KA43: 25.6349 | KB43: 26.7372 | KC43: 26.4724 | KD43: 26.3797 | KG43: 26.8273 | KH43: 26.7971 | KI43: 26.2295 | KJ43: 27.4972 | KK43: 27.2653 | KN43: 26.3018 | KO43: 26.0714 | KP43: 25.966 | KQ43: 26.4848 | KR43: 24.4849 | KU43: 24.4994 | KV43: 24.724 | KW43: 24.8806 | KX43: 24.9252 | KY43: 25.0117 | LB43: 23.918 | LC43: 23.9321 | LD43: 23.4454 | LE43: 23.5647 | LF43: 23.8689 | LI43: 23.6186 | LJ43: 23.5671 | LK43: 23.9781 | LL43: 23.5571 | LM43: 23.5709 | LP43: 23.7162 | LQ43: 23.7302 | LR43: 23.7442 | LS43: 22.5411 | LT43: 22.4084 | LW43: 22.4213 | LX43: 22.3651 | LY43: 22.378 | LZ43: 22.4168 | MA43: 22.4298 | MD43: 22.4427 | ME43: 21.0867 | MF43: 21.1963 | MG43: 21.068 | MH43: 20.8606 | MK43: 20.8723 | ML43: 20.884 | MM43: 20.8958 | MN43: 22.0916 | MO43: 21.2754 | MR43: 21.8588 | MS43: 22.2253 | MT43: 22.286 | MU43: 22.436 | MV43: 22.5025 | MY43: 22.6034 | MZ43: 23.6978 | NA43: 23.3119 | NB43: 25.5548 | NC43: 21.7906 | NF43: 21.8033 | NG43: 21.2464 | NH43: 20.7096 | NI43: 20.7451 | NJ43: 20.4359
A44: Euro 2033 Discount III | B44: 40350 | C44: XS0501195308
A45: Euro Par 2038 I | B45: 38626 | C45: XS0205537581
A46: Euro Par 2038 II and III | B46: 40296 | C46: XS0501195993
A47: Euro Par 2038 III | B47: 40296 | C47: XS0501196025
